Workbook

Sheet XQ5
A1: 开发区 | F1: 产品信息区 | O1: 46056 | S1: 46046 | T1: 45921 | AF1: 入full区 | BT1: 补货区 | CZ1: 46077 | DA1: 46072 | DB1: 46077 | DG1: 广告促销区 | DU1: 调价区 | EE1: 本月汇率（比索）： | EI1: 2.61 | EJ1: 毛利区 | EL1: 运费区 | ER1: 产品参数区 | FB1: 采购价更新区 | FF1: 参数更新区
A2: 开发日期 | B2: 选品标题（带链接） | C2: 蓝鲸7天销量 | D2: 蓝鲸30天销量 | E2: 抓取时间 | F2: 一类 | G2: 产品类型 | H2: 产品名 | J2: 产品标题（上架） | K2: SKU | L2: 上架编码 | M2: 状态 | N2: 购物体验分 | O2: 平台在线库存 | P2: 私仓 | Q2: 在墨库存销售天数 | R2: 评估 | S2: full分_旧产品数量 | T2: 仓储费产品__2月以上 | U2: 发货周期 | V2: 销售周期 | W2: 日均销量（7天） | X2: 在墨库存数 | AF2: full和 | AG2: 2.24-2.26 #62128153 | AH2: 2/16-2.18 #61590631 | AI2: 1/31-2/2 #60400687 | AJ2: 1/27-1/29 #60073000 | AK2: 1/27-1/29 #60072244 | AL2: 1/24-1/26 #60071284 | BS2: 私仓 | BT2: 在途总和 | CW2: 已采购 | CX2: 实际补货 | CY2: 理论补货 | CZ2: 7天销量(每日2点更新) | DA2: 7天销量(每日2点更新) | DB2: 单日销量 | DC2: 自然销量 | DD2: 广告销量 | DE2: 直接 | DF2: 间接 | DG2: 广告花费 | DH2: 展现量 | DI2: 点击数 | DJ2: Acos | DK2: TAcos7天 | DL2: TAcos30天 | DM2: ROAS输出值 | DN2: ROAS目标值 | DO2: 广告开关 | DP2: 广告组 | DQ2: 促销截止时间 | DU2: 评估 | DX2: 46078 | DY2: 46077 | DZ2: 2月21 | EA2: 46069 | EB2: 46067 | EC2: 46064 | ED2: 46057 | EE2: 售价M·XN | EF2: 原价 | EG2: 采购价RMB | EH2: 投入产出比 | EI2: 采购价MXN | EJ2: 海运毛利 | EK2: 海运毛利率 | EL2: 海运头程 | EM2: 是否包邮 | EN2: 仓库操作费 | EO2: ML佣金（经典曝光/优质曝光） | EP2: 包邮-尾端配送费 | EQ2: 企业增值税10.5% | ER2: 实重kg | ES2: 长cm | ET2: 宽cm | EU2: 高cm | EV2: 体积重 | EW2: 计费重 | EX2: CBM | EZ2: 日均实时销量7天 | FB2: 新价格 | FC2: 旧价格 | FF2: 包装重量kg | FG2: 包装长cm | FH2: 包装宽cm | FI2: 包装高cm | FK2: 散货1/装柜2
B3: Yyugolo Mesa Cromada Uso Rudo Sencilla Con Ruedas Inoxidable | Envío gratis (mercadolibre.com.mx) | C3: 46 | D3: 138 | E3: 45887 | G3: 推车 | H3: 二层小推车-外拦 | J3: Yyugolo Mesa Cromada Uso Rudo Sencilla Con Ruedas Inoxidable | K3: XQ5-ECXTC-WL | L3: 4238699688 | M3: 已上架 | N3: =_xlfn.XLOOKUP(L3,数据更新表!J:J,数据更新表!K:K) -> 100 | O3: =IFERROR(_xlfn.XLOOKUP(K3,数据更新表!A:A,数据更新表!B:B),"0") -> 16 | P3: =_xlfn.XLOOKUP(K3,[1]库销表!$F:$F,[1]库销表!$L:$L) -> 0 | Q3: =X3/W3 -> 19.6 | S3: =_xlfn.XLOOKUP(K3,数据更新表!R:R,数据更新表!S:S) -> #N/A | T3: =_xlfn.XLOOKUP(K3,数据更新表!V:V,数据更新表!W:W) -> #N/A | V3: =IFERROR(7*O3/CZ3,"0") -> 5.6 | W3: =CZ3/7 -> 2.8571429 | X3: =O3+P3+SUM(AH3:BQ3) -> 56 | AF3: =SUM(AG3:BQ3) -> 100 | AG3: 60 | AH3: 40 | BS3: =_xlfn.XLOOKUP(K3,[1]库销表!$F:$F,[1]库销表!$L:$L) -> 0 | BT3: =SUM(BU3:CV3) -> 0 | CW3: =_xlfn.XLOOKUP(K3,[1]库销表!$F:$F,[1]库销表!$IE:$IE) -> 0 | CX3: =_xlfn.XLOOKUP(K3,[1]库销表!$F:$F,[1]库销表!$IF:$IF) -> 0 | CY3: =_xlfn.XLOOKUP(K3,[1]库销表!$F:$F,[1]库销表!$FL:$FL) -> 0 | CZ3: =_xlfn.XLOOKUP(K3,数据更新表!E:E,数据更新表!F:F,0) -> 20 | DA3: 1 | DB3: =_xlfn.XLOOKUP(K3,数据更新表!E:E,数据更新表!G:G) -> 1 | DC3: =_xlfn.XLOOKUP(L3,数据更新表!Z:Z,数据更新表!AH:AH) -> 8 | DD3: =_xlfn.XLOOKUP(L3,数据更新表!Z:Z,数据更新表!AE:AE) -> 12 | DE3: =_xlfn.XLOOKUP(L3,数据更新表!Z:Z,数据更新表!AF:AF) -> 12 | DF3: =_xlfn.XLOOKUP(K3,数据更新表!Z:Z,数据更新表!AG:AG) -> #N/A | DG3: =_xlfn.XLOOKUP(L3,数据更新表!Z:Z,数据更新表!AD:AD) -> 642.72 | DH3: =_xlfn.XLOOKUP(L3,数据更新表!Z:Z,数据更新表!AA:AA) -> 9008 | DI3: =_xlfn.XLOOKUP(L3,数据更新表!Z:Z,数据更新表!AB:AB) -> 119 | DJ3: =_xlfn.XLOOKUP(L3,数据更新表!Z:Z,数据更新表!AC:AC) -> 3.20% | DK3: =_xlfn.XLOOKUP(L3,数据更新表!Z:Z,数据更新表!AI:AI) -> 1.93% | DL3: =_xlfn.XLOOKUP(L3,数据更新表!AL:AL,数据更新表!AM:AM) -> 1.97% | DM3: =_xlfn.XLOOKUP(L3,数据更新表!Z:Z,数据更新表!AJ:AJ) -> 31.25 | DN3: 20 | DO3: 关 | DP3: Medical trolley | DQ3: 46052 | DU3: 独家 | DZ3: 关广 | EE3: 1699 | EF3: =EE3/0.7 -> 2427.1429 | EG3: 120 | EH3: =EJ3/(EI3+EL3) -> 0.57467775 | EI3: =EG3*$EI$1 -> 313.2 | EJ3: =EE3-EI3-EL3-EO3-EN3-EP3-EQ3 -> 356.49355 | EK3: =EJ3/EE3 -> 0.20982552 | EL3: =EX3*2500*$EI$1 -> 307.13645 | EM3: =IF(EE3>299,"是","否") -> 是 | EN3: =EE3*0.05 -> 84.95 | EO3: =EE3*0.175 -> 297.325 | EP3: =IF(EE3<299,IF(EE3<99,25,IF(EE3<=149,30,IF(EE3<=299,37,85))),IF(EE3<=498,_xlfn.XLOOKUP(EW3,运费表!A:A,运费表!C:C,"重量超限",-1),_xlfn.XLOOKUP(EW3,运费表!A:A,运费表!D:D,"重量超限",-1))) -> 161.5 | EQ3: =EE3*0.105 -> 178.395 | ER3: =_xlfn.XLOOKUP(K3,[4]目录表!$H:$H,[4]目录表!$X:$X) -> 7 | ES3: =_xlfn.XLOOKUP(K3,[4]目录表!$H:$H,[4]目录表!$Y:$Y) -> 82 | ET3: =_xlfn.XLOOKUP(K3,[4]目录表!$H:$H,[4]目录表!$Z:$Z) -> 44 | EU3: =_xlfn.XLOOKUP(K3,[4]目录表!$H:$H,[4]目录表!$AA:$AA) -> 14 | EV3: =ES3*ET3*EU3/5000 -> 10.1024 | EW3: =IF(EV3>=ER3,EV3,ER3) -> 10.1024 | EX3: =_xlfn.XLOOKUP(K3,[2]目录表!$H:$H,[2]目录表!$AB:$AB) -> 0.04707072 | EZ3: =CZ3/7 -> 2.8571429 | FK3: =_xlfn.XLOOKUP(K3,[2]目录表!$H:$H,[2]目录表!$AJ:$AJ) -> 装柜
B4: Mesa Para Intrumental Medico Mesa Pasteur Mesa Con 4 Ruedas | Meses sin interés (mercadolibre.com.mx) | C4: 27 | D4: 42 | E4: 45887 | G4: 推车 | H4: 二层小推车-内拦 | J4: Mesa Para Intrumental Medico Mesa Pasteur Mesa Con 4 Ruedas | K4: XQ5-ECXTC-NL | L4: 4238574572 | M4: 已上架 | N4: =_xlfn.XLOOKUP(L4,数据更新表!J:J,数据更新表!K:K) -> 100 | O4: =IFERROR(_xlfn.XLOOKUP(K4,数据更新表!A:A,数据更新表!B:B),"0") -> 8 | P4: =_xlfn.XLOOKUP(K4,[1]库销表!$F:$F,[1]库销表!$L:$L) -> 0 | Q4: =X4/W4 -> 10.83871 | S4: =_xlfn.XLOOKUP(K4,数据更新表!R:R,数据更新表!S:S) -> #N/A | T4: =_xlfn.XLOOKUP(K4,数据更新表!V:V,数据更新表!W:W) -> #N/A | V4: =IFERROR(7*O4/CZ4,"0") -> 1.8064516 | W4: =CZ4/7 -> 4.4285714 | X4: =O4+P4+SUM(AH4:BQ4) -> 48 | AF4: =SUM(AG4:BQ4) -> 100 | AG4: 60 | AH4: 40 | BS4: =_xlfn.XLOOKUP(K4,[1]库销表!$F:$F,[1]库销表!$L:$L) -> 0 | BT4: =SUM(BU4:CV4) -> 0 | CW4: =_xlfn.XLOOKUP(K4,[1]库销表!$F:$F,[1]库销表!$IE:$IE) -> 0 | CX4: =_xlfn.XLOOKUP(K4,[1]库销表!$F:$F,[1]库销表!$IF:$IF) -> 0 | CY4: =_xlfn.XLOOKUP(K4,[1]库销表!$F:$F,[1]库销表!$FL:$FL) -> 0 | CZ4: =_xlfn.XLOOKUP(K4,数据更新表!E:E,数据更新表!F:F,0) -> 31 | DA4: 1 | DB4: =_xlfn.XLOOKUP(K4,数据更新表!E:E,数据更新表!G:G) -> 3 | DC4: =_xlfn.XLOOKUP(L4,数据更新表!Z:Z,数据更新表!AH:AH) -> 10 | DD4: =_xlfn.XLOOKUP(L4,数据更新表!Z:Z,数据更新表!AE:AE) -> 21 | DE4: =_xlfn.XLOOKUP(L4,数据更新表!Z:Z,数据更新表!AF:AF) -> 20 | DF4: =_xlfn.XLOOKUP(K4,数据更新表!Z:Z,数据更新表!AG:AG) -> #N/A | DG4: =_xlfn.XLOOKUP(L4,数据更新表!Z:Z,数据更新表!AD:AD) -> 702.95 | DH4: =_xlfn.XLOOKUP(L4,数据更新表!Z:Z,数据更新表!AA:AA) -> 10833 | DI4: =_xlfn.XLOOKUP(L4,数据更新表!Z:Z,数据更新表!AB:AB) -> 132 | DJ4: =_xlfn.XLOOKUP(L4,数据更新表!Z:Z,数据更新表!AC:AC) -> 2.28% | DK4: =_xlfn.XLOOKUP(L4,数据更新表!Z:Z,数据更新表!AI:AI) -> 1.53% | DL4: =_xlfn.XLOOKUP(L4,数据更新表!AL:AL,数据更新表!AM:AM) -> 1.56% | DM4: =_xlfn.XLOOKUP(L4,数据更新表!Z:Z,数据更新表!AJ:AJ) -> 43.78 | DN4: 20 | DO4: 关 | DP4: Medical trolley | DQ4: 46052 | DU4: 独家 | DZ4: 1458升1558 | EE4: 1558 | EF4: =EE4/0.7 -> 2225.7143 | EG4: 105 | EH4: =EJ4/(EI4+EL4) -> 0.28750142 | EI4: =EG4*$EI$1 -> 274.05 | EJ4: =EE4-EI4-EL4-EO4-EN4-EP4-EQ4 -> 190.6685 | EK4: =EJ4/EE4 -> 0.1223803 | EL4: =EX4*2500*$EI$1 -> 389.1415 | EM4: =IF(EE4>299,"是","否") -> 是 | EN4: =EE4*0.05 -> 77.9 | EO4: =EE4*0.175 -> 272.65 | EP4: =IF(EE4<299,IF(EE4<99,25,IF(EE4<=149,30,IF(EE4<=299,37,85))),IF(EE4<=498,_xlfn.XLOOKUP(EW4,运费表!A:A,运费表!C:C,"重量超限",-1),_xlfn.XLOOKUP(EW4,运费表!A:A,运费表!D:D,"重量超限",-1))) -> 190 | EQ4: =EE4*0.105 -> 163.59 | ER4: =_xlfn.XLOOKUP(K4,[4]目录表!$H:$H,[4]目录表!$X:$X) -> 6.4 | ES4: =_xlfn.XLOOKUP(K4,[4]目录表!$H:$H,[4]目录表!$Y:$Y) -> 80 | ET4: =_xlfn.XLOOKUP(K4,[4]目录表!$H:$H,[4]目录表!$Z:$Z) -> 43 | EU4: =_xlfn.XLOOKUP(K4,[4]目录表!$H:$H,[4]目录表!$AA:$AA) -> 19 | EV4: =ES4*ET4*EU4/5000 -> 13.072 | EW4: =IF(EV4>=ER4,EV4,ER4) -> 13.072 | EX4: =_xlfn.XLOOKUP(K4,[2]目录表!$H:$H,[2]目录表!$AB:$AB) -> 0.059638544 | EZ4: =CZ4/7 -> 4.4285714 | FK4: =_xlfn.XLOOKUP(K4,[2]目录表!$H:$H,[2]目录表!$AJ:$AJ) -> 装柜
B5: Mesa Pasteur Con Cajon Rodable Uso Rudo Envío Gratis | Envío gratis (mercadolibre.com.mx) | C5: 7 | D5: 37 | E5: 45889 | G5: 麻醉车 | H5: 麻醉车 | J5: Mesa Pasteur Con Cajon Rodable Uso Rudo Envío Gratis | K5: XQ5-MZC | L5: 2515489727 | M5: 已上架 | N5: =_xlfn.XLOOKUP(L5,数据更新表!J:J,数据更新表!K:K) -> 100 | O5: =IFERROR(_xlfn.XLOOKUP(K5,数据更新表!A:A,数据更新表!B:B),"0") -> 37 | P5: =_xlfn.XLOOKUP(K5,[1]库销表!$F:$F,[1]库销表!$L:$L) -> 60 | Q5: =X5/W5 -> 479.5 | S5: =_xlfn.XLOOKUP(K5,数据更新表!R:R,数据更新表!S:S) -> #N/A | T5: =_xlfn.XLOOKUP(K5,数据更新表!V:V,数据更新表!W:W) -> #N/A | V5: =IFERROR(7*O5/CZ5,"0") -> 129.5 | W5: =CZ5/7 -> 0.28571429 | X5: =O5+P5+SUM(AH5:BQ5) -> 137 | AF5: =SUM(AG5:BQ5) -> 40 | AH5: 40 | BS5: =_xlfn.XLOOKUP(K5,[1]库销表!$F:$F,[1]库销表!$L:$L) -> 60 | BT5: =SUM(BU5:CV5) -> 0 | CW5: =_xlfn.XLOOKUP(K5,[1]库销表!$F:$F,[1]库销表!$IE:$IE) -> 0 | CX5: =_xlfn.XLOOKUP(K5,[1]库销表!$F:$F,[1]库销表!$IF:$IF) -> 0 | CY5: =_xlfn.XLOOKUP(K5,[1]库销表!$F:$F,[1]库销表!$FL:$FL) -> 0 | CZ5: =_xlfn.XLOOKUP(K5,数据更新表!E:E,数据更新表!F:F,0) -> 2 | DA5: 0 | DB5: =_xlfn.XLOOKUP(K5,数据更新表!E:E,数据更新表!G:G) -> 1 | DC5: =_xlfn.XLOOKUP(L5,数据更新表!Z:Z,数据更新表!AH:AH) -> 2 | DD5: =_xlfn.XLOOKUP(L5,数据更新表!Z:Z,数据更新表!AE:AE) -> 0 | DE5: =_xlfn.XLOOKUP(L5,数据更新表!Z:Z,数据更新表!AF:AF) -> 0 | DF5: =_xlfn.XLOOKUP(K5,数据更新表!Z:Z,数据更新表!AG:AG) -> #N/A | DG5: =_xlfn.XLOOKUP(L5,数据更新表!Z:Z,数据更新表!AD:AD) -> 346.04 | DH5: =_xlfn.XLOOKUP(L5,数据更新表!Z:Z,数据更新表!AA:AA) -> 5564 | DI5: =_xlfn.XLOOKUP(L5,数据更新表!Z:Z,数据更新表!AB:AB) -> 41 | DJ5: =_xlfn.XLOOKUP(L5,数据更新表!Z:Z,数据更新表!AC:AC) -> 0.00% | DK5: =_xlfn.XLOOKUP(L5,数据更新表!Z:Z,数据更新表!AI:AI) -> 7.15% | DL5: =_xlfn.XLOOKUP(L5,数据更新表!AL:AL,数据更新表!AM:AM) -> 7.15% | DM5: =_xlfn.XLOOKUP(L5,数据更新表!Z:Z,数据更新表!AJ:AJ) -> 0 | DN5: 20 | DO5: 开 | DP5: Medical trolley | DX5: 2420降2398 | EE5: 2398 | EF5: =EE5/0.7 -> 3425.7143 | EG5: 180 | EH5: =EJ5/(EI5+EL5) -> 0.30928293 | EI5: =EG5*$EI$1 -> 469.8 | EJ5: =EE5-EI5-EL5-EO5-EN5-EP5-EQ5 -> 326.97063 | EK5: =EJ5/EE5 -> 0.13635139 | EL5: =EX5*2500*$EI$1 -> 587.38937 | EM5: =IF(EE5>299,"是","否") -> 是 | EN5: =EE5*0.05 -> 119.9 | EO5: =EE5*0.175 -> 419.65 | EP5: =IF(EE5<299,IF(EE5<99,25,IF(EE5<=149,30,IF(EE5<=299,37,85))),IF(EE5<=498,_xlfn.XLOOKUP(EW5,运费表!A:A,运费表!C:C,"重量超限",-1),_xlfn.XLOOKUP(EW5,运费表!A:A,运费表!D:D,"重量超限",-1))) -> 222.5 | EQ5: =EE5*0.105 -> 251.79 | ER5: =_xlfn.XLOOKUP(K5,[4]目录表!$H:$H,[4]目录表!$X:$X) -> 8.4 | ES5: =_xlfn.XLOOKUP(K5,[4]目录表!$H:$H,[4]目录表!$Y:$Y) -> 59 | ET5: =_xlfn.XLOOKUP(K5,[4]目录表!$H:$H,[4]目录表!$Z:$Z) -> 43 | EU5: =_xlfn.XLOOKUP(K5,[4]目录表!$H:$H,[4]目录表!$AA:$AA) -> 38 | EV5: =ES5*ET5*EU5/5000 -> 19.2812 | EW5: =IF(EV5>=ER5,EV5,ER5) -> 19.2812 | EX5: =_xlfn.XLOOKUP(K5,[2]目录表!$H:$H,[2]目录表!$AB:$AB) -> 0.09002136 | EZ5: =CZ5/7 -> 0.28571429 | FK5: =_xlfn.XLOOKUP(K5,[2]目录表!$H:$H,[2]目录表!$AJ:$AJ) -> 装柜
B6: Mesa Mayo Con Charola Acero Inoxidable Ajustable Uso Rudo | Envío gratis (mercadolibre.com.mx) | C6: 16 | D6: 18 | E6: 45889 | G6: 托盘架 | H6: 四脚托盘架-45*35 | J6: Mesa Mayo Con Charola Acero Inoxidable Ajustable Uso Rudo | K6: XQ5-SJTPJ-45*35 | L6: 2515701467 | M6: 已上架 | N6: =_xlfn.XLOOKUP(L6,数据更新表!J:J,数据更新表!K:K) -> 65 | O6: =IFERROR(_xlfn.XLOOKUP(K6,数据更新表!A:A,数据更新表!B:B),"0") -> 36 | P6: =_xlfn.XLOOKUP(K6,[1]库销表!$F:$F,[1]库销表!$L:$L) -> 60 | Q6: =X6/W6 -> 238 | S6: =_xlfn.XLOOKUP(K6,数据更新表!R:R,数据更新表!S:S) -> #N/A | T6: =_xlfn.XLOOKUP(K6,数据更新表!V:V,数据更新表!W:W) -> #N/A | V6: =IFERROR(7*O6/CZ6,"0") -> 63 | W6: =CZ6/7 -> 0.57142857 | X6: =O6+P6+SUM(AH6:BQ6) -> 136 | AF6: =SUM(AG6:BQ6) -> 40 | AH6: 40 | BS6: =_xlfn.XLOOKUP(K6,[1]库销表!$F:$F,[1]库销表!$L:$L) -> 60 | BT6: =SUM(BU6:CV6) -> 0 | CW6: =_xlfn.XLOOKUP(K6,[1]库销表!$F:$F,[1]库销表!$IE:$IE) -> 0 | CX6: =_xlfn.XLOOKUP(K6,[1]库销表!$F:$F,[1]库销表!$IF:$IF) -> 0 | CY6: =_xlfn.XLOOKUP(K6,[1]库销表!$F:$F,[1]库销表!$FL:$FL) -> 0 | CZ6: =_xlfn.XLOOKUP(K6,数据更新表!E:E,数据更新表!F:F,0) -> 4 | DA6: 0 | DB6: =_xlfn.XLOOKUP(K6,数据更新表!E:E,数据更新表!G:G) -> 0 | DC6: =_xlfn.XLOOKUP(L6,数据更新表!Z:Z,数据更新表!AH:AH) -> 0 | DD6: =_xlfn.XLOOKUP(L6,数据更新表!Z:Z,数据更新表!AE:AE) -> 4 | DE6: =_xlfn.XLOOKUP(L6,数据更新表!Z:Z,数据更新表!AF:AF) -> 3 | DF6: =_xlfn.XLOOKUP(K6,数据更新表!Z:Z,数据更新表!AG:AG) -> #N/A | DG6: =_xlfn.XLOOKUP(L6,数据更新表!Z:Z,数据更新表!AD:AD) -> 314.46 | DH6: =_xlfn.XLOOKUP(L6,数据更新表!Z:Z,数据更新表!AA:AA) -> 5804 | DI6: =_xlfn.XLOOKUP(L6,数据更新表!Z:Z,数据更新表!AB:AB) -> 53 | DJ6: =_xlfn.XLOOKUP(L6,数据更新表!Z:Z,数据更新表!AC:AC) -> 6.93% | DK6: =_xlfn.XLOOKUP(L6,数据更新表!Z:Z,数据更新表!AI:AI) -> 7.65% | DL6: =_xlfn.XLOOKUP(L6,数据更新表!AL:AL,数据更新表!AM:AM) -> 7.65% | DM6: =_xlfn.XLOOKUP(L6,数据更新表!Z:Z,数据更新表!AJ:AJ) -> 14.44 | DN6: 20 | DO6: 开 | DP6: Medical trolley | EE6: 1090 | EF6: =_xlfn.XLOOKUP(L6,数据更新表!J:J,数据更新表!M:M) -> 1369.4 | EG6: 78 | EH6: =EJ6/(EI6+EL6) -> 0.18662614 | EI6: =EG6*$EI$1 -> 203.58 | EJ6: =EE6-EI6-EL6-EO6-EN6-EP6-EQ6 -> 89.457788 | EK6: =EJ6/EE6 -> 0.082071365 | EL6: =EX6*2500*$EI$1 -> 275.76221 | EM6: =IF(EE6>299,"是","否") -> 是 | EN6: =EE6*0.05 -> 54.5 | EO6: =EE6*0.175 -> 190.75 | EP6: =IF(EE6<299,IF(EE6<99,25,IF(EE6<=149,30,IF(EE6<=299,37,85))),IF(EE6<=498,_xlfn.XLOOKUP(EW6,运费表!A:A,运费表!C:C,"重量超限",-1),_xlfn.XLOOKUP(EW6,运费表!A:A,运费表!D:D,"重量超限",-1))) -> 161.5 | EQ6: =EE6*0.105 -> 114.45 | ER6: =_xlfn.XLOOKUP(K6,[4]目录表!$H:$H,[4]目录表!$X:$X) -> 4.2 | ES6: =_xlfn.XLOOKUP(K6,[4]目录表!$H:$H,[4]目录表!$Y:$Y) -> 81 | ET6: =_xlfn.XLOOKUP(K6,[4]目录表!$H:$H,[4]目录表!$Z:$Z) -> 46 | EU6: =_xlfn.XLOOKUP(K6,[4]目录表!$H:$H,[4]目录表!$AA:$AA) -> 13 | EV6: =ES6*ET6*EU6/5000 -> 9.6876 | EW6: =IF(EV6>=ER6,EV6,ER6) -> 9.6876 | EX6: =_xlfn.XLOOKUP(K6,[2]目录表!$H:$H,[2]目录表!$AB:$AB) -> 0.042262408 | EZ6: =CZ6/7 -> 0.57142857 | FK6: =_xlfn.XLOOKUP(K6,[2]目录表!$H:$H,[2]目录表!$AJ:$AJ) -> 装柜
B7: Andadera Ortopedica de Doble Apoyo para Adulto Andador Ortopédico de Aluminio Plegable Soporta 100kg Tikun Color Negro | Envío gratis (mercadolibre.com.mx) | C7: 75 | D7: 341 | E7: 45889 | G7: 助行器 | H7: 双弯助行器 | J7: Andadera Ortopedica De Doble Apoyo Para Adulto Soporta 100kg | K7: XQ5-SWZXQ | L7: 4238819076 | M7: 已上架 | N7: =_xlfn.XLOOKUP(L7,数据更新表!J:J,数据更新表!K:K) -> 100 | O7: =IFERROR(_xlfn.XLOOKUP(K7,数据更新表!A:A,数据更新表!B:B),"0") -> 10 | P7: =_xlfn.XLOOKUP(K7,[1]库销表!$F:$F,[1]库销表!$L:$L) -> 0 | Q7: =X7/W7 -> 35 | S7: =_xlfn.XLOOKUP(K7,数据更新表!R:R,数据更新表!S:S) -> #N/A | T7: =_xlfn.XLOOKUP(K7,数据更新表!V:V,数据更新表!W:W) -> #N/A | V7: =IFERROR(7*O7/CZ7,"0") -> 35 | W7: =CZ7/7 -> 0.28571429 | X7: =O7+P7+SUM(BN7:BR7) -> 10 | AF7: =SUM(AG7:BQ7) -> 0 | BS7: =_xlfn.XLOOKUP(K7,[1]库销表!$F:$F,[1]库销表!$L:$L) -> 0 | BT7: =SUM(BU7:CV7) -> 0 | CW7: =_xlfn.XLOOKUP(K7,[1]库销表!$F:$F,[1]库销表!$IE:$IE) -> 0 | CX7: =_xlfn.XLOOKUP(K7,[1]库销表!$F:$F,[1]库销表!$IF:$IF) -> 0 | CY7: =_xlfn.XLOOKUP(K7,[1]库销表!$F:$F,[1]库销表!$FL:$FL) -> 0 | CZ7: =_xlfn.XLOOKUP(K7,数据更新表!E:E,数据更新表!F:F,0) -> 2 | DA7: 4 | DB7: =_xlfn.XLOOKUP(K7,数据更新表!E:E,数据更新表!G:G) -> 0 | DC7: =_xlfn.XLOOKUP(L7,数据更新表!Z:Z,数据更新表!AH:AH) -> 2 | DD7: =_xlfn.XLOOKUP(L7,数据更新表!Z:Z,数据更新表!AE:AE) -> 0 | DE7: =_xlfn.XLOOKUP(L7,数据更新表!Z:Z,数据更新表!AF:AF) -> 0 | DF7: =_xlfn.XLOOKUP(K7,数据更新表!Z:Z,数据更新表!AG:AG) -> #N/A | DG7: =_xlfn.XLOOKUP(L7,数据更新表!Z:Z,数据更新表!AD:AD) -> 28.89 | DH7: =_xlfn.XLOOKUP(L7,数据更新表!Z:Z,数据更新表!AA:AA) -> 30981 | DI7: =_xlfn.XLOOKUP(L7,数据更新表!Z:Z,数据更新表!AB:AB) -> 13 | DJ7: =_xlfn.XLOOKUP(L7,数据更新表!Z:Z,数据更新表!AC:AC) -> 0.00% | DK7: =_xlfn.XLOOKUP(L7,数据更新表!Z:Z,数据更新表!AI:AI) -> 2.08% | DL7: =_xlfn.XLOOKUP(L7,数据更新表!AL:AL,数据更新表!AM:AM) -> 3.91% | DM7: =_xlfn.XLOOKUP(L7,数据更新表!Z:Z,数据更新表!AJ:AJ) -> 0 | DN7: 20 | DO7: 开 | DP7: walking aid_3 | DQ7: 46074 | DU7: 价优 无优势 清 | EE7: 696 | EF7: =EE7/0.7 -> 994.28571 | EG7: 34.5 | EH7: =EJ7/(EI7+EL7) -> -0.008631628 | EI7: =EG7*$EI$1 -> 90.045 | EJ7: =EE7-EI7-EL7-EO7-EN7-EP7-EQ7 -> -2.8455504 | EK7: =EJ7/EE7 -> -0.0040884345 | EL7: =EX7*2500*$EI$1 -> 239.62055 | EM7: =IF(EE7>299,"是","否") -> 是 | EN7: =EE7*0.05 -> 34.8 | EO7: =EE7*0.175 -> 121.8 | EP7: =IF(EE7<299,IF(EE7<99,25,IF(EE7<=149,30,IF(EE7<=299,37,85))),IF(EE7<=498,_xlfn.XLOOKUP(EW7,运费表!A:A,运费表!C:C,"重量超限",-1),_xlfn.XLOOKUP(EW7,运费表!A:A,运费表!D:D,"重量超限",-1))) -> 139.5 | EQ7: =EE7*0.105 -> 73.08 | ER7: =_xlfn.XLOOKUP(K7,[4]目录表!$H:$H,[4]目录表!$X:$X) -> 3 | ES7: =_xlfn.XLOOKUP(K7,[4]目录表!$H:$H,[4]目录表!$Y:$Y) -> 75.6 | ET7: =_xlfn.XLOOKUP(K7,[4]目录表!$H:$H,[4]目录表!$Z:$Z) -> 55.2 | EU7: =_xlfn.XLOOKUP(K7,[4]目录表!$H:$H,[4]目录表!$AA:$AA) -> 8.8 | EV7: =ES7*ET7*EU7/5000 -> 7.3446912 | EW7: =IF(EV7>=ER7,EV7,ER7) -> 7.3446912 | EX7: =_xlfn.XLOOKUP(K7,[2]目录表!$H:$H,[2]目录表!$AB:$AB) -> 0.036723456 | EZ7: =CZ7/7 -> 0.28571429 | FK7: =_xlfn.XLOOKUP(K7,[2]目录表!$H:$H,[2]目录表!$AJ:$AJ) -> 装柜
B8: Andadera Ortopédica Fija Tikun Para Adulto Plegable De Aluminio Negro | Envío gratis (mercadolibre.com.mx) | C8: 26 | D8: 202 | E8: 45889 | G8: 助行器 | H8: 单弯助行器 | J8: Andadera Ortopédica Fija De Aluminio Plegable Color Negro | K8: XQ5-DWZXQ | L8: 4239173046 | M8: 已上架 | N8: =_xlfn.XLOOKUP(L8,数据更新表!J:J,数据更新表!K:K) -> #N/A | O8: =IFERROR(_xlfn.XLOOKUP(K8,数据更新表!A:A,数据更新表!B:B),"0") -> 0 | P8: =_xlfn.XLOOKUP(K8,[1]库销表!$F:$F,[1]库销表!$L:$L) -> 0 | Q8: =X8/W8 -> #DIV/0! | S8: =_xlfn.XLOOKUP(K8,数据更新表!R:R,数据更新表!S:S) -> 12 | T8: =_xlfn.XLOOKUP(K8,数据更新表!V:V,数据更新表!W:W) -> #N/A | V8: =IFERROR(7*O8/CZ8,"0") -> 0 | W8: =CZ8/7 -> 0 | X8: =O8+P8+SUM(BN8:BR8) -> 0 | AF8: =SUM(AG8:BQ8) -> 0 | BS8: =_xlfn.XLOOKUP(K8,[1]库销表!$F:$F,[1]库销表!$L:$L) -> 0 | BT8: =SUM(BU8:CV8) -> 0 | CW8: =_xlfn.XLOOKUP(K8,[1]库销表!$F:$F,[1]库销表!$IE:$IE) -> 0 | CX8: =_xlfn.XLOOKUP(K8,[1]库销表!$F:$F,[1]库销表!$IF:$IF) -> 0 | CY8: =_xlfn.XLOOKUP(K8,[1]库销表!$F:$F,[1]库销表!$FL:$FL) -> 0 | CZ8: =_xlfn.XLOOKUP(K8,数据更新表!E:E,数据更新表!F:F,0) -> 0 | DA8: 0 | DB8: =_xlfn.XLOOKUP(K8,数据更新表!E:E,数据更新表!G:G) -> #N/A | DC8: =_xlfn.XLOOKUP(L8,数据更新表!Z:Z,数据更新表!AH:AH) -> #N/A | DD8: =_xlfn.XLOOKUP(L8,数据更新表!Z:Z,数据更新表!AE:AE) -> #N/A | DE8: =_xlfn.XLOOKUP(L8,数据更新表!Z:Z,数据更新表!AF:AF) -> #N/A | DF8: =_xlfn.XLOOKUP(K8,数据更新表!Z:Z,数据更新表!AG:AG) -> #N/A | DG8: =_xlfn.XLOOKUP(L8,数据更新表!Z:Z,数据更新表!AD:AD) -> #N/A | DH8: =_xlfn.XLOOKUP(L8,数据更新表!Z:Z,数据更新表!AA:AA) -> #N/A | DI8: =_xlfn.XLOOKUP(L8,数据更新表!Z:Z,数据更新表!AB:AB) -> #N/A | DJ8: =_xlfn.XLOOKUP(L8,数据更新表!Z:Z,数据更新表!AC:AC) -> #N/A | DK8: =_xlfn.XLOOKUP(L8,数据更新表!Z:Z,数据更新表!AI:AI) -> #N/A | DL8: =_xlfn.XLOOKUP(L8,数据更新表!AL:AL,数据更新表!AM:AM) -> 11.79% | DM8: =_xlfn.XLOOKUP(L8,数据更新表!Z:Z,数据更新表!AJ:AJ) -> #N/A | DN8: 10 | DO8: 已禁用 | DP8: walking aid_1 | DQ8: 46074 | EE8: =_xlfn.XLOOKUP(L8,数据更新表!J:J,数据更新表!L:L) -> #N/A | EF8: =_xlfn.XLOOKUP(L8,数据更新表!J:J,数据更新表!M:M) -> #N/A | EG8: 30.5 | EH8: =EJ8/(EI8+EL8) -> #N/A | EI8: =EG8*$EI$1 -> 79.605 | EJ8: =EE8-EI8-EL8-EO8-EN8-EP8-EQ8 -> #N/A | EK8: =EJ8/EE8 -> #N/A | EL8: =EX8*2500*$EI$1 -> 222.67476 | EM8: =IF(EE8>299,"是","否") -> #N/A | EN8: =EE8*0.05 -> #N/A | EO8: =EE8*0.175 -> #N/A | EP8: =IF(EE8<299,IF(EE8<99,25,IF(EE8<=149,30,IF(EE8<=299,37,85))),IF(EE8<=498,_xlfn.XLOOKUP(EW8,运费表!A:A,运费表!C:C,"重量超限",-1),_xlfn.XLOOKUP(EW8,运费表!A:A,运费表!D:D,"重量超限",-1))) -> #N/A | EQ8: =EE8*0.105 -> #N/A | ER8: =_xlfn.XLOOKUP(K8,[4]目录表!$H:$H,[4]目录表!$X:$X) -> 2.8 | ES8: =_xlfn.XLOOKUP(K8,[4]目录表!$H:$H,[4]目录表!$Y:$Y) -> 77 | ET8: =_xlfn.XLOOKUP(K8,[4]目录表!$H:$H,[4]目录表!$Z:$Z) -> 55.4 | EU8: =_xlfn.XLOOKUP(K8,[4]目录表!$H:$H,[4]目录表!$AA:$AA) -> 8 | EV8: =ES8*ET8*EU8/5000 -> 6.82528 | EW8: =IF(EV8>=ER8,EV8,ER8) -> 6.82528 | EX8: =_xlfn.XLOOKUP(K8,[2]目录表!$H:$H,[2]目录表!$AB:$AB) -> 0.0341264 | EZ8: =CZ8/7 -> 0 | FK8: =_xlfn.XLOOKUP(K8,[2]目录表!$H:$H,[2]目录表!$AJ:$AJ) -> 装柜
B9: Andadera ortopédica con ruedas Dewinner HS-ZLQ color plateado | Envío gratis (mercadolibre.com.mx) | C9: 51 | D9: 275 | E9: 45889 | G9: 助行器 | H9: 双弯带轮带板助行器 | J9: Andadera ortopédica con ruedas Dewinner HS-ZLQ color plateado | K9: XQ5-SWDLDBZXQ | L9: 4239812144 | M9: 已上架 | N9: =_xlfn.XLOOKUP(L9,数据更新表!J:J,数据更新表!K:K) -> #N/A | O9: =IFERROR(_xlfn.XLOOKUP(K9,数据更新表!A:A,数据更新表!B:B),"0") -> 0 | P9: =_xlfn.XLOOKUP(K9,[1]库销表!$F:$F,[1]库销表!$L:$L) -> 0 | Q9: =X9/W9 -> #DIV/0! | S9: =_xlfn.XLOOKUP(K9,数据更新表!R:R,数据更新表!S:S) -> #N/A | T9: =_xlfn.XLOOKUP(K9,数据更新表!V:V,数据更新表!W:W) -> #N/A | V9: =IFERROR(7*O9/CZ9,"0") -> 0 | W9: =CZ9/7 -> 0 | X9: =O9+P9+SUM(BN9:BR9) -> 0 | AF9: =SUM(AG9:BQ9) -> 0 | BS9: =_xlfn.XLOOKUP(K9,[1]库销表!$F:$F,[1]库销表!$L:$L) -> 0 | BT9: =SUM(BU9:CV9) -> 0 | CW9: =_xlfn.XLOOKUP(K9,[1]库销表!$F:$F,[1]库销表!$IE:$IE) -> 0 | CX9: =_xlfn.XLOOKUP(K9,[1]库销表!$F:$F,[1]库销表!$IF:$IF) -> 0 | CY9: =_xlfn.XLOOKUP(K9,[1]库销表!$F:$F,[1]库销表!$FL:$FL) -> 0 | CZ9: =_xlfn.XLOOKUP(K9,数据更新表!E:E,数据更新表!F:F,0) -> 0 | DA9: 0 | DB9: =_xlfn.XLOOKUP(K9,数据更新表!E:E,数据更新表!G:G) -> #N/A | DC9: =_xlfn.XLOOKUP(L9,数据更新表!Z:Z,数据更新表!AH:AH) -> #N/A | DD9: =_xlfn.XLOOKUP(L9,数据更新表!Z:Z,数据更新表!AE:AE) -> #N/A | DE9: =_xlfn.XLOOKUP(L9,数据更新表!Z:Z,数据更新表!AF:AF) -> #N/A | DF9: =_xlfn.XLOOKUP(K9,数据更新表!Z:Z,数据更新表!AG:AG) -> #N/A | DG9: =_xlfn.XLOOKUP(L9,数据更新表!Z:Z,数据更新表!AD:AD) -> #N/A | DH9: =_xlfn.XLOOKUP(L9,数据更新表!Z:Z,数据更新表!AA:AA) -> #N/A | DI9: =_xlfn.XLOOKUP(L9,数据更新表!Z:Z,数据更新表!AB:AB) -> #N/A | DJ9: =_xlfn.XLOOKUP(L9,数据更新表!Z:Z,数据更新表!AC:AC) -> #N/A | DK9: =_xlfn.XLOOKUP(L9,数据更新表!Z:Z,数据更新表!AI:AI) -> #N/A | DL9: =_xlfn.XLOOKUP(L9,数据更新表!AL:AL,数据更新表!AM:AM) -> 7.90% | DM9: =_xlfn.XLOOKUP(L9,数据更新表!Z:Z,数据更新表!AJ:AJ) -> #N/A | DN9: 10 | DO9: 已禁用 | DP9: walking aid_2 | DQ9: 46074 | DU9: 价高 同958 | EE9: =_xlfn.XLOOKUP(L9,数据更新表!J:J,数据更新表!L:L) -> #N/A | EF9: =_xlfn.XLOOKUP(L9,数据更新表!J:J,数据更新表!M:M) -> #N/A | EG9: 51.5 | EH9: =EJ9/(EI9+EL9) -> #N/A | EI9: =EG9*$EI$1 -> 134.415 | EJ9: =EE9-EI9-EL9-EO9-EN9-EP9-EQ9 -> #N/A | EK9: =EJ9/EE9 -> #N/A | EL9: =EX9*2500*$EI$1 -> 266.31814 | EM9: =IF(EE9>299,"是","否") -> #N/A | EN9: =EE9*0.05 -> #N/A | EO9: =EE9*0.175 -> #N/A | EP9: =IF(EE9<299,IF(EE9<99,25,IF(EE9<=149,30,IF(EE9<=299,37,85))),IF(EE9<=498,_xlfn.XLOOKUP(EW9,运费表!A:A,运费表!C:C,"重量超限",-1),_xlfn.XLOOKUP(EW9,运费表!A:A,运费表!D:D,"重量超限",-1))) -> #N/A | EQ9: =EE9*0.105 -> #N/A | ER9: =_xlfn.XLOOKUP(K9,[4]目录表!$H:$H,[4]目录表!$X:$X) -> 4.4 | ES9: =_xlfn.XLOOKUP(K9,[4]目录表!$H:$H,[4]目录表!$Y:$Y) -> 76 | ET9: =_xlfn.XLOOKUP(K9,[4]目录表!$H:$H,[4]目录表!$Z:$Z) -> 54.8 | EU9: =_xlfn.XLOOKUP(K9,[4]目录表!$H:$H,[4]目录表!$AA:$AA) -> 9.8 | EV9: =ES9*ET9*EU9/5000 -> 8.163008 | EW9: =IF(EV9>=ER9,EV9,ER9) -> 8.163008 | EX9: =_xlfn.XLOOKUP(K9,[2]目录表!$H:$H,[2]目录表!$AB:$AB) -> 0.04081504 | EZ9: =CZ9/7 -> 0 | FK9: =_xlfn.XLOOKUP(K9,[2]目录表!$H:$H,[2]目录表!$AJ:$AJ) -> 装柜
B10: Porta Sueros Acero Inox 3 Ruedas Base De Hierro Con Cubierta | Meses sin interés (mercadolibre.com.mx) | C10: 14 | D10: 46 | E10: 45889 | G10: 输液架 | H10: 输液架-折叠 | J10: Porta Sueros Acero Inox 3 Ruedas Base De Hierro Con Cubierta | K10: ZD-XQ5-SYJ | L10: 2515831365 | M10: 已上架 | N10: =_xlfn.XLOOKUP(L10,数据更新表!J:J,数据更新表!K:K) -> #N/A | O10: =IFERROR(_xlfn.XLOOKUP(K10,数据更新表!A:A,数据更新表!B:B),"0") -> 0 | P10: =_xlfn.XLOOKUP(K10,[1]库销表!$F:$F,[1]库销表!$L:$L) -> 0 | Q10: =X10/W10 -> 0 | S10: =_xlfn.XLOOKUP(K10,数据更新表!R:R,数据更新表!S:S) -> #N/A | T10: =_xlfn.XLOOKUP(K10,数据更新表!V:V,数据更新表!W:W) -> #N/A | V10: =IFERROR(7*O10/CZ10,"0") -> 0 | W10: =CZ10/7 -> 0.71428571 | X10: =O10+P10+SUM(BN10:BR10) -> 0 | AF10: =SUM(AG10:BQ10) -> 0 | BS10: =_xlfn.XLOOKUP(K10,[1]库销表!$F:$F,[1]库销表!$L:$L) -> 0 | BT10: =SUM(BU10:CV10) -> 0 | CW10: =_xlfn.XLOOKUP(K10,[1]库销表!$F:$F,[1]库销表!$IE:$IE) -> 0 | CX10: =_xlfn.XLOOKUP(K10,[1]库销表!$F:$F,[1]库销表!$IF:$IF) -> 0 | CY10: =_xlfn.XLOOKUP(K10,[1]库销表!$F:$F,[1]库销表!$FL:$FL) -> 0 | CZ10: =_xlfn.XLOOKUP(K10,数据更新表!E:E,数据更新表!F:F,0) -> 5 | DA10: 5 | DB10: =_xlfn.XLOOKUP(K10,数据更新表!E:E,数据更新表!G:G) -> 0 | DC10: =_xlfn.XLOOKUP(L10,数据更新表!Z:Z,数据更新表!AH:AH) -> 4 | DD10: =_xlfn.XLOOKUP(L10,数据更新表!Z:Z,数据更新表!AE:AE) -> 1 | DE10: =_xlfn.XLOOKUP(L10,数据更新表!Z:Z,数据更新表!AF:AF) -> 1 | DF10: =_xlfn.XLOOKUP(K10,数据更新表!Z:Z,数据更新表!AG:AG) -> #N/A | DG10: =_xlfn.XLOOKUP(L10,数据更新表!Z:Z,数据更新表!AD:AD) -> 36.96 | DH10: =_xlfn.XLOOKUP(L10,数据更新表!Z:Z,数据更新表!AA:AA) -> 3717 | DI10: =_xlfn.XLOOKUP(L10,数据更新表!Z:Z,数据更新表!AB:AB) -> 21 | DJ10: =_xlfn.XLOOKUP(L10,数据更新表!Z:Z,数据更新表!AC:AC) -> 8.05% | DK10: =_xlfn.XLOOKUP(L10,数据更新表!Z:Z,数据更新表!AI:AI) -> 1.61% | DL10: =_xlfn.XLOOKUP(L10,数据更新表!AL:AL,数据更新表!AM:AM) -> 1.61% | DM10: =_xlfn.XLOOKUP(L10,数据更新表!Z:Z,数据更新表!AJ:AJ) -> 12.42 | DN10: 10 | DO10: 开 | DP10: Ordinary items | DQ10: 46074 | DU10: 价高 无优势 | EE10: 459 | EF10: =EE10/0.7 -> 655.71429 | EG10: 50 | EH10: =EJ10/(EI10+EL10) -> 0.27744979 | EI10: =EG10*$EI$1 -> 130.5 | EJ10: =EE10-EI10-EL10-EO10-EN10-EP10-EQ10 -> 52.110485 | EK10: =EJ10/EE10 -> 0.11353047 | EL10: =EX10*3000*$EI$1 -> 57.319515 | EM10: =IF(EE10>299,"是","否") -> 是 | EN10: =EE10*0.05 -> 22.95 | EO10: =EE10*0.175 -> 80.325 | EP10: =IF(EE10<299,IF(EE10<99,25,IF(EE10<=149,30,IF(EE10<=299,37,85))),IF(EE10<=498,_xlfn.XLOOKUP(EW10,运费表!A:A,运费表!C:C,"重量超限",-1),_xlfn.XLOOKUP(EW10,运费表!A:A,运费表!D:D,"重量超限",-1))) -> 67.6 | EQ10: =EE10*0.105 -> 48.195 | ER10: =_xlfn.XLOOKUP(K10,[4]目录表!$H:$H,[4]目录表!$X:$X) -> 1.8 | ES10: =_xlfn.XLOOKUP(K10,[4]目录表!$H:$H,[4]目录表!$Y:$Y) -> 60.5 | ET10: =_xlfn.XLOOKUP(K10,[4]目录表!$H:$H,[4]目录表!$Z:$Z) -> 11 | EU10: =_xlfn.XLOOKUP(K10,[4]目录表!$H:$H,[4]目录表!$AA:$AA) -> 11 | EV10: =ES10*ET10*EU10/5000 -> 1.4641 | EW10: =IF(EV10>=ER10,EV10,ER10) -> 1.8 | EX10: =_xlfn.XLOOKUP(K10,[2]目录表!$H:$H,[2]目录表!$AB:$AB) -> 0.0073205 | EZ10: =CZ10/7 -> 0.71428571 | FK10: =_xlfn.XLOOKUP(K10,[2]目录表!$H:$H,[2]目录表!$AJ:$AJ) -> 散货
B11: Modulo Ventilador Para Mazda 3 5 Ford Focus Fusion Escape | Meses sin interés | C11: 15 | D11: 47 | E11: 46041 | G11: 风扇散热器 | H11: 风扇散热器1137328464 | J11: Modulo Ventilador Para Mazda 3 5 Ford Focus Fusion Escape | K11: XQ5-QP001-1137328464 | L11: 4683662970 | M11: 新上架 | N11: =_xlfn.XLOOKUP(L11,数据更新表!J:J,数据更新表!K:K) -> -- | O11: =IFERROR(_xlfn.XLOOKUP(K11,数据更新表!A:A,数据更新表!B:B),"0") -> 30 | P11: =_xlfn.XLOOKUP(K11,[1]库销表!$F:$F,[1]库销表!$L:$L) -> 0 | Q11: =X11/W11 -> #DIV/0! | S11: =_xlfn.XLOOKUP(K11,数据更新表!R:R,数据更新表!S:S) -> #N/A | T11: =_xlfn.XLOOKUP(K11,数据更新表!V:V,数据更新表!W:W) -> #N/A | V11: =IFERROR(7*O11/CZ11,"0") -> 0 | W11: =CZ11/7 -> 0 | X11: =O11+P11+SUM(BN11:BR11) -> 30 | AF11: =SUM(AG11:BQ11) -> 30 | AK11: 30 | BS11: =_xlfn.XLOOKUP(K11,[1]库销表!$F:$F,[1]库销表!$L:$L) -> 0 | BT11: =SUM(BU11:CV11) -> 0 | CW11: =_xlfn.XLOOKUP(K11,[1]库销表!$F:$F,[1]库销表!$IE:$IE) -> 0 | CX11: =_xlfn.XLOOKUP(K11,[1]库销表!$F:$F,[1]库销表!$IF:$IF) -> 0 | CY11: =_xlfn.XLOOKUP(K11,[1]库销表!$F:$F,[1]库销表!$FL:$FL) -> 0 | CZ11: =_xlfn.XLOOKUP(K11,数据更新表!E:E,数据更新表!F:F,0) -> 0 | DA11: 0 | DB11: =_xlfn.XLOOKUP(K11,数据更新表!E:E,数据更新表!G:G) -> #N/A | DC11: =_xlfn.XLOOKUP(L11,数据更新表!Z:Z,数据更新表!AH:AH) -> 0 | DD11: =_xlfn.XLOOKUP(L11,数据更新表!Z:Z,数据更新表!AE:AE) -> 0 | DE11: =_xlfn.XLOOKUP(L11,数据更新表!Z:Z,数据更新表!AF:AF) -> 0 | DF11: =_xlfn.XLOOKUP(K11,数据更新表!Z:Z,数据更新表!AG:AG) -> #N/A | DG11: =_xlfn.XLOOKUP(L11,数据更新表!Z:Z,数据更新表!AD:AD) -> 3.64 | DH11: =_xlfn.XLOOKUP(L11,数据更新表!Z:Z,数据更新表!AA:AA) -> 1495 | DI11: =_xlfn.XLOOKUP(L11,数据更新表!Z:Z,数据更新表!AB:AB) -> 2 | DJ11: =_xlfn.XLOOKUP(L11,数据更新表!Z:Z,数据更新表!AC:AC) -> 0.00% | DK11: =_xlfn.XLOOKUP(L11,数据更新表!Z:Z,数据更新表!AI:AI) -> 0.00% | DL11: =_xlfn.XLOOKUP(L11,数据更新表!AL:AL,数据更新表!AM:AM) -> 0.00% | DM11: =_xlfn.XLOOKUP(L11,数据更新表!Z:Z,数据更新表!AJ:AJ) -> 0 | DN11: 6.6 | DO11: 开 | DP11: san re_1 | DQ11: 46084 | DU11: 没权重，等广告清货 | DY11: 469降288 | ED11: 调474 开广 | EE11: 288 | EF11: =EE11/0.7 -> 411.42857 | EG11: 51 | EH11: =EJ11/(EI11+EL11) -> 0.11275213 | EI11: =EG11*$EI$1 -> 133.11 | EJ11: =EE11-EI11-EL11-EO11-EN11-EP11-EQ11 -> 15.803 | EK11: =EJ11/EE11 -> 0.054871528 | EL11: =EX11*3000*$EI$1 -> 7.047 | EM11: =IF(EE11>299,"是","否") -> 否 | EN11: =EE11*0.05 -> 14.4 | EO11: =EE11*0.175 -> 50.4 | EP11: =IF(EE11<299,IF(EE11<99,25,IF(EE11<=149,30,IF(EE11<=299,37,85))),IF(EE11<=498,_xlfn.XLOOKUP(EW11,运费表!A:A,运费表!C:C,"重量超限",-1),_xlfn.XLOOKUP(EW11,运费表!A:A,运费表!D:D,"重量超限",-1))) -> 37 | EQ11: =EE11*0.105 -> 30.24 | ER11: =_xlfn.XLOOKUP(K11,[4]目录表!$H:$H,[4]目录表!$X:$X) -> 0.3 | ES11: =_xlfn.XLOOKUP(K11,[4]目录表!$H:$H,[4]目录表!$Y:$Y) -> 0 | ET11: =_xlfn.XLOOKUP(K11,[4]目录表!$H:$H,[4]目录表!$Z:$Z) -> 0 | EU11: =_xlfn.XLOOKUP(K11,[4]目录表!$H:$H,[4]目录表!$AA:$AA) -> 0 | EV11: =(50*30*30)/50/5000 -> 0.18 | EW11: =IF(EV11>=ER11,EV11,ER11) -> 0.3 | EX11: =_xlfn.XLOOKUP(K11,[2]目录表!$H:$H,[2]目录表!$AB:$AB) -> 0.0009 | EZ11: =CZ11/7 -> 0 | FK11: =_xlfn.XLOOKUP(K11,[2]目录表!$H:$H,[2]目录表!$AJ:$AJ) -> 散货
B12: Modulo Moto Ventilador Ford Edge 3.5l 2007 Al 2015 | Envío gratis | C12: 0 | D12: 5 | E12: 46038 | G12: 风扇散热器 | H12: 风扇散热器4M519A810AA | J12: Modulo Moto Ventilador Ford Edge 3.5l 2007 Al 2015 | K12: XQ5-QP002-4M519A810AA | L12: 4683845582 | M12: 新上架 | N12: =_xlfn.XLOOKUP(L12,数据更新表!J:J,数据更新表!K:K) -> -- | O12: =IFERROR(_xlfn.XLOOKUP(K12,数据更新表!A:A,数据更新表!B:B),"0") -> 30 | P12: =_xlfn.XLOOKUP(K12,[1]库销表!$F:$F,[1]库销表!$L:$L) -> 0 | Q12: =X12/W12 -> #DIV/0! | S12: =_xlfn.XLOOKUP(K12,数据更新表!R:R,数据更新表!S:S) -> #N/A | T12: =_xlfn.XLOOKUP(K12,数据更新表!V:V,数据更新表!W:W) -> #N/A | V12: =IFERROR(7*O12/CZ12,"0") -> 0 | W12: =CZ12/7 -> 0 | X12: =O12+P12+SUM(BN12:BR12) -> 30 | AF12: =SUM(AG12:BQ12) -> 30 | AK12: 30 | BS12: =_xlfn.XLOOKUP(K12,[1]库销表!$F:$F,[1]库销表!$L:$L) -> 0 | BT12: =SUM(BU12:CV12) -> 0 | CW12: =_xlfn.XLOOKUP(K12,[1]库销表!$F:$F,[1]库销表!$IE:$IE) -> 0 | CX12: =_xlfn.XLOOKUP(K12,[1]库销表!$F:$F,[1]库销表!$IF:$IF) -> 0 | CY12: =_xlfn.XLOOKUP(K12,[1]库销表!$F:$F,[1]库销表!$FL:$FL) -> 0 | CZ12: =_xlfn.XLOOKUP(K12,数据更新表!E:E,数据更新表!F:F,0) -> 0 | DA12: 0 | DB12: =_xlfn.XLOOKUP(K12,数据更新表!E:E,数据更新表!G:G) -> #N/A | DC12: =_xlfn.XLOOKUP(L12,数据更新表!Z:Z,数据更新表!AH:AH) -> 0 | DD12: =_xlfn.XLOOKUP(L12,数据更新表!Z:Z,数据更新表!AE:AE) -> 0 | DE12: =_xlfn.XLOOKUP(L12,数据更新表!Z:Z,数据更新表!AF:AF) -> 0 | DF12: =_xlfn.XLOOKUP(K12,数据更新表!Z:Z,数据更新表!AG:AG) -> #N/A | DG12: =_xlfn.XLOOKUP(L12,数据更新表!Z:Z,数据更新表!AD:AD) -> 2.32 | DH12: =_xlfn.XLOOKUP(L12,数据更新表!Z:Z,数据更新表!AA:AA) -> 1860 | DI12: =_xlfn.XLOOKUP(L12,数据更新表!Z:Z,数据更新表!AB:AB) -> 2 | DJ12: =_xlfn.XLOOKUP(L12,数据更新表!Z:Z,数据更新表!AC:AC) -> 0.00% | DK12: =_xlfn.XLOOKUP(L12,数据更新表!Z:Z,数据更新表!AI:AI) -> 0.00% | DL12: =_xlfn.XLOOKUP(L12,数据更新表!AL:AL,数据更新表!AM:AM) -> 0.00% | DM12: =_xlfn.XLOOKUP(L12,数据更新表!Z:Z,数据更新表!AJ:AJ) -> 0 | DN12: 6.6 | DO12: 开 | DP12: san re_1 | DQ12: 46084 | DU12: 没权重，等广告清货 | ED12: 调636 开广 | EE12: 238 | EF12: =EE12/0.7 -> 340 | EG12: 43 | EH12: =EJ12/(EI12+EL12) -> 0.026685782 | EI12: =EG12*$EI$1 -> 112.23 | EJ12: =EE12-EI12-EL12-EO12-EN12-EP12-EQ12 -> 3.183 | EK12: =EJ12/EE12 -> 0.01337395 | EL12: =EX12*3000*$EI$1 -> 7.047 | EM12: =IF(EE12>299,"是","否") -> 否 | EN12: =EE12*0.05 -> 11.9 | EO12: =EE12*0.175 -> 41.65 | EP12: =IF(EE12<299,IF(EE12<99,25,IF(EE12<=149,30,IF(EE12<=299,37,85))),IF(EE12<=498,_xlfn.XLOOKUP(EW12,运费表!A:A,运费表!C:C,"重量超限",-1),_xlfn.XLOOKUP(EW12,运费表!A:A,运费表!D:D,"重量超限",-1))) -> 37 | EQ12: =EE12*0.105 -> 24.99 | ER12: =_xlfn.XLOOKUP(K12,[4]目录表!$H:$H,[4]目录表!$X:$X) -> 0.34 | ES12: =_xlfn.XLOOKUP(K12,[4]目录表!$H:$H,[4]目录表!$Y:$Y) -> 0 | ET12: =_xlfn.XLOOKUP(K12,[4]目录表!$H:$H,[4]目录表!$Z:$Z) -> 0 | EU12: =_xlfn.XLOOKUP(K12,[4]目录表!$H:$H,[4]目录表!$AA:$AA) -> 0 | EV12: =(50*30*30)/50/5000 -> 0.18 | EW12: =IF(EV12>=ER12,EV12,ER12) -> 0.34 | EX12: =_xlfn.XLOOKUP(K12,[2]目录表!$H:$H,[2]目录表!$AB:$AB) -> 0.0009 | EZ12: =CZ12/7 -> 0 | FK12: =_xlfn.XLOOKUP(K12,[2]目录表!$H:$H,[2]目录表!$AJ:$AJ) -> 散货
B13: Modulo Control Ventilador Focus 2 Mazda 3 Volvo C30 S40 V50 | Envío gratis | C13: 1 | D13: 2 | E13: 46038 | G13: 风扇散热器 | H13: 风扇散热器1137328365 | J13: Modulo Control Ventilador Focus 2 Mazda 3 Volvo C30 S40 V50 | K13: XQ5-QP003-1137328365 | L13: 4683730910 | M13: 新上架 | N13: =_xlfn.XLOOKUP(L13,数据更新表!J:J,数据更新表!K:K) -> -- | O13: =IFERROR(_xlfn.XLOOKUP(K13,数据更新表!A:A,数据更新表!B:B),"0") -> 30 | P13: =_xlfn.XLOOKUP(K13,[1]库销表!$F:$F,[1]库销表!$L:$L) -> 0 | Q13: =X13/W13 -> #DIV/0! | S13: =_xlfn.XLOOKUP(K13,数据更新表!R:R,数据更新表!S:S) -> #N/A | T13: =_xlfn.XLOOKUP(K13,数据更新表!V:V,数据更新表!W:W) -> #N/A | V13: =IFERROR(7*O13/CZ13,"0") -> 0 | W13: =CZ13/7 -> 0 | X13: =O13+P13+SUM(BN13:BR13) -> 30 | AF13: =SUM(AG13:BQ13) -> 30 | AK13: 30 | BS13: =_xlfn.XLOOKUP(K13,[1]库销表!$F:$F,[1]库销表!$L:$L) -> 0 | BT13: =SUM(BU13:CV13) -> 0 | CW13: =_xlfn.XLOOKUP(K13,[1]库销表!$F:$F,[1]库销表!$IE:$IE) -> 0 | CX13: =_xlfn.XLOOKUP(K13,[1]库销表!$F:$F,[1]库销表!$IF:$IF) -> 0 | CY13: =_xlfn.XLOOKUP(K13,[1]库销表!$F:$F,[1]库销表!$FL:$FL) -> 0 | CZ13: =_xlfn.XLOOKUP(K13,数据更新表!E:E,数据更新表!F:F,0) -> 0 | DA13: 0 | DB13: =_xlfn.XLOOKUP(K13,数据更新表!E:E,数据更新表!G:G) -> #N/A | DC13: =_xlfn.XLOOKUP(L13,数据更新表!Z:Z,数据更新表!AH:AH) -> 0 | DD13: =_xlfn.XLOOKUP(L13,数据更新表!Z:Z,数据更新表!AE:AE) -> 0 | DE13: =_xlfn.XLOOKUP(L13,数据更新表!Z:Z,数据更新表!AF:AF) -> 0 | DF13: =_xlfn.XLOOKUP(K13,数据更新表!Z:Z,数据更新表!AG:AG) -> #N/A | DG13: =_xlfn.XLOOKUP(L13,数据更新表!Z:Z,数据更新表!AD:AD) -> 1.81 | DH13: =_xlfn.XLOOKUP(L13,数据更新表!Z:Z,数据更新表!AA:AA) -> 1595 | DI13: =_xlfn.XLOOKUP(L13,数据更新表!Z:Z,数据更新表!AB:AB) -> 1 | DJ13: =_xlfn.XLOOKUP(L13,数据更新表!Z:Z,数据更新表!AC:AC) -> 0.00% | DK13: =_xlfn.XLOOKUP(L13,数据更新表!Z:Z,数据更新表!AI:AI) -> 0.00% | DL13: =_xlfn.XLOOKUP(L13,数据更新表!AL:AL,数据更新表!AM:AM) -> 0.00% | DM13: =_xlfn.XLOOKUP(L13,数据更新表!Z:Z,数据更新表!AJ:AJ) -> 0 | DN13: 9.98 | DO13: 开 | DP13: fengshan-1 | DQ13: 46084 | DU13: 清货 | DV13: 400降369 | DY13: 400降369 | ED13: 调949 开广 | EE13: 369 | EF13: =EE13/0.7 -> 527.14286 | EG13: 57 | EH13: =EJ13/(EI13+EL13) -> 0.19484995 | EI13: =EG13*$EI$1 -> 148.77 | EJ13: =EE13-EI13-EL13-EO13-EN13-EP13-EQ13 -> 31.1848 | EK13: =EJ13/EE13 -> 0.084511653 | EL13: =EX13*3000*$EI$1 -> 11.2752 | EM13: =IF(EE13>299,"是","否") -> 是 | EN13: =EE13*0.05 -> 18.45 | EO13: =EE13*0.175 -> 64.575 | EP13: =IF(EE13<299,IF(EE13<99,25,IF(EE13<=149,30,IF(EE13<=299,37,85))),IF(EE13<=498,_xlfn.XLOOKUP(EW13,运费表!A:A,运费表!C:C,"重量超限",-1),_xlfn.XLOOKUP(EW13,运费表!A:A,运费表!D:D,"重量超限",-1))) -> 56 | EQ13: =EE13*0.105 -> 38.745 | ER13: =_xlfn.XLOOKUP(K13,[4]目录表!$H:$H,[4]目录表!$X:$X) -> 0.3 | ES13: =_xlfn.XLOOKUP(K13,[4]目录表!$H:$H,[4]目录表!$Y:$Y) -> 0 | ET13: =_xlfn.XLOOKUP(K13,[4]目录表!$H:$H,[4]目录表!$Z:$Z) -> 0 | EU13: =_xlfn.XLOOKUP(K13,[4]目录表!$H:$H,[4]目录表!$AA:$AA) -> 0 | EV13: =(50*30*30)/50/5000 -> 0.18 | EW13: =IF(EV13>=ER13,EV13,ER13) -> 0.3 | EX13: =_xlfn.XLOOKUP(K13,[2]目录表!$H:$H,[2]目录表!$AB:$AB) -> 0.00144 | EZ13: =CZ13/7 -> 0 | FK13: =_xlfn.XLOOKUP(K13,[2]目录表!$H:$H,[2]目录表!$AJ:$AJ) -> 散货
B14: Modulo Ventilador Ford Land Rover Jaguar Volvo S60 Xc60 | Envío gratis | C14: 2 | D14: 17 | E14: 46041 | G14: 风扇散热器 | H14: 风扇散热器940009402 | J14: Modulo Ventilador Ford Land Rover Jaguar Volvo S60 Xc60 | K14: XQ5-QP004-940009402 | L14: 4683874212 | M14: 新上架 | N14: =_xlfn.XLOOKUP(L14,数据更新表!J:J,数据更新表!K:K) -> 100 | O14: =IFERROR(_xlfn.XLOOKUP(K14,数据更新表!A:A,数据更新表!B:B),"0") -> 27 | P14: =_xlfn.XLOOKUP(K14,[1]库销表!$F:$F,[1]库销表!$L:$L) -> 0 | Q14: =X14/W14 -> 189 | S14: =_xlfn.XLOOKUP(K14,数据更新表!R:R,数据更新表!S:S) -> #N/A | T14: =_xlfn.XLOOKUP(K14,数据更新表!V:V,数据更新表!W:W) -> #N/A | V14: =IFERROR(7*O14/CZ14,"0") -> 189 | W14: =CZ14/7 -> 0.14285714 | X14: =O14+P14+SUM(BN14:BR14) -> 27 | AF14: =SUM(AG14:BQ14) -> 30 | AK14: 30 | BS14: =_xlfn.XLOOKUP(K14,[1]库销表!$F:$F,[1]库销表!$L:$L) -> 0 | BT14: =SUM(BU14:CV14) -> 0 | CW14: =_xlfn.XLOOKUP(K14,[1]库销表!$F:$F,[1]库销表!$IE:$IE) -> 0 | CX14: =_xlfn.XLOOKUP(K14,[1]库销表!$F:$F,[1]库销表!$IF:$IF) -> 0 | CY14: =_xlfn.XLOOKUP(K14,[1]库销表!$F:$F,[1]库销表!$FL:$FL) -> 0 | CZ14: =_xlfn.XLOOKUP(K14,数据更新表!E:E,数据更新表!F:F,0) -> 1 | DA14: 1 | DB14: =_xlfn.XLOOKUP(K14,数据更新表!E:E,数据更新表!G:G) -> 0 | DC14: =_xlfn.XLOOKUP(L14,数据更新表!Z:Z,数据更新表!AH:AH) -> 0 | DD14: =_xlfn.XLOOKUP(L14,数据更新表!Z:Z,数据更新表!AE:AE) -> 1 | DE14: =_xlfn.XLOOKUP(L14,数据更新表!Z:Z,数据更新表!AF:AF) -> 1 | DF14: =_xlfn.XLOOKUP(K14,数据更新表!Z:Z,数据更新表!AG:AG) -> #N/A | DG14: =_xlfn.XLOOKUP(L14,数据更新表!Z:Z,数据更新表!AD:AD) -> 62.28 | DH14: =_xlfn.XLOOKUP(L14,数据更新表!Z:Z,数据更新表!AA:AA) -> 1120 | DI14: =_xlfn.XLOOKUP(L14,数据更新表!Z:Z,数据更新表!AB:AB) -> 14 | DJ14: =_xlfn.XLOOKUP(L14,数据更新表!Z:Z,数据更新表!AC:AC) -> 12.28% | DK14: =_xlfn.XLOOKUP(L14,数据更新表!Z:Z,数据更新表!AI:AI) -> 12.28% | DL14: =_xlfn.XLOOKUP(L14,数据更新表!AL:AL,数据更新表!AM:AM) -> 3.84% | DM14: =_xlfn.XLOOKUP(L14,数据更新表!Z:Z,数据更新表!AJ:AJ) -> 8.14 | DN14: 9.98 | DO14: 开 | DP14: fengshan-1 | DQ14: 46084 | ED14: 调507 开广 | EE14: =_xlfn.XLOOKUP(L14,数据更新表!J:J,数据更新表!L:L) -> 507 | EF14: =EE14/0.7 -> 724.28571 | EG14: 65 | EH14: =EJ14/(EI14+EL14) -> 0.52628511 | EI14: =EG14*$EI$1 -> 169.65 | EJ14: =EE14-EI14-EL14-EO14-EN14-EP14-EQ14 -> 92.993 | EK14: =EJ14/EE14 -> 0.18341815 | EL14: =EX14*3000*$EI$1 -> 7.047 | EM14: =IF(EE14>299,"是","否") -> 是 | EN14: =EE14*0.05 -> 25.35 | EO14: =EE14*0.175 -> 88.725 | EP14: =IF(EE14<299,IF(EE14<99,25,IF(EE14<=149,30,IF(EE14<=299,37,85))),IF(EE14<=498,_xlfn.XLOOKUP(EW14,运费表!A:A,运费表!C:C,"重量超限",-1),_xlfn.XLOOKUP(EW14,运费表!A:A,运费表!D:D,"重量超限",-1))) -> 70 | EQ14: =EE14*0.105 -> 53.235 | ER14: =_xlfn.XLOOKUP(K14,[4]目录表!$H:$H,[4]目录表!$X:$X) -> 0.38 | ES14: =_xlfn.XLOOKUP(K14,[4]目录表!$H:$H,[4]目录表!$Y:$Y) -> 0 | ET14: =_xlfn.XLOOKUP(K14,[4]目录表!$H:$H,[4]目录表!$Z:$Z) -> 0 | EU14: =_xlfn.XLOOKUP(K14,[4]目录表!$H:$H,[4]目录表!$AA:$AA) -> 0 | EV14: =(50*30*30)/50/5000 -> 0.18 | EW14: =IF(EV14>=ER14,EV14,ER14) -> 0.38 | EX14: =_xlfn.XLOOKUP(K14,[2]目录表!$H:$H,[2]目录表!$AB:$AB) -> 0.0009 | EZ14: =CZ14/7 -> 0.14285714 | FK14: =_xlfn.XLOOKUP(K14,[2]目录表!$H:$H,[2]目录表!$AJ:$AJ) -> 散货
B15: Módulo Ventilador Ford Fusion Lincoln Mkz 3.5 2010 2011 2012 | Envío gratis | C15: 0 | D15: 4 | E15: 46038 | G15: 风扇散热器 | H15: 风扇散热器1137328617 | J15: Módulo Ventilador Ford Fusion Lincoln Mkz 3.5 2010 2011 2012 | K15: XQ5-QP005-1137328617 | L15: 4683876182 | M15: 新上架 | N15: =_xlfn.XLOOKUP(L15,数据更新表!J:J,数据更新表!K:K) -> -- | O15: =IFERROR(_xlfn.XLOOKUP(K15,数据更新表!A:A,数据更新表!B:B),"0") -> 19 | P15: =_xlfn.XLOOKUP(K15,[1]库销表!$F:$F,[1]库销表!$L:$L) -> 0 | Q15: =X15/W15 -> #DIV/0! | S15: =_xlfn.XLOOKUP(K15,数据更新表!R:R,数据更新表!S:S) -> #N/A | T15: =_xlfn.XLOOKUP(K15,数据更新表!V:V,数据更新表!W:W) -> #N/A | V15: =IFERROR(7*O15/CZ15,"0") -> 0 | W15: =CZ15/7 -> 0 | X15: =O15+P15+SUM(BN15:BR15) -> 19 | AF15: =SUM(AG15:BQ15) -> 19 | AK15: 19 | BS15: =_xlfn.XLOOKUP(K15,[1]库销表!$F:$F,[1]库销表!$L:$L) -> 0 | BT15: =SUM(BU15:CV15) -> 0 | CW15: =_xlfn.XLOOKUP(K15,[1]库销表!$F:$F,[1]库销表!$IE:$IE) -> 0 | CX15: =_xlfn.XLOOKUP(K15,[1]库销表!$F:$F,[1]库销表!$IF:$IF) -> 0 | CY15: =_xlfn.XLOOKUP(K15,[1]库销表!$F:$F,[1]库销表!$FL:$FL) -> 0 | CZ15: =_xlfn.XLOOKUP(K15,数据更新表!E:E,数据更新表!F:F,0) -> 0 | DA15: 0 | DB15: =_xlfn.XLOOKUP(K15,数据更新表!E:E,数据更新表!G:G) -> #N/A | DC15: =_xlfn.XLOOKUP(L15,数据更新表!Z:Z,数据更新表!AH:AH) -> 0 | DD15: =_xlfn.XLOOKUP(L15,数据更新表!Z:Z,数据更新表!AE:AE) -> 0 | DE15: =_xlfn.XLOOKUP(L15,数据更新表!Z:Z,数据更新表!AF:AF) -> 0 | DF15: =_xlfn.XLOOKUP(K15,数据更新表!Z:Z,数据更新表!AG:AG) -> #N/A | DG15: =_xlfn.XLOOKUP(L15,数据更新表!Z:Z,数据更新表!AD:AD) -> 0 | DH15: =_xlfn.XLOOKUP(L15,数据更新表!Z:Z,数据更新表!AA:AA) -> 1448 | DI15: =_xlfn.XLOOKUP(L15,数据更新表!Z:Z,数据更新表!AB:AB) -> 0 | DJ15: =_xlfn.XLOOKUP(L15,数据更新表!Z:Z,数据更新表!AC:AC) -> 0.00% | DK15: =_xlfn.XLOOKUP(L15,数据更新表!Z:Z,数据更新表!AI:AI) -> 0.00% | DL15: =_xlfn.XLOOKUP(L15,数据更新表!AL:AL,数据更新表!AM:AM) -> 0.00% | DM15: =_xlfn.XLOOKUP(L15,数据更新表!Z:Z,数据更新表!AJ:AJ) -> 0 | DN15: 9.98 | DO15: 开 | DP15: fengshan-1 | DQ15: 46084 | DU15: 没毛利，最低价215，上榜379 | ED15: 调559 开广 | EE15: 199 | EF15: =EE15/0.7 -> 284.28571 | EG15: 85 | EH15: =EJ15/(EI15+EL15) -> -0.57915569 | EI15: =EG15*$EI$1 -> 221.85 | EJ15: =EE15-EI15-EL15-EO15-EN15-EP15-EQ15 -> -132.567 | EK15: =EJ15/EE15 -> -0.66616583 | EL15: =EX15*3000*$EI$1 -> 7.047 | EM15: =IF(EE15>299,"是","否") -> 否 | EN15: =EE15*0.05 -> 9.95 | EO15: =EE15*0.175 -> 34.825 | EP15: =IF(EE15<299,IF(EE15<99,25,IF(EE15<=149,30,IF(EE15<=299,37,85))),IF(EE15<=498,_xlfn.XLOOKUP(EW15,运费表!A:A,运费表!C:C,"重量超限",-1),_xlfn.XLOOKUP(EW15,运费表!A:A,运费表!D:D,"重量超限",-1))) -> 37 | EQ15: =EE15*0.105 -> 20.895 | ER15: =_xlfn.XLOOKUP(K15,[4]目录表!$H:$H,[4]目录表!$X:$X) -> 0.46 | ES15: =_xlfn.XLOOKUP(K15,[4]目录表!$H:$H,[4]目录表!$Y:$Y) -> 0 | ET15: =_xlfn.XLOOKUP(K15,[4]目录表!$H:$H,[4]目录表!$Z:$Z) -> 0 | EU15: =_xlfn.XLOOKUP(K15,[4]目录表!$H:$H,[4]目录表!$AA:$AA) -> 0 | EV15: =(50*30*30)/50/5000 -> 0.18 | EW15: =IF(EV15>=ER15,EV15,ER15) -> 0.46 | EX15: =_xlfn.XLOOKUP(K15,[2]目录表!$H:$H,[2]目录表!$AB:$AB) -> 0.0009 | EZ15: =CZ15/7 -> 0 | FK15: =_xlfn.XLOOKUP(K15,[2]目录表!$H:$H,[2]目录表!$AJ:$AJ) -> 散货
B16: https://articulo.mercadolibre.com.mx/MLM-3117809716-alternador-chevrolet-aveo-15-85a-2018-2019-2020-2021-2022-_JM#polycard_client=search_best-seller&tracking_id=308eb0f8-3e9c-40b5-988b-e5fca241b761 | C16: 11 | D16: 23 | E16: 45943 | G16: 交流发电机 | H16: 交流发电机A1137 | J16: Alternador Chevrolet Aveo 1.5 85a 2018 2019 2020 2021 2022 | K16: XQ5-QP023-A1137 | M16: 未上架 | N16: =_xlfn.XLOOKUP(L16,数据更新表!J:J,数据更新表!K:K) -> 0 | O16: =IFERROR(_xlfn.XLOOKUP(K16,数据更新表!A:A,数据更新表!B:B),"0") -> 0 | P16: =_xlfn.XLOOKUP(K16,[1]库销表!$F:$F,[1]库销表!$L:$L) -> 0 | Q16: =X16/W16 -> #DIV/0! | S16: =_xlfn.XLOOKUP(K16,数据更新表!R:R,数据更新表!S:S) -> #N/A | T16: =_xlfn.XLOOKUP(K16,数据更新表!V:V,数据更新表!W:W) -> #N/A | V16: =IFERROR(7*O16/CZ16,"0") -> 0 | W16: =CZ16/7 -> 0 | X16: =O16+P16+SUM(BN16:BR16) -> 0 | AF16: =SUM(AG16:BQ16) -> 0 | BS16: =_xlfn.XLOOKUP(K16,[1]库销表!$F:$F,[1]库销表!$L:$L) -> 0 | BT16: =SUM(BU16:CV16) -> 0 | CW16: =_xlfn.XLOOKUP(K16,[1]库销表!$F:$F,[1]库销表!$IE:$IE) -> 0 | CX16: =_xlfn.XLOOKUP(K16,[1]库销表!$F:$F,[1]库销表!$IF:$IF) -> 0 | CY16: =_xlfn.XLOOKUP(K16,[1]库销表!$F:$F,[1]库销表!$FL:$FL) -> 0 | CZ16: =_xlfn.XLOOKUP(K16,数据更新表!E:E,数据更新表!F:F,0) -> 0 | DA16: 0 | DB16: =_xlfn.XLOOKUP(K16,数据更新表!E:E,数据更新表!G:G) -> #N/A | DC16: =_xlfn.XLOOKUP(L16,数据更新表!Z:Z,数据更新表!AH:AH) -> 0 | DD16: =_xlfn.XLOOKUP(L16,数据更新表!Z:Z,数据更新表!AE:AE) -> 0 | DE16: =_xlfn.XLOOKUP(L16,数据更新表!Z:Z,数据更新表!AF:AF) -> 0 | DF16: =_xlfn.XLOOKUP(K16,数据更新表!Z:Z,数据更新表!AG:AG) -> #N/A | DG16: =_xlfn.XLOOKUP(L16,数据更新表!Z:Z,数据更新表!AD:AD) -> 0 | DH16: =_xlfn.XLOOKUP(L16,数据更新表!Z:Z,数据更新表!AA:AA) -> 0 | DI16: =_xlfn.XLOOKUP(L16,数据更新表!Z:Z,数据更新表!AB:AB) -> 0 | DJ16: =_xlfn.XLOOKUP(L16,数据更新表!Z:Z,数据更新表!AC:AC) -> 0 | DK16: =_xlfn.XLOOKUP(L16,数据更新表!Z:Z,数据更新表!AI:AI) -> 0 | DL16: =_xlfn.XLOOKUP(L16,数据更新表!AL:AL,数据更新表!AM:AM) -> 0 | DM16: =_xlfn.XLOOKUP(L16,数据更新表!Z:Z,数据更新表!AJ:AJ) -> 0 | EE16: =_xlfn.XLOOKUP(L16,数据更新表!J:J,数据更新表!L:L) -> 0 | EF16: =_xlfn.XLOOKUP(L16,数据更新表!J:J,数据更新表!M:M) -> 0 | EG16: 265 | EH16: =EJ16/(EI16+EL16) -> -1.0321104 | EI16: =EG16*$EI$1 -> 691.65 | EJ16: =EE16-EI16-EL16-EO16-EN16-EP16-EQ16 -> -803.563 | EK16: =EJ16/EE16 -> #DIV/0! | EL16: =EX16*3000*$EI$1 -> 86.913 | EM16: =IF(EE16>299,"是","否") -> 否 | EN16: =EE16*0.05 -> 0 | EO16: =EE16*0.175 -> 0 | EP16: =IF(EE16<299,IF(EE16<99,25,IF(EE16<=149,30,IF(EE16<=299,37,85))),IF(EE16<=498,_xlfn.XLOOKUP(EW16,运费表!A:A,运费表!C:C,"重量超限",-1),_xlfn.XLOOKUP(EW16,运费表!A:A,运费表!D:D,"重量超限",-1))) -> 25 | EQ16: =EE16*0.105 -> 0 | ER16: =_xlfn.XLOOKUP(K16,[4]目录表!$H:$H,[4]目录表!$X:$X) -> 6.55 | ES16: =_xlfn.XLOOKUP(K16,[4]目录表!$H:$H,[4]目录表!$Y:$Y) -> 25 | ET16: =_xlfn.XLOOKUP(K16,[4]目录表!$H:$H,[4]目录表!$Z:$Z) -> 24 | EU16: =_xlfn.XLOOKUP(K16,[4]目录表!$H:$H,[4]目录表!$AA:$AA) -> 18.5 | EV16: =ES16*ET16*EU16/5000 -> 2.22 | EW16: =IF(EV16>=ER16,EV16,ER16) -> 6.55 | EX16: =_xlfn.XLOOKUP(K16,[2]目录表!$H:$H,[2]目录表!$AB:$AB) -> 0.0111 | EZ16: =CZ16/7 -> 0 | FK16: =_xlfn.XLOOKUP(K16,[2]目录表!$H:$H,[2]目录表!$AJ:$AJ) -> 散货
B17: https://www.mercadolibre.com.mx/alternador-para-fiat-uno-mobi-500-092023-ram-rapid-1723/up/MLMU458091911#polycard_client=search_best-seller&tracking_id=c00fdf92-bf20-49d5-890d-57c15933cb7e&wid=MLM3311433164&sid=search | C17: 13 | D17: 30 | E17: 45943 | G17: 交流发电机 | H17: 交流发电机101210-1650 | J17: Alternador Para Fiat Uno, Mobi, 500 09-2023, Ram Rapid 17-23 | K17: XQ5-QP024-101210-1650 | M17: 未上架 | N17: =_xlfn.XLOOKUP(L17,数据更新表!J:J,数据更新表!K:K) -> 0 | O17: =IFERROR(_xlfn.XLOOKUP(K17,数据更新表!A:A,数据更新表!B:B),"0") -> 0 | P17: =_xlfn.XLOOKUP(K17,[1]库销表!$F:$F,[1]库销表!$L:$L) -> 0 | Q17: =X17/W17 -> #DIV/0! | S17: =_xlfn.XLOOKUP(K17,数据更新表!R:R,数据更新表!S:S) -> #N/A | T17: =_xlfn.XLOOKUP(K17,数据更新表!V:V,数据更新表!W:W) -> #N/A | V17: =IFERROR(7*O17/CZ17,"0") -> 0 | W17: =CZ17/7 -> 0 | X17: =O17+P17+SUM(BN17:BR17) -> 0 | AF17: =SUM(AG17:BQ17) -> 0 | BS17: =_xlfn.XLOOKUP(K17,[1]库销表!$F:$F,[1]库销表!$L:$L) -> 0 | BT17: =SUM(BU17:CV17) -> 0 | CW17: =_xlfn.XLOOKUP(K17,[1]库销表!$F:$F,[1]库销表!$IE:$IE) -> 0 | CX17: =_xlfn.XLOOKUP(K17,[1]库销表!$F:$F,[1]库销表!$IF:$IF) -> 0 | CY17: =_xlfn.XLOOKUP(K17,[1]库销表!$F:$F,[1]库销表!$FL:$FL) -> 0 | CZ17: =_xlfn.XLOOKUP(K17,数据更新表!E:E,数据更新表!F:F,0) -> 0 | DA17: 0 | DB17: =_xlfn.XLOOKUP(K17,数据更新表!E:E,数据更新表!G:G) -> #N/A | DC17: =_xlfn.XLOOKUP(L17,数据更新表!Z:Z,数据更新表!AH:AH) -> 0 | DD17: =_xlfn.XLOOKUP(L17,数据更新表!Z:Z,数据更新表!AE:AE) -> 0 | DE17: =_xlfn.XLOOKUP(L17,数据更新表!Z:Z,数据更新表!AF:AF) -> 0 | DF17: =_xlfn.XLOOKUP(K17,数据更新表!Z:Z,数据更新表!AG:AG) -> #N/A | DG17: =_xlfn.XLOOKUP(L17,数据更新表!Z:Z,数据更新表!AD:AD) -> 0 | DH17: =_xlfn.XLOOKUP(L17,数据更新表!Z:Z,数据更新表!AA:AA) -> 0 | DI17: =_xlfn.XLOOKUP(L17,数据更新表!Z:Z,数据更新表!AB:AB) -> 0 | DJ17: =_xlfn.XLOOKUP(L17,数据更新表!Z:Z,数据更新表!AC:AC) -> 0 | DK17: =_xlfn.XLOOKUP(L17,数据更新表!Z:Z,数据更新表!AI:AI) -> 0 | DL17: =_xlfn.XLOOKUP(L17,数据更新表!AL:AL,数据更新表!AM:AM) -> 0 | DM17: =_xlfn.XLOOKUP(L17,数据更新表!Z:Z,数据更新表!AJ:AJ) -> 0 | EE17: =_xlfn.XLOOKUP(L17,数据更新表!J:J,数据更新表!L:L) -> 0 | EF17: =_xlfn.XLOOKUP(L17,数据更新表!J:J,数据更新表!M:M) -> 0 | EG17: 265 | EH17: =EJ17/(EI17+EL17) -> -1.0321104 | EI17: =EG17*$EI$1 -> 691.65 | EJ17: =EE17-EI17-EL17-EO17-EN17-EP17-EQ17 -> -803.563 | EK17: =EJ17/EE17 -> #DIV/0! | EL17: =EX17*3000*$EI$1 -> 86.913 | EM17: =IF(EE17>299,"是","否") -> 否 | EN17: =EE17*0.05 -> 0 | EO17: =EE17*0.175 -> 0 | EP17: =IF(EE17<299,IF(EE17<99,25,IF(EE17<=149,30,IF(EE17<=299,37,85))),IF(EE17<=498,_xlfn.XLOOKUP(EW17,运费表!A:A,运费表!C:C,"重量超限",-1),_xlfn.XLOOKUP(EW17,运费表!A:A,运费表!D:D,"重量超限",-1))) -> 25 | EQ17: =EE17*0.105 -> 0 | ER17: =_xlfn.XLOOKUP(K17,[4]目录表!$H:$H,[4]目录表!$X:$X) -> 7.5 | ES17: =_xlfn.XLOOKUP(K17,[4]目录表!$H:$H,[4]目录表!$Y:$Y) -> 25 | ET17: =_xlfn.XLOOKUP(K17,[4]目录表!$H:$H,[4]目录表!$Z:$Z) -> 24 | EU17: =_xlfn.XLOOKUP(K17,[4]目录表!$H:$H,[4]目录表!$AA:$AA) -> 18.5 | EV17: =ES17*ET17*EU17/5000 -> 2.22 | EW17: =IF(EV17>=ER17,EV17,ER17) -> 7.5 | EX17: =_xlfn.XLOOKUP(K17,[2]目录表!$H:$H,[2]目录表!$AB:$AB) -> 0.0111 | EZ17: =CZ17/7 -> 0 | FK17: =_xlfn.XLOOKUP(K17,[2]目录表!$H:$H,[2]目录表!$AJ:$AJ) -> 散货
B18: Muelle Reloj Para Nissan Np300 Navara D23 2.5lts 2016-2020 | Meses sin interés | C18: 15 | D18: 38 | E18: 46044 | G18: 气囊游丝 | H18: 气囊游丝25554-3TS0A | J18: Muelle Reloj Para Nissan Np300 Navara D23 2.5lts 2016-2020 | K18: XQ5-QP020-25554-3TS0A | L18: 2705951099 | M18: 新上架 | N18: =_xlfn.XLOOKUP(L18,数据更新表!J:J,数据更新表!K:K) -> -- | O18: =IFERROR(_xlfn.XLOOKUP(K18,数据更新表!A:A,数据更新表!B:B),"0") -> 49 | P18: =_xlfn.XLOOKUP(K18,[1]库销表!$F:$F,[1]库销表!$L:$L) -> 0 | Q18: =X18/W18 -> 343 | S18: =_xlfn.XLOOKUP(K18,数据更新表!R:R,数据更新表!S:S) -> #N/A | T18: =_xlfn.XLOOKUP(K18,数据更新表!V:V,数据更新表!W:W) -> #N/A | V18: =IFERROR(7*O18/CZ18,"0") -> 343 | W18: =CZ18/7 -> 0.14285714 | X18: =O18+P18+SUM(BN18:BR18) -> 49 | AF18: =SUM(AG18:BQ18) -> 50 | AI18: 50 | BS18: =_xlfn.XLOOKUP(K18,[1]库销表!$F:$F,[1]库销表!$L:$L) -> 0 | BT18: =SUM(BU18:CV18) -> 0 | CW18: =_xlfn.XLOOKUP(K18,[1]库销表!$F:$F,[1]库销表!$IE:$IE) -> 0 | CX18: =_xlfn.XLOOKUP(K18,[1]库销表!$F:$F,[1]库销表!$IF:$IF) -> 0 | CY18: =_xlfn.XLOOKUP(K18,[1]库销表!$F:$F,[1]库销表!$FL:$FL) -> 0 | CZ18: =_xlfn.XLOOKUP(K18,数据更新表!E:E,数据更新表!F:F,0) -> 1 | DA18: 0 | DB18: =_xlfn.XLOOKUP(K18,数据更新表!E:E,数据更新表!G:G) -> 1 | DC18: =_xlfn.XLOOKUP(L18,数据更新表!Z:Z,数据更新表!AH:AH) -> 1 | DD18: =_xlfn.XLOOKUP(L18,数据更新表!Z:Z,数据更新表!AE:AE) -> 0 | DE18: =_xlfn.XLOOKUP(L18,数据更新表!Z:Z,数据更新表!AF:AF) -> 0 | DF18: =_xlfn.XLOOKUP(K18,数据更新表!Z:Z,数据更新表!AG:AG) -> #N/A | DG18: =_xlfn.XLOOKUP(L18,数据更新表!Z:Z,数据更新表!AD:AD) -> 0 | DH18: =_xlfn.XLOOKUP(L18,数据更新表!Z:Z,数据更新表!AA:AA) -> 511 | DI18: =_xlfn.XLOOKUP(L18,数据更新表!Z:Z,数据更新表!AB:AB) -> 0 | DJ18: =_xlfn.XLOOKUP(L18,数据更新表!Z:Z,数据更新表!AC:AC) -> 0.00% | DK18: =_xlfn.XLOOKUP(L18,数据更新表!Z:Z,数据更新表!AI:AI) -> 0.00% | DL18: =_xlfn.XLOOKUP(L18,数据更新表!AL:AL,数据更新表!AM:AM) -> 0.05% | DM18: =_xlfn.XLOOKUP(L18,数据更新表!Z:Z,数据更新表!AJ:AJ) -> 0 | DN18: 6.6 | DO18: 开 | DP18: qi nang_5 | DQ18: 46084 | ED18: 调394 开广 | EE18: 298 | EF18: =EE18/0.7 -> 425.71429 | EG18: 26 | EH18: =EJ18/(EI18+EL18) -> 1.0784772 | EI18: =EG18*$EI$1 -> 67.86 | EJ18: =EE18-EI18-EL18-EO18-EN18-EP18-EQ18 -> 84.400781 | EK18: =EJ18/EE18 -> 0.2832241 | EL18: =EX18*3000*$EI$1 -> 10.399219 | EM18: =IF(EE18>299,"是","否") -> 否 | EN18: =EE18*0.05 -> 14.9 | EO18: =EE18*0.175 -> 52.15 | EP18: =IF(EE18<299,IF(EE18<99,25,IF(EE18<=149,30,IF(EE18<=299,37,85))),IF(EE18<=498,_xlfn.XLOOKUP(EW18,运费表!A:A,运费表!C:C,"重量超限",-1),_xlfn.XLOOKUP(EW18,运费表!A:A,运费表!D:D,"重量超限",-1))) -> 37 | EQ18: =EE18*0.105 -> 31.29 | ER18: =_xlfn.XLOOKUP(K18,[4]目录表!$H:$H,[4]目录表!$X:$X) -> 0.18 | ES18: =_xlfn.XLOOKUP(K18,[4]目录表!$H:$H,[4]目录表!$Y:$Y) -> 12.5 | ET18: =_xlfn.XLOOKUP(K18,[4]目录表!$H:$H,[4]目录表!$Z:$Z) -> 12.5 | EU18: =_xlfn.XLOOKUP(K18,[4]目录表!$H:$H,[4]目录表!$AA:$AA) -> 8.5 | EV18: =ES18*ET18*EU18/5000 -> 0.265625 | EW18: =IF(EV18>=ER18,EV18,ER18) -> 0.265625 | EX18: =_xlfn.XLOOKUP(K18,[2]目录表!$H:$H,[2]目录表!$AB:$AB) -> 0.001328125 | EZ18: =CZ18/7 -> 0.14285714 | FK18: =_xlfn.XLOOKUP(K18,[2]目录表!$H:$H,[2]目录表!$AJ:$AJ) -> 散货
B19: Resorte Reloj 84306-22010 Para 2006-2014 Toyota Yaris | Envío gratis | C19: 5 | D19: 22 | E19: 46044 | G19: 气囊游丝 | H19: 气囊游丝84306-22010 | J19: Resorte Reloj 84306-22010 Para 2006-2014 Toyota Yaris | K19: XQ5-QP021-84306-22010 | L19: 2705860671 | M19: 新上架 | N19: =_xlfn.XLOOKUP(L19,数据更新表!J:J,数据更新表!K:K) -> #N/A | O19: =IFERROR(_xlfn.XLOOKUP(K19,数据更新表!A:A,数据更新表!B:B),"0") -> 50 | P19: =_xlfn.XLOOKUP(K19,[1]库销表!$F:$F,[1]库销表!$L:$L) -> 0 | Q19: =X19/W19 -> #DIV/0! | S19: =_xlfn.XLOOKUP(K19,数据更新表!R:R,数据更新表!S:S) -> #N/A | T19: =_xlfn.XLOOKUP(K19,数据更新表!V:V,数据更新表!W:W) -> #N/A | V19: =IFERROR(7*O19/CZ19,"0") -> 0 | W19: =CZ19/7 -> 0 | X19: =O19+P19+SUM(BN19:BR19) -> 50 | AF19: =SUM(AG19:BQ19) -> 50 | AI19: 50 | BS19: =_xlfn.XLOOKUP(K19,[1]库销表!$F:$F,[1]库销表!$L:$L) -> 0 | BT19: =SUM(BU19:CV19) -> 0 | CW19: =_xlfn.XLOOKUP(K19,[1]库销表!$F:$F,[1]库销表!$IE:$IE) -> 0 | CX19: =_xlfn.XLOOKUP(K19,[1]库销表!$F:$F,[1]库销表!$IF:$IF) -> 0 | CY19: =_xlfn.XLOOKUP(K19,[1]库销表!$F:$F,[1]库销表!$FL:$FL) -> 0 | CZ19: =_xlfn.XLOOKUP(K19,数据更新表!E:E,数据更新表!F:F,0) -> 0 | DA19: 0 | DB19: =_xlfn.XLOOKUP(K19,数据更新表!E:E,数据更新表!G:G) -> #N/A | DC19: =_xlfn.XLOOKUP(L19,数据更新表!Z:Z,数据更新表!AH:AH) -> #N/A | DD19: =_xlfn.XLOOKUP(L19,数据更新表!Z:Z,数据更新表!AE:AE) -> #N/A | DE19: =_xlfn.XLOOKUP(L19,数据更新表!Z:Z,数据更新表!AF:AF) -> #N/A | DF19: =_xlfn.XLOOKUP(K19,数据更新表!Z:Z,数据更新表!AG:AG) -> #N/A | DG19: =_xlfn.XLOOKUP(L19,数据更新表!Z:Z,数据更新表!AD:AD) -> #N/A | DH19: =_xlfn.XLOOKUP(L19,数据更新表!Z:Z,数据更新表!AA:AA) -> #N/A | DI19: =_xlfn.XLOOKUP(L19,数据更新表!Z:Z,数据更新表!AB:AB) -> #N/A | DJ19: =_xlfn.XLOOKUP(L19,数据更新表!Z:Z,数据更新表!AC:AC) -> #N/A | DK19: =_xlfn.XLOOKUP(L19,数据更新表!Z:Z,数据更新表!AI:AI) -> #N/A | DL19: =_xlfn.XLOOKUP(L19,数据更新表!AL:AL,数据更新表!AM:AM) -> 0.00% | DM19: =_xlfn.XLOOKUP(L19,数据更新表!Z:Z,数据更新表!AJ:AJ) -> #N/A | DN19: 6.6 | DO19: 开 | DP19: qi nang_5 | DQ19: 46084 | ED19: 调415 开广 | EE19: 149 | EF19: =EE19/0.7 -> 212.85714 | EG19: 16 | EH19: =EJ19/(EI19+EL19) -> 0.33878539 | EI19: =EG19*$EI$1 -> 41.76 | EJ19: =EE19-EI19-EL19-EO19-EN19-EP19-EQ19 -> 17.670781 | EK19: =EJ19/EE19 -> 0.11859585 | EL19: =EX19*3000*$EI$1 -> 10.399219 | EM19: =IF(EE19>299,"是","否") -> 否 | EN19: =EE19*0.05 -> 7.45 | EO19: =EE19*0.175 -> 26.075 | EP19: =IF(EE19<299,IF(EE19<99,25,IF(EE19<=149,30,IF(EE19<=299,37,85))),IF(EE19<=498,_xlfn.XLOOKUP(EW19,运费表!A:A,运费表!C:C,"重量超限",-1),_xlfn.XLOOKUP(EW19,运费表!A:A,运费表!D:D,"重量超限",-1))) -> 30 | EQ19: =EE19*0.105 -> 15.645 | ER19: =_xlfn.XLOOKUP(K19,[4]目录表!$H:$H,[4]目录表!$X:$X) -> 0.18 | ES19: =_xlfn.XLOOKUP(K19,[4]目录表!$H:$H,[4]目录表!$Y:$Y) -> 12.5 | ET19: =_xlfn.XLOOKUP(K19,[4]目录表!$H:$H,[4]目录表!$Z:$Z) -> 12.5 | EU19: =_xlfn.XLOOKUP(K19,[4]目录表!$H:$H,[4]目录表!$AA:$AA) -> 8.5 | EV19: =ES19*ET19*EU19/5000 -> 0.265625 | EW19: =IF(EV19>=ER19,EV19,ER19) -> 0.265625 | EX19: =_xlfn.XLOOKUP(K19,[2]目录表!$H:$H,[2]目录表!$AB:$AB) -> 0.001328125 | EZ19: =CZ19/7 -> 0 | FK19: =_xlfn.XLOOKUP(K19,[2]目录表!$H:$H,[2]目录表!$AJ:$AJ) -> 散货
B20: Espiral Reloj Pista Carrete Mazda 3 2004 2005 2006 2007 2008 | Envío gratis | C20: 0 | D20: 3 | E20: 46045 | G20: 气囊游丝 | H20: 气囊游丝BP4K-66-CS0 | J20: Espiral Reloj Pista Carrete Mazda 3 2004 2005 2006 2007 2008 | K20: XQ5-QP022-BP4K-66-CS0 | L20: 4700259114 | M20: 新上架 | N20: =_xlfn.XLOOKUP(L20,数据更新表!J:J,数据更新表!K:K) -> 100 | O20: =IFERROR(_xlfn.XLOOKUP(K20,数据更新表!A:A,数据更新表!B:B),"0") -> 49 | P20: =_xlfn.XLOOKUP(K20,[1]库销表!$F:$F,[1]库销表!$L:$L) -> 0 | Q20: =X20/W20 -> 343 | S20: =_xlfn.XLOOKUP(K20,数据更新表!R:R,数据更新表!S:S) -> #N/A | T20: =_xlfn.XLOOKUP(K20,数据更新表!V:V,数据更新表!W:W) -> #N/A | V20: =IFERROR(7*O20/CZ20,"0") -> 343 | W20: =CZ20/7 -> 0.14285714 | X20: =O20+P20+SUM(BN20:BR20) -> 49 | AF20: =SUM(AG20:BQ20) -> 50 | AI20: 50 | BS20: =_xlfn.XLOOKUP(K20,[1]库销表!$F:$F,[1]库销表!$L:$L) -> 0 | BT20: =SUM(BU20:CV20) -> 0 | CW20: =_xlfn.XLOOKUP(K20,[1]库销表!$F:$F,[1]库销表!$IE:$IE) -> 0 | CX20: =_xlfn.XLOOKUP(K20,[1]库销表!$F:$F,[1]库销表!$IF:$IF) -> 0 | CY20: =_xlfn.XLOOKUP(K20,[1]库销表!$F:$F,[1]库销表!$FL:$FL) -> 0 | CZ20: =_xlfn.XLOOKUP(K20,数据更新表!E:E,数据更新表!F:F,0) -> 1 | DA20: 0 | DB20: =_xlfn.XLOOKUP(K20,数据更新表!E:E,数据更新表!G:G) -> 0 | DC20: =_xlfn.XLOOKUP(L20,数据更新表!Z:Z,数据更新表!AH:AH) -> 0 | DD20: =_xlfn.XLOOKUP(L20,数据更新表!Z:Z,数据更新表!AE:AE) -> 1 | DE20: =_xlfn.XLOOKUP(L20,数据更新表!Z:Z,数据更新表!AF:AF) -> 1 | DF20: =_xlfn.XLOOKUP(K20,数据更新表!Z:Z,数据更新表!AG:AG) -> #N/A | DG20: =_xlfn.XLOOKUP(L20,数据更新表!Z:Z,数据更新表!AD:AD) -> 185.29 | DH20: =_xlfn.XLOOKUP(L20,数据更新表!Z:Z,数据更新表!AA:AA) -> 7336 | DI20: =_xlfn.XLOOKUP(L20,数据更新表!Z:Z,数据更新表!AB:AB) -> 17 | DJ20: =_xlfn.XLOOKUP(L20,数据更新表!Z:Z,数据更新表!AC:AC) -> 42.21% | DK20: =_xlfn.XLOOKUP(L20,数据更新表!Z:Z,数据更新表!AI:AI) -> 42.21% | DL20: =_xlfn.XLOOKUP(L20,数据更新表!AL:AL,数据更新表!AM:AM) -> 45.69% | DM20: =_xlfn.XLOOKUP(L20,数据更新表!Z:Z,数据更新表!AJ:AJ) -> 2.37 | DN20: 6.6 | DO20: 开 | DP20: qi nang_5 | DQ20: 46084 | ED20: 调527 开广 | EE20: 439 | EF20: =EE20/0.7 -> 627.14286 | EG20: 26 | EH20: =EJ20/(EI20+EL20) -> 2.0888374 | EI20: =EG20*$EI$1 -> 67.86 | EJ20: =EE20-EI20-EL20-EO20-EN20-EP20-EQ20 -> 163.47078 | EK20: =EJ20/EE20 -> 0.3723708 | EL20: =EX20*3000*$EI$1 -> 10.399219 | EM20: =IF(EE20>299,"是","否") -> 是 | EN20: =EE20*0.05 -> 21.95 | EO20: =EE20*0.175 -> 76.825 | EP20: =IF(EE20<299,IF(EE20<99,25,IF(EE20<=149,30,IF(EE20<=299,37,85))),IF(EE20<=498,_xlfn.XLOOKUP(EW20,运费表!A:A,运费表!C:C,"重量超限",-1),_xlfn.XLOOKUP(EW20,运费表!A:A,运费表!D:D,"重量超限",-1))) -> 52.4 | EQ20: =EE20*0.105 -> 46.095 | ER20: =_xlfn.XLOOKUP(K20,[4]目录表!$H:$H,[4]目录表!$X:$X) -> 0.18 | ES20: =_xlfn.XLOOKUP(K20,[4]目录表!$H:$H,[4]目录表!$Y:$Y) -> 12.5 | ET20: =_xlfn.XLOOKUP(K20,[4]目录表!$H:$H,[4]目录表!$Z:$Z) -> 12.5 | EU20: =_xlfn.XLOOKUP(K20,[4]目录表!$H:$H,[4]目录表!$AA:$AA) -> 8.5 | EV20: =ES20*ET20*EU20/5000 -> 0.265625 | EW20: =IF(EV20>=ER20,EV20,ER20) -> 0.265625 | EX20: =_xlfn.XLOOKUP(K20,[2]目录表!$H:$H,[2]目录表!$AB:$AB) -> 0.001328125 | EZ20: =CZ20/7 -> 0.14285714 | FK20: =_xlfn.XLOOKUP(K20,[2]目录表!$H:$H,[2]目录表!$AJ:$AJ) -> 散货
B21: Pista Espiral Volante Claxon Bolsa Versa 12-19 March 12-20 | Meses sin interés | C21: 15 | D21: 31 | E21: 46038 | G21: 气囊游丝 | H21: 气囊游丝25554-3DN0A | J21: Pista Espiral Volante Claxon Bolsa Versa 12-19 March 12-20 | K21: XQ5-QP006-25554-3DN0A | L21: 4684129758 | M21: 新上架 | N21: =_xlfn.XLOOKUP(L21,数据更新表!J:J,数据更新表!K:K) -> 100 | O21: =IFERROR(_xlfn.XLOOKUP(K21,数据更新表!A:A,数据更新表!B:B),"0") -> 33 | P21: =_xlfn.XLOOKUP(K21,[1]库销表!$F:$F,[1]库销表!$L:$L) -> 0 | Q21: =X21/W21 -> 57.75 | S21: =_xlfn.XLOOKUP(K21,数据更新表!R:R,数据更新表!S:S) -> #N/A | T21: =_xlfn.XLOOKUP(K21,数据更新表!V:V,数据更新表!W:W) -> #N/A | V21: =IFERROR(7*O21/CZ21,"0") -> 57.75 | W21: =CZ21/7 -> 0.57142857 | X21: =O21+P21+SUM(BN21:BR21) -> 33 | AF21: =SUM(AG21:BQ21) -> 50 | AL21: 50 | BS21: =_xlfn.XLOOKUP(K21,[1]库销表!$F:$F,[1]库销表!$L:$L) -> 0 | BT21: =SUM(BU21:CV21) -> 0 | CW21: =_xlfn.XLOOKUP(K21,[1]库销表!$F:$F,[1]库销表!$IE:$IE) -> 0 | CX21: =_xlfn.XLOOKUP(K21,[1]库销表!$F:$F,[1]库销表!$IF:$IF) -> 0 | CY21: =_xlfn.XLOOKUP(K21,[1]库销表!$F:$F,[1]库销表!$FL:$FL) -> 0 | CZ21: =_xlfn.XLOOKUP(K21,数据更新表!E:E,数据更新表!F:F,0) -> 4 | DA21: 5 | DB21: =_xlfn.XLOOKUP(K21,数据更新表!E:E,数据更新表!G:G) -> 1 | DC21: =_xlfn.XLOOKUP(L21,数据更新表!Z:Z,数据更新表!AH:AH) -> 4 | DD21: =_xlfn.XLOOKUP(L21,数据更新表!Z:Z,数据更新表!AE:AE) -> 0 | DE21: =_xlfn.XLOOKUP(L21,数据更新表!Z:Z,数据更新表!AF:AF) -> 0 | DF21: =_xlfn.XLOOKUP(K21,数据更新表!Z:Z,数据更新表!AG:AG) -> #N/A | DG21: =_xlfn.XLOOKUP(L21,数据更新表!Z:Z,数据更新表!AD:AD) -> 77.4 | DH21: =_xlfn.XLOOKUP(L21,数据更新表!Z:Z,数据更新表!AA:AA) -> 6619 | DI21: =_xlfn.XLOOKUP(L21,数据更新表!Z:Z,数据更新表!AB:AB) -> 24 | DJ21: =_xlfn.XLOOKUP(L21,数据更新表!Z:Z,数据更新表!AC:AC) -> 0.00% | DK21: =_xlfn.XLOOKUP(L21,数据更新表!Z:Z,数据更新表!AI:AI) -> 7.47% | DL21: =_xlfn.XLOOKUP(L21,数据更新表!AL:AL,数据更新表!AM:AM) -> 5.49% | DM21: =_xlfn.XLOOKUP(L21,数据更新表!Z:Z,数据更新表!AJ:AJ) -> 0 | DN21: 8 | DO21: 开 | DP21: qi nang-8 | DQ21: 46074 | DU21: 同366 | EE21: 259 | EF21: =EE21/0.7 -> 370 | EG21: 27 | EH21: =EJ21/(EI21+EL21) -> 0.54035173 | EI21: =EG21*$EI$1 -> 70.47 | EJ21: =EE21-EI21-EL21-EO21-EN21-EP21-EQ21 -> 47.8944 | EK21: =EJ21/EE21 -> 0.18492046 | EL21: =EX21*3000*$EI$1 -> 18.1656 | EM21: =IF(EE21>299,"是","否") -> 否 | EN21: =EE21*0.05 -> 12.95 | EO21: =EE21*0.175 -> 45.325 | EP21: =IF(EE21<299,IF(EE21<99,25,IF(EE21<=149,30,IF(EE21<=299,37,85))),IF(EE21<=498,_xlfn.XLOOKUP(EW21,运费表!A:A,运费表!C:C,"重量超限",-1),_xlfn.XLOOKUP(EW21,运费表!A:A,运费表!D:D,"重量超限",-1))) -> 37 | EQ21: =EE21*0.105 -> 27.195 | ER21: =_xlfn.XLOOKUP(K21,[4]目录表!$H:$H,[4]目录表!$X:$X) -> 0.38 | ES21: =_xlfn.XLOOKUP(K21,[4]目录表!$H:$H,[4]目录表!$Y:$Y) -> 16 | ET21: =_xlfn.XLOOKUP(K21,[4]目录表!$H:$H,[4]目录表!$Z:$Z) -> 14.5 | EU21: =_xlfn.XLOOKUP(K21,[4]目录表!$H:$H,[4]目录表!$AA:$AA) -> 10 | EV21: =ES21*ET21*EU21/5000 -> 0.464 | EW21: =IF(EV21>=ER21,EV21,ER21) -> 0.464 | EX21: =_xlfn.XLOOKUP(K21,[2]目录表!$H:$H,[2]目录表!$AB:$AB) -> 0.00232 | EZ21: =CZ21/7 -> 0.57142857 | FK21: =_xlfn.XLOOKUP(K21,[2]目录表!$H:$H,[2]目录表!$AJ:$AJ) -> 散货
B22: Resorte Reloj Sensor Para Jeep Patriot 2007 A 2016 | Meses sin interés | C22: 5 | D22: 11 | E22: 46040 | G22: 气囊游丝 | H22: 气囊游丝5156106AF-带角度 | J22: Resorte Reloj Sensor Para Jeep Patriot 2007 A 2016 | K22: XQ5-QP007-5156106AF | L22: 2697065107 | M22: 新上架 | N22: =_xlfn.XLOOKUP(L22,数据更新表!J:J,数据更新表!K:K) -> #N/A | O22: =IFERROR(_xlfn.XLOOKUP(K22,数据更新表!A:A,数据更新表!B:B),"0") -> 0 | P22: =_xlfn.XLOOKUP(K22,[1]库销表!$F:$F,[1]库销表!$L:$L) -> 0 | Q22: =X22/W22 -> #DIV/0! | S22: =_xlfn.XLOOKUP(K22,数据更新表!R:R,数据更新表!S:S) -> #N/A | T22: =_xlfn.XLOOKUP(K22,数据更新表!V:V,数据更新表!W:W) -> #N/A | V22: =IFERROR(7*O22/CZ22,"0") -> 0 | W22: =CZ22/7 -> 0 | X22: =O22+P22+SUM(BN22:BR22) -> 0 | AF22: =SUM(AG22:BQ22) -> 20 | AL22: 20 | BS22: =_xlfn.XLOOKUP(K22,[1]库销表!$F:$F,[1]库销表!$L:$L) -> 0 | BT22: =SUM(BU22:CV22) -> 0 | CW22: =_xlfn.XLOOKUP(K22,[1]库销表!$F:$F,[1]库销表!$IE:$IE) -> 0 | CX22: =_xlfn.XLOOKUP(K22,[1]库销表!$F:$F,[1]库销表!$IF:$IF) -> 0 | CY22: =_xlfn.XLOOKUP(K22,[1]库销表!$F:$F,[1]库销表!$FL:$FL) -> 0 | CZ22: =_xlfn.XLOOKUP(K22,数据更新表!E:E,数据更新表!F:F,0) -> 0 | DA22: 8 | DB22: =_xlfn.XLOOKUP(K22,数据更新表!E:E,数据更新表!G:G) -> #N/A | DC22: =_xlfn.XLOOKUP(L22,数据更新表!Z:Z,数据更新表!AH:AH) -> #N/A | DD22: =_xlfn.XLOOKUP(L22,数据更新表!Z:Z,数据更新表!AE:AE) -> #N/A | DE22: =_xlfn.XLOOKUP(L22,数据更新表!Z:Z,数据更新表!AF:AF) -> #N/A | DF22: =_xlfn.XLOOKUP(K22,数据更新表!Z:Z,数据更新表!AG:AG) -> #N/A | DG22: =_xlfn.XLOOKUP(L22,数据更新表!Z:Z,数据更新表!AD:AD) -> #N/A | DH22: =_xlfn.XLOOKUP(L22,数据更新表!Z:Z,数据更新表!AA:AA) -> #N/A | DI22: =_xlfn.XLOOKUP(L22,数据更新表!Z:Z,数据更新表!AB:AB) -> #N/A | DJ22: =_xlfn.XLOOKUP(L22,数据更新表!Z:Z,数据更新表!AC:AC) -> #N/A | DK22: =_xlfn.XLOOKUP(L22,数据更新表!Z:Z,数据更新表!AI:AI) -> #N/A | DL22: =_xlfn.XLOOKUP(L22,数据更新表!AL:AL,数据更新表!AM:AM) -> 5.52% | DM22: =_xlfn.XLOOKUP(L22,数据更新表!Z:Z,数据更新表!AJ:AJ) -> #N/A | DN22: 10 | DO22: 开 | DP22: qi nang_1 | DQ22: 46074 | DU22: 同行1025 | EE22: 999 | EF22: =EE22/0.7 -> 1427.1429 | EG22: 165 | EH22: =EJ22/(EI22+EL22) -> 0.33535911 | EI22: =EG22*$EI$1 -> 430.65 | EJ22: =EE22-EI22-EL22-EO22-EN22-EP22-EQ22 -> 150.5144 | EK22: =EJ22/EE22 -> 0.15066507 | EL22: =EX22*3000*$EI$1 -> 18.1656 | EM22: =IF(EE22>299,"是","否") -> 是 | EN22: =EE22*0.05 -> 49.95 | EO22: =EE22*0.175 -> 174.825 | EP22: =IF(EE22<299,IF(EE22<99,25,IF(EE22<=149,30,IF(EE22<=299,37,85))),IF(EE22<=498,_xlfn.XLOOKUP(EW22,运费表!A:A,运费表!C:C,"重量超限",-1),_xlfn.XLOOKUP(EW22,运费表!A:A,运费表!D:D,"重量超限",-1))) -> 70 | EQ22: =EE22*0.105 -> 104.895 | ER22: =_xlfn.XLOOKUP(K22,[4]目录表!$H:$H,[4]目录表!$X:$X) -> 0.38 | ES22: =_xlfn.XLOOKUP(K22,[4]目录表!$H:$H,[4]目录表!$Y:$Y) -> 16 | ET22: =_xlfn.XLOOKUP(K22,[4]目录表!$H:$H,[4]目录表!$Z:$Z) -> 14.5 | EU22: =_xlfn.XLOOKUP(K22,[4]目录表!$H:$H,[4]目录表!$AA:$AA) -> 10 | EV22: =ES22*ET22*EU22/5000 -> 0.464 | EW22: =IF(EV22>=ER22,EV22,ER22) -> 0.464 | EX22: =_xlfn.XLOOKUP(K22,[2]目录表!$H:$H,[2]目录表!$AB:$AB) -> 0.00232 | EZ22: =CZ22/7 -> 0 | FK22: =_xlfn.XLOOKUP(K22,[2]目录表!$H:$H,[2]目录表!$AJ:$AJ) -> 散货
B23: Resorte Reloj Pista Carrete Para Nissan X-tail Tiida 07-18 | MercadoLibre | C23: 8 | D23: 46 | E23: 46040 | G23: 气囊游丝 | H23: 气囊游丝25567-ET225 | J23: Resorte Reloj Pista Carrete Para Nissan X-tail Tiida 07-18 | K23: XQ5-QP008-25567-ET225 | L23: 4684057184 | M23: 新上架 | N23: =_xlfn.XLOOKUP(L23,数据更新表!J:J,数据更新表!K:K) -> 100 | O23: =IFERROR(_xlfn.XLOOKUP(K23,数据更新表!A:A,数据更新表!B:B),"0") -> 30 | P23: =_xlfn.XLOOKUP(K23,[1]库销表!$F:$F,[1]库销表!$L:$L) -> 0 | Q23: =X23/W23 -> 42 | S23: =_xlfn.XLOOKUP(K23,数据更新表!R:R,数据更新表!S:S) -> #N/A | T23: =_xlfn.XLOOKUP(K23,数据更新表!V:V,数据更新表!W:W) -> #N/A | V23: =IFERROR(7*O23/CZ23,"0") -> 42 | W23: =CZ23/7 -> 0.71428571 | X23: =O23+P23+SUM(BN23:BR23) -> 30 | AF23: =SUM(AG23:BQ23) -> 50 | AL23: 50 | BS23: =_xlfn.XLOOKUP(K23,[1]库销表!$F:$F,[1]库销表!$L:$L) -> 0 | BT23: =SUM(BU23:CV23) -> 0 | CW23: =_xlfn.XLOOKUP(K23,[1]库销表!$F:$F,[1]库销表!$IE:$IE) -> 0 | CX23: =_xlfn.XLOOKUP(K23,[1]库销表!$F:$F,[1]库销表!$IF:$IF) -> 0 | CY23: =_xlfn.XLOOKUP(K23,[1]库销表!$F:$F,[1]库销表!$FL:$FL) -> 0 | CZ23: =_xlfn.XLOOKUP(K23,数据更新表!E:E,数据更新表!F:F,0) -> 5 | DA23: 4 | DB23: =_xlfn.XLOOKUP(K23,数据更新表!E:E,数据更新表!G:G) -> 0 | DC23: =_xlfn.XLOOKUP(L23,数据更新表!Z:Z,数据更新表!AH:AH) -> 4 | DD23: =_xlfn.XLOOKUP(L23,数据更新表!Z:Z,数据更新表!AE:AE) -> 1 | DE23: =_xlfn.XLOOKUP(L23,数据更新表!Z:Z,数据更新表!AF:AF) -> 1 | DF23: =_xlfn.XLOOKUP(K23,数据更新表!Z:Z,数据更新表!AG:AG) -> #N/A | DG23: =_xlfn.XLOOKUP(L23,数据更新表!Z:Z,数据更新表!AD:AD) -> 16.01 | DH23: =_xlfn.XLOOKUP(L23,数据更新表!Z:Z,数据更新表!AA:AA) -> 7071 | DI23: =_xlfn.XLOOKUP(L23,数据更新表!Z:Z,数据更新表!AB:AB) -> 9 | DJ23: =_xlfn.XLOOKUP(L23,数据更新表!Z:Z,数据更新表!AC:AC) -> 5.99% | DK23: =_xlfn.XLOOKUP(L23,数据更新表!Z:Z,数据更新表!AI:AI) -> 1.20% | DL23: =_xlfn.XLOOKUP(L23,数据更新表!AL:AL,数据更新表!AM:AM) -> 0.78% | DM23: =_xlfn.XLOOKUP(L23,数据更新表!Z:Z,数据更新表!AJ:AJ) -> 16.69 | DN23: 8 | DO23: 开 | DP23: qi nang-7 | DQ23: 46074 | DU23: 同271 | EE23: =_xlfn.XLOOKUP(L23,数据更新表!J:J,数据更新表!L:L) -> 267.14 | EF23: =EE23/0.7 -> 381.62857 | EG23: 27 | EH23: =EJ23/(EI23+EL23) -> 0.60188231 | EI23: =EG23*$EI$1 -> 70.47 | EJ23: =EE23-EI23-EL23-EO23-EN23-EP23-EQ23 -> 53.3482 | EK23: =EJ23/EE23 -> 0.19970128 | EL23: =EX23*3000*$EI$1 -> 18.1656 | EM23: =IF(EE23>299,"是","否") -> 否 | EN23: =EE23*0.05 -> 13.357 | EO23: =EE23*0.175 -> 46.7495 | EP23: =IF(EE23<299,IF(EE23<99,25,IF(EE23<=149,30,IF(EE23<=299,37,85))),IF(EE23<=498,_xlfn.XLOOKUP(EW23,运费表!A:A,运费表!C:C,"重量超限",-1),_xlfn.XLOOKUP(EW23,运费表!A:A,运费表!D:D,"重量超限",-1))) -> 37 | EQ23: =EE23*0.105 -> 28.0497 | ER23: =_xlfn.XLOOKUP(K23,[4]目录表!$H:$H,[4]目录表!$X:$X) -> 0.38 | ES23: =_xlfn.XLOOKUP(K23,[4]目录表!$H:$H,[4]目录表!$Y:$Y) -> 16 | ET23: =_xlfn.XLOOKUP(K23,[4]目录表!$H:$H,[4]目录表!$Z:$Z) -> 14.5 | EU23: =_xlfn.XLOOKUP(K23,[4]目录表!$H:$H,[4]目录表!$AA:$AA) -> 10 | EV23: =ES23*ET23*EU23/5000 -> 0.464 | EW23: =IF(EV23>=ER23,EV23,ER23) -> 0.464 | EX23: =_xlfn.XLOOKUP(K23,[2]目录表!$H:$H,[2]目录表!$AB:$AB) -> 0.00232 | EZ23: =CZ23/7 -> 0.71428571 | FK23: =_xlfn.XLOOKUP(K23,[2]目录表!$H:$H,[2]目录表!$AJ:$AJ) -> 散货
B24: Resorte De Reloj Para Toyota Tacoma Corolla 2009 - 2013 Bsj | MercadoLibre | C24: 5 | D24: 24 | E24: 46041 | G24: 气囊游丝 | H24: 气囊游丝84306-48030 | J24: Resorte De Reloj Para Toyota Tacoma Corolla 2009 - 2013 Bsj | K24: XQ5-QP009-84306-48030 | L24: 2696975635 | M24: 新上架 | N24: =_xlfn.XLOOKUP(L24,数据更新表!J:J,数据更新表!K:K) -> 100 | O24: =IFERROR(_xlfn.XLOOKUP(K24,数据更新表!A:A,数据更新表!B:B),"0") -> 40 | P24: =_xlfn.XLOOKUP(K24,[1]库销表!$F:$F,[1]库销表!$L:$L) -> 0 | Q24: =X24/W24 -> 140 | S24: =_xlfn.XLOOKUP(K24,数据更新表!R:R,数据更新表!S:S) -> #N/A | T24: =_xlfn.XLOOKUP(K24,数据更新表!V:V,数据更新表!W:W) -> #N/A | V24: =IFERROR(7*O24/CZ24,"0") -> 140 | W24: =CZ24/7 -> 0.28571429 | X24: =O24+P24+SUM(BN24:BR24) -> 40 | AF24: =SUM(AG24:BQ24) -> 50 | AL24: 50 | BS24: =_xlfn.XLOOKUP(K24,[1]库销表!$F:$F,[1]库销表!$L:$L) -> 0 | BT24: =SUM(BU24:CV24) -> 0 | CW24: =_xlfn.XLOOKUP(K24,[1]库销表!$F:$F,[1]库销表!$IE:$IE) -> 0 | CX24: =_xlfn.XLOOKUP(K24,[1]库销表!$F:$F,[1]库销表!$IF:$IF) -> 0 | CY24: =_xlfn.XLOOKUP(K24,[1]库销表!$F:$F,[1]库销表!$FL:$FL) -> 0 | CZ24: =_xlfn.XLOOKUP(K24,数据更新表!E:E,数据更新表!F:F,0) -> 2 | DA24: 2 | DB24: =_xlfn.XLOOKUP(K24,数据更新表!E:E,数据更新表!G:G) -> 0 | DC24: =_xlfn.XLOOKUP(L24,数据更新表!Z:Z,数据更新表!AH:AH) -> 2 | DD24: =_xlfn.XLOOKUP(L24,数据更新表!Z:Z,数据更新表!AE:AE) -> 0 | DE24: =_xlfn.XLOOKUP(L24,数据更新表!Z:Z,数据更新表!AF:AF) -> 0 | DF24: =_xlfn.XLOOKUP(K24,数据更新表!Z:Z,数据更新表!AG:AG) -> #N/A | DG24: =_xlfn.XLOOKUP(L24,数据更新表!Z:Z,数据更新表!AD:AD) -> 9.21 | DH24: =_xlfn.XLOOKUP(L24,数据更新表!Z:Z,数据更新表!AA:AA) -> 5151 | DI24: =_xlfn.XLOOKUP(L24,数据更新表!Z:Z,数据更新表!AB:AB) -> 4 | DJ24: =_xlfn.XLOOKUP(L24,数据更新表!Z:Z,数据更新表!AC:AC) -> 0.00% | DK24: =_xlfn.XLOOKUP(L24,数据更新表!Z:Z,数据更新表!AI:AI) -> 1.96% | DL24: =_xlfn.XLOOKUP(L24,数据更新表!AL:AL,数据更新表!AM:AM) -> 7.90% | DM24: =_xlfn.XLOOKUP(L24,数据更新表!Z:Z,数据更新表!AJ:AJ) -> 0 | DN24: 10 | DO24: 开 | DP24: qi nang_2 | DQ24: 46074 | DU24: 同 238 | EE24: =_xlfn.XLOOKUP(L24,数据更新表!J:J,数据更新表!L:L) -> 235.08 | EF24: =EE24/0.7 -> 335.82857 | EG24: 17 | EH24: =EJ24/(EI24+EL24) -> 0.92696 | EI24: =EG24*$EI$1 -> 44.37 | EJ24: =EE24-EI24-EL24-EO24-EN24-EP24-EQ24 -> 57.968 | EK24: =EJ24/EE24 -> 0.2465884 | EL24: =EX24*3000*$EI$1 -> 18.1656 | EM24: =IF(EE24>299,"是","否") -> 否 | EN24: =EE24*0.05 -> 11.754 | EO24: =EE24*0.175 -> 41.139 | EP24: =IF(EE24<299,IF(EE24<99,25,IF(EE24<=149,30,IF(EE24<=299,37,85))),IF(EE24<=498,_xlfn.XLOOKUP(EW24,运费表!A:A,运费表!C:C,"重量超限",-1),_xlfn.XLOOKUP(EW24,运费表!A:A,运费表!D:D,"重量超限",-1))) -> 37 | EQ24: =EE24*0.105 -> 24.6834 | ER24: =_xlfn.XLOOKUP(K24,[4]目录表!$H:$H,[4]目录表!$X:$X) -> 0.38 | ES24: =_xlfn.XLOOKUP(K24,[4]目录表!$H:$H,[4]目录表!$Y:$Y) -> 16 | ET24: =_xlfn.XLOOKUP(K24,[4]目录表!$H:$H,[4]目录表!$Z:$Z) -> 14.5 | EU24: =_xlfn.XLOOKUP(K24,[4]目录表!$H:$H,[4]目录表!$AA:$AA) -> 10 | EV24: =ES24*ET24*EU24/5000 -> 0.464 | EW24: =IF(EV24>=ER24,EV24,ER24) -> 0.464 | EX24: =_xlfn.XLOOKUP(K24,[2]目录表!$H:$H,[2]目录表!$AB:$AB) -> 0.00232 | EZ24: =CZ24/7 -> 0.28571429 | FK24: =_xlfn.XLOOKUP(K24,[2]目录表!$H:$H,[2]目录表!$AJ:$AJ) -> 散货
B25: Resorte Reloj S/sensor Ángulo Compass Patriot 200 2007-2018 | Envío gratis | C25: 8 | D25: 11 | E25: 46038 | G25: 气囊游丝 | H25: 气囊游丝05156106AG-S-不带角度 | J25: Resorte Reloj S/sensor Ángulo Compass Patriot 200 2007-2018 | K25: XQ5-QP010-05156106AG-S | L25: 2696841915 | M25: 新上架 | N25: =_xlfn.XLOOKUP(L25,数据更新表!J:J,数据更新表!K:K) -> 100 | O25: =IFERROR(_xlfn.XLOOKUP(K25,数据更新表!A:A,数据更新表!B:B),"0") -> 40 | P25: =_xlfn.XLOOKUP(K25,[1]库销表!$F:$F,[1]库销表!$L:$L) -> 0 | Q25: =X25/W25 -> 93.333333 | S25: =_xlfn.XLOOKUP(K25,数据更新表!R:R,数据更新表!S:S) -> #N/A | T25: =_xlfn.XLOOKUP(K25,数据更新表!V:V,数据更新表!W:W) -> #N/A | V25: =IFERROR(7*O25/CZ25,"0") -> 93.333333 | W25: =CZ25/7 -> 0.42857143 | X25: =O25+P25+SUM(BN25:BR25) -> 40 | AF25: =SUM(AG25:BQ25) -> 50 | AL25: 50 | BS25: =_xlfn.XLOOKUP(K25,[1]库销表!$F:$F,[1]库销表!$L:$L) -> 0 | BT25: =SUM(BU25:CV25) -> 0 | CW25: =_xlfn.XLOOKUP(K25,[1]库销表!$F:$F,[1]库销表!$IE:$IE) -> 0 | CX25: =_xlfn.XLOOKUP(K25,[1]库销表!$F:$F,[1]库销表!$IF:$IF) -> 0 | CY25: =_xlfn.XLOOKUP(K25,[1]库销表!$F:$F,[1]库销表!$FL:$FL) -> 0 | CZ25: =_xlfn.XLOOKUP(K25,数据更新表!E:E,数据更新表!F:F,0) -> 3 | DA25: 1 | DB25: =_xlfn.XLOOKUP(K25,数据更新表!E:E,数据更新表!G:G) -> 0 | DC25: =_xlfn.XLOOKUP(L25,数据更新表!Z:Z,数据更新表!AH:AH) -> 3 | DD25: =_xlfn.XLOOKUP(L25,数据更新表!Z:Z,数据更新表!AE:AE) -> 0 | DE25: =_xlfn.XLOOKUP(L25,数据更新表!Z:Z,数据更新表!AF:AF) -> 0 | DF25: =_xlfn.XLOOKUP(K25,数据更新表!Z:Z,数据更新表!AG:AG) -> #N/A | DG25: =_xlfn.XLOOKUP(L25,数据更新表!Z:Z,数据更新表!AD:AD) -> 36.22 | DH25: =_xlfn.XLOOKUP(L25,数据更新表!Z:Z,数据更新表!AA:AA) -> 4344 | DI25: =_xlfn.XLOOKUP(L25,数据更新表!Z:Z,数据更新表!AB:AB) -> 9 | DJ25: =_xlfn.XLOOKUP(L25,数据更新表!Z:Z,数据更新表!AC:AC) -> 0.00% | DK25: =_xlfn.XLOOKUP(L25,数据更新表!Z:Z,数据更新表!AI:AI) -> 2.83% | DL25: =_xlfn.XLOOKUP(L25,数据更新表!AL:AL,数据更新表!AM:AM) -> 3.99% | DM25: =_xlfn.XLOOKUP(L25,数据更新表!Z:Z,数据更新表!AJ:AJ) -> 0 | DN25: 8 | DO25: 开 | DP25: qi nang_3 | DQ25: 46074 | DU25: 同497 | EA25: 426降399 | EE25: 399 | EF25: =EE25/0.7 -> 570 | EG25: 45 | EH25: =EJ25/(EI25+EL25) -> 0.55830155 | EI25: =EG25*$EI$1 -> 117.45 | EJ25: =EE25-EI25-EL25-EO25-EN25-EP25-EQ25 -> 75.7144 | EK25: =EJ25/EE25 -> 0.1897604 | EL25: =EX25*3000*$EI$1 -> 18.1656 | EM25: =IF(EE25>299,"是","否") -> 是 | EN25: =EE25*0.05 -> 19.95 | EO25: =EE25*0.175 -> 69.825 | EP25: =IF(EE25<299,IF(EE25<99,25,IF(EE25<=149,30,IF(EE25<=299,37,85))),IF(EE25<=498,_xlfn.XLOOKUP(EW25,运费表!A:A,运费表!C:C,"重量超限",-1),_xlfn.XLOOKUP(EW25,运费表!A:A,运费表!D:D,"重量超限",-1))) -> 56 | EQ25: =EE25*0.105 -> 41.895 | ER25: =_xlfn.XLOOKUP(K25,[4]目录表!$H:$H,[4]目录表!$X:$X) -> 0.38 | ES25: =_xlfn.XLOOKUP(K25,[4]目录表!$H:$H,[4]目录表!$Y:$Y) -> 16 | ET25: =_xlfn.XLOOKUP(K25,[4]目录表!$H:$H,[4]目录表!$Z:$Z) -> 14.5 | EU25: =_xlfn.XLOOKUP(K25,[4]目录表!$H:$H,[4]目录表!$AA:$AA) -> 10 | EV25: =ES25*ET25*EU25/5000 -> 0.464 | EW25: =IF(EV25>=ER25,EV25,ER25) -> 0.464 | EX25: =_xlfn.XLOOKUP(K25,[2]目录表!$H:$H,[2]目录表!$AB:$AB) -> 0.00232 | EZ25: =CZ25/7 -> 0.42857143 | FK25: =_xlfn.XLOOKUP(K25,[2]目录表!$H:$H,[2]目录表!$AJ:$AJ) -> 散货
B26: Fy Pista Carrete Resorte Reloj Para Chevrolet Beat 2018-2021 | Meses sin interés | C26: 7 | D26: 38 | E26: 46038 | G26: 气囊游丝 | H26: 气囊游丝94529531 | J26: Fy Pista Carrete Resorte Reloj Para Chevrolet Beat 2018-2021 | K26: XQ5-QP011-94529531 | L26: 4684059764 | M26: 新上架 | N26: =_xlfn.XLOOKUP(L26,数据更新表!J:J,数据更新表!K:K) -> 100 | O26: =IFERROR(_xlfn.XLOOKUP(K26,数据更新表!A:A,数据更新表!B:B),"0") -> 45 | P26: =_xlfn.XLOOKUP(K26,[1]库销表!$F:$F,[1]库销表!$L:$L) -> 0 | Q26: =X26/W26 -> 315 | S26: =_xlfn.XLOOKUP(K26,数据更新表!R:R,数据更新表!S:S) -> #N/A | T26: =_xlfn.XLOOKUP(K26,数据更新表!V:V,数据更新表!W:W) -> #N/A | V26: =IFERROR(7*O26/CZ26,"0") -> 315 | W26: =CZ26/7 -> 0.14285714 | X26: =O26+P26+SUM(BN26:BR26) -> 45 | AF26: =SUM(AG26:BQ26) -> 50 | AL26: 50 | BS26: =_xlfn.XLOOKUP(K26,[1]库销表!$F:$F,[1]库销表!$L:$L) -> 0 | BT26: =SUM(BU26:CV26) -> 0 | CW26: =_xlfn.XLOOKUP(K26,[1]库销表!$F:$F,[1]库销表!$IE:$IE) -> 0 | CX26: =_xlfn.XLOOKUP(K26,[1]库销表!$F:$F,[1]库销表!$IF:$IF) -> 0 | CY26: =_xlfn.XLOOKUP(K26,[1]库销表!$F:$F,[1]库销表!$FL:$FL) -> 0 | CZ26: =_xlfn.XLOOKUP(K26,数据更新表!E:E,数据更新表!F:F,0) -> 1 | DA26: 1 | DB26: =_xlfn.XLOOKUP(K26,数据更新表!E:E,数据更新表!G:G) -> 0 | DC26: =_xlfn.XLOOKUP(L26,数据更新表!Z:Z,数据更新表!AH:AH) -> 1 | DD26: =_xlfn.XLOOKUP(L26,数据更新表!Z:Z,数据更新表!AE:AE) -> 0 | DE26: =_xlfn.XLOOKUP(L26,数据更新表!Z:Z,数据更新表!AF:AF) -> 0 | DF26: =_xlfn.XLOOKUP(K26,数据更新表!Z:Z,数据更新表!AG:AG) -> #N/A | DG26: =_xlfn.XLOOKUP(L26,数据更新表!Z:Z,数据更新表!AD:AD) -> 25.53 | DH26: =_xlfn.XLOOKUP(L26,数据更新表!Z:Z,数据更新表!AA:AA) -> 4580 | DI26: =_xlfn.XLOOKUP(L26,数据更新表!Z:Z,数据更新表!AB:AB) -> 13 | DJ26: =_xlfn.XLOOKUP(L26,数据更新表!Z:Z,数据更新表!AC:AC) -> 0.00% | DK26: =_xlfn.XLOOKUP(L26,数据更新表!Z:Z,数据更新表!AI:AI) -> 8.57% | DL26: =_xlfn.XLOOKUP(L26,数据更新表!AL:AL,数据更新表!AM:AM) -> 6.53% | DM26: =_xlfn.XLOOKUP(L26,数据更新表!Z:Z,数据更新表!AJ:AJ) -> 0 | DN26: 8 | DO26: 开 | DP26: qi nang_3 | DQ26: 46074 | DU26: 同380 | EC26: 320降298 | EE26: 298 | EF26: =EE26/0.7 -> 425.71429 | EG26: 27 | EH26: =EJ26/(EI26+EL26) -> 0.83515427 | EI26: =EG26*$EI$1 -> 70.47 | EJ26: =EE26-EI26-EL26-EO26-EN26-EP26-EQ26 -> 74.0244 | EK26: =EJ26/EE26 -> 0.24840403 | EL26: =EX26*3000*$EI$1 -> 18.1656 | EM26: =IF(EE26>299,"是","否") -> 否 | EN26: =EE26*0.05 -> 14.9 | EO26: =EE26*0.175 -> 52.15 | EP26: =IF(EE26<299,IF(EE26<99,25,IF(EE26<=149,30,IF(EE26<=299,37,85))),IF(EE26<=498,_xlfn.XLOOKUP(EW26,运费表!A:A,运费表!C:C,"重量超限",-1),_xlfn.XLOOKUP(EW26,运费表!A:A,运费表!D:D,"重量超限",-1))) -> 37 | EQ26: =EE26*0.105 -> 31.29 | ER26: =_xlfn.XLOOKUP(K26,[4]目录表!$H:$H,[4]目录表!$X:$X) -> 0.38 | ES26: =_xlfn.XLOOKUP(K26,[4]目录表!$H:$H,[4]目录表!$Y:$Y) -> 16 | ET26: =_xlfn.XLOOKUP(K26,[4]目录表!$H:$H,[4]目录表!$Z:$Z) -> 14.5 | EU26: =_xlfn.XLOOKUP(K26,[4]目录表!$H:$H,[4]目录表!$AA:$AA) -> 10 | EV26: =ES26*ET26*EU26/5000 -> 0.464 | EW26: =IF(EV26>=ER26,EV26,ER26) -> 0.464 | EX26: =_xlfn.XLOOKUP(K26,[2]目录表!$H:$H,[2]目录表!$AB:$AB) -> 0.00232 | EZ26: =CZ26/7 -> 0.14285714 | FK26: =_xlfn.XLOOKUP(K26,[2]目录表!$H:$H,[2]目录表!$AJ:$AJ) -> 散货
B27: https://articulo.mercadolibre.com.mx/MLM-2236159097-resorte-reloj-para-elantra-sonata-2011-2012-2013-2014-2015-_JM | C27: 7 | D27: 24 | E27: 46041 | G27: 气囊游丝 | H27: 气囊游丝93490-3Q120 | J27: Resorte Reloj Para Elantra Sonata 2011 2012 2013 2014 2015 | K27: XQ5-QP012-93490-3Q120 | L27: 4687079756 | M27: 新上架 | N27: =_xlfn.XLOOKUP(L27,数据更新表!J:J,数据更新表!K:K) -> 100 | O27: =IFERROR(_xlfn.XLOOKUP(K27,数据更新表!A:A,数据更新表!B:B),"0") -> 47 | P27: =_xlfn.XLOOKUP(K27,[1]库销表!$F:$F,[1]库销表!$L:$L) -> 0 | Q27: =X27/W27 -> 109.66667 | S27: =_xlfn.XLOOKUP(K27,数据更新表!R:R,数据更新表!S:S) -> #N/A | T27: =_xlfn.XLOOKUP(K27,数据更新表!V:V,数据更新表!W:W) -> #N/A | V27: =IFERROR(7*O27/CZ27,"0") -> 109.66667 | W27: =CZ27/7 -> 0.42857143 | X27: =O27+P27+SUM(BN27:BR27) -> 47 | AF27: =SUM(AG27:BQ27) -> 50 | AL27: 50 | BS27: =_xlfn.XLOOKUP(K27,[1]库销表!$F:$F,[1]库销表!$L:$L) -> 0 | BT27: =SUM(BU27:CV27) -> 0 | CW27: =_xlfn.XLOOKUP(K27,[1]库销表!$F:$F,[1]库销表!$IE:$IE) -> 0 | CX27: =_xlfn.XLOOKUP(K27,[1]库销表!$F:$F,[1]库销表!$IF:$IF) -> 0 | CY27: =_xlfn.XLOOKUP(K27,[1]库销表!$F:$F,[1]库销表!$FL:$FL) -> 0 | CZ27: =_xlfn.XLOOKUP(K27,数据更新表!E:E,数据更新表!F:F,0) -> 3 | DA27: 1 | DB27: =_xlfn.XLOOKUP(K27,数据更新表!E:E,数据更新表!G:G) -> 0 | DC27: =_xlfn.XLOOKUP(L27,数据更新表!Z:Z,数据更新表!AH:AH) -> 1 | DD27: =_xlfn.XLOOKUP(L27,数据更新表!Z:Z,数据更新表!AE:AE) -> 2 | DE27: =_xlfn.XLOOKUP(L27,数据更新表!Z:Z,数据更新表!AF:AF) -> 2 | DF27: =_xlfn.XLOOKUP(K27,数据更新表!Z:Z,数据更新表!AG:AG) -> #N/A | DG27: =_xlfn.XLOOKUP(L27,数据更新表!Z:Z,数据更新表!AD:AD) -> 34.51 | DH27: =_xlfn.XLOOKUP(L27,数据更新表!Z:Z,数据更新表!AA:AA) -> 1936 | DI27: =_xlfn.XLOOKUP(L27,数据更新表!Z:Z,数据更新表!AB:AB) -> 8 | DJ27: =_xlfn.XLOOKUP(L27,数据更新表!Z:Z,数据更新表!AC:AC) -> 8.26% | DK27: =_xlfn.XLOOKUP(L27,数据更新表!Z:Z,数据更新表!AI:AI) -> 5.50% | DL27: =_xlfn.XLOOKUP(L27,数据更新表!AL:AL,数据更新表!AM:AM) -> 6.03% | DM27: =_xlfn.XLOOKUP(L27,数据更新表!Z:Z,数据更新表!AJ:AJ) -> 12.11 | DN27: 6.6 | DO27: 开 | DP27: qi nang-9 | DQ27: 46074 | DU27: 同209 | EE27: =_xlfn.XLOOKUP(L27,数据更新表!J:J,数据更新表!L:L) -> 208.97 | EF27: =EE27/0.7 -> 298.52857 | EG27: 17 | EH27: =EJ27/(EI27+EL27) -> 0.64722014 | EI27: =EG27*$EI$1 -> 44.37 | EJ27: =EE27-EI27-EL27-EO27-EN27-EP27-EQ27 -> 40.4743 | EK27: =EJ27/EE27 -> 0.19368474 | EL27: =EX27*3000*$EI$1 -> 18.1656 | EM27: =IF(EE27>299,"是","否") -> 否 | EN27: =EE27*0.05 -> 10.4485 | EO27: =EE27*0.175 -> 36.56975 | EP27: =IF(EE27<299,IF(EE27<99,25,IF(EE27<=149,30,IF(EE27<=299,37,85))),IF(EE27<=498,_xlfn.XLOOKUP(EW27,运费表!A:A,运费表!C:C,"重量超限",-1),_xlfn.XLOOKUP(EW27,运费表!A:A,运费表!D:D,"重量超限",-1))) -> 37 | EQ27: =EE27*0.105 -> 21.94185 | ER27: =_xlfn.XLOOKUP(K27,[4]目录表!$H:$H,[4]目录表!$X:$X) -> 0.38 | ES27: =_xlfn.XLOOKUP(K27,[4]目录表!$H:$H,[4]目录表!$Y:$Y) -> 16 | ET27: =_xlfn.XLOOKUP(K27,[4]目录表!$H:$H,[4]目录表!$Z:$Z) -> 14.5 | EU27: =_xlfn.XLOOKUP(K27,[4]目录表!$H:$H,[4]目录表!$AA:$AA) -> 10 | EV27: =ES27*ET27*EU27/5000 -> 0.464 | EW27: =IF(EV27>=ER27,EV27,ER27) -> 0.464 | EX27: =_xlfn.XLOOKUP(K27,[2]目录表!$H:$H,[2]目录表!$AB:$AB) -> 0.00232 | EZ27: =CZ27/7 -> 0.42857143 | FK27: =_xlfn.XLOOKUP(K27,[2]目录表!$H:$H,[2]目录表!$AJ:$AJ) -> 散货
B28: Resorte Reloj Pista Carrete Nissan X-trail 2008-2014 1 Cable | MercadoLibre | C28: 7 | D28: 17 | E28: 46041 | G28: 气囊游丝 | H28: 气囊游丝B5567-JM50AN | J28: Resorte Reloj Pista Carrete Nissan X-trail 2008-2014 1 Cable | K28: XQ5-QP013-B5567-JM50AN | L28: 4687132032 | M28: 新上架 | N28: =_xlfn.XLOOKUP(L28,数据更新表!J:J,数据更新表!K:K) -> 100 | O28: =IFERROR(_xlfn.XLOOKUP(K28,数据更新表!A:A,数据更新表!B:B),"0") -> 42 | P28: =_xlfn.XLOOKUP(K28,[1]库销表!$F:$F,[1]库销表!$L:$L) -> 0 | Q28: =X28/W28 -> 147 | S28: =_xlfn.XLOOKUP(K28,数据更新表!R:R,数据更新表!S:S) -> #N/A | T28: =_xlfn.XLOOKUP(K28,数据更新表!V:V,数据更新表!W:W) -> #N/A | V28: =IFERROR(7*O28/CZ28,"0") -> 147 | W28: =CZ28/7 -> 0.28571429 | X28: =O28+P28+SUM(BN28:BR28) -> 42 | AF28: =SUM(AG28:BR28) -> 50 | AK28: 50 | BS28: =_xlfn.XLOOKUP(K28,[1]库销表!$F:$F,[1]库销表!$L:$L) -> 0 | BT28: =SUM(BU28:CV28) -> 0 | CW28: =_xlfn.XLOOKUP(K28,[1]库销表!$F:$F,[1]库销表!$IE:$IE) -> 0 | CX28: =_xlfn.XLOOKUP(K28,[1]库销表!$F:$F,[1]库销表!$IF:$IF) -> 0 | CY28: =_xlfn.XLOOKUP(K28,[1]库销表!$F:$F,[1]库销表!$FL:$FL) -> 0 | CZ28: =_xlfn.XLOOKUP(K28,数据更新表!E:E,数据更新表!F:F,0) -> 2 | DA28: 1 | DB28: =_xlfn.XLOOKUP(K28,数据更新表!E:E,数据更新表!G:G) -> 2 | DC28: =_xlfn.XLOOKUP(L28,数据更新表!Z:Z,数据更新表!AH:AH) -> 2 | DD28: =_xlfn.XLOOKUP(L28,数据更新表!Z:Z,数据更新表!AE:AE) -> 0 | DE28: =_xlfn.XLOOKUP(L28,数据更新表!Z:Z,数据更新表!AF:AF) -> 0 | DF28: =_xlfn.XLOOKUP(K28,数据更新表!Z:Z,数据更新表!AG:AG) -> #N/A | DG28: =_xlfn.XLOOKUP(L28,数据更新表!Z:Z,数据更新表!AD:AD) -> 16.33 | DH28: =_xlfn.XLOOKUP(L28,数据更新表!Z:Z,数据更新表!AA:AA) -> 3084 | DI28: =_xlfn.XLOOKUP(L28,数据更新表!Z:Z,数据更新表!AB:AB) -> 6 | DJ28: =_xlfn.XLOOKUP(L28,数据更新表!Z:Z,数据更新表!AC:AC) -> 0.00% | DK28: =_xlfn.XLOOKUP(L28,数据更新表!Z:Z,数据更新表!AI:AI) -> 2.92% | DL28: =_xlfn.XLOOKUP(L28,数据更新表!AL:AL,数据更新表!AM:AM) -> 2.04% | DM28: =_xlfn.XLOOKUP(L28,数据更新表!Z:Z,数据更新表!AJ:AJ) -> 0 | DN28: 10 | DO28: 开 | DP28: qi nang-6 | DQ28: 46084 | ED28: 调240 开广 | EE28: 280 | EF28: =EE28/0.7 -> 400 | EG28: 27 | EH28: =EJ28/(EI28+EL28) -> 0.69909156 | EI28: =EG28*$EI$1 -> 70.47 | EJ28: =EE28-EI28-EL28-EO28-EN28-EP28-EQ28 -> 61.9644 | EK28: =EJ28/EE28 -> 0.22130143 | EL28: =EX28*3000*$EI$1 -> 18.1656 | EM28: =IF(EE28>299,"是","否") -> 否 | EN28: =EE28*0.05 -> 14 | EO28: =EE28*0.175 -> 49 | EP28: =IF(EE28<299,IF(EE28<99,25,IF(EE28<=149,30,IF(EE28<=299,37,85))),IF(EE28<=498,_xlfn.XLOOKUP(EW28,运费表!A:A,运费表!C:C,"重量超限",-1),_xlfn.XLOOKUP(EW28,运费表!A:A,运费表!D:D,"重量超限",-1))) -> 37 | EQ28: =EE28*0.105 -> 29.4 | ER28: =_xlfn.XLOOKUP(K28,[4]目录表!$H:$H,[4]目录表!$X:$X) -> 0.38 | ES28: =_xlfn.XLOOKUP(K28,[4]目录表!$H:$H,[4]目录表!$Y:$Y) -> 16 | ET28: =_xlfn.XLOOKUP(K28,[4]目录表!$H:$H,[4]目录表!$Z:$Z) -> 14.5 | EU28: =_xlfn.XLOOKUP(K28,[4]目录表!$H:$H,[4]目录表!$AA:$AA) -> 10 | EV28: =ES28*ET28*EU28/5000 -> 0.464 | EW28: =IF(EV28>=ER28,EV28,ER28) -> 0.464 | EX28: =_xlfn.XLOOKUP(K28,[2]目录表!$H:$H,[2]目录表!$AB:$AB) -> 0.00232 | EZ28: =CZ28/7 -> 0.28571429 | FK28: =_xlfn.XLOOKUP(K28,[2]目录表!$H:$H,[2]目录表!$AJ:$AJ) -> 散货
B29: Resorte Reloj Pista Carrete Espiral Toyota Tacoma 2005-2014 Negro | Envío gratis | C29: 28 | D29: 69 | E29: 46038 | G29: 气囊游丝 | H29: 气囊游丝84306 - 06140 | J29: Resorte Reloj Pista Carrete Espiral Toyota Tacoma 2005-2014 Negro | K29: XQ5-QP014-84306-06140 | L29: 4687067332 | M29: 新上架 | N29: =_xlfn.XLOOKUP(L29,数据更新表!J:J,数据更新表!K:K) -> 100 | O29: =IFERROR(_xlfn.XLOOKUP(K29,数据更新表!A:A,数据更新表!B:B),"0") -> 42 | P29: =_xlfn.XLOOKUP(K29,[1]库销表!$F:$F,[1]库销表!$L:$L) -> 0 | Q29: =X29/W29 -> 294 | S29: =_xlfn.XLOOKUP(K29,数据更新表!R:R,数据更新表!S:S) -> #N/A | T29: =_xlfn.XLOOKUP(K29,数据更新表!V:V,数据更新表!W:W) -> #N/A | V29: =IFERROR(7*O29/CZ29,"0") -> 294 | W29: =CZ29/7 -> 0.14285714 | X29: =O29+P29+SUM(BN29:BR29) -> 42 | AF29: =SUM(AG29:BR29) -> 50 | AK29: 50 | BS29: =_xlfn.XLOOKUP(K29,[1]库销表!$F:$F,[1]库销表!$L:$L) -> 0 | BT29: =SUM(BU29:CV29) -> 0 | CW29: =_xlfn.XLOOKUP(K29,[1]库销表!$F:$F,[1]库销表!$IE:$IE) -> 0 | CX29: =_xlfn.XLOOKUP(K29,[1]库销表!$F:$F,[1]库销表!$IF:$IF) -> 0 | CY29: =_xlfn.XLOOKUP(K29,[1]库销表!$F:$F,[1]库销表!$FL:$FL) -> 0 | CZ29: =_xlfn.XLOOKUP(K29,数据更新表!E:E,数据更新表!F:F,0) -> 1 | DA29: 1 | DB29: =_xlfn.XLOOKUP(K29,数据更新表!E:E,数据更新表!G:G) -> 0 | DC29: =_xlfn.XLOOKUP(L29,数据更新表!Z:Z,数据更新表!AH:AH) -> 0 | DD29: =_xlfn.XLOOKUP(L29,数据更新表!Z:Z,数据更新表!AE:AE) -> 2 | DE29: =_xlfn.XLOOKUP(L29,数据更新表!Z:Z,数据更新表!AF:AF) -> 1 | DF29: =_xlfn.XLOOKUP(K29,数据更新表!Z:Z,数据更新表!AG:AG) -> #N/A | DG29: =_xlfn.XLOOKUP(L29,数据更新表!Z:Z,数据更新表!AD:AD) -> 26.94 | DH29: =_xlfn.XLOOKUP(L29,数据更新表!Z:Z,数据更新表!AA:AA) -> 7231 | DI29: =_xlfn.XLOOKUP(L29,数据更新表!Z:Z,数据更新表!AB:AB) -> 8 | DJ29: =_xlfn.XLOOKUP(L29,数据更新表!Z:Z,数据更新表!AC:AC) -> 6.37% | DK29: =_xlfn.XLOOKUP(L29,数据更新表!Z:Z,数据更新表!AI:AI) -> 17.27% | DL29: =_xlfn.XLOOKUP(L29,数据更新表!AL:AL,数据更新表!AM:AM) -> 5.76% | DM29: =_xlfn.XLOOKUP(L29,数据更新表!Z:Z,数据更新表!AJ:AJ) -> 15.71 | DN29: 10 | DO29: 开 | DP29: qi nang-6 | DQ29: 46084 | DU29: 清货 | ED29: 调179 开广 | EE29: =_xlfn.XLOOKUP(L29,数据更新表!J:J,数据更新表!L:L) -> 155.98 | EF29: =EE29/0.7 -> 222.82857 | EG29: 17 | EH29: =EJ29/(EI29+EL29) -> 0.079490722 | EI29: =EG29*$EI$1 -> 44.37 | EJ29: =EE29-EI29-EL29-EO29-EN29-EP29-EQ29 -> 4.971 | EK29: =EJ29/EE29 -> 0.03186947 | EL29: =EX29*3000*$EI$1 -> 18.1656 | EM29: =IF(EE29>299,"是","否") -> 否 | EN29: =EE29*0.05 -> 7.799 | EO29: =EE29*0.175 -> 27.2965 | EP29: =IF(EE29<299,IF(EE29<99,25,IF(EE29<=149,30,IF(EE29<=299,37,85))),IF(EE29<=498,_xlfn.XLOOKUP(EW29,运费表!A:A,运费表!C:C,"重量超限",-1),_xlfn.XLOOKUP(EW29,运费表!A:A,运费表!D:D,"重量超限",-1))) -> 37 | EQ29: =EE29*0.105 -> 16.3779 | ER29: =_xlfn.XLOOKUP(K29,[4]目录表!$H:$H,[4]目录表!$X:$X) -> 0.38 | ES29: =_xlfn.XLOOKUP(K29,[4]目录表!$H:$H,[4]目录表!$Y:$Y) -> 16 | ET29: =_xlfn.XLOOKUP(K29,[4]目录表!$H:$H,[4]目录表!$Z:$Z) -> 14.5 | EU29: =_xlfn.XLOOKUP(K29,[4]目录表!$H:$H,[4]目录表!$AA:$AA) -> 10 | EV29: =ES29*ET29*EU29/5000 -> 0.464 | EW29: =IF(EV29>=ER29,EV29,ER29) -> 0.464 | EX29: =_xlfn.XLOOKUP(K29,[2]目录表!$H:$H,[2]目录表!$AB:$AB) -> 0.00232 | EZ29: =CZ29/7 -> 0.14285714 | FK29: =_xlfn.XLOOKUP(K29,[2]目录表!$H:$H,[2]目录表!$AJ:$AJ) -> 散货
B30: Fy Carrete Resorte Reloj Espiral For Aveo Ng 2018/21 | MercadoLibre | C30: 6 | D30: 19 | E30: 46038 | G30: 气囊游丝 | H30: 气囊游丝26685762 | J30: Fy Carrete Resorte Reloj Espiral For Aveo Ng 2018/21 | K30: XQ5-QP015-26685762 | L30: 4687080914 | M30: 新上架 | N30: =_xlfn.XLOOKUP(L30,数据更新表!J:J,数据更新表!K:K) -> 100 | O30: =IFERROR(_xlfn.XLOOKUP(K30,数据更新表!A:A,数据更新表!B:B),"0") -> 16 | P30: =_xlfn.XLOOKUP(K30,[1]库销表!$F:$F,[1]库销表!$L:$L) -> 0 | Q30: =X30/W30 -> 10.181818 | S30: =_xlfn.XLOOKUP(K30,数据更新表!R:R,数据更新表!S:S) -> #N/A | T30: =_xlfn.XLOOKUP(K30,数据更新表!V:V,数据更新表!W:W) -> #N/A | V30: =IFERROR(7*O30/CZ30,"0") -> 10.181818 | W30: =CZ30/7 -> 1.5714286 | X30: =O30+P30+SUM(BN30:BR30) -> 16 | AF30: =SUM(AG30:BR30) -> 50 | AK30: 50 | BS30: =_xlfn.XLOOKUP(K30,[1]库销表!$F:$F,[1]库销表!$L:$L) -> 0 | BT30: =SUM(BU30:CV30) -> 0 | CW30: =_xlfn.XLOOKUP(K30,[1]库销表!$F:$F,[1]库销表!$IE:$IE) -> 0 | CX30: =_xlfn.XLOOKUP(K30,[1]库销表!$F:$F,[1]库销表!$IF:$IF) -> 0 | CY30: =_xlfn.XLOOKUP(K30,[1]库销表!$F:$F,[1]库销表!$FL:$FL) -> 0 | CZ30: =_xlfn.XLOOKUP(K30,数据更新表!E:E,数据更新表!F:F,0) -> 11 | DA30: 8 | DB30: =_xlfn.XLOOKUP(K30,数据更新表!E:E,数据更新表!G:G) -> 1 | DC30: =_xlfn.XLOOKUP(L30,数据更新表!Z:Z,数据更新表!AH:AH) -> 6 | DD30: =_xlfn.XLOOKUP(L30,数据更新表!Z:Z,数据更新表!AE:AE) -> 5 | DE30: =_xlfn.XLOOKUP(L30,数据更新表!Z:Z,数据更新表!AF:AF) -> 5 | DF30: =_xlfn.XLOOKUP(K30,数据更新表!Z:Z,数据更新表!AG:AG) -> #N/A | DG30: =_xlfn.XLOOKUP(L30,数据更新表!Z:Z,数据更新表!AD:AD) -> 129.72 | DH30: =_xlfn.XLOOKUP(L30,数据更新表!Z:Z,数据更新表!AA:AA) -> 20990 | DI30: =_xlfn.XLOOKUP(L30,数据更新表!Z:Z,数据更新表!AB:AB) -> 35 | DJ30: =_xlfn.XLOOKUP(L30,数据更新表!Z:Z,数据更新表!AC:AC) -> 6.50% | DK30: =_xlfn.XLOOKUP(L30,数据更新表!Z:Z,数据更新表!AI:AI) -> 2.96% | DL30: =_xlfn.XLOOKUP(L30,数据更新表!AL:AL,数据更新表!AM:AM) -> 1.92% | DM30: =_xlfn.XLOOKUP(L30,数据更新表!Z:Z,数据更新表!AJ:AJ) -> 15.38 | DN30: 15 | DO30: 开 | DP30: qi nang_4 | DQ30: 46084 | DU30: 上榜，最低价 | EA30: 开广告 | EB30: 380涨399 | ED30: 调380 开广 | EE30: 399 | EF30: =EE30/0.7 -> 570 | EG30: 33 | EH30: =EJ30/(EI30+EL30) -> 1.02626 | EI30: =EG30*$EI$1 -> 86.13 | EJ30: =EE30-EI30-EL30-EO30-EN30-EP30-EQ30 -> 107.0344 | EK30: =EJ30/EE30 -> 0.26825664 | EL30: =EX30*3000*$EI$1 -> 18.1656 | EM30: =IF(EE30>299,"是","否") -> 是 | EN30: =EE30*0.05 -> 19.95 | EO30: =EE30*0.175 -> 69.825 | EP30: =IF(EE30<299,IF(EE30<99,25,IF(EE30<=149,30,IF(EE30<=299,37,85))),IF(EE30<=498,_xlfn.XLOOKUP(EW30,运费表!A:A,运费表!C:C,"重量超限",-1),_xlfn.XLOOKUP(EW30,运费表!A:A,运费表!D:D,"重量超限",-1))) -> 56 | EQ30: =EE30*0.105 -> 41.895 | ER30: =_xlfn.XLOOKUP(K30,[4]目录表!$H:$H,[4]目录表!$X:$X) -> 0.38 | ES30: =_xlfn.XLOOKUP(K30,[4]目录表!$H:$H,[4]目录表!$Y:$Y) -> 16 | ET30: =_xlfn.XLOOKUP(K30,[4]目录表!$H:$H,[4]目录表!$Z:$Z) -> 14.5 | EU30: =_xlfn.XLOOKUP(K30,[4]目录表!$H:$H,[4]目录表!$AA:$AA) -> 10 | EV30: =ES30*ET30*EU30/5000 -> 0.464 | EW30: =IF(EV30>=ER30,EV30,ER30) -> 0.464 | EX30: =_xlfn.XLOOKUP(K30,[2]目录表!$H:$H,[2]目录表!$AB:$AB) -> 0.00232 | EZ30: =CZ30/7 -> 1.5714286 | FK30: =_xlfn.XLOOKUP(K30,[2]目录表!$H:$H,[2]目录表!$AJ:$AJ) -> 散货
B31: https://articulo.mercadolibre.com.mx/MLM-3359259692-marcha-volkswage-golf-jetta-87-99-caribe-78-89-encendido-_JM#polycard_client=search_best-seller&tracking_id=4de6f91b-01bf-43f2-bd15-e757002642ed | C31: 21 | D31: 62 | E31: 45944 | G31: 汽车马达 | H31: 汽车马达020911023 | J31: Marcha Volkswage Golf Jetta 87-99 Caribe 78-89 Encendido | K31: XQ5-QP025-020911023 | M31: 未上架 | N31: =_xlfn.XLOOKUP(L31,数据更新表!J:J,数据更新表!K:K) -> 0 | O31: =IFERROR(_xlfn.XLOOKUP(K31,数据更新表!A:A,数据更新表!B:B),"0") -> 0 | P31: =_xlfn.XLOOKUP(K31,[1]库销表!$F:$F,[1]库销表!$L:$L) -> 0 | Q31: =X31/W31 -> #DIV/0! | S31: =_xlfn.XLOOKUP(K31,数据更新表!R:R,数据更新表!S:S) -> #N/A | T31: =_xlfn.XLOOKUP(K31,数据更新表!V:V,数据更新表!W:W) -> #N/A | V31: =IFERROR(7*O31/CZ31,"0") -> 0 | W31: =CZ31/7 -> 0 | X31: =O31+P31+SUM(BN31:BR31) -> 0 | AF31: =SUM(AG31:BR31) -> 0 | BS31: =_xlfn.XLOOKUP(K31,[1]库销表!$F:$F,[1]库销表!$L:$L) -> 0 | BT31: =SUM(BU31:CV31) -> 0 | CW31: =_xlfn.XLOOKUP(K31,[1]库销表!$F:$F,[1]库销表!$IE:$IE) -> 0 | CX31: =_xlfn.XLOOKUP(K31,[1]库销表!$F:$F,[1]库销表!$IF:$IF) -> 0 | CY31: =_xlfn.XLOOKUP(K31,[1]库销表!$F:$F,[1]库销表!$FL:$FL) -> 0 | CZ31: =_xlfn.XLOOKUP(K31,数据更新表!E:E,数据更新表!F:F,0) -> 0 | DA31: 0 | DB31: =_xlfn.XLOOKUP(K31,数据更新表!E:E,数据更新表!G:G) -> #N/A | DC31: =_xlfn.XLOOKUP(L31,数据更新表!Z:Z,数据更新表!AH:AH) -> 0 | DD31: =_xlfn.XLOOKUP(L31,数据更新表!Z:Z,数据更新表!AE:AE) -> 0 | DE31: =_xlfn.XLOOKUP(L31,数据更新表!Z:Z,数据更新表!AF:AF) -> 0 | DF31: =_xlfn.XLOOKUP(K31,数据更新表!Z:Z,数据更新表!AG:AG) -> #N/A | DG31: =_xlfn.XLOOKUP(L31,数据更新表!Z:Z,数据更新表!AD:AD) -> 0 | DH31: =_xlfn.XLOOKUP(L31,数据更新表!Z:Z,数据更新表!AA:AA) -> 0 | DI31: =_xlfn.XLOOKUP(L31,数据更新表!Z:Z,数据更新表!AB:AB) -> 0 | DJ31: =_xlfn.XLOOKUP(L31,数据更新表!Z:Z,数据更新表!AC:AC) -> 0 | DK31: =_xlfn.XLOOKUP(L31,数据更新表!Z:Z,数据更新表!AI:AI) -> 0 | DL31: =_xlfn.XLOOKUP(L31,数据更新表!AL:AL,数据更新表!AM:AM) -> 0 | DM31: =_xlfn.XLOOKUP(L31,数据更新表!Z:Z,数据更新表!AJ:AJ) -> 0 | EE31: =_xlfn.XLOOKUP(L31,数据更新表!J:J,数据更新表!L:L) -> 0 | EF31: =_xlfn.XLOOKUP(L31,数据更新表!J:J,数据更新表!M:M) -> 0 | EG31: 140 | EH31: =EJ31/(EI31+EL31) -> -1.0599949 | EI31: =EG31*$EI$1 -> 365.4 | EJ31: =EE31-EI31-EL31-EO31-EN31-EP31-EQ31 -> -441.70216 | EK31: =EJ31/EE31 -> #DIV/0! | EL31: =EX31*3000*$EI$1 -> 51.30216 | EM31: =IF(EE31>299,"是","否") -> 否 | EN31: =EE31*0.05 -> 0 | EO31: =EE31*0.175 -> 0 | EP31: =IF(EE31<299,IF(EE31<99,25,IF(EE31<=149,30,IF(EE31<=299,37,85))),IF(EE31<=498,_xlfn.XLOOKUP(EW31,运费表!A:A,运费表!C:C,"重量超限",-1),_xlfn.XLOOKUP(EW31,运费表!A:A,运费表!D:D,"重量超限",-1))) -> 25 | EQ31: =EE31*0.105 -> 0 | ER31: =_xlfn.XLOOKUP(K31,[4]目录表!$H:$H,[4]目录表!$X:$X) -> 3.3 | ES31: =_xlfn.XLOOKUP(K31,[4]目录表!$H:$H,[4]目录表!$Y:$Y) -> 26 | ET31: =_xlfn.XLOOKUP(K31,[4]目录表!$H:$H,[4]目录表!$Z:$Z) -> 16.8 | EU31: =_xlfn.XLOOKUP(K31,[4]目录表!$H:$H,[4]目录表!$AA:$AA) -> 15 | EV31: =ES31*ET31*EU31/5000 -> 1.3104 | EW31: =IF(EV31>=ER31,EV31,ER31) -> 3.3 | EX31: =_xlfn.XLOOKUP(K31,[2]目录表!$H:$H,[2]目录表!$AB:$AB) -> 0.006552 | EZ31: =CZ31/7 -> 0 | FK31: =_xlfn.XLOOKUP(K31,[2]目录表!$H:$H,[2]目录表!$AJ:$AJ) -> 散货
B32: https://www.mercadolibre.com.mx/marcha-para-chevrolet-aveo-0417-tornado-0410-pontiac-g3/up/MLMU2863668269#polycard_client=search_best-seller&tracking_id=0f2c14e6-eaa7-4f26-87e4-67e0a36b0da7&wid=MLM3481305334&sid=search | C32: 2 | D32: 58 | E32: 45944 | G32: 汽车马达 | H32: 汽车马达96469963 | J32: Marcha Para Chevrolet Aveo 04-17, Tornado 04-10, Pontiac G3 | K32: XQ5-QP026-96469963 | M32: 未上架 | N32: =_xlfn.XLOOKUP(L32,数据更新表!J:J,数据更新表!K:K) -> 0 | O32: =IFERROR(_xlfn.XLOOKUP(K32,数据更新表!A:A,数据更新表!B:B),"0") -> 0 | P32: =_xlfn.XLOOKUP(K32,[1]库销表!$F:$F,[1]库销表!$L:$L) -> 0 | Q32: =X32/W32 -> #DIV/0! | S32: =_xlfn.XLOOKUP(K32,数据更新表!R:R,数据更新表!S:S) -> #N/A | T32: =_xlfn.XLOOKUP(K32,数据更新表!V:V,数据更新表!W:W) -> #N/A | V32: =IFERROR(7*O32/CZ32,"0") -> 0 | W32: =CZ32/7 -> 0 | X32: =O32+P32+SUM(BN32:BR32) -> 0 | AF32: =SUM(AG32:BR32) -> 0 | BS32: =_xlfn.XLOOKUP(K32,[1]库销表!$F:$F,[1]库销表!$L:$L) -> 0 | BT32: =SUM(BU32:CV32) -> 0 | CW32: =_xlfn.XLOOKUP(K32,[1]库销表!$F:$F,[1]库销表!$IE:$IE) -> 0 | CX32: =_xlfn.XLOOKUP(K32,[1]库销表!$F:$F,[1]库销表!$IF:$IF) -> 0 | CY32: =_xlfn.XLOOKUP(K32,[1]库销表!$F:$F,[1]库销表!$FL:$FL) -> 0 | CZ32: =_xlfn.XLOOKUP(K32,数据更新表!E:E,数据更新表!F:F,0) -> 0 | DA32: 0 | DB32: =_xlfn.XLOOKUP(K32,数据更新表!E:E,数据更新表!G:G) -> #N/A | DC32: =_xlfn.XLOOKUP(L32,数据更新表!Z:Z,数据更新表!AH:AH) -> 0 | DD32: =_xlfn.XLOOKUP(L32,数据更新表!Z:Z,数据更新表!AE:AE) -> 0 | DE32: =_xlfn.XLOOKUP(L32,数据更新表!Z:Z,数据更新表!AF:AF) -> 0 | DF32: =_xlfn.XLOOKUP(K32,数据更新表!Z:Z,数据更新表!AG:AG) -> #N/A | DG32: =_xlfn.XLOOKUP(L32,数据更新表!Z:Z,数据更新表!AD:AD) -> 0 | DH32: =_xlfn.XLOOKUP(L32,数据更新表!Z:Z,数据更新表!AA:AA) -> 0 | DI32: =_xlfn.XLOOKUP(L32,数据更新表!Z:Z,数据更新表!AB:AB) -> 0 | DJ32: =_xlfn.XLOOKUP(L32,数据更新表!Z:Z,数据更新表!AC:AC) -> 0 | DK32: =_xlfn.XLOOKUP(L32,数据更新表!Z:Z,数据更新表!AI:AI) -> 0 | DL32: =_xlfn.XLOOKUP(L32,数据更新表!AL:AL,数据更新表!AM:AM) -> 0 | DM32: =_xlfn.XLOOKUP(L32,数据更新表!Z:Z,数据更新表!AJ:AJ) -> 0 | EE32: =_xlfn.XLOOKUP(L32,数据更新表!J:J,数据更新表!L:L) -> 0 | EF32: =_xlfn.XLOOKUP(L32,数据更新表!J:J,数据更新表!M:M) -> 0 | EG32: 120 | EH32: =EJ32/(EI32+EL32) -> -1.0685867 | EI32: =EG32*$EI$1 -> 313.2 | EJ32: =EE32-EI32-EL32-EO32-EN32-EP32-EQ32 -> -389.50216 | EK32: =EJ32/EE32 -> #DIV/0! | EL32: =EX32*3000*$EI$1 -> 51.30216 | EM32: =IF(EE32>299,"是","否") -> 否 | EN32: =EE32*0.05 -> 0 | EO32: =EE32*0.175 -> 0 | EP32: =IF(EE32<299,IF(EE32<99,25,IF(EE32<=149,30,IF(EE32<=299,37,85))),IF(EE32<=498,_xlfn.XLOOKUP(EW32,运费表!A:A,运费表!C:C,"重量超限",-1),_xlfn.XLOOKUP(EW32,运费表!A:A,运费表!D:D,"重量超限",-1))) -> 25 | EQ32: =EE32*0.105 -> 0 | ER32: =_xlfn.XLOOKUP(K32,[4]目录表!$H:$H,[4]目录表!$X:$X) -> 3.3 | ES32: =_xlfn.XLOOKUP(K32,[4]目录表!$H:$H,[4]目录表!$Y:$Y) -> 26 | ET32: =_xlfn.XLOOKUP(K32,[4]目录表!$H:$H,[4]目录表!$Z:$Z) -> 16.8 | EU32: =_xlfn.XLOOKUP(K32,[4]目录表!$H:$H,[4]目录表!$AA:$AA) -> 15 | EV32: =ES32*ET32*EU32/5000 -> 1.3104 | EW32: =IF(EV32>=ER32,EV32,ER32) -> 3.3 | EX32: =_xlfn.XLOOKUP(K32,[2]目录表!$H:$H,[2]目录表!$AB:$AB) -> 0.006552 | EZ32: =CZ32/7 -> 0 | FK32: =_xlfn.XLOOKUP(K32,[2]目录表!$H:$H,[2]目录表!$AJ:$AJ) -> 散货
B33: Marcha Para Chevrolet Chevy 1994-2012, Astra, Corsa 00-08 9d | Envío gratis | C33: 48 | D33: 236 | E33: 45944 | G33: 汽车马达 | H33: 汽车马达0001107402 | J33: Marcha Para Chevrolet Chevy 1994-2012, Astra, Corsa 00-08 9d | K33: XQ5-QP027-0001107402 | M33: 未上架 | N33: =_xlfn.XLOOKUP(L33,数据更新表!J:J,数据更新表!K:K) -> 0 | O33: =IFERROR(_xlfn.XLOOKUP(K33,数据更新表!A:A,数据更新表!B:B),"0") -> 0 | P33: =_xlfn.XLOOKUP(K33,[1]库销表!$F:$F,[1]库销表!$L:$L) -> 0 | Q33: =X33/W33 -> #DIV/0! | S33: =_xlfn.XLOOKUP(K33,数据更新表!R:R,数据更新表!S:S) -> #N/A | T33: =_xlfn.XLOOKUP(K33,数据更新表!V:V,数据更新表!W:W) -> #N/A | V33: =IFERROR(7*O33/CZ33,"0") -> 0 | W33: =CZ33/7 -> 0 | X33: =O33+P33+SUM(BN33:BR33) -> 0 | AF33: =SUM(AG33:BR33) -> 0 | BS33: =_xlfn.XLOOKUP(K33,[1]库销表!$F:$F,[1]库销表!$L:$L) -> 0 | BT33: =SUM(BU33:CV33) -> 0 | CW33: =_xlfn.XLOOKUP(K33,[1]库销表!$F:$F,[1]库销表!$IE:$IE) -> 0 | CX33: =_xlfn.XLOOKUP(K33,[1]库销表!$F:$F,[1]库销表!$IF:$IF) -> 0 | CY33: =_xlfn.XLOOKUP(K33,[1]库销表!$F:$F,[1]库销表!$FL:$FL) -> 0 | CZ33: =_xlfn.XLOOKUP(K33,数据更新表!E:E,数据更新表!F:F,0) -> 0 | DA33: 0 | DB33: =_xlfn.XLOOKUP(K33,数据更新表!E:E,数据更新表!G:G) -> #N/A | DC33: =_xlfn.XLOOKUP(L33,数据更新表!Z:Z,数据更新表!AH:AH) -> 0 | DD33: =_xlfn.XLOOKUP(L33,数据更新表!Z:Z,数据更新表!AE:AE) -> 0 | DE33: =_xlfn.XLOOKUP(L33,数据更新表!Z:Z,数据更新表!AF:AF) -> 0 | DF33: =_xlfn.XLOOKUP(K33,数据更新表!Z:Z,数据更新表!AG:AG) -> #N/A | DG33: =_xlfn.XLOOKUP(L33,数据更新表!Z:Z,数据更新表!AD:AD) -> 0 | DH33: =_xlfn.XLOOKUP(L33,数据更新表!Z:Z,数据更新表!AA:AA) -> 0 | DI33: =_xlfn.XLOOKUP(L33,数据更新表!Z:Z,数据更新表!AB:AB) -> 0 | DJ33: =_xlfn.XLOOKUP(L33,数据更新表!Z:Z,数据更新表!AC:AC) -> 0 | DK33: =_xlfn.XLOOKUP(L33,数据更新表!Z:Z,数据更新表!AI:AI) -> 0 | DL33: =_xlfn.XLOOKUP(L33,数据更新表!AL:AL,数据更新表!AM:AM) -> 0 | DM33: =_xlfn.XLOOKUP(L33,数据更新表!Z:Z,数据更新表!AJ:AJ) -> 0 | EE33: =_xlfn.XLOOKUP(L33,数据更新表!J:J,数据更新表!L:L) -> 0 | EF33: =_xlfn.XLOOKUP(L33,数据更新表!J:J,数据更新表!M:M) -> 0 | EG33: 115 | EH33: =EJ33/(EI33+EL33) -> -1.0711334 | EI33: =EG33*$EI$1 -> 300.15 | EJ33: =EE33-EI33-EL33-EO33-EN33-EP33-EQ33 -> -376.45216 | EK33: =EJ33/EE33 -> #DIV/0! | EL33: =EX33*3000*$EI$1 -> 51.30216 | EM33: =IF(EE33>299,"是","否") -> 否 | EN33: =EE33*0.05 -> 0 | EO33: =EE33*0.175 -> 0 | EP33: =IF(EE33<299,IF(EE33<99,25,IF(EE33<=149,30,IF(EE33<=299,37,85))),IF(EE33<=498,_xlfn.XLOOKUP(EW33,运费表!A:A,运费表!C:C,"重量超限",-1),_xlfn.XLOOKUP(EW33,运费表!A:A,运费表!D:D,"重量超限",-1))) -> 25 | EQ33: =EE33*0.105 -> 0 | ER33: =_xlfn.XLOOKUP(K33,[4]目录表!$H:$H,[4]目录表!$X:$X) -> 3.3 | ES33: =_xlfn.XLOOKUP(K33,[4]目录表!$H:$H,[4]目录表!$Y:$Y) -> 26 | ET33: =_xlfn.XLOOKUP(K33,[4]目录表!$H:$H,[4]目录表!$Z:$Z) -> 16.8 | EU33: =_xlfn.XLOOKUP(K33,[4]目录表!$H:$H,[4]目录表!$AA:$AA) -> 15 | EV33: =ES33*ET33*EU33/5000 -> 1.3104 | EW33: =IF(EV33>=ER33,EV33,ER33) -> 3.3 | EX33: =_xlfn.XLOOKUP(K33,[2]目录表!$H:$H,[2]目录表!$AB:$AB) -> 0.006552 | EZ33: =CZ33/7 -> 0 | FK33: =_xlfn.XLOOKUP(K33,[2]目录表!$H:$H,[2]目录表!$AJ:$AJ) -> 散货
B34: https://www.mercadolibre.com.mx/marcha-para-nissan-versa-tiida-march-note-20092019-16l/up/MLMU2908349051#polycard_client=search_best-seller&tracking_id=9d239245-9811-4bc1-aa4b-95c57c8549b5&wid=MLM2209491185&sid=search | C34: 16 | D34: 56 | E34: 45944 | G34: 汽车马达 | H34: 汽车马达S114-901A | J34: Marcha Para Nissan Versa, Tiida, March, Note 2009-2019 1.6l | K34: XQ5-QP028-S114-901A | M34: 未上架 | N34: =_xlfn.XLOOKUP(L34,数据更新表!J:J,数据更新表!K:K) -> 0 | O34: =IFERROR(_xlfn.XLOOKUP(K34,数据更新表!A:A,数据更新表!B:B),"0") -> 0 | P34: =_xlfn.XLOOKUP(K34,[1]库销表!$F:$F,[1]库销表!$L:$L) -> 0 | Q34: =X34/W34 -> #DIV/0! | S34: =_xlfn.XLOOKUP(K34,数据更新表!R:R,数据更新表!S:S) -> #N/A | T34: =_xlfn.XLOOKUP(K34,数据更新表!V:V,数据更新表!W:W) -> #N/A | V34: =IFERROR(7*O34/CZ34,"0") -> 0 | W34: =CZ34/7 -> 0 | X34: =O34+P34+SUM(BN34:BR34) -> 0 | AF34: =SUM(AG34:BR34) -> 0 | BS34: =_xlfn.XLOOKUP(K34,[1]库销表!$F:$F,[1]库销表!$L:$L) -> 0 | BT34: =SUM(BU34:CV34) -> 0 | CW34: =_xlfn.XLOOKUP(K34,[1]库销表!$F:$F,[1]库销表!$IE:$IE) -> 0 | CX34: =_xlfn.XLOOKUP(K34,[1]库销表!$F:$F,[1]库销表!$IF:$IF) -> 0 | CY34: =_xlfn.XLOOKUP(K34,[1]库销表!$F:$F,[1]库销表!$FL:$FL) -> 0 | CZ34: =_xlfn.XLOOKUP(K34,数据更新表!E:E,数据更新表!F:F,0) -> 0 | DA34: 0 | DB34: =_xlfn.XLOOKUP(K34,数据更新表!E:E,数据更新表!G:G) -> #N/A | DC34: =_xlfn.XLOOKUP(L34,数据更新表!Z:Z,数据更新表!AH:AH) -> 0 | DD34: =_xlfn.XLOOKUP(L34,数据更新表!Z:Z,数据更新表!AE:AE) -> 0 | DE34: =_xlfn.XLOOKUP(L34,数据更新表!Z:Z,数据更新表!AF:AF) -> 0 | DF34: =_xlfn.XLOOKUP(K34,数据更新表!Z:Z,数据更新表!AG:AG) -> #N/A | DG34: =_xlfn.XLOOKUP(L34,数据更新表!Z:Z,数据更新表!AD:AD) -> 0 | DH34: =_xlfn.XLOOKUP(L34,数据更新表!Z:Z,数据更新表!AA:AA) -> 0 | DI34: =_xlfn.XLOOKUP(L34,数据更新表!Z:Z,数据更新表!AB:AB) -> 0 | DJ34: =_xlfn.XLOOKUP(L34,数据更新表!Z:Z,数据更新表!AC:AC) -> 0 | DK34: =_xlfn.XLOOKUP(L34,数据更新表!Z:Z,数据更新表!AI:AI) -> 0 | DL34: =_xlfn.XLOOKUP(L34,数据更新表!AL:AL,数据更新表!AM:AM) -> 0 | DM34: =_xlfn.XLOOKUP(L34,数据更新表!Z:Z,数据更新表!AJ:AJ) -> 0 | EE34: =_xlfn.XLOOKUP(L34,数据更新表!J:J,数据更新表!L:L) -> 0 | EF34: =_xlfn.XLOOKUP(L34,数据更新表!J:J,数据更新表!M:M) -> 0 | EG34: 125 | EH34: =EJ34/(EI34+EL34) -> -1.066216 | EI34: =EG34*$EI$1 -> 326.25 | EJ34: =EE34-EI34-EL34-EO34-EN34-EP34-EQ34 -> -402.55216 | EK34: =EJ34/EE34 -> #DIV/0! | EL34: =EX34*3000*$EI$1 -> 51.30216 | EM34: =IF(EE34>299,"是","否") -> 否 | EN34: =EE34*0.05 -> 0 | EO34: =EE34*0.175 -> 0 | EP34: =IF(EE34<299,IF(EE34<99,25,IF(EE34<=149,30,IF(EE34<=299,37,85))),IF(EE34<=498,_xlfn.XLOOKUP(EW34,运费表!A:A,运费表!C:C,"重量超限",-1),_xlfn.XLOOKUP(EW34,运费表!A:A,运费表!D:D,"重量超限",-1))) -> 25 | EQ34: =EE34*0.105 -> 0 | ER34: =_xlfn.XLOOKUP(K34,[4]目录表!$H:$H,[4]目录表!$X:$X) -> 3.3 | ES34: =_xlfn.XLOOKUP(K34,[4]目录表!$H:$H,[4]目录表!$Y:$Y) -> 26 | ET34: =_xlfn.XLOOKUP(K34,[4]目录表!$H:$H,[4]目录表!$Z:$Z) -> 16.8 | EU34: =_xlfn.XLOOKUP(K34,[4]目录表!$H:$H,[4]目录表!$AA:$AA) -> 15 | EV34: =ES34*ET34*EU34/5000 -> 1.3104 | EW34: =IF(EV34>=ER34,EV34,ER34) -> 3.3 | EX34: =_xlfn.XLOOKUP(K34,[2]目录表!$H:$H,[2]目录表!$AB:$AB) -> 0.006552 | EZ34: =CZ34/7 -> 0 | FK34: =_xlfn.XLOOKUP(K34,[2]目录表!$H:$H,[2]目录表!$AJ:$AJ) -> 散货
B35: https://www.mercadolibre.com.mx/marcha-tsuru-19842017-sentra-821999-transmision-std-8-dts/up/MLMU509343700#polycard_client=search_best-seller&tracking_id=36da195b-0e57-462b-8963-8765c8e102b9&wid=MLM3098337328&sid=search | C35: 18 | D35: 84 | E35: 45944 | G35: 汽车马达 | H35: 汽车马达S114-769 | J35: Marcha Tsuru 1984-2017, Sentra 82-1999 Transmision Std 8 Dts | K35: XQ5-QP029-S114-769 | M35: 未上架 | N35: =_xlfn.XLOOKUP(L35,数据更新表!J:J,数据更新表!K:K) -> 0 | O35: =IFERROR(_xlfn.XLOOKUP(K35,数据更新表!A:A,数据更新表!B:B),"0") -> 0 | P35: =_xlfn.XLOOKUP(K35,[1]库销表!$F:$F,[1]库销表!$L:$L) -> 0 | Q35: =X35/W35 -> #DIV/0! | S35: =_xlfn.XLOOKUP(K35,数据更新表!R:R,数据更新表!S:S) -> #N/A | T35: =_xlfn.XLOOKUP(K35,数据更新表!V:V,数据更新表!W:W) -> #N/A | V35: =IFERROR(7*O35/CZ35,"0") -> 0 | W35: =CZ35/7 -> 0 | X35: =O35+P35+SUM(BN35:BR35) -> 0 | AF35: =SUM(AG35:BR35) -> 0 | BS35: =_xlfn.XLOOKUP(K35,[1]库销表!$F:$F,[1]库销表!$L:$L) -> 0 | BT35: =SUM(BU35:CV35) -> 0 | CW35: =_xlfn.XLOOKUP(K35,[1]库销表!$F:$F,[1]库销表!$IE:$IE) -> 0 | CX35: =_xlfn.XLOOKUP(K35,[1]库销表!$F:$F,[1]库销表!$IF:$IF) -> 0 | CY35: =_xlfn.XLOOKUP(K35,[1]库销表!$F:$F,[1]库销表!$FL:$FL) -> 0 | CZ35: =_xlfn.XLOOKUP(K35,数据更新表!E:E,数据更新表!F:F,0) -> 0 | DA35: 0 | DB35: =_xlfn.XLOOKUP(K35,数据更新表!E:E,数据更新表!G:G) -> #N/A | DC35: =_xlfn.XLOOKUP(L35,数据更新表!Z:Z,数据更新表!AH:AH) -> 0 | DD35: =_xlfn.XLOOKUP(L35,数据更新表!Z:Z,数据更新表!AE:AE) -> 0 | DE35: =_xlfn.XLOOKUP(L35,数据更新表!Z:Z,数据更新表!AF:AF) -> 0 | DF35: =_xlfn.XLOOKUP(K35,数据更新表!Z:Z,数据更新表!AG:AG) -> #N/A | DG35: =_xlfn.XLOOKUP(L35,数据更新表!Z:Z,数据更新表!AD:AD) -> 0 | DH35: =_xlfn.XLOOKUP(L35,数据更新表!Z:Z,数据更新表!AA:AA) -> 0 | DI35: =_xlfn.XLOOKUP(L35,数据更新表!Z:Z,数据更新表!AB:AB) -> 0 | DJ35: =_xlfn.XLOOKUP(L35,数据更新表!Z:Z,数据更新表!AC:AC) -> 0 | DK35: =_xlfn.XLOOKUP(L35,数据更新表!Z:Z,数据更新表!AI:AI) -> 0 | DL35: =_xlfn.XLOOKUP(L35,数据更新表!AL:AL,数据更新表!AM:AM) -> 0 | DM35: =_xlfn.XLOOKUP(L35,数据更新表!Z:Z,数据更新表!AJ:AJ) -> 0 | EE35: =_xlfn.XLOOKUP(L35,数据更新表!J:J,数据更新表!L:L) -> 0 | EF35: =_xlfn.XLOOKUP(L35,数据更新表!J:J,数据更新表!M:M) -> 0 | EG35: 165 | EH35: =EJ35/(EI35+EL35) -> -1.0518724 | EI35: =EG35*$EI$1 -> 430.65 | EJ35: =EE35-EI35-EL35-EO35-EN35-EP35-EQ35 -> -506.95216 | EK35: =EJ35/EE35 -> #DIV/0! | EL35: =EX35*3000*$EI$1 -> 51.30216 | EM35: =IF(EE35>299,"是","否") -> 否 | EN35: =EE35*0.05 -> 0 | EO35: =EE35*0.175 -> 0 | EP35: =IF(EE35<299,IF(EE35<99,25,IF(EE35<=149,30,IF(EE35<=299,37,85))),IF(EE35<=498,_xlfn.XLOOKUP(EW35,运费表!A:A,运费表!C:C,"重量超限",-1),_xlfn.XLOOKUP(EW35,运费表!A:A,运费表!D:D,"重量超限",-1))) -> 25 | EQ35: =EE35*0.105 -> 0 | ER35: =_xlfn.XLOOKUP(K35,[4]目录表!$H:$H,[4]目录表!$X:$X) -> 3.3 | ES35: =_xlfn.XLOOKUP(K35,[4]目录表!$H:$H,[4]目录表!$Y:$Y) -> 26 | ET35: =_xlfn.XLOOKUP(K35,[4]目录表!$H:$H,[4]目录表!$Z:$Z) -> 16.8 | EU35: =_xlfn.XLOOKUP(K35,[4]目录表!$H:$H,[4]目录表!$AA:$AA) -> 15 | EV35: =ES35*ET35*EU35/5000 -> 1.3104 | EW35: =IF(EV35>=ER35,EV35,ER35) -> 3.3 | EX35: =_xlfn.XLOOKUP(K35,[2]目录表!$H:$H,[2]目录表!$AB:$AB) -> 0.006552 | EZ35: =CZ35/7 -> 0 | FK35: =_xlfn.XLOOKUP(K35,[2]目录表!$H:$H,[2]目录表!$AJ:$AJ) -> 散货
B36: https://www.mercadolibre.com.mx/marcha-p-chevrolet-c1500-c2500-c3500-silverado-suburban-11d/up/MLMU2836302409#polycard_client=search_best-seller&tracking_id=e485248c-2905-47ae-bd09-2a75f1d94977&wid=MLM3472649120&sid=search | C36: 11 | D36: 50 | E36: 45944 | G36: 汽车马达 | H36: 汽车马达8000727 | J36: Marcha P/ Chevrolet C1500 C2500 C3500 Silverado Suburban 11d | K36: XQ5-QP030-8000727 | M36: 未上架 | N36: =_xlfn.XLOOKUP(L36,数据更新表!J:J,数据更新表!K:K) -> 0 | O36: =IFERROR(_xlfn.XLOOKUP(K36,数据更新表!A:A,数据更新表!B:B),"0") -> 0 | P36: =_xlfn.XLOOKUP(K36,[1]库销表!$F:$F,[1]库销表!$L:$L) -> 0 | Q36: =X36/W36 -> #DIV/0! | S36: =_xlfn.XLOOKUP(K36,数据更新表!R:R,数据更新表!S:S) -> #N/A | T36: =_xlfn.XLOOKUP(K36,数据更新表!V:V,数据更新表!W:W) -> #N/A | V36: =IFERROR(7*O36/CZ36,"0") -> 0 | W36: =CZ36/7 -> 0 | X36: =O36+P36+SUM(BN36:BR36) -> 0 | AF36: =SUM(AG36:BR36) -> 0 | BS36: =_xlfn.XLOOKUP(K36,[1]库销表!$F:$F,[1]库销表!$L:$L) -> 0 | BT36: =SUM(BU36:CV36) -> 0 | CW36: =_xlfn.XLOOKUP(K36,[1]库销表!$F:$F,[1]库销表!$IE:$IE) -> 0 | CX36: =_xlfn.XLOOKUP(K36,[1]库销表!$F:$F,[1]库销表!$IF:$IF) -> 0 | CY36: =_xlfn.XLOOKUP(K36,[1]库销表!$F:$F,[1]库销表!$FL:$FL) -> 0 | CZ36: =_xlfn.XLOOKUP(K36,数据更新表!E:E,数据更新表!F:F,0) -> 0 | DA36: 0 | DB36: =_xlfn.XLOOKUP(K36,数据更新表!E:E,数据更新表!G:G) -> #N/A | DC36: =_xlfn.XLOOKUP(L36,数据更新表!Z:Z,数据更新表!AH:AH) -> 0 | DD36: =_xlfn.XLOOKUP(L36,数据更新表!Z:Z,数据更新表!AE:AE) -> 0 | DE36: =_xlfn.XLOOKUP(L36,数据更新表!Z:Z,数据更新表!AF:AF) -> 0 | DF36: =_xlfn.XLOOKUP(K36,数据更新表!Z:Z,数据更新表!AG:AG) -> #N/A | DG36: =_xlfn.XLOOKUP(L36,数据更新表!Z:Z,数据更新表!AD:AD) -> 0 | DH36: =_xlfn.XLOOKUP(L36,数据更新表!Z:Z,数据更新表!AA:AA) -> 0 | DI36: =_xlfn.XLOOKUP(L36,数据更新表!Z:Z,数据更新表!AB:AB) -> 0 | DJ36: =_xlfn.XLOOKUP(L36,数据更新表!Z:Z,数据更新表!AC:AC) -> 0 | DK36: =_xlfn.XLOOKUP(L36,数据更新表!Z:Z,数据更新表!AI:AI) -> 0 | DL36: =_xlfn.XLOOKUP(L36,数据更新表!AL:AL,数据更新表!AM:AM) -> 0 | DM36: =_xlfn.XLOOKUP(L36,数据更新表!Z:Z,数据更新表!AJ:AJ) -> 0 | EE36: =_xlfn.XLOOKUP(L36,数据更新表!J:J,数据更新表!L:L) -> 0 | EF36: =_xlfn.XLOOKUP(L36,数据更新表!J:J,数据更新表!M:M) -> 0 | EG36: 140 | EH36: =EJ36/(EI36+EL36) -> -1.0599949 | EI36: =EG36*$EI$1 -> 365.4 | EJ36: =EE36-EI36-EL36-EO36-EN36-EP36-EQ36 -> -441.70216 | EK36: =EJ36/EE36 -> #DIV/0! | EL36: =EX36*3000*$EI$1 -> 51.30216 | EM36: =IF(EE36>299,"是","否") -> 否 | EN36: =EE36*0.05 -> 0 | EO36: =EE36*0.175 -> 0 | EP36: =IF(EE36<299,IF(EE36<99,25,IF(EE36<=149,30,IF(EE36<=299,37,85))),IF(EE36<=498,_xlfn.XLOOKUP(EW36,运费表!A:A,运费表!C:C,"重量超限",-1),_xlfn.XLOOKUP(EW36,运费表!A:A,运费表!D:D,"重量超限",-1))) -> 25 | EQ36: =EE36*0.105 -> 0 | ER36: =_xlfn.XLOOKUP(K36,[4]目录表!$H:$H,[4]目录表!$X:$X) -> 3.3 | ES36: =_xlfn.XLOOKUP(K36,[4]目录表!$H:$H,[4]目录表!$Y:$Y) -> 26 | ET36: =_xlfn.XLOOKUP(K36,[4]目录表!$H:$H,[4]目录表!$Z:$Z) -> 16.8 | EU36: =_xlfn.XLOOKUP(K36,[4]目录表!$H:$H,[4]目录表!$AA:$AA) -> 15 | EV36: =ES36*ET36*EU36/5000 -> 1.3104 | EW36: =IF(EV36>=ER36,EV36,ER36) -> 3.3 | EX36: =_xlfn.XLOOKUP(K36,[2]目录表!$H:$H,[2]目录表!$AB:$AB) -> 0.006552 | EZ36: =CZ36/7 -> 0 | FK36: =_xlfn.XLOOKUP(K36,[2]目录表!$H:$H,[2]目录表!$AJ:$AJ) -> 散货
B37: Bomba Vacio Booster Frenos Trax Onix 1.0 1.2 2021 2022 | Envío gratis | C37: 19 | D37: 32 | E37: 46038 | G37: 真空泵 | H37: 真空泵55503109 | J37: Bomba Vacio Booster Frenos Trax Onix 1.0 1.2 2021 2022 | K37: XQ5-QP016-55503109 | L37: 4687042964 | M37: 新上架 | N37: =_xlfn.XLOOKUP(L37,数据更新表!J:J,数据更新表!K:K) -> 100 | O37: =IFERROR(_xlfn.XLOOKUP(K37,数据更新表!A:A,数据更新表!B:B),"0") -> 20 | P37: =_xlfn.XLOOKUP(K37,[1]库销表!$F:$F,[1]库销表!$L:$L) -> 0 | Q37: =X37/W37 -> 35 | S37: =_xlfn.XLOOKUP(K37,数据更新表!R:R,数据更新表!S:S) -> #N/A | T37: =_xlfn.XLOOKUP(K37,数据更新表!V:V,数据更新表!W:W) -> #N/A | V37: =IFERROR(7*O37/CZ37,"0") -> 35 | W37: =CZ37/7 -> 0.57142857 | X37: =O37+P37+SUM(BN37:BR37) -> 20 | AF37: =SUM(AG37:BR37) -> 24 | AJ37: 24 | BS37: =_xlfn.XLOOKUP(K37,[1]库销表!$F:$F,[1]库销表!$L:$L) -> 0 | BT37: =SUM(BU37:CV37) -> 0 | CW37: =_xlfn.XLOOKUP(K37,[1]库销表!$F:$F,[1]库销表!$IE:$IE) -> 0 | CX37: =_xlfn.XLOOKUP(K37,[1]库销表!$F:$F,[1]库销表!$IF:$IF) -> 0 | CY37: =_xlfn.XLOOKUP(K37,[1]库销表!$F:$F,[1]库销表!$FL:$FL) -> 0 | CZ37: =_xlfn.XLOOKUP(K37,数据更新表!E:E,数据更新表!F:F,0) -> 4 | DA37: 1 | DB37: =_xlfn.XLOOKUP(K37,数据更新表!E:E,数据更新表!G:G) -> 0 | DC37: =_xlfn.XLOOKUP(L37,数据更新表!Z:Z,数据更新表!AH:AH) -> 3 | DD37: =_xlfn.XLOOKUP(L37,数据更新表!Z:Z,数据更新表!AE:AE) -> 1 | DE37: =_xlfn.XLOOKUP(L37,数据更新表!Z:Z,数据更新表!AF:AF) -> 1 | DF37: =_xlfn.XLOOKUP(K37,数据更新表!Z:Z,数据更新表!AG:AG) -> #N/A | DG37: =_xlfn.XLOOKUP(L37,数据更新表!Z:Z,数据更新表!AD:AD) -> 986.47 | DH37: =_xlfn.XLOOKUP(L37,数据更新表!Z:Z,数据更新表!AA:AA) -> 12445 | DI37: =_xlfn.XLOOKUP(L37,数据更新表!Z:Z,数据更新表!AB:AB) -> 42 | DJ37: =_xlfn.XLOOKUP(L37,数据更新表!Z:Z,数据更新表!AC:AC) -> 75.94% | DK37: =_xlfn.XLOOKUP(L37,数据更新表!Z:Z,数据更新表!AI:AI) -> 18.99% | DL37: =_xlfn.XLOOKUP(L37,数据更新表!AL:AL,数据更新表!AM:AM) -> 19.03% | DM37: =_xlfn.XLOOKUP(L37,数据更新表!Z:Z,数据更新表!AJ:AJ) -> 1.32 | DN37: 6.6 | DO37: 开 | DP37: zhen kong beng-3 | DQ37: 46084 | ED37: 调1653 开广 | EE37: 1299 | EF37: =EE37/0.7 -> 1855.7143 | EG37: 155 | EH37: =EJ37/(EI37+EL37) -> 0.85635996 | EI37: =EG37*$EI$1 -> 404.55 | EJ37: =EE37-EI37-EL37-EO37-EN37-EP37-EQ37 -> 367.12543 | EK37: =EJ37/EE37 -> 0.28262158 | EL37: =EX37*3000*$EI$1 -> 24.154571 | EM37: =IF(EE37>299,"是","否") -> 是 | EN37: =EE37*0.05 -> 64.95 | EO37: =EE37*0.175 -> 227.325 | EP37: =IF(EE37<299,IF(EE37<99,25,IF(EE37<=149,30,IF(EE37<=299,37,85))),IF(EE37<=498,_xlfn.XLOOKUP(EW37,运费表!A:A,运费表!C:C,"重量超限",-1),_xlfn.XLOOKUP(EW37,运费表!A:A,运费表!D:D,"重量超限",-1))) -> 74.5 | EQ37: =EE37*0.105 -> 136.395 | ER37: =_xlfn.XLOOKUP(K37,[4]目录表!$H:$H,[4]目录表!$X:$X) -> 0.6 | ES37: =_xlfn.XLOOKUP(K37,[4]目录表!$H:$H,[4]目录表!$Y:$Y) -> 18.5 | ET37: =_xlfn.XLOOKUP(K37,[4]目录表!$H:$H,[4]目录表!$Z:$Z) -> 14.5 | EU37: =_xlfn.XLOOKUP(K37,[4]目录表!$H:$H,[4]目录表!$AA:$AA) -> 11.5 | EV37: =ES37*ET37*EU37/5000 -> 0.616975 | EW37: =IF(EV37>=ER37,EV37,ER37) -> 0.616975 | EX37: =_xlfn.XLOOKUP(K37,[2]目录表!$H:$H,[2]目录表!$AB:$AB) -> 0.003084875 | EZ37: =CZ37/7 -> 0.57142857 | FK37: =_xlfn.XLOOKUP(K37,[2]目录表!$H:$H,[2]目录表!$AJ:$AJ) -> 散货
B38: https://articulo.mercadolibre.com.mx/MLM-2283820517-bomba-vacio-cruze-spark-malibu-14-15-2016-2017-2018-2019-_JM#polycard_client=search_best-seller&tracking_id=0b0dbe29-5eda-4616-8069-322daa9e055a | C38: 15 | D38: 41 | E38: 46038 | G38: 真空泵 | H38: 真空泵12704586 | J38: Bomba Vacío Cruze Spark Malibu 1.4 1.5 2016 2017 2018 2019 | K38: XQ5-QP017-12704586 | L38: 4686991600 | M38: 新上架 | N38: =_xlfn.XLOOKUP(L38,数据更新表!J:J,数据更新表!K:K) -> 100 | O38: =IFERROR(_xlfn.XLOOKUP(K38,数据更新表!A:A,数据更新表!B:B),"0") -> 13 | P38: =_xlfn.XLOOKUP(K38,[1]库销表!$F:$F,[1]库销表!$L:$L) -> 0 | Q38: =X38/W38 -> 22.75 | S38: =_xlfn.XLOOKUP(K38,数据更新表!R:R,数据更新表!S:S) -> #N/A | T38: =_xlfn.XLOOKUP(K38,数据更新表!V:V,数据更新表!W:W) -> #N/A | V38: =IFERROR(7*O38/CZ38,"0") -> 22.75 | W38: =CZ38/7 -> 0.57142857 | X38: =O38+P38+SUM(BN38:BR38) -> 13 | AF38: =SUM(AG38:BR38) -> 24 | AJ38: 24 | BS38: =_xlfn.XLOOKUP(K38,[1]库销表!$F:$F,[1]库销表!$L:$L) -> 0 | BT38: =SUM(BU38:CV38) -> 0 | CW38: =_xlfn.XLOOKUP(K38,[1]库销表!$F:$F,[1]库销表!$IE:$IE) -> 0 | CX38: =_xlfn.XLOOKUP(K38,[1]库销表!$F:$F,[1]库销表!$IF:$IF) -> 0 | CY38: =_xlfn.XLOOKUP(K38,[1]库销表!$F:$F,[1]库销表!$FL:$FL) -> 0 | CZ38: =_xlfn.XLOOKUP(K38,数据更新表!E:E,数据更新表!F:F,0) -> 4 | DA38: 3 | DB38: =_xlfn.XLOOKUP(K38,数据更新表!E:E,数据更新表!G:G) -> 0 | DC38: =_xlfn.XLOOKUP(L38,数据更新表!Z:Z,数据更新表!AH:AH) -> 2 | DD38: =_xlfn.XLOOKUP(L38,数据更新表!Z:Z,数据更新表!AE:AE) -> 2 | DE38: =_xlfn.XLOOKUP(L38,数据更新表!Z:Z,数据更新表!AF:AF) -> 2 | DF38: =_xlfn.XLOOKUP(K38,数据更新表!Z:Z,数据更新表!AG:AG) -> #N/A | DG38: =_xlfn.XLOOKUP(L38,数据更新表!Z:Z,数据更新表!AD:AD) -> 122.54 | DH38: =_xlfn.XLOOKUP(L38,数据更新表!Z:Z,数据更新表!AA:AA) -> 10729 | DI38: =_xlfn.XLOOKUP(L38,数据更新表!Z:Z,数据更新表!AB:AB) -> 16 | DJ38: =_xlfn.XLOOKUP(L38,数据更新表!Z:Z,数据更新表!AC:AC) -> 9.16% | DK38: =_xlfn.XLOOKUP(L38,数据更新表!Z:Z,数据更新表!AI:AI) -> 4.58% | DL38: =_xlfn.XLOOKUP(L38,数据更新表!AL:AL,数据更新表!AM:AM) -> 4.21% | DM38: =_xlfn.XLOOKUP(L38,数据更新表!Z:Z,数据更新表!AJ:AJ) -> 10.92 | DN38: 15 | DO38: 开 | DP38: zhen kong beng_1 | DQ38: 46084 | DU38: 清货 | ED38: 调700 开广 | EE38: 669 | EF38: =EE38/0.7 -> 955.71429 | EG38: 128 | EH38: =EJ38/(EI38+EL38) -> 0.02523591 | EI38: =EG38*$EI$1 -> 334.08 | EJ38: =EE38-EI38-EL38-EO38-EN38-EP38-EQ38 -> 8.9531176 | EK38: =EJ38/EE38 -> 0.013382836 | EL38: =EX38*3000*$EI$1 -> 20.696882 | EM38: =IF(EE38>299,"是","否") -> 是 | EN38: =EE38*0.05 -> 33.45 | EO38: =EE38*0.175 -> 117.075 | EP38: =IF(EE38<299,IF(EE38<99,25,IF(EE38<=149,30,IF(EE38<=299,37,85))),IF(EE38<=498,_xlfn.XLOOKUP(EW38,运费表!A:A,运费表!C:C,"重量超限",-1),_xlfn.XLOOKUP(EW38,运费表!A:A,运费表!D:D,"重量超限",-1))) -> 84.5 | EQ38: =EE38*0.105 -> 70.245 | ER38: =_xlfn.XLOOKUP(K38,[4]目录表!$H:$H,[4]目录表!$X:$X) -> 1.22 | ES38: =_xlfn.XLOOKUP(K38,[4]目录表!$H:$H,[4]目录表!$Y:$Y) -> 18.8 | ET38: =_xlfn.XLOOKUP(K38,[4]目录表!$H:$H,[4]目录表!$Z:$Z) -> 14.8 | EU38: =_xlfn.XLOOKUP(K38,[4]目录表!$H:$H,[4]目录表!$AA:$AA) -> 9.5 | EV38: =ES38*ET38*EU38/5000 -> 0.528656 | EW38: =IF(EV38>=ER38,EV38,ER38) -> 1.22 | EX38: =_xlfn.XLOOKUP(K38,[2]目录表!$H:$H,[2]目录表!$AB:$AB) -> 0.00264328 | EZ38: =CZ38/7 -> 0.57142857 | FK38: =_xlfn.XLOOKUP(K38,[2]目录表!$H:$H,[2]目录表!$AJ:$AJ) -> 散货
B39: Bomba Vacio Chevrolet S10 Malibu 2.0 2.5 2016 2017 2018-2022 | Envío gratis | C39: 9 | D39: 36 | E39: 46038 | G39: 真空泵 | H39: 真空泵12686657 | J39: Bomba Vacio Chevrolet S10 Malibu 2.0 2.5 2016 2017 2018-2022 | K39: XQ5-QP018-12686657 | L39: 4687030984 | M39: 新上架 | N39: =_xlfn.XLOOKUP(L39,数据更新表!J:J,数据更新表!K:K) -> 100 | O39: =IFERROR(_xlfn.XLOOKUP(K39,数据更新表!A:A,数据更新表!B:B),"0") -> 8 | P39: =_xlfn.XLOOKUP(K39,[1]库销表!$F:$F,[1]库销表!$L:$L) -> 0 | Q39: =X39/W39 -> 7 | S39: =_xlfn.XLOOKUP(K39,数据更新表!R:R,数据更新表!S:S) -> #N/A | T39: =_xlfn.XLOOKUP(K39,数据更新表!V:V,数据更新表!W:W) -> #N/A | V39: =IFERROR(7*O39/CZ39,"0") -> 7 | W39: =CZ39/7 -> 1.1428571 | X39: =O39+P39+SUM(BN39:BR39) -> 8 | AF39: =SUM(AG39:BR39) -> 24 | AJ39: 24 | BS39: =_xlfn.XLOOKUP(K39,[1]库销表!$F:$F,[1]库销表!$L:$L) -> 0 | BT39: =SUM(BU39:CV39) -> 0 | CW39: =_xlfn.XLOOKUP(K39,[1]库销表!$F:$F,[1]库销表!$IE:$IE) -> 0 | CX39: =_xlfn.XLOOKUP(K39,[1]库销表!$F:$F,[1]库销表!$IF:$IF) -> 0 | CY39: =_xlfn.XLOOKUP(K39,[1]库销表!$F:$F,[1]库销表!$FL:$FL) -> 0 | CZ39: =_xlfn.XLOOKUP(K39,数据更新表!E:E,数据更新表!F:F,0) -> 8 | DA39: 11 | DB39: =_xlfn.XLOOKUP(K39,数据更新表!E:E,数据更新表!G:G) -> 1 | DC39: =_xlfn.XLOOKUP(L39,数据更新表!Z:Z,数据更新表!AH:AH) -> 2 | DD39: =_xlfn.XLOOKUP(L39,数据更新表!Z:Z,数据更新表!AE:AE) -> 6 | DE39: =_xlfn.XLOOKUP(L39,数据更新表!Z:Z,数据更新表!AF:AF) -> 6 | DF39: =_xlfn.XLOOKUP(K39,数据更新表!Z:Z,数据更新表!AG:AG) -> #N/A | DG39: =_xlfn.XLOOKUP(L39,数据更新表!Z:Z,数据更新表!AD:AD) -> 788.65 | DH39: =_xlfn.XLOOKUP(L39,数据更新表!Z:Z,数据更新表!AA:AA) -> 11984 | DI39: =_xlfn.XLOOKUP(L39,数据更新表!Z:Z,数据更新表!AB:AB) -> 39 | DJ39: =_xlfn.XLOOKUP(L39,数据更新表!Z:Z,数据更新表!AC:AC) -> 16.45% | DK39: =_xlfn.XLOOKUP(L39,数据更新表!Z:Z,数据更新表!AI:AI) -> 12.34% | DL39: =_xlfn.XLOOKUP(L39,数据更新表!AL:AL,数据更新表!AM:AM) -> 10.48% | DM39: =_xlfn.XLOOKUP(L39,数据更新表!Z:Z,数据更新表!AJ:AJ) -> 6.08 | DN39: 8 | DO39: 开 | DP39: zhen kong beng_2 | DQ39: 46084 | DU39: 清货 | ED39: 调891 开广 | EE39: 799 | EF39: =EE39/0.7 -> 1141.4286 | EG39: 130 | EH39: =EJ39/(EI39+EL39) -> 0.2523164 | EI39: =EG39*$EI$1 -> 339.3 | EJ39: =EE39-EI39-EL39-EO39-EN39-EP39-EQ39 -> 90.833118 | EK39: =EJ39/EE39 -> 0.1136835 | EL39: =EX39*3000*$EI$1 -> 20.696882 | EM39: =IF(EE39>299,"是","否") -> 是 | EN39: =EE39*0.05 -> 39.95 | EO39: =EE39*0.175 -> 139.825 | EP39: =IF(EE39<299,IF(EE39<99,25,IF(EE39<=149,30,IF(EE39<=299,37,85))),IF(EE39<=498,_xlfn.XLOOKUP(EW39,运费表!A:A,运费表!C:C,"重量超限",-1),_xlfn.XLOOKUP(EW39,运费表!A:A,运费表!D:D,"重量超限",-1))) -> 84.5 | EQ39: =EE39*0.105 -> 83.895 | ER39: =_xlfn.XLOOKUP(K39,[4]目录表!$H:$H,[4]目录表!$X:$X) -> 1.18 | ES39: =_xlfn.XLOOKUP(K39,[4]目录表!$H:$H,[4]目录表!$Y:$Y) -> 18.8 | ET39: =_xlfn.XLOOKUP(K39,[4]目录表!$H:$H,[4]目录表!$Z:$Z) -> 14.8 | EU39: =_xlfn.XLOOKUP(K39,[4]目录表!$H:$H,[4]目录表!$AA:$AA) -> 9.5 | EV39: =ES39*ET39*EU39/5000 -> 0.528656 | EW39: =IF(EV39>=ER39,EV39,ER39) -> 1.18 | EX39: =_xlfn.XLOOKUP(K39,[2]目录表!$H:$H,[2]目录表!$AB:$AB) -> 0.00264328 | EZ39: =CZ39/7 -> 1.1428571 | FK39: =_xlfn.XLOOKUP(K39,[2]目录表!$H:$H,[2]目录表!$AJ:$AJ) -> 散货
B40: Bomba Vacio Vw Golf Beetle Bora Passat Jetta 2.5 2005-2017 | Envío gratis | C40: 10 | D40: 40 | E40: 46041 | G40: 真空泵 | H40: 真空泵07K-145100C | J40: Bomba Vacio Vw Golf Beetle Bora Passat Jetta 2.5 2005-2017 | K40: XQ5-QP019-07K-145100C | L40: 4687109248 | M40: 新上架 | N40: =_xlfn.XLOOKUP(L40,数据更新表!J:J,数据更新表!K:K) -> 100 | O40: =IFERROR(_xlfn.XLOOKUP(K40,数据更新表!A:A,数据更新表!B:B),"0") -> 12 | P40: =_xlfn.XLOOKUP(K40,[1]库销表!$F:$F,[1]库销表!$L:$L) -> 0 | Q40: =X40/W40 -> 14 | S40: =_xlfn.XLOOKUP(K40,数据更新表!R:R,数据更新表!S:S) -> #N/A | T40: =_xlfn.XLOOKUP(K40,数据更新表!V:V,数据更新表!W:W) -> #N/A | V40: =IFERROR(7*O40/CZ40,"0") -> 14 | W40: =CZ40/7 -> 0.85714286 | X40: =O40+P40+SUM(BN40:BR40) -> 12 | AF40: =SUM(AG40:BR40) -> 24 | AJ40: 24 | BS40: =_xlfn.XLOOKUP(K40,[1]库销表!$F:$F,[1]库销表!$L:$L) -> 0 | BT40: =SUM(BU40:CV40) -> 0 | CW40: =_xlfn.XLOOKUP(K40,[1]库销表!$F:$F,[1]库销表!$IE:$IE) -> 0 | CX40: =_xlfn.XLOOKUP(K40,[1]库销表!$F:$F,[1]库销表!$IF:$IF) -> 0 | CY40: =_xlfn.XLOOKUP(K40,[1]库销表!$F:$F,[1]库销表!$FL:$FL) -> 0 | CZ40: =_xlfn.XLOOKUP(K40,数据更新表!E:E,数据更新表!F:F,0) -> 6 | DA40: 6 | DB40: =_xlfn.XLOOKUP(K40,数据更新表!E:E,数据更新表!G:G) -> 2 | DC40: =_xlfn.XLOOKUP(L40,数据更新表!Z:Z,数据更新表!AH:AH) -> 5 | DD40: =_xlfn.XLOOKUP(L40,数据更新表!Z:Z,数据更新表!AE:AE) -> 1 | DE40: =_xlfn.XLOOKUP(L40,数据更新表!Z:Z,数据更新表!AF:AF) -> 1 | DF40: =_xlfn.XLOOKUP(K40,数据更新表!Z:Z,数据更新表!AG:AG) -> #N/A | DG40: =_xlfn.XLOOKUP(L40,数据更新表!Z:Z,数据更新表!AD:AD) -> 632.84 | DH40: =_xlfn.XLOOKUP(L40,数据更新表!Z:Z,数据更新表!AA:AA) -> 11886 | DI40: =_xlfn.XLOOKUP(L40,数据更新表!Z:Z,数据更新表!AB:AB) -> 42 | DJ40: =_xlfn.XLOOKUP(L40,数据更新表!Z:Z,数据更新表!AC:AC) -> 46.23% | DK40: =_xlfn.XLOOKUP(L40,数据更新表!Z:Z,数据更新表!AI:AI) -> 7.70% | DL40: =_xlfn.XLOOKUP(L40,数据更新表!AL:AL,数据更新表!AM:AM) -> 6.99% | DM40: =_xlfn.XLOOKUP(L40,数据更新表!Z:Z,数据更新表!AJ:AJ) -> 2.16 | DN40: 8 | DO40: 开 | DP40: zhen kong beng_2 | DQ40: 46084 | ED40: 调1589 开广 | EE40: 1369 | EF40: =EE40/0.7 -> 1955.7143 | EG40: 160 | EH40: =EJ40/(EI40+EL40) -> 0.90768824 | EI40: =EG40*$EI$1 -> 417.6 | EJ40: =EE40-EI40-EL40-EO40-EN40-EP40-EQ40 -> 400.97543 | EK40: =EJ40/EE40 -> 0.29289659 | EL40: =EX40*3000*$EI$1 -> 24.154571 | EM40: =IF(EE40>299,"是","否") -> 是 | EN40: =EE40*0.05 -> 68.45 | EO40: =EE40*0.175 -> 239.575 | EP40: =IF(EE40<299,IF(EE40<99,25,IF(EE40<=149,30,IF(EE40<=299,37,85))),IF(EE40<=498,_xlfn.XLOOKUP(EW40,运费表!A:A,运费表!C:C,"重量超限",-1),_xlfn.XLOOKUP(EW40,运费表!A:A,运费表!D:D,"重量超限",-1))) -> 74.5 | EQ40: =EE40*0.105 -> 143.745 | ER40: =_xlfn.XLOOKUP(K40,[4]目录表!$H:$H,[4]目录表!$X:$X) -> 0.96 | ES40: =_xlfn.XLOOKUP(K40,[4]目录表!$H:$H,[4]目录表!$Y:$Y) -> 18.5 | ET40: =_xlfn.XLOOKUP(K40,[4]目录表!$H:$H,[4]目录表!$Z:$Z) -> 14.5 | EU40: =_xlfn.XLOOKUP(K40,[4]目录表!$H:$H,[4]目录表!$AA:$AA) -> 11.5 | EV40: =ES40*ET40*EU40/5000 -> 0.616975 | EW40: =IF(EV40>=ER40,EV40,ER40) -> 0.96 | EX40: =_xlfn.XLOOKUP(K40,[2]目录表!$H:$H,[2]目录表!$AB:$AB) -> 0.003084875 | EZ40: =CZ40/7 -> 0.85714286 | FK40: =_xlfn.XLOOKUP(K40,[2]目录表!$H:$H,[2]目录表!$AJ:$AJ) -> 散货
B41: Bobina Encendido Peugeot 206 207 308 Partner 1.6 2001-2013 | Envío gratis | C41: 14 | D41: 58 | E41: 46037 | G41: 点火线圈 | H41: 点火线圈597080 | J41: Bobina Encendido Peugeot 206 207 308 Partner 1.6 2001-2013 | K41: XQ5-QP031-597080 | L41: 4686940782 | M41: 新上架 | N41: =_xlfn.XLOOKUP(L41,数据更新表!J:J,数据更新表!K:K) -> 100 | O41: =IFERROR(_xlfn.XLOOKUP(K41,数据更新表!A:A,数据更新表!B:B),"0") -> 15 | P41: =_xlfn.XLOOKUP(K41,[1]库销表!$F:$F,[1]库销表!$L:$L) -> 0 | Q41: =X41/W41 -> 10.5 | S41: =_xlfn.XLOOKUP(K41,数据更新表!R:R,数据更新表!S:S) -> #N/A | T41: =_xlfn.XLOOKUP(K41,数据更新表!V:V,数据更新表!W:W) -> #N/A | V41: =IFERROR(7*O41/CZ41,"0") -> 10.5 | W41: =CZ41/7 -> 1.4285714 | X41: =O41+P41+SUM(BN41:BR41) -> 15 | AF41: =SUM(AG41:BR41) -> 30 | AJ41: 30 | BS41: =_xlfn.XLOOKUP(K41,[1]库销表!$F:$F,[1]库销表!$L:$L) -> 0 | BT41: =SUM(BU41:CV41) -> 0 | CW41: =_xlfn.XLOOKUP(K41,[1]库销表!$F:$F,[1]库销表!$IE:$IE) -> 0 | CX41: =_xlfn.XLOOKUP(K41,[1]库销表!$F:$F,[1]库销表!$IF:$IF) -> 0 | CY41: =_xlfn.XLOOKUP(K41,[1]库销表!$F:$F,[1]库销表!$FL:$FL) -> 0 | CZ41: =_xlfn.XLOOKUP(K41,数据更新表!E:E,数据更新表!F:F,0) -> 10 | DA41: 3 | DB41: =_xlfn.XLOOKUP(K41,数据更新表!E:E,数据更新表!G:G) -> 1 | DC41: =_xlfn.XLOOKUP(L41,数据更新表!Z:Z,数据更新表!AH:AH) -> 8 | DD41: =_xlfn.XLOOKUP(L41,数据更新表!Z:Z,数据更新表!AE:AE) -> 2 | DE41: =_xlfn.XLOOKUP(L41,数据更新表!Z:Z,数据更新表!AF:AF) -> 2 | DF41: =_xlfn.XLOOKUP(K41,数据更新表!Z:Z,数据更新表!AG:AG) -> #N/A | DG41: =_xlfn.XLOOKUP(L41,数据更新表!Z:Z,数据更新表!AD:AD) -> 149.77 | DH41: =_xlfn.XLOOKUP(L41,数据更新表!Z:Z,数据更新表!AA:AA) -> 1893 | DI41: =_xlfn.XLOOKUP(L41,数据更新表!Z:Z,数据更新表!AB:AB) -> 26 | DJ41: =_xlfn.XLOOKUP(L41,数据更新表!Z:Z,数据更新表!AC:AC) -> 12.50% | DK41: =_xlfn.XLOOKUP(L41,数据更新表!Z:Z,数据更新表!AI:AI) -> 2.50% | DL41: =_xlfn.XLOOKUP(L41,数据更新表!AL:AL,数据更新表!AM:AM) -> 2.94% | DM41: =_xlfn.XLOOKUP(L41,数据更新表!Z:Z,数据更新表!AJ:AJ) -> 8 | DN41: 6.6 | DO41: 开 | DP41: xian quan_1 | DQ41: 46084 | DU41: 观察广告，准备涨价 | ED41: 调599 开广 | EE41: =_xlfn.XLOOKUP(L41,数据更新表!J:J,数据更新表!L:L) -> 599 | EF41: =EE41/0.7 -> 855.71429 | EG41: 87 | EH41: =EJ41/(EI41+EL41) -> 0.10662113 | EI41: =EG41*$EI$1 -> 227.07 | EJ41: =EE41-EI41-EL41-EO41-EN41-EP41-EQ41 -> 30.52605 | EK41: =EJ41/EE41 -> 0.050961686 | EL41: =EX41*3000*$EI$1 -> 59.23395 | EM41: =IF(EE41>299,"是","否") -> 是 | EN41: =EE41*0.05 -> 29.95 | EO41: =EE41*0.175 -> 104.825 | EP41: =IF(EE41<299,IF(EE41<99,25,IF(EE41<=149,30,IF(EE41<=299,37,85))),IF(EE41<=498,_xlfn.XLOOKUP(EW41,运费表!A:A,运费表!C:C,"重量超限",-1),_xlfn.XLOOKUP(EW41,运费表!A:A,运费表!D:D,"重量超限",-1))) -> 84.5 | EQ41: =EE41*0.105 -> 62.895 | ER41: =_xlfn.XLOOKUP(K41,[4]目录表!$H:$H,[4]目录表!$X:$X) -> 1.4 | ES41: =_xlfn.XLOOKUP(K41,[4]目录表!$H:$H,[4]目录表!$Y:$Y) -> 44.5 | ET41: =_xlfn.XLOOKUP(K41,[4]目录表!$H:$H,[4]目录表!$Z:$Z) -> 8.5 | EU41: =_xlfn.XLOOKUP(K41,[4]目录表!$H:$H,[4]目录表!$AA:$AA) -> 20 | EV41: =ES41*ET41*EU41/5000 -> 1.513 | EW41: =IF(EV41>=ER41,EV41,ER41) -> 1.513 | EX41: =_xlfn.XLOOKUP(K41,[2]目录表!$H:$H,[2]目录表!$AB:$AB) -> 0.007565 | EZ41: =CZ41/7 -> 1.4285714 | FK41: =_xlfn.XLOOKUP(K41,[2]目录表!$H:$H,[2]目录表!$AJ:$AJ) -> 散货
B42: https://articulo.mercadolibre.com.mx/MLM-2595008336-bobina-encendido-x-trail-25-2002-2003-2004-2005-2006-2007-_JM | C42: 9 | D42: 15 | E42: 46041 | G42: 点火线圈 | H42: 点火线圈224338H315 | J42: Bobina Encendido X-trail 2.5 2002 2003 2004 2005 2006 2007 | K42: XQ5-QP032-224338H315 | L42: 4687019062 | M42: 新上架 | N42: =_xlfn.XLOOKUP(L42,数据更新表!J:J,数据更新表!K:K) -> -- | O42: =IFERROR(_xlfn.XLOOKUP(K42,数据更新表!A:A,数据更新表!B:B),"0") -> 30 | P42: =_xlfn.XLOOKUP(K42,[1]库销表!$F:$F,[1]库销表!$L:$L) -> 0 | Q42: =X42/W42 -> #DIV/0! | S42: =_xlfn.XLOOKUP(K42,数据更新表!R:R,数据更新表!S:S) -> #N/A | T42: =_xlfn.XLOOKUP(K42,数据更新表!V:V,数据更新表!W:W) -> #N/A | V42: =IFERROR(7*O42/CZ42,"0") -> 0 | W42: =CZ42/7 -> 0 | X42: =O42+P42+SUM(BN42:BR42) -> 30 | AF42: =SUM(AG42:BR42) -> 30 | AJ42: 30 | BS42: =_xlfn.XLOOKUP(K42,[1]库销表!$F:$F,[1]库销表!$L:$L) -> 0 | BT42: =SUM(BU42:CV42) -> 0 | CW42: =_xlfn.XLOOKUP(K42,[1]库销表!$F:$F,[1]库销表!$IE:$IE) -> 0 | CX42: =_xlfn.XLOOKUP(K42,[1]库销表!$F:$F,[1]库销表!$IF:$IF) -> 0 | CY42: =_xlfn.XLOOKUP(K42,[1]库销表!$F:$F,[1]库销表!$FL:$FL) -> 0 | CZ42: =_xlfn.XLOOKUP(K42,数据更新表!E:E,数据更新表!F:F,0) -> 0 | DA42: 0 | DB42: =_xlfn.XLOOKUP(K42,数据更新表!E:E,数据更新表!G:G) -> #N/A | DC42: =_xlfn.XLOOKUP(L42,数据更新表!Z:Z,数据更新表!AH:AH) -> 0 | DD42: =_xlfn.XLOOKUP(L42,数据更新表!Z:Z,数据更新表!AE:AE) -> 0 | DE42: =_xlfn.XLOOKUP(L42,数据更新表!Z:Z,数据更新表!AF:AF) -> 0 | DF42: =_xlfn.XLOOKUP(K42,数据更新表!Z:Z,数据更新表!AG:AG) -> #N/A | DG42: =_xlfn.XLOOKUP(L42,数据更新表!Z:Z,数据更新表!AD:AD) -> 0 | DH42: =_xlfn.XLOOKUP(L42,数据更新表!Z:Z,数据更新表!AA:AA) -> 1073 | DI42: =_xlfn.XLOOKUP(L42,数据更新表!Z:Z,数据更新表!AB:AB) -> 0 | DJ42: =_xlfn.XLOOKUP(L42,数据更新表!Z:Z,数据更新表!AC:AC) -> 0.00% | DK42: =_xlfn.XLOOKUP(L42,数据更新表!Z:Z,数据更新表!AI:AI) -> 0.00% | DL42: =_xlfn.XLOOKUP(L42,数据更新表!AL:AL,数据更新表!AM:AM) -> 0.00% | DM42: =_xlfn.XLOOKUP(L42,数据更新表!Z:Z,数据更新表!AJ:AJ) -> 0 | DN42: 6.6 | DO42: 开 | DP42: xian quan_1 | DQ42: 46084 | ED42: 调269 开广 | EE42: 229 | EF42: =EE42/0.7 -> 327.14286 | EG42: 29 | EH42: =EJ42/(EI42+EL42) -> 0.33820895 | EI42: =EG42*$EI$1 -> 75.69 | EJ42: =EE42-EI42-EL42-EO42-EN42-EP42-EQ42 -> 29.42565 | EK42: =EJ42/EE42 -> 0.12849629 | EL42: =EX42*3000*$EI$1 -> 11.31435 | EM42: =IF(EE42>299,"是","否") -> 否 | EN42: =EE42*0.05 -> 11.45 | EO42: =EE42*0.175 -> 40.075 | EP42: =IF(EE42<299,IF(EE42<99,25,IF(EE42<=149,30,IF(EE42<=299,37,85))),IF(EE42<=498,_xlfn.XLOOKUP(EW42,运费表!A:A,运费表!C:C,"重量超限",-1),_xlfn.XLOOKUP(EW42,运费表!A:A,运费表!D:D,"重量超限",-1))) -> 37 | EQ42: =EE42*0.105 -> 24.045 | ER42: =_xlfn.XLOOKUP(K42,[4]目录表!$H:$H,[4]目录表!$X:$X) -> 0.18 | ES42: =_xlfn.XLOOKUP(K42,[4]目录表!$H:$H,[4]目录表!$Y:$Y) -> 8.5 | ET42: =_xlfn.XLOOKUP(K42,[4]目录表!$H:$H,[4]目录表!$Z:$Z) -> 8.5 | EU42: =_xlfn.XLOOKUP(K42,[4]目录表!$H:$H,[4]目录表!$AA:$AA) -> 20 | EV42: =ES42*ET42*EU42/5000 -> 0.289 | EW42: =IF(EV42>=ER42,EV42,ER42) -> 0.289 | EX42: =_xlfn.XLOOKUP(K42,[2]目录表!$H:$H,[2]目录表!$AB:$AB) -> 0.001445 | EZ42: =CZ42/7 -> 0 | FK42: =_xlfn.XLOOKUP(K42,[2]目录表!$H:$H,[2]目录表!$AJ:$AJ) -> 散货
B43: https://articulo.mercadolibre.com.mx/MLM-2048104771-bobina-encendido-f-350-super-duty-54l-99-04-fd503-ic39-_JM | C43: 0 | D43: 1 | E43: 46006 | G43: 点火线圈 | H43: 点火线圈1L2U12029AA | J43: Bobina Encendido F-350 Super Duty 5.4l 99-04 Fd503 Ic39 | K43: XQ5-QP033-1L2U12029AA | L43: 2698952707 | M43: 新上架 | N43: =_xlfn.XLOOKUP(L43,数据更新表!J:J,数据更新表!K:K) -> -- | O43: =IFERROR(_xlfn.XLOOKUP(K43,数据更新表!A:A,数据更新表!B:B),"0") -> 30 | P43: =_xlfn.XLOOKUP(K43,[1]库销表!$F:$F,[1]库销表!$L:$L) -> 0 | Q43: =X43/W43 -> #DIV/0! | S43: =_xlfn.XLOOKUP(K43,数据更新表!R:R,数据更新表!S:S) -> #N/A | T43: =_xlfn.XLOOKUP(K43,数据更新表!V:V,数据更新表!W:W) -> #N/A | V43: =IFERROR(7*O43/CZ43,"0") -> 0 | W43: =CZ43/7 -> 0 | X43: =O43+P43+SUM(BN43:BR43) -> 30 | AF43: =SUM(AG43:BR43) -> 30 | AJ43: 30 | BS43: =_xlfn.XLOOKUP(K43,[1]库销表!$F:$F,[1]库销表!$L:$L) -> 0 | BT43: =SUM(BU43:CV43) -> 0 | CW43: =_xlfn.XLOOKUP(K43,[1]库销表!$F:$F,[1]库销表!$IE:$IE) -> 0 | CX43: =_xlfn.XLOOKUP(K43,[1]库销表!$F:$F,[1]库销表!$IF:$IF) -> 0 | CY43: =_xlfn.XLOOKUP(K43,[1]库销表!$F:$F,[1]库销表!$FL:$FL) -> 0 | CZ43: =_xlfn.XLOOKUP(K43,数据更新表!E:E,数据更新表!F:F,0) -> 0 | DA43: 0 | DB43: =_xlfn.XLOOKUP(K43,数据更新表!E:E,数据更新表!G:G) -> #N/A | DC43: =_xlfn.XLOOKUP(L43,数据更新表!Z:Z,数据更新表!AH:AH) -> 0 | DD43: =_xlfn.XLOOKUP(L43,数据更新表!Z:Z,数据更新表!AE:AE) -> 0 | DE43: =_xlfn.XLOOKUP(L43,数据更新表!Z:Z,数据更新表!AF:AF) -> 0 | DF43: =_xlfn.XLOOKUP(K43,数据更新表!Z:Z,数据更新表!AG:AG) -> #N/A | DG43: =_xlfn.XLOOKUP(L43,数据更新表!Z:Z,数据更新表!AD:AD) -> 0 | DH43: =_xlfn.XLOOKUP(L43,数据更新表!Z:Z,数据更新表!AA:AA) -> 36 | DI43: =_xlfn.XLOOKUP(L43,数据更新表!Z:Z,数据更新表!AB:AB) -> 0 | DJ43: =_xlfn.XLOOKUP(L43,数据更新表!Z:Z,数据更新表!AC:AC) -> 0.00% | DK43: =_xlfn.XLOOKUP(L43,数据更新表!Z:Z,数据更新表!AI:AI) -> 0.00% | DL43: =_xlfn.XLOOKUP(L43,数据更新表!AL:AL,数据更新表!AM:AM) -> 0.00% | DM43: =_xlfn.XLOOKUP(L43,数据更新表!Z:Z,数据更新表!AJ:AJ) -> 0 | DN43: 6.6 | DO43: 开 | DP43: xian quan_1 | DQ43: 46084 | ED43: 调155 开广 | EE43: 148 | EF43: =EE43/0.7 -> 211.42857 | EG43: 15 | EH43: =EJ43/(EI43+EL43) -> 0.37047242 | EI43: =EG43*$EI$1 -> 39.15 | EJ43: =EE43-EI43-EL43-EO43-EN43-EP43-EQ43 -> 18.69565 | EK43: =EJ43/EE43 -> 0.12632196 | EL43: =EX43*3000*$EI$1 -> 11.31435 | EM43: =IF(EE43>299,"是","否") -> 否 | EN43: =EE43*0.05 -> 7.4 | EO43: =EE43*0.175 -> 25.9 | EP43: =IF(EE43<299,IF(EE43<99,25,IF(EE43<=149,30,IF(EE43<=299,37,85))),IF(EE43<=498,_xlfn.XLOOKUP(EW43,运费表!A:A,运费表!C:C,"重量超限",-1),_xlfn.XLOOKUP(EW43,运费表!A:A,运费表!D:D,"重量超限",-1))) -> 30 | EQ43: =EE43*0.105 -> 15.54 | ER43: =_xlfn.XLOOKUP(K43,[4]目录表!$H:$H,[4]目录表!$X:$X) -> 0.2 | ES43: =_xlfn.XLOOKUP(K43,[4]目录表!$H:$H,[4]目录表!$Y:$Y) -> 8.5 | ET43: =_xlfn.XLOOKUP(K43,[4]目录表!$H:$H,[4]目录表!$Z:$Z) -> 8.5 | EU43: =_xlfn.XLOOKUP(K43,[4]目录表!$H:$H,[4]目录表!$AA:$AA) -> 20 | EV43: =ES43*ET43*EU43/5000 -> 0.289 | EW43: =IF(EV43>=ER43,EV43,ER43) -> 0.289 | EX43: =_xlfn.XLOOKUP(K43,[2]目录表!$H:$H,[2]目录表!$AB:$AB) -> 0.001445 | EZ43: =CZ43/7 -> 0 | FK43: =_xlfn.XLOOKUP(K43,[2]目录表!$H:$H,[2]目录表!$AJ:$AJ) -> 散货
B44: https://articulo.mercadolibre.com.mx/MLM-2264069447-par-solenoide-vvt-captiva-equinox-hhr-malibu-terrain-nuevo-_JM#polycard_client=search_best-seller&tracking_id=9e0727a3-de60-4246-8cf6-107bae10046a&wid=MLM2264069447&sid=search | C44: 36 | D44: 106 | E44: 46041 | G44: 电磁阀 | H44: 电磁阀12655421 | J44: Par Solenoide Vvt Captiva Equinox Hhr Malibu Terrain Nuevo | K44: XQ5-QP034-12655421 | L44: 2698823949 | M44: 新上架 | N44: =_xlfn.XLOOKUP(L44,数据更新表!J:J,数据更新表!K:K) -> 100 | O44: =IFERROR(_xlfn.XLOOKUP(K44,数据更新表!A:A,数据更新表!B:B),"0") -> 29 | P44: =_xlfn.XLOOKUP(K44,[1]库销表!$F:$F,[1]库销表!$L:$L) -> 0 | Q44: =X44/W44 -> #DIV/0! | S44: =_xlfn.XLOOKUP(K44,数据更新表!R:R,数据更新表!S:S) -> #N/A | T44: =_xlfn.XLOOKUP(K44,数据更新表!V:V,数据更新表!W:W) -> #N/A | V44: =IFERROR(7*O44/CZ44,"0") -> 0 | W44: =CZ44/7 -> 0 | X44: =O44+P44+SUM(BN44:BR44) -> 29 | AF44: =SUM(AG44:BR44) -> 30 | AJ44: 30 | BS44: =_xlfn.XLOOKUP(K44,[1]库销表!$F:$F,[1]库销表!$L:$L) -> 0 | BT44: =SUM(BU44:CV44) -> 0 | CW44: =_xlfn.XLOOKUP(K44,[1]库销表!$F:$F,[1]库销表!$IE:$IE) -> 0 | CX44: =_xlfn.XLOOKUP(K44,[1]库销表!$F:$F,[1]库销表!$IF:$IF) -> 0 | CY44: =_xlfn.XLOOKUP(K44,[1]库销表!$F:$F,[1]库销表!$FL:$FL) -> 0 | CZ44: =_xlfn.XLOOKUP(K44,数据更新表!E:E,数据更新表!F:F,0) -> 0 | DA44: 0 | DB44: =_xlfn.XLOOKUP(K44,数据更新表!E:E,数据更新表!G:G) -> #N/A | DC44: =_xlfn.XLOOKUP(L44,数据更新表!Z:Z,数据更新表!AH:AH) -> 0 | DD44: =_xlfn.XLOOKUP(L44,数据更新表!Z:Z,数据更新表!AE:AE) -> 0 | DE44: =_xlfn.XLOOKUP(L44,数据更新表!Z:Z,数据更新表!AF:AF) -> 0 | DF44: =_xlfn.XLOOKUP(K44,数据更新表!Z:Z,数据更新表!AG:AG) -> #N/A | DG44: =_xlfn.XLOOKUP(L44,数据更新表!Z:Z,数据更新表!AD:AD) -> 16.7 | DH44: =_xlfn.XLOOKUP(L44,数据更新表!Z:Z,数据更新表!AA:AA) -> 4176 | DI44: =_xlfn.XLOOKUP(L44,数据更新表!Z:Z,数据更新表!AB:AB) -> 5 | DJ44: =_xlfn.XLOOKUP(L44,数据更新表!Z:Z,数据更新表!AC:AC) -> 0.00% | DK44: =_xlfn.XLOOKUP(L44,数据更新表!Z:Z,数据更新表!AI:AI) -> 0.00% | DL44: =_xlfn.XLOOKUP(L44,数据更新表!AL:AL,数据更新表!AM:AM) -> 11.03% | DM44: =_xlfn.XLOOKUP(L44,数据更新表!Z:Z,数据更新表!AJ:AJ) -> 0 | DN44: 8 | DO44: 开 | DP44: dian ci fa_1 | DQ44: 46084 | ED44: 调346 开广 | EE44: =_xlfn.XLOOKUP(L44,数据更新表!J:J,数据更新表!L:L) -> 296.57 | EF44: =EE44/0.7 -> 423.67143 | EG44: 48 | EH44: =EJ44/(EI44+EL44) -> 0.2330776 | EI44: =EG44*$EI$1 -> 125.28 | EJ44: =EE44-EI44-EL44-EO44-EN44-EP44-EQ44 -> 30.56506 | EK44: =EJ44/EE44 -> 0.10306187 | EL44: =EX44*3000*$EI$1 -> 5.85684 | EM44: =IF(EE44>299,"是","否") -> 否 | EN44: =EE44*0.05 -> 14.8285 | EO44: =EE44*0.175 -> 51.89975 | EP44: =IF(EE44<299,IF(EE44<99,25,IF(EE44<=149,30,IF(EE44<=299,37,85))),IF(EE44<=498,_xlfn.XLOOKUP(EW44,运费表!A:A,运费表!C:C,"重量超限",-1),_xlfn.XLOOKUP(EW44,运费表!A:A,运费表!D:D,"重量超限",-1))) -> 37 | EQ44: =EE44*0.105 -> 31.13985 | ER44: =_xlfn.XLOOKUP(K44,[4]目录表!$H:$H,[4]目录表!$X:$X) -> 0.405 | ES44: =_xlfn.XLOOKUP(K44,[4]目录表!$H:$H,[4]目录表!$Y:$Y) -> 17 | ET44: =_xlfn.XLOOKUP(K44,[4]目录表!$H:$H,[4]目录表!$Z:$Z) -> 8 | EU44: =_xlfn.XLOOKUP(K44,[4]目录表!$H:$H,[4]目录表!$AA:$AA) -> 5.5 | EV44: =ES44*ET44*EU44/5000 -> 0.1496 | EW44: =IF(EV44>=ER44,EV44,ER44) -> 0.405 | EX44: =_xlfn.XLOOKUP(K44,[2]目录表!$H:$H,[2]目录表!$AB:$AB) -> 0.000748 | EZ44: =CZ44/7 -> 0 | FK44: =_xlfn.XLOOKUP(K44,[2]目录表!$H:$H,[2]目录表!$AJ:$AJ) -> 散货
B45: Válvula Solenoide Vvt Nissan Tiida Versa 1.8 2007-2015 Nuevo | Meses sin interés | C45: 13 | D45: 48 | E45: 46041 | G45: 电磁阀 | H45: 电磁阀23796-ET00A | J45: Válvula Solenoide Vvt Nissan Tiida Versa 1.8 2007-2015 Nuevo | K45: XQ5-QP035-23796-ET00A | L45: 2698915223 | M45: 新上架 | N45: =_xlfn.XLOOKUP(L45,数据更新表!J:J,数据更新表!K:K) -> 100 | O45: =IFERROR(_xlfn.XLOOKUP(K45,数据更新表!A:A,数据更新表!B:B),"0") -> 26 | P45: =_xlfn.XLOOKUP(K45,[1]库销表!$F:$F,[1]库销表!$L:$L) -> 0 | Q45: =X45/W45 -> 45.5 | S45: =_xlfn.XLOOKUP(K45,数据更新表!R:R,数据更新表!S:S) -> #N/A | T45: =_xlfn.XLOOKUP(K45,数据更新表!V:V,数据更新表!W:W) -> #N/A | V45: =IFERROR(7*O45/CZ45,"0") -> 45.5 | W45: =CZ45/7 -> 0.57142857 | X45: =O45+P45+SUM(BN45:BR45) -> 26 | AF45: =SUM(AG45:BR45) -> 30 | AJ45: 30 | BS45: =_xlfn.XLOOKUP(K45,[1]库销表!$F:$F,[1]库销表!$L:$L) -> 0 | BT45: =SUM(BU45:CV45) -> 0 | CW45: =_xlfn.XLOOKUP(K45,[1]库销表!$F:$F,[1]库销表!$IE:$IE) -> 0 | CX45: =_xlfn.XLOOKUP(K45,[1]库销表!$F:$F,[1]库销表!$IF:$IF) -> 0 | CY45: =_xlfn.XLOOKUP(K45,[1]库销表!$F:$F,[1]库销表!$FL:$FL) -> 0 | CZ45: =_xlfn.XLOOKUP(K45,数据更新表!E:E,数据更新表!F:F,0) -> 4 | DA45: 0 | DB45: =_xlfn.XLOOKUP(K45,数据更新表!E:E,数据更新表!G:G) -> 1 | DC45: =_xlfn.XLOOKUP(L45,数据更新表!Z:Z,数据更新表!AH:AH) -> #N/A | DD45: =_xlfn.XLOOKUP(L45,数据更新表!Z:Z,数据更新表!AE:AE) -> #N/A | DE45: =_xlfn.XLOOKUP(L45,数据更新表!Z:Z,数据更新表!AF:AF) -> #N/A | DF45: =_xlfn.XLOOKUP(K45,数据更新表!Z:Z,数据更新表!AG:AG) -> #N/A | DG45: =_xlfn.XLOOKUP(L45,数据更新表!Z:Z,数据更新表!AD:AD) -> #N/A | DH45: =_xlfn.XLOOKUP(L45,数据更新表!Z:Z,数据更新表!AA:AA) -> #N/A | DI45: =_xlfn.XLOOKUP(L45,数据更新表!Z:Z,数据更新表!AB:AB) -> #N/A | DJ45: =_xlfn.XLOOKUP(L45,数据更新表!Z:Z,数据更新表!AC:AC) -> #N/A | DK45: =_xlfn.XLOOKUP(L45,数据更新表!Z:Z,数据更新表!AI:AI) -> #N/A | DL45: =_xlfn.XLOOKUP(L45,数据更新表!AL:AL,数据更新表!AM:AM) -> 0.11% | DM45: =_xlfn.XLOOKUP(L45,数据更新表!Z:Z,数据更新表!AJ:AJ) -> #N/A | DN45: 8 | DO45: 开 | DP45: dian ci fa-3 | DQ45: 46084 | EA45: 258降249 | ED45: 调297 开广 | EE45: 249 | EF45: =EE45/0.7 -> 355.71429 | EG45: 35 | EH45: =EJ45/(EI45+EL45) -> 0.36238209 | EI45: =EG45*$EI$1 -> 91.35 | EJ45: =EE45-EI45-EL45-EO45-EN45-EP45-EQ45 -> 34.53368 | EK45: =EJ45/EE45 -> 0.13868948 | EL45: =EX45*3000*$EI$1 -> 3.94632 | EM45: =IF(EE45>299,"是","否") -> 否 | EN45: =EE45*0.05 -> 12.45 | EO45: =EE45*0.175 -> 43.575 | EP45: =IF(EE45<299,IF(EE45<99,25,IF(EE45<=149,30,IF(EE45<=299,37,85))),IF(EE45<=498,_xlfn.XLOOKUP(EW45,运费表!A:A,运费表!C:C,"重量超限",-1),_xlfn.XLOOKUP(EW45,运费表!A:A,运费表!D:D,"重量超限",-1))) -> 37 | EQ45: =EE45*0.105 -> 26.145 | ER45: =_xlfn.XLOOKUP(K45,[4]目录表!$H:$H,[4]目录表!$X:$X) -> 0.145 | ES45: =_xlfn.XLOOKUP(K45,[4]目录表!$H:$H,[4]目录表!$Y:$Y) -> 6 | ET45: =_xlfn.XLOOKUP(K45,[4]目录表!$H:$H,[4]目录表!$Z:$Z) -> 6 | EU45: =_xlfn.XLOOKUP(K45,[4]目录表!$H:$H,[4]目录表!$AA:$AA) -> 14 | EV45: =ES45*ET45*EU45/5000 -> 0.1008 | EW45: =IF(EV45>=ER45,EV45,ER45) -> 0.145 | EX45: =_xlfn.XLOOKUP(K45,[2]目录表!$H:$H,[2]目录表!$AB:$AB) -> 0.000504 | EZ45: =CZ45/7 -> 0.57142857 | FK45: =_xlfn.XLOOKUP(K45,[2]目录表!$H:$H,[2]目录表!$AJ:$AJ) -> 散货
B46: https://articulo.mercadolibre.com.mx/MLM-2166283691-valvula-selenoide-vtec-para-honda-crv-24l-anos-2002-2009-_JM#polycard_client=search_best-seller&tracking_id=e9ca670c-8b60-4804-ba37-94a81c0ba396&wid=MLM2166283691&sid=search | C46: 12 | D46: 54 | E46: 46037 | G46: 电磁阀 | H46: 电磁阀15810-RAA-A01 | J46: Válvula Selenoide Vtec Para Honda Crv 2.4l Años 2002-2009 | K46: XQ5-QP036-15810-RAA-A01 | L46: 2698981225 | M46: 新上架 | N46: =_xlfn.XLOOKUP(L46,数据更新表!J:J,数据更新表!K:K) -> 100 | O46: =IFERROR(_xlfn.XLOOKUP(K46,数据更新表!A:A,数据更新表!B:B),"0") -> 17 | P46: =_xlfn.XLOOKUP(K46,[1]库销表!$F:$F,[1]库销表!$L:$L) -> 0 | Q46: =X46/W46 -> 17 | S46: =_xlfn.XLOOKUP(K46,数据更新表!R:R,数据更新表!S:S) -> #N/A | T46: =_xlfn.XLOOKUP(K46,数据更新表!V:V,数据更新表!W:W) -> #N/A | V46: =IFERROR(7*O46/CZ46,"0") -> 17 | W46: =CZ46/7 -> 1 | X46: =O46+P46+SUM(BN46:BR46) -> 17 | AF46: =SUM(AG46:BR46) -> 30 | AJ46: 30 | BS46: =_xlfn.XLOOKUP(K46,[1]库销表!$F:$F,[1]库销表!$L:$L) -> 0 | BT46: =SUM(BU46:CV46) -> 0 | CW46: =_xlfn.XLOOKUP(K46,[1]库销表!$F:$F,[1]库销表!$IE:$IE) -> 0 | CX46: =_xlfn.XLOOKUP(K46,[1]库销表!$F:$F,[1]库销表!$IF:$IF) -> 0 | CY46: =_xlfn.XLOOKUP(K46,[1]库销表!$F:$F,[1]库销表!$FL:$FL) -> 0 | CZ46: =_xlfn.XLOOKUP(K46,数据更新表!E:E,数据更新表!F:F,0) -> 7 | DA46: 5 | DB46: =_xlfn.XLOOKUP(K46,数据更新表!E:E,数据更新表!G:G) -> 1 | DC46: =_xlfn.XLOOKUP(L46,数据更新表!Z:Z,数据更新表!AH:AH) -> 6 | DD46: =_xlfn.XLOOKUP(L46,数据更新表!Z:Z,数据更新表!AE:AE) -> 1 | DE46: =_xlfn.XLOOKUP(L46,数据更新表!Z:Z,数据更新表!AF:AF) -> 1 | DF46: =_xlfn.XLOOKUP(K46,数据更新表!Z:Z,数据更新表!AG:AG) -> #N/A | DG46: =_xlfn.XLOOKUP(L46,数据更新表!Z:Z,数据更新表!AD:AD) -> 87.15 | DH46: =_xlfn.XLOOKUP(L46,数据更新表!Z:Z,数据更新表!AA:AA) -> 3230 | DI46: =_xlfn.XLOOKUP(L46,数据更新表!Z:Z,数据更新表!AB:AB) -> 14 | DJ46: =_xlfn.XLOOKUP(L46,数据更新表!Z:Z,数据更新表!AC:AC) -> 17.58% | DK46: =_xlfn.XLOOKUP(L46,数据更新表!Z:Z,数据更新表!AI:AI) -> 2.51% | DL46: =_xlfn.XLOOKUP(L46,数据更新表!AL:AL,数据更新表!AM:AM) -> 2.43% | DM46: =_xlfn.XLOOKUP(L46,数据更新表!Z:Z,数据更新表!AJ:AJ) -> 5.69 | DN46: 10 | DO46: 开 | DP46: dian ci fa-2 | DQ46: 46084 | ED46: 调495 开广 | EE46: =_xlfn.XLOOKUP(L46,数据更新表!J:J,数据更新表!L:L) -> 495.81 | EF46: =EE46/0.7 -> 708.3 | EG46: 65 | EH46: =EJ46/(EI46+EL46) -> 0.60913041 | EI46: =EG46*$EI$1 -> 169.65 | EJ46: =EE46-EI46-EL46-EO46-EN46-EP46-EQ46 -> 105.9145 | EK46: =EJ46/EE46 -> 0.21361913 | EL46: =EX46*3000*$EI$1 -> 4.2282 | EM46: =IF(EE46>299,"是","否") -> 是 | EN46: =EE46*0.05 -> 24.7905 | EO46: =EE46*0.175 -> 86.76675 | EP46: =IF(EE46<299,IF(EE46<99,25,IF(EE46<=149,30,IF(EE46<=299,37,85))),IF(EE46<=498,_xlfn.XLOOKUP(EW46,运费表!A:A,运费表!C:C,"重量超限",-1),_xlfn.XLOOKUP(EW46,运费表!A:A,运费表!D:D,"重量超限",-1))) -> 52.4 | EQ46: =EE46*0.105 -> 52.06005 | ER46: =_xlfn.XLOOKUP(K46,[4]目录表!$H:$H,[4]目录表!$X:$X) -> 0.18 | ES46: =_xlfn.XLOOKUP(K46,[4]目录表!$H:$H,[4]目录表!$Y:$Y) -> 6 | ET46: =_xlfn.XLOOKUP(K46,[4]目录表!$H:$H,[4]目录表!$Z:$Z) -> 6 | EU46: =_xlfn.XLOOKUP(K46,[4]目录表!$H:$H,[4]目录表!$AA:$AA) -> 15 | EV46: =ES46*ET46*EU46/5000 -> 0.108 | EW46: =IF(EV46>=ER46,EV46,ER46) -> 0.18 | EX46: =_xlfn.XLOOKUP(K46,[2]目录表!$H:$H,[2]目录表!$AB:$AB) -> 0.00054 | EZ46: =CZ46/7 -> 1 | FK46: =_xlfn.XLOOKUP(K46,[2]目录表!$H:$H,[2]目录表!$AJ:$AJ) -> 散货
B47: Par Amortiguadores De Cajuela Nissan March 2012-2018 90451 | Envío gratis | C47: 17 | D47: 233 | E47: 46045 | G47: 后备箱减震器 | H47: 后备箱减震器（左右）904501HL0A | J47: Par Amortiguadores De Cajuela Nissan March 2012-2018 90451 | K47: XQ5-QP037-904501HL0A | L47: 4704500652 | M47: 新上架 | N47: =_xlfn.XLOOKUP(L47,数据更新表!J:J,数据更新表!K:K) -> #N/A | O47: =IFERROR(_xlfn.XLOOKUP(K47,数据更新表!A:A,数据更新表!B:B),"0") -> 0 | P47: =_xlfn.XLOOKUP(K47,[1]库销表!$F:$F,[1]库销表!$L:$L) -> 30 | Q47: =X47/W47 -> #DIV/0! | S47: =_xlfn.XLOOKUP(K47,数据更新表!R:R,数据更新表!S:S) -> #N/A | T47: =_xlfn.XLOOKUP(K47,数据更新表!V:V,数据更新表!W:W) -> #N/A | V47: =IFERROR(7*O47/CZ47,"0") -> 0 | W47: =CZ47/7 -> 0 | X47: =O47+P47+SUM(BN47:BR47) -> 30 | AF47: =SUM(AG47:BR47) -> 0 | BS47: =_xlfn.XLOOKUP(K47,[1]库销表!$F:$F,[1]库销表!$L:$L) -> 30 | BT47: =SUM(BU47:CV47) -> 0 | CW47: =_xlfn.XLOOKUP(K47,[1]库销表!$F:$F,[1]库销表!$IE:$IE) -> 0 | CX47: =_xlfn.XLOOKUP(K47,[1]库销表!$F:$F,[1]库销表!$IF:$IF) -> 0 | CY47: =_xlfn.XLOOKUP(K47,[1]库销表!$F:$F,[1]库销表!$FL:$FL) -> 0 | CZ47: =_xlfn.XLOOKUP(K47,数据更新表!E:E,数据更新表!F:F,0) -> 0 | DA47: 0 | DB47: =_xlfn.XLOOKUP(K47,数据更新表!E:E,数据更新表!G:G) -> #N/A | DC47: =_xlfn.XLOOKUP(L47,数据更新表!Z:Z,数据更新表!AH:AH) -> #N/A | DD47: =_xlfn.XLOOKUP(L47,数据更新表!Z:Z,数据更新表!AE:AE) -> #N/A | DE47: =_xlfn.XLOOKUP(L47,数据更新表!Z:Z,数据更新表!AF:AF) -> #N/A | DF47: =_xlfn.XLOOKUP(K47,数据更新表!Z:Z,数据更新表!AG:AG) -> #N/A | DG47: =_xlfn.XLOOKUP(L47,数据更新表!Z:Z,数据更新表!AD:AD) -> #N/A | DH47: =_xlfn.XLOOKUP(L47,数据更新表!Z:Z,数据更新表!AA:AA) -> #N/A | DI47: =_xlfn.XLOOKUP(L47,数据更新表!Z:Z,数据更新表!AB:AB) -> #N/A | DJ47: =_xlfn.XLOOKUP(L47,数据更新表!Z:Z,数据更新表!AC:AC) -> #N/A | DK47: =_xlfn.XLOOKUP(L47,数据更新表!Z:Z,数据更新表!AI:AI) -> #N/A | DL47: =_xlfn.XLOOKUP(L47,数据更新表!AL:AL,数据更新表!AM:AM) -> #N/A | DM47: =_xlfn.XLOOKUP(L47,数据更新表!Z:Z,数据更新表!AJ:AJ) -> #N/A | EE47: =_xlfn.XLOOKUP(L47,数据更新表!J:J,数据更新表!L:L) -> #N/A | EF47: =EE47/0.7 -> #N/A | EG47: 33.5 | EH47: =EJ47/(EI47+EL47) -> #N/A | EI47: =EG47*$EI$1 -> 87.435 | EJ47: =EE47-EI47-EL47-EO47-EN47-EP47-EQ47 -> #N/A | EK47: =EJ47/EE47 -> #N/A | EL47: =EX47*3000*$EI$1 -> 9.396 | EM47: =IF(EE47>299,"是","否") -> #N/A | EN47: =EE47*0.05 -> #N/A | EO47: =EE47*0.175 -> #N/A | EP47: =IF(EE47<299,IF(EE47<99,25,IF(EE47<=149,30,IF(EE47<=299,37,85))),IF(EE47<=498,_xlfn.XLOOKUP(EW47,运费表!A:A,运费表!C:C,"重量超限",-1),_xlfn.XLOOKUP(EW47,运费表!A:A,运费表!D:D,"重量超限",-1))) -> #N/A | EQ47: =EE47*0.105 -> #N/A | ER47: =_xlfn.XLOOKUP(K47,[4]目录表!$H:$H,[4]目录表!$X:$X) -> 0.6 | ES47: =_xlfn.XLOOKUP(K47,[4]目录表!$H:$H,[4]目录表!$Y:$Y) -> 60 | ET47: =_xlfn.XLOOKUP(K47,[4]目录表!$H:$H,[4]目录表!$Z:$Z) -> 4 | EU47: =_xlfn.XLOOKUP(K47,[4]目录表!$H:$H,[4]目录表!$AA:$AA) -> 5 | EV47: =ES47*ET47*EU47/5000 -> 0.24 | EW47: =IF(EV47>=ER47,EV47,ER47) -> 0.6 | EX47: =_xlfn.XLOOKUP(K47,[2]目录表!$H:$H,[2]目录表!$AB:$AB) -> 0.0012 | EZ47: =CZ47/7 -> 0 | FK47: =_xlfn.XLOOKUP(K47,[2]目录表!$H:$H,[2]目录表!$AJ:$AJ) -> 散货
B48: Par De Amortiguadores Cajuela Vw Pointer 1998 Al 2009 Oep | Envío gratis | C48: 31 | D48: 150 | E48: 46045 | G48: 后备箱减震器 | H48: 后备箱减震器（左右）377827550C | J48: Par De Amortiguadores Cajuela Vw Pointer 1998 Al 2009 Oep | K48: XQ5-QP038-377827550C | L48: 2709120719 | M48: 新上架 | N48: =_xlfn.XLOOKUP(L48,数据更新表!J:J,数据更新表!K:K) -> #N/A | O48: =IFERROR(_xlfn.XLOOKUP(K48,数据更新表!A:A,数据更新表!B:B),"0") -> 0 | P48: =_xlfn.XLOOKUP(K48,[1]库销表!$F:$F,[1]库销表!$L:$L) -> 30 | Q48: =X48/W48 -> #DIV/0! | S48: =_xlfn.XLOOKUP(K48,数据更新表!R:R,数据更新表!S:S) -> #N/A | T48: =_xlfn.XLOOKUP(K48,数据更新表!V:V,数据更新表!W:W) -> #N/A | V48: =IFERROR(7*O48/CZ48,"0") -> 0 | W48: =CZ48/7 -> 0 | X48: =O48+P48+SUM(BN48:BR48) -> 30 | AF48: =SUM(AG48:BR48) -> 0 | BS48: =_xlfn.XLOOKUP(K48,[1]库销表!$F:$F,[1]库销表!$L:$L) -> 30 | BT48: =SUM(BU48:CV48) -> 0 | CW48: =_xlfn.XLOOKUP(K48,[1]库销表!$F:$F,[1]库销表!$IE:$IE) -> 0 | CX48: =_xlfn.XLOOKUP(K48,[1]库销表!$F:$F,[1]库销表!$IF:$IF) -> 0 | CY48: =_xlfn.XLOOKUP(K48,[1]库销表!$F:$F,[1]库销表!$FL:$FL) -> 0 | CZ48: =_xlfn.XLOOKUP(K48,数据更新表!E:E,数据更新表!F:F,0) -> 0 | DA48: 0 | DB48: =_xlfn.XLOOKUP(K48,数据更新表!E:E,数据更新表!G:G) -> #N/A | DC48: =_xlfn.XLOOKUP(L48,数据更新表!Z:Z,数据更新表!AH:AH) -> #N/A | DD48: =_xlfn.XLOOKUP(L48,数据更新表!Z:Z,数据更新表!AE:AE) -> #N/A | DE48: =_xlfn.XLOOKUP(L48,数据更新表!Z:Z,数据更新表!AF:AF) -> #N/A | DF48: =_xlfn.XLOOKUP(K48,数据更新表!Z:Z,数据更新表!AG:AG) -> #N/A | DG48: =_xlfn.XLOOKUP(L48,数据更新表!Z:Z,数据更新表!AD:AD) -> #N/A | DH48: =_xlfn.XLOOKUP(L48,数据更新表!Z:Z,数据更新表!AA:AA) -> #N/A | DI48: =_xlfn.XLOOKUP(L48,数据更新表!Z:Z,数据更新表!AB:AB) -> #N/A | DJ48: =_xlfn.XLOOKUP(L48,数据更新表!Z:Z,数据更新表!AC:AC) -> #N/A | DK48: =_xlfn.XLOOKUP(L48,数据更新表!Z:Z,数据更新表!AI:AI) -> #N/A | DL48: =_xlfn.XLOOKUP(L48,数据更新表!AL:AL,数据更新表!AM:AM) -> #N/A | DM48: =_xlfn.XLOOKUP(L48,数据更新表!Z:Z,数据更新表!AJ:AJ) -> #N/A | EE48: =_xlfn.XLOOKUP(L48,数据更新表!J:J,数据更新表!L:L) -> #N/A | EF48: =EE48/0.7 -> #N/A | EG48: 27.5 | EH48: =EJ48/(EI48+EL48) -> #N/A | EI48: =EG48*$EI$1 -> 71.775 | EJ48: =EE48-EI48-EL48-EO48-EN48-EP48-EQ48 -> #N/A | EK48: =EJ48/EE48 -> #N/A | EL48: =EX48*3000*$EI$1 -> 9.396 | EM48: =IF(EE48>299,"是","否") -> #N/A | EN48: =EE48*0.05 -> #N/A | EO48: =EE48*0.175 -> #N/A | EP48: =IF(EE48<299,IF(EE48<99,25,IF(EE48<=149,30,IF(EE48<=299,37,85))),IF(EE48<=498,_xlfn.XLOOKUP(EW48,运费表!A:A,运费表!C:C,"重量超限",-1),_xlfn.XLOOKUP(EW48,运费表!A:A,运费表!D:D,"重量超限",-1))) -> #N/A | EQ48: =EE48*0.105 -> #N/A | ER48: =_xlfn.XLOOKUP(K48,[4]目录表!$H:$H,[4]目录表!$X:$X) -> 0.6 | ES48: =_xlfn.XLOOKUP(K48,[4]目录表!$H:$H,[4]目录表!$Y:$Y) -> 60 | ET48: =_xlfn.XLOOKUP(K48,[4]目录表!$H:$H,[4]目录表!$Z:$Z) -> 4 | EU48: =_xlfn.XLOOKUP(K48,[4]目录表!$H:$H,[4]目录表!$AA:$AA) -> 5 | EV48: =ES48*ET48*EU48/5000 -> 0.24 | EW48: =IF(EV48>=ER48,EV48,ER48) -> 0.6 | EX48: =_xlfn.XLOOKUP(K48,[2]目录表!$H:$H,[2]目录表!$AB:$AB) -> 0.0012 | EZ48: =CZ48/7 -> 0 | FK48: =_xlfn.XLOOKUP(K48,[2]目录表!$H:$H,[2]目录表!$AJ:$AJ) -> 散货
B49: 2 Amortiguadores Cajuela Jetta A4 1999-2015 | Envío gratis | C49: 40 | D49: 115 | E49: 46037 | G49: 后备箱减震器 | H49: 后备箱减震器（左右）3B5-827-550A | J49: 2 Amortiguadores Cajuela Jetta A4 1999-2015 | K49: XQ5-QP039-3B5-827-550A | L49: 4704295418 | M49: 新上架 | N49: =_xlfn.XLOOKUP(L49,数据更新表!J:J,数据更新表!K:K) -> #N/A | O49: =IFERROR(_xlfn.XLOOKUP(K49,数据更新表!A:A,数据更新表!B:B),"0") -> 0 | P49: =_xlfn.XLOOKUP(K49,[1]库销表!$F:$F,[1]库销表!$L:$L) -> 30 | Q49: =X49/W49 -> #DIV/0! | S49: =_xlfn.XLOOKUP(K49,数据更新表!R:R,数据更新表!S:S) -> #N/A | T49: =_xlfn.XLOOKUP(K49,数据更新表!V:V,数据更新表!W:W) -> #N/A | V49: =IFERROR(7*O49/CZ49,"0") -> 0 | W49: =CZ49/7 -> 0 | X49: =O49+P49+SUM(BN49:BR49) -> 30 | AF49: =SUM(AG49:BR49) -> 0 | BS49: =_xlfn.XLOOKUP(K49,[1]库销表!$F:$F,[1]库销表!$L:$L) -> 30 | BT49: =SUM(BU49:CV49) -> 0 | CW49: =_xlfn.XLOOKUP(K49,[1]库销表!$F:$F,[1]库销表!$IE:$IE) -> 0 | CX49: =_xlfn.XLOOKUP(K49,[1]库销表!$F:$F,[1]库销表!$IF:$IF) -> 0 | CY49: =_xlfn.XLOOKUP(K49,[1]库销表!$F:$F,[1]库销表!$FL:$FL) -> 0 | CZ49: =_xlfn.XLOOKUP(K49,数据更新表!E:E,数据更新表!F:F,0) -> 0 | DA49: 0 | DB49: =_xlfn.XLOOKUP(K49,数据更新表!E:E,数据更新表!G:G) -> #N/A | DC49: =_xlfn.XLOOKUP(L49,数据更新表!Z:Z,数据更新表!AH:AH) -> #N/A | DD49: =_xlfn.XLOOKUP(L49,数据更新表!Z:Z,数据更新表!AE:AE) -> #N/A | DE49: =_xlfn.XLOOKUP(L49,数据更新表!Z:Z,数据更新表!AF:AF) -> #N/A | DF49: =_xlfn.XLOOKUP(K49,数据更新表!Z:Z,数据更新表!AG:AG) -> #N/A | DG49: =_xlfn.XLOOKUP(L49,数据更新表!Z:Z,数据更新表!AD:AD) -> #N/A | DH49: =_xlfn.XLOOKUP(L49,数据更新表!Z:Z,数据更新表!AA:AA) -> #N/A | DI49: =_xlfn.XLOOKUP(L49,数据更新表!Z:Z,数据更新表!AB:AB) -> #N/A | DJ49: =_xlfn.XLOOKUP(L49,数据更新表!Z:Z,数据更新表!AC:AC) -> #N/A | DK49: =_xlfn.XLOOKUP(L49,数据更新表!Z:Z,数据更新表!AI:AI) -> #N/A | DL49: =_xlfn.XLOOKUP(L49,数据更新表!AL:AL,数据更新表!AM:AM) -> #N/A | DM49: =_xlfn.XLOOKUP(L49,数据更新表!Z:Z,数据更新表!AJ:AJ) -> #N/A | EE49: =_xlfn.XLOOKUP(L49,数据更新表!J:J,数据更新表!L:L) -> #N/A | EF49: =EE49/0.7 -> #N/A | EG49: 23.5 | EH49: =EJ49/(EI49+EL49) -> #N/A | EI49: =EG49*$EI$1 -> 61.335 | EJ49: =EE49-EI49-EL49-EO49-EN49-EP49-EQ49 -> #N/A | EK49: =EJ49/EE49 -> #N/A | EL49: =EX49*3000*$EI$1 -> 9.396 | EM49: =IF(EE49>299,"是","否") -> #N/A | EN49: =EE49*0.05 -> #N/A | EO49: =EE49*0.175 -> #N/A | EP49: =IF(EE49<299,IF(EE49<99,25,IF(EE49<=149,30,IF(EE49<=299,37,85))),IF(EE49<=498,_xlfn.XLOOKUP(EW49,运费表!A:A,运费表!C:C,"重量超限",-1),_xlfn.XLOOKUP(EW49,运费表!A:A,运费表!D:D,"重量超限",-1))) -> #N/A | EQ49: =EE49*0.105 -> #N/A | ER49: =_xlfn.XLOOKUP(K49,[4]目录表!$H:$H,[4]目录表!$X:$X) -> 0.6 | ES49: =_xlfn.XLOOKUP(K49,[4]目录表!$H:$H,[4]目录表!$Y:$Y) -> 60 | ET49: =_xlfn.XLOOKUP(K49,[4]目录表!$H:$H,[4]目录表!$Z:$Z) -> 4 | EU49: =_xlfn.XLOOKUP(K49,[4]目录表!$H:$H,[4]目录表!$AA:$AA) -> 5 | EV49: =ES49*ET49*EU49/5000 -> 0.24 | EW49: =IF(EV49>=ER49,EV49,ER49) -> 0.6 | EX49: =_xlfn.XLOOKUP(K49,[2]目录表!$H:$H,[2]目录表!$AB:$AB) -> 0.0012 | EZ49: =CZ49/7 -> 0 | FK49: =_xlfn.XLOOKUP(K49,[2]目录表!$H:$H,[2]目录表!$AJ:$AJ) -> 散货
B50: Par De Amortiguadores Cajuela Seat Ibiza 2003-2009 | Meses sin interés | C50: 19 | D50: 116 | E50: 46045 | G50: 后备箱减震器 | H50: 后备箱减震器（左右）6L6-827-550B | J50: Par De Amortiguadores Cajuela Seat Ibiza 2003-2009 | K50: XQ5-QP040-6L6-827-550B | L50: 4704541614 | M50: 新上架 | N50: =_xlfn.XLOOKUP(L50,数据更新表!J:J,数据更新表!K:K) -> #N/A | O50: =IFERROR(_xlfn.XLOOKUP(K50,数据更新表!A:A,数据更新表!B:B),"0") -> 0 | P50: =_xlfn.XLOOKUP(K50,[1]库销表!$F:$F,[1]库销表!$L:$L) -> 30 | Q50: =X50/W50 -> #DIV/0! | S50: =_xlfn.XLOOKUP(K50,数据更新表!R:R,数据更新表!S:S) -> #N/A | T50: =_xlfn.XLOOKUP(K50,数据更新表!V:V,数据更新表!W:W) -> #N/A | V50: =IFERROR(7*O50/CZ50,"0") -> 0 | W50: =CZ50/7 -> 0 | X50: =O50+P50+SUM(BN50:BR50) -> 30 | AF50: =SUM(AG50:BR50) -> 0 | BS50: =_xlfn.XLOOKUP(K50,[1]库销表!$F:$F,[1]库销表!$L:$L) -> 30 | BT50: =SUM(BU50:CV50) -> 0 | CW50: =_xlfn.XLOOKUP(K50,[1]库销表!$F:$F,[1]库销表!$IE:$IE) -> 0 | CX50: =_xlfn.XLOOKUP(K50,[1]库销表!$F:$F,[1]库销表!$IF:$IF) -> 0 | CY50: =_xlfn.XLOOKUP(K50,[1]库销表!$F:$F,[1]库销表!$FL:$FL) -> 0 | CZ50: =_xlfn.XLOOKUP(K50,数据更新表!E:E,数据更新表!F:F,0) -> 0 | DA50: 0 | DB50: =_xlfn.XLOOKUP(K50,数据更新表!E:E,数据更新表!G:G) -> #N/A | DC50: =_xlfn.XLOOKUP(L50,数据更新表!Z:Z,数据更新表!AH:AH) -> #N/A | DD50: =_xlfn.XLOOKUP(L50,数据更新表!Z:Z,数据更新表!AE:AE) -> #N/A | DE50: =_xlfn.XLOOKUP(L50,数据更新表!Z:Z,数据更新表!AF:AF) -> #N/A | DF50: =_xlfn.XLOOKUP(K50,数据更新表!Z:Z,数据更新表!AG:AG) -> #N/A | DG50: =_xlfn.XLOOKUP(L50,数据更新表!Z:Z,数据更新表!AD:AD) -> #N/A | DH50: =_xlfn.XLOOKUP(L50,数据更新表!Z:Z,数据更新表!AA:AA) -> #N/A | DI50: =_xlfn.XLOOKUP(L50,数据更新表!Z:Z,数据更新表!AB:AB) -> #N/A | DJ50: =_xlfn.XLOOKUP(L50,数据更新表!Z:Z,数据更新表!AC:AC) -> #N/A | DK50: =_xlfn.XLOOKUP(L50,数据更新表!Z:Z,数据更新表!AI:AI) -> #N/A | DL50: =_xlfn.XLOOKUP(L50,数据更新表!AL:AL,数据更新表!AM:AM) -> #N/A | DM50: =_xlfn.XLOOKUP(L50,数据更新表!Z:Z,数据更新表!AJ:AJ) -> #N/A | EE50: =_xlfn.XLOOKUP(L50,数据更新表!J:J,数据更新表!L:L) -> #N/A | EF50: =EE50/0.7 -> #N/A | EG50: 27.5 | EH50: =EJ50/(EI50+EL50) -> #N/A | EI50: =EG50*$EI$1 -> 71.775 | EJ50: =EE50-EI50-EL50-EO50-EN50-EP50-EQ50 -> #N/A | EK50: =EJ50/EE50 -> #N/A | EL50: =EX50*3000*$EI$1 -> 9.396 | EM50: =IF(EE50>299,"是","否") -> #N/A | EN50: =EE50*0.05 -> #N/A | EO50: =EE50*0.175 -> #N/A | EP50: =IF(EE50<299,IF(EE50<99,25,IF(EE50<=149,30,IF(EE50<=299,37,85))),IF(EE50<=498,_xlfn.XLOOKUP(EW50,运费表!A:A,运费表!C:C,"重量超限",-1),_xlfn.XLOOKUP(EW50,运费表!A:A,运费表!D:D,"重量超限",-1))) -> #N/A | EQ50: =EE50*0.105 -> #N/A | ER50: =_xlfn.XLOOKUP(K50,[4]目录表!$H:$H,[4]目录表!$X:$X) -> 0.6 | ES50: =_xlfn.XLOOKUP(K50,[4]目录表!$H:$H,[4]目录表!$Y:$Y) -> 60 | ET50: =_xlfn.XLOOKUP(K50,[4]目录表!$H:$H,[4]目录表!$Z:$Z) -> 4 | EU50: =_xlfn.XLOOKUP(K50,[4]目录表!$H:$H,[4]目录表!$AA:$AA) -> 5 | EV50: =ES50*ET50*EU50/5000 -> 0.24 | EW50: =IF(EV50>=ER50,EV50,ER50) -> 0.6 | EX50: =_xlfn.XLOOKUP(K50,[2]目录表!$H:$H,[2]目录表!$AB:$AB) -> 0.0012 | EZ50: =CZ50/7 -> 0 | FK50: =_xlfn.XLOOKUP(K50,[2]目录表!$H:$H,[2]目录表!$AJ:$AJ) -> 散货
B51: Mesa Pasteur Cromada Uso Rudo Envío Gratis Y Factura | Envío gratis | C51: 15 | D51: 30 | E51: =_xlfn.XLOOKUP(K51,[3]工业配件!$AA:$AA,[3]工业配件!$L:$L) -> #N/A | G51: 不锈钢推车 | H51: 麻醉车-特小号 | J51: Mesa Pasteur Cromada Uso Rudo Envío Gratis Y Factura | K51: XQ5-YL015 | M51: 未上架 | N51: =_xlfn.XLOOKUP(L51,数据更新表!J:J,数据更新表!K:K) -> 0 | O51: =IFERROR(_xlfn.XLOOKUP(K51,数据更新表!A:A,数据更新表!B:B),"0") -> 0 | P51: =_xlfn.XLOOKUP(K51,[1]库销表!$F:$F,[1]库销表!$L:$L) -> 0 | Q51: =X51/W51 -> #DIV/0! | S51: =_xlfn.XLOOKUP(K51,数据更新表!R:R,数据更新表!S:S) -> #N/A | T51: =_xlfn.XLOOKUP(K51,数据更新表!V:V,数据更新表!W:W) -> #N/A | V51: =IFERROR(7*O51/CZ51,"0") -> 0 | W51: =CZ51/7 -> 0 | X51: =O51+P51+SUM(BN51:BR51) -> 0 | AF51: =SUM(AG51:BR51) -> 0 | BS51: =_xlfn.XLOOKUP(K51,[1]库销表!$F:$F,[1]库销表!$L:$L) -> 0 | BT51: =SUM(BU51:CV51) -> 0 | CW51: =_xlfn.XLOOKUP(K51,[1]库销表!$F:$F,[1]库销表!$IE:$IE) -> 0 | CX51: =_xlfn.XLOOKUP(K51,[1]库销表!$F:$F,[1]库销表!$IF:$IF) -> 0 | CY51: =_xlfn.XLOOKUP(K51,[1]库销表!$F:$F,[1]库销表!$FL:$FL) -> 0 | CZ51: =_xlfn.XLOOKUP(K51,数据更新表!E:E,数据更新表!F:F,0) -> 0 | DA51: 0 | DB51: =_xlfn.XLOOKUP(K51,数据更新表!E:E,数据更新表!G:G) -> #N/A | DC51: =_xlfn.XLOOKUP(L51,数据更新表!Z:Z,数据更新表!AH:AH) -> 0 | DD51: =_xlfn.XLOOKUP(L51,数据更新表!Z:Z,数据更新表!AE:AE) -> 0 | DE51: =_xlfn.XLOOKUP(L51,数据更新表!Z:Z,数据更新表!AF:AF) -> 0 | DF51: =_xlfn.XLOOKUP(K51,数据更新表!Z:Z,数据更新表!AG:AG) -> #N/A | DG51: =_xlfn.XLOOKUP(L51,数据更新表!Z:Z,数据更新表!AD:AD) -> 0 | DH51: =_xlfn.XLOOKUP(L51,数据更新表!Z:Z,数据更新表!AA:AA) -> 0 | DI51: =_xlfn.XLOOKUP(L51,数据更新表!Z:Z,数据更新表!AB:AB) -> 0 | DJ51: =_xlfn.XLOOKUP(L51,数据更新表!Z:Z,数据更新表!AC:AC) -> 0 | DK51: =_xlfn.XLOOKUP(L51,数据更新表!Z:Z,数据更新表!AI:AI) -> 0 | DL51: =_xlfn.XLOOKUP(L51,数据更新表!AL:AL,数据更新表!AM:AM) -> 0 | DM51: =_xlfn.XLOOKUP(L51,数据更新表!Z:Z,数据更新表!AJ:AJ) -> 0 | EE51: =_xlfn.XLOOKUP(L51,数据更新表!J:J,数据更新表!L:L) -> 0 | EF51: =_xlfn.XLOOKUP(L51,数据更新表!J:J,数据更新表!M:M) -> 0 | EG51: 140 | EH51: =EJ51/(EI51+EL51) -> -1.0395834 | EI51: =EG51*$EI$1 -> 365.4 | EJ51: =EE51-EI51-EL51-EO51-EN51-EP51-EQ51 -> -656.5782 | EK51: =EJ51/EE51 -> #DIV/0! | EL51: =EX51*2500*$EI$1 -> 266.1782 | EM51: =IF(EE51>299,"是","否") -> 否 | EN51: =EE51*0.05 -> 0 | EO51: =EE51*0.175 -> 0 | EP51: =IF(EE51<299,IF(EE51<99,25,IF(EE51<=149,30,IF(EE51<=299,37,85))),IF(EE51<=498,_xlfn.XLOOKUP(EW51,运费表!A:A,运费表!C:C,"重量超限",-1),_xlfn.XLOOKUP(EW51,运费表!A:A,运费表!D:D,"重量超限",-1))) -> 25 | EQ51: =EE51*0.105 -> 0 | ER51: =_xlfn.XLOOKUP(K51,[4]目录表!$H:$H,[4]目录表!$X:$X) -> 9 | ES51: =_xlfn.XLOOKUP(K51,[4]目录表!$H:$H,[4]目录表!$Y:$Y) -> 0 | ET51: =_xlfn.XLOOKUP(K51,[4]目录表!$H:$H,[4]目录表!$Z:$Z) -> 0 | EU51: =_xlfn.XLOOKUP(K51,[4]目录表!$H:$H,[4]目录表!$AA:$AA) -> 0 | EV51: =ES51*ET51*EU51/5000 -> 0 | EW51: =IF(EV51>=ER51,EV51,ER51) -> 9 | EX51: =_xlfn.XLOOKUP(K51,[2]目录表!$H:$H,[2]目录表!$AB:$AB) -> 0.040793594 | EY51: 箱规为4个 | EZ51: =CZ51/7 -> 0 | FK51: =_xlfn.XLOOKUP(K51,[2]目录表!$H:$H,[2]目录表!$AJ:$AJ) -> 装柜
B52: Mesa Pasteur Totalmente De Acero Inoxidable | Meses sin interés | C52: 5 | D52: 28 | E52: =_xlfn.XLOOKUP(K52,[3]工业配件!$AA:$AA,[3]工业配件!$L:$L) -> #N/A | G52: 不锈钢推车 | H52: 器械车-特小号 | J52: Mesa Pasteur Totalmente De Acero Inoxidable | K52: XQ5-YL016 | M52: 未上架 | N52: =_xlfn.XLOOKUP(L52,数据更新表!J:J,数据更新表!K:K) -> 0 | O52: =IFERROR(_xlfn.XLOOKUP(K52,数据更新表!A:A,数据更新表!B:B),"0") -> 0 | P52: =_xlfn.XLOOKUP(K52,[1]库销表!$F:$F,[1]库销表!$L:$L) -> 0 | Q52: =X52/W52 -> #DIV/0! | S52: =_xlfn.XLOOKUP(K52,数据更新表!R:R,数据更新表!S:S) -> #N/A | T52: =_xlfn.XLOOKUP(K52,数据更新表!V:V,数据更新表!W:W) -> #N/A | V52: =IFERROR(7*O52/CZ52,"0") -> 0 | W52: =CZ52/7 -> 0 | X52: =O52+P52+SUM(BN52:BR52) -> 0 | AF52: =SUM(AG52:BR52) -> 0 | BS52: =_xlfn.XLOOKUP(K52,[1]库销表!$F:$F,[1]库销表!$L:$L) -> 0 | BT52: =SUM(BU52:CV52) -> 0 | CW52: =_xlfn.XLOOKUP(K52,[1]库销表!$F:$F,[1]库销表!$IE:$IE) -> 0 | CX52: =_xlfn.XLOOKUP(K52,[1]库销表!$F:$F,[1]库销表!$IF:$IF) -> 0 | CY52: =_xlfn.XLOOKUP(K52,[1]库销表!$F:$F,[1]库销表!$FL:$FL) -> 0 | CZ52: =_xlfn.XLOOKUP(K52,数据更新表!E:E,数据更新表!F:F,0) -> 0 | DA52: 0 | DB52: =_xlfn.XLOOKUP(K52,数据更新表!E:E,数据更新表!G:G) -> #N/A | DC52: =_xlfn.XLOOKUP(L52,数据更新表!Z:Z,数据更新表!AH:AH) -> 0 | DD52: =_xlfn.XLOOKUP(L52,数据更新表!Z:Z,数据更新表!AE:AE) -> 0 | DE52: =_xlfn.XLOOKUP(L52,数据更新表!Z:Z,数据更新表!AF:AF) -> 0 | DF52: =_xlfn.XLOOKUP(K52,数据更新表!Z:Z,数据更新表!AG:AG) -> #N/A | DG52: =_xlfn.XLOOKUP(L52,数据更新表!Z:Z,数据更新表!AD:AD) -> 0 | DH52: =_xlfn.XLOOKUP(L52,数据更新表!Z:Z,数据更新表!AA:AA) -> 0 | DI52: =_xlfn.XLOOKUP(L52,数据更新表!Z:Z,数据更新表!AB:AB) -> 0 | DJ52: =_xlfn.XLOOKUP(L52,数据更新表!Z:Z,数据更新表!AC:AC) -> 0 | DK52: =_xlfn.XLOOKUP(L52,数据更新表!Z:Z,数据更新表!AI:AI) -> 0 | DL52: =_xlfn.XLOOKUP(L52,数据更新表!AL:AL,数据更新表!AM:AM) -> 0 | DM52: =_xlfn.XLOOKUP(L52,数据更新表!Z:Z,数据更新表!AJ:AJ) -> 0 | EE52: =_xlfn.XLOOKUP(L52,数据更新表!J:J,数据更新表!L:L) -> 0 | EF52: =_xlfn.XLOOKUP(L52,数据更新表!J:J,数据更新表!M:M) -> 0 | EG52: 130 | EH52: =EJ52/(EI52+EL52) -> -1.0391753 | EI52: =EG52*$EI$1 -> 339.3 | EJ52: =EE52-EI52-EL52-EO52-EN52-EP52-EQ52 -> -663.15723 | EK52: =EJ52/EE52 -> #DIV/0! | EL52: =EX52*2500*$EI$1 -> 298.85723 | EM52: =IF(EE52>299,"是","否") -> 否 | EN52: =EE52*0.05 -> 0 | EO52: =EE52*0.175 -> 0 | EP52: =IF(EE52<299,IF(EE52<99,25,IF(EE52<=149,30,IF(EE52<=299,37,85))),IF(EE52<=498,_xlfn.XLOOKUP(EW52,运费表!A:A,运费表!C:C,"重量超限",-1),_xlfn.XLOOKUP(EW52,运费表!A:A,运费表!D:D,"重量超限",-1))) -> 25 | EQ52: =EE52*0.105 -> 0 | ER52: =_xlfn.XLOOKUP(K52,[4]目录表!$H:$H,[4]目录表!$X:$X) -> 9 | ES52: =_xlfn.XLOOKUP(K52,[4]目录表!$H:$H,[4]目录表!$Y:$Y) -> 0 | ET52: =_xlfn.XLOOKUP(K52,[4]目录表!$H:$H,[4]目录表!$Z:$Z) -> 0 | EU52: =_xlfn.XLOOKUP(K52,[4]目录表!$H:$H,[4]目录表!$AA:$AA) -> 0 | EV52: =ES52*ET52*EU52/5000 -> 0 | EW52: =IF(EV52>=ER52,EV52,ER52) -> 9 | EX52: =_xlfn.XLOOKUP(K52,[2]目录表!$H:$H,[2]目录表!$AB:$AB) -> 0.045801875 | EY52: 箱规为3个 | EZ52: =CZ52/7 -> 0 | FK52: =_xlfn.XLOOKUP(K52,[2]目录表!$H:$H,[2]目录表!$AJ:$AJ) -> 装柜
B53: Mesa Pasteur Para Dialisis Con Portasueros Envío Gratis | Envío gratis | C53: 8 | D53: 34 | E53: =_xlfn.XLOOKUP(K53,[3]工业配件!$AA:$AA,[3]工业配件!$L:$L) -> #N/A | G53: 不锈钢推车 | H53: 输液车-特小号 | J53: Mesa Pasteur Para Dialisis Con Portasueros Envío Gratis | K53: XQ5-YL017 | M53: 未上架 | N53: =_xlfn.XLOOKUP(L53,数据更新表!J:J,数据更新表!K:K) -> 0 | O53: =IFERROR(_xlfn.XLOOKUP(K53,数据更新表!A:A,数据更新表!B:B),"0") -> 0 | P53: =_xlfn.XLOOKUP(K53,[1]库销表!$F:$F,[1]库销表!$L:$L) -> 0 | Q53: =X53/W53 -> #DIV/0! | S53: =_xlfn.XLOOKUP(K53,数据更新表!R:R,数据更新表!S:S) -> #N/A | T53: =_xlfn.XLOOKUP(K53,数据更新表!V:V,数据更新表!W:W) -> #N/A | V53: =IFERROR(7*O53/CZ53,"0") -> 0 | W53: =CZ53/7 -> 0 | X53: =O53+P53+SUM(BN53:BR53) -> 0 | AF53: =SUM(AG53:BR53) -> 0 | BS53: =_xlfn.XLOOKUP(K53,[1]库销表!$F:$F,[1]库销表!$L:$L) -> 0 | BT53: =SUM(BU53:CV53) -> 0 | CW53: =_xlfn.XLOOKUP(K53,[1]库销表!$F:$F,[1]库销表!$IE:$IE) -> 0 | CX53: =_xlfn.XLOOKUP(K53,[1]库销表!$F:$F,[1]库销表!$IF:$IF) -> 0 | CY53: =_xlfn.XLOOKUP(K53,[1]库销表!$F:$F,[1]库销表!$FL:$FL) -> 0 | CZ53: =_xlfn.XLOOKUP(K53,数据更新表!E:E,数据更新表!F:F,0) -> 0 | DA53: 0 | DB53: =_xlfn.XLOOKUP(K53,数据更新表!E:E,数据更新表!G:G) -> #N/A | DC53: =_xlfn.XLOOKUP(L53,数据更新表!Z:Z,数据更新表!AH:AH) -> 0 | DD53: =_xlfn.XLOOKUP(L53,数据更新表!Z:Z,数据更新表!AE:AE) -> 0 | DE53: =_xlfn.XLOOKUP(L53,数据更新表!Z:Z,数据更新表!AF:AF) -> 0 | DF53: =_xlfn.XLOOKUP(K53,数据更新表!Z:Z,数据更新表!AG:AG) -> #N/A | DG53: =_xlfn.XLOOKUP(L53,数据更新表!Z:Z,数据更新表!AD:AD) -> 0 | DH53: =_xlfn.XLOOKUP(L53,数据更新表!Z:Z,数据更新表!AA:AA) -> 0 | DI53: =_xlfn.XLOOKUP(L53,数据更新表!Z:Z,数据更新表!AB:AB) -> 0 | DJ53: =_xlfn.XLOOKUP(L53,数据更新表!Z:Z,数据更新表!AC:AC) -> 0 | DK53: =_xlfn.XLOOKUP(L53,数据更新表!Z:Z,数据更新表!AI:AI) -> 0 | DL53: =_xlfn.XLOOKUP(L53,数据更新表!AL:AL,数据更新表!AM:AM) -> 0 | DM53: =_xlfn.XLOOKUP(L53,数据更新表!Z:Z,数据更新表!AJ:AJ) -> 0 | EE53: =_xlfn.XLOOKUP(L53,数据更新表!J:J,数据更新表!L:L) -> 0 | EF53: =_xlfn.XLOOKUP(L53,数据更新表!J:J,数据更新表!M:M) -> 0 | EG53: 155 | EH53: =EJ53/(EI53+EL53) -> -1.0274322 | EI53: =EG53*$EI$1 -> 404.55 | EJ53: =EE53-EI53-EL53-EO53-EN53-EP53-EQ53 -> -936.33655 | EK53: =EJ53/EE53 -> #DIV/0! | EL53: =EX53*2500*$EI$1 -> 506.78655 | EM53: =IF(EE53>299,"是","否") -> 否 | EN53: =EE53*0.05 -> 0 | EO53: =EE53*0.175 -> 0 | EP53: =IF(EE53<299,IF(EE53<99,25,IF(EE53<=149,30,IF(EE53<=299,37,85))),IF(EE53<=498,_xlfn.XLOOKUP(EW53,运费表!A:A,运费表!C:C,"重量超限",-1),_xlfn.XLOOKUP(EW53,运费表!A:A,运费表!D:D,"重量超限",-1))) -> 25 | EQ53: =EE53*0.105 -> 0 | ER53: =_xlfn.XLOOKUP(K53,[4]目录表!$H:$H,[4]目录表!$X:$X) -> 9 | ES53: =_xlfn.XLOOKUP(K53,[4]目录表!$H:$H,[4]目录表!$Y:$Y) -> 0 | ET53: =_xlfn.XLOOKUP(K53,[4]目录表!$H:$H,[4]目录表!$Z:$Z) -> 0 | EU53: =_xlfn.XLOOKUP(K53,[4]目录表!$H:$H,[4]目录表!$AA:$AA) -> 0 | EV53: =ES53*ET53*EU53/5000 -> 0 | EW53: =IF(EV53>=ER53,EV53,ER53) -> 9 | EX53: =_xlfn.XLOOKUP(K53,[2]目录表!$H:$H,[2]目录表!$AB:$AB) -> 0.077668438 | EY53: 箱规为2个 | EZ53: =CZ53/7 -> 0 | FK53: =_xlfn.XLOOKUP(K53,[2]目录表!$H:$H,[2]目录表!$AJ:$AJ) -> 装柜
B54: Carrito De Médico De Acero Inoxidable, Mesa Para Instrumental Médico, Con 2 Cajones + 2 Bandejas De Acero Inoxidable Adicionales | Envío gratis | C54: 23 | D54: 82 | E54: =_xlfn.XLOOKUP(K54,[3]工业配件!$AA:$AA,[3]工业配件!$L:$L) -> #N/A | G54: 不锈钢推车 | H54: 外栏治疗车-小号二层双抽 | J54: Carrito De Médico De Acero Inoxidable, Mesa Para Instrumental Médico, Con 2 Cajones + 2 Bandejas De Acero Inoxidable Adicionales | K54: XQ5-YL018 | M54: 未上架 | N54: =_xlfn.XLOOKUP(L54,数据更新表!J:J,数据更新表!K:K) -> 0 | O54: =IFERROR(_xlfn.XLOOKUP(K54,数据更新表!A:A,数据更新表!B:B),"0") -> 0 | P54: =_xlfn.XLOOKUP(K54,[1]库销表!$F:$F,[1]库销表!$L:$L) -> 0 | Q54: =X54/W54 -> #DIV/0! | S54: =_xlfn.XLOOKUP(K54,数据更新表!R:R,数据更新表!S:S) -> #N/A | T54: =_xlfn.XLOOKUP(K54,数据更新表!V:V,数据更新表!W:W) -> #N/A | V54: =IFERROR(7*O54/CZ54,"0") -> 0 | W54: =CZ54/7 -> 0 | X54: =O54+P54+SUM(BN54:BR54) -> 0 | AF54: =SUM(AG54:BR54) -> 0 | BS54: =_xlfn.XLOOKUP(K54,[1]库销表!$F:$F,[1]库销表!$L:$L) -> 0 | BT54: =SUM(BU54:CV54) -> 0 | CW54: =_xlfn.XLOOKUP(K54,[1]库销表!$F:$F,[1]库销表!$IE:$IE) -> 0 | CX54: =_xlfn.XLOOKUP(K54,[1]库销表!$F:$F,[1]库销表!$IF:$IF) -> 0 | CY54: =_xlfn.XLOOKUP(K54,[1]库销表!$F:$F,[1]库销表!$FL:$FL) -> 0 | CZ54: =_xlfn.XLOOKUP(K54,数据更新表!E:E,数据更新表!F:F,0) -> 0 | DA54: 0 | DB54: =_xlfn.XLOOKUP(K54,数据更新表!E:E,数据更新表!G:G) -> #N/A | DC54: =_xlfn.XLOOKUP(L54,数据更新表!Z:Z,数据更新表!AH:AH) -> 0 | DD54: =_xlfn.XLOOKUP(L54,数据更新表!Z:Z,数据更新表!AE:AE) -> 0 | DE54: =_xlfn.XLOOKUP(L54,数据更新表!Z:Z,数据更新表!AF:AF) -> 0 | DF54: =_xlfn.XLOOKUP(K54,数据更新表!Z:Z,数据更新表!AG:AG) -> #N/A | DG54: =_xlfn.XLOOKUP(L54,数据更新表!Z:Z,数据更新表!AD:AD) -> 0 | DH54: =_xlfn.XLOOKUP(L54,数据更新表!Z:Z,数据更新表!AA:AA) -> 0 | DI54: =_xlfn.XLOOKUP(L54,数据更新表!Z:Z,数据更新表!AB:AB) -> 0 | DJ54: =_xlfn.XLOOKUP(L54,数据更新表!Z:Z,数据更新表!AC:AC) -> 0 | DK54: =_xlfn.XLOOKUP(L54,数据更新表!Z:Z,数据更新表!AI:AI) -> 0 | DL54: =_xlfn.XLOOKUP(L54,数据更新表!AL:AL,数据更新表!AM:AM) -> 0 | DM54: =_xlfn.XLOOKUP(L54,数据更新表!Z:Z,数据更新表!AJ:AJ) -> 0 | EE54: =_xlfn.XLOOKUP(L54,数据更新表!J:J,数据更新表!L:L) -> 0 | EF54: =_xlfn.XLOOKUP(L54,数据更新表!J:J,数据更新表!M:M) -> 0 | EG54: 192 | EH54: =EJ54/(EI54+EL54) -> -1.0240612 | EI54: =EG54*$EI$1 -> 501.12 | EJ54: =EE54-EI54-EL54-EO54-EN54-EP54-EQ54 -> -1064.0165 | EK54: =EJ54/EE54 -> #DIV/0! | EL54: =EX54*2500*$EI$1 -> 537.89653 | EM54: =IF(EE54>299,"是","否") -> 否 | EN54: =EE54*0.05 -> 0 | EO54: =EE54*0.175 -> 0 | EP54: =IF(EE54<299,IF(EE54<99,25,IF(EE54<=149,30,IF(EE54<=299,37,85))),IF(EE54<=498,_xlfn.XLOOKUP(EW54,运费表!A:A,运费表!C:C,"重量超限",-1),_xlfn.XLOOKUP(EW54,运费表!A:A,运费表!D:D,"重量超限",-1))) -> 25 | EQ54: =EE54*0.105 -> 0 | ER54: =_xlfn.XLOOKUP(K54,[4]目录表!$H:$H,[4]目录表!$X:$X) -> 10 | ES54: =_xlfn.XLOOKUP(K54,[4]目录表!$H:$H,[4]目录表!$Y:$Y) -> 0 | ET54: =_xlfn.XLOOKUP(K54,[4]目录表!$H:$H,[4]目录表!$Z:$Z) -> 0 | EU54: =_xlfn.XLOOKUP(K54,[4]目录表!$H:$H,[4]目录表!$AA:$AA) -> 0 | EV54: =ES54*ET54*EU54/5000 -> 0 | EW54: =IF(EV54>=ER54,EV54,ER54) -> 10 | EX54: =_xlfn.XLOOKUP(K54,[2]目录表!$H:$H,[2]目录表!$AB:$AB) -> 0.08243625 | EY54: 箱规为2个 | EZ54: =CZ54/7 -> 0 | FK54: =_xlfn.XLOOKUP(K54,[2]目录表!$H:$H,[2]目录表!$AJ:$AJ) -> 装柜
B55: https://www.mercadolibre.com.mx/mesa-pasteur-con-cajon-uso-rudo-envio-gratis-facturada/p/MLM2039970772?pdp_filters=item_id:MLM2294543411 | C55: 7 | D55: 7 | E55: =_xlfn.XLOOKUP(K55,[3]工业配件!$AA:$AA,[3]工业配件!$L:$L) -> #N/A | G55: 不锈钢推车 | H55: 麻醉车-特小号单抽 | J55: Mesa Pasteur Con Cajon Uso Rudo Envio Gratis Facturada | K55: XQ5-YL019 | M55: 未上架 | N55: =_xlfn.XLOOKUP(L55,数据更新表!J:J,数据更新表!K:K) -> 0 | O55: =IFERROR(_xlfn.XLOOKUP(K55,数据更新表!A:A,数据更新表!B:B),"0") -> 0 | P55: =_xlfn.XLOOKUP(K55,[1]库销表!$F:$F,[1]库销表!$L:$L) -> 0 | Q55: =X55/W55 -> #DIV/0! | S55: =_xlfn.XLOOKUP(K55,数据更新表!R:R,数据更新表!S:S) -> #N/A | T55: =_xlfn.XLOOKUP(K55,数据更新表!V:V,数据更新表!W:W) -> #N/A | V55: =IFERROR(7*O55/CZ55,"0") -> 0 | W55: =CZ55/7 -> 0 | X55: =O55+P55+SUM(BN55:BR55) -> 0 | AF55: =SUM(AG55:BR55) -> 0 | BS55: =_xlfn.XLOOKUP(K55,[1]库销表!$F:$F,[1]库销表!$L:$L) -> 0 | BT55: =SUM(BU55:CV55) -> 0 | CW55: =_xlfn.XLOOKUP(K55,[1]库销表!$F:$F,[1]库销表!$IE:$IE) -> 0 | CX55: =_xlfn.XLOOKUP(K55,[1]库销表!$F:$F,[1]库销表!$IF:$IF) -> 0 | CY55: =_xlfn.XLOOKUP(K55,[1]库销表!$F:$F,[1]库销表!$FL:$FL) -> 0 | CZ55: =_xlfn.XLOOKUP(K55,数据更新表!E:E,数据更新表!F:F,0) -> 0 | DA55: 0 | DB55: =_xlfn.XLOOKUP(K55,数据更新表!E:E,数据更新表!G:G) -> #N/A | DC55: =_xlfn.XLOOKUP(L55,数据更新表!Z:Z,数据更新表!AH:AH) -> 0 | DD55: =_xlfn.XLOOKUP(L55,数据更新表!Z:Z,数据更新表!AE:AE) -> 0 | DE55: =_xlfn.XLOOKUP(L55,数据更新表!Z:Z,数据更新表!AF:AF) -> 0 | DF55: =_xlfn.XLOOKUP(K55,数据更新表!Z:Z,数据更新表!AG:AG) -> #N/A | DG55: =_xlfn.XLOOKUP(L55,数据更新表!Z:Z,数据更新表!AD:AD) -> 0 | DH55: =_xlfn.XLOOKUP(L55,数据更新表!Z:Z,数据更新表!AA:AA) -> 0 | DI55: =_xlfn.XLOOKUP(L55,数据更新表!Z:Z,数据更新表!AB:AB) -> 0 | DJ55: =_xlfn.XLOOKUP(L55,数据更新表!Z:Z,数据更新表!AC:AC) -> 0 | DK55: =_xlfn.XLOOKUP(L55,数据更新表!Z:Z,数据更新表!AI:AI) -> 0 | DL55: =_xlfn.XLOOKUP(L55,数据更新表!AL:AL,数据更新表!AM:AM) -> 0 | DM55: =_xlfn.XLOOKUP(L55,数据更新表!Z:Z,数据更新表!AJ:AJ) -> 0 | EE55: =_xlfn.XLOOKUP(L55,数据更新表!J:J,数据更新表!L:L) -> 0 | EF55: =_xlfn.XLOOKUP(L55,数据更新表!J:J,数据更新表!M:M) -> 0 | EG55: 192 | EH55: =EJ55/(EI55+EL55) -> -1.0231994 | EI55: =EG55*$EI$1 -> 501.12 | EJ55: =EE55-EI55-EL55-EO55-EN55-EP55-EQ55 -> -1102.6123 | EK55: =EJ55/EE55 -> #DIV/0! | EL55: =EX55*2500*$EI$1 -> 576.49231 | EM55: =IF(EE55>299,"是","否") -> 否 | EN55: =EE55*0.05 -> 0 | EO55: =EE55*0.175 -> 0 | EP55: =IF(EE55<299,IF(EE55<99,25,IF(EE55<=149,30,IF(EE55<=299,37,85))),IF(EE55<=498,_xlfn.XLOOKUP(EW55,运费表!A:A,运费表!C:C,"重量超限",-1),_xlfn.XLOOKUP(EW55,运费表!A:A,运费表!D:D,"重量超限",-1))) -> 25 | EQ55: =EE55*0.105 -> 0 | ER55: =_xlfn.XLOOKUP(K55,[4]目录表!$H:$H,[4]目录表!$X:$X) -> 10 | ES55: =_xlfn.XLOOKUP(K55,[4]目录表!$H:$H,[4]目录表!$Y:$Y) -> 0 | ET55: =_xlfn.XLOOKUP(K55,[4]目录表!$H:$H,[4]目录表!$Z:$Z) -> 0 | EU55: =_xlfn.XLOOKUP(K55,[4]目录表!$H:$H,[4]目录表!$AA:$AA) -> 0 | EV55: =ES55*ET55*EU55/5000 -> 0 | EW55: =IF(EV55>=ER55,EV55,ER55) -> 10 | EX55: =_xlfn.XLOOKUP(K55,[2]目录表!$H:$H,[2]目录表!$AB:$AB) -> 0.088351313 | EY55: 箱规为2个 | EZ55: =CZ55/7 -> 0 | FK55: =_xlfn.XLOOKUP(K55,[2]目录表!$H:$H,[2]目录表!$AJ:$AJ) -> 装柜
B56: Mesa Pasteur 100% Acero Inoxidable 60x40x90 Cm | Envío gratis | C56: 5 | D56: 7 | E56: =_xlfn.XLOOKUP(K56,[3]工业配件!$AA:$AA,[3]工业配件!$L:$L) -> #N/A | G56: 不锈钢推车 | H56: 麻醉车-小号 | J56: Mesa Pasteur 100% Acero Inoxidable 60x40x90 Cm | K56: XQ5-YL020 | M56: 未上架 | N56: =_xlfn.XLOOKUP(L56,数据更新表!J:J,数据更新表!K:K) -> 0 | O56: =IFERROR(_xlfn.XLOOKUP(K56,数据更新表!A:A,数据更新表!B:B),"0") -> 0 | P56: =_xlfn.XLOOKUP(K56,[1]库销表!$F:$F,[1]库销表!$L:$L) -> 0 | Q56: =X56/W56 -> #DIV/0! | S56: =_xlfn.XLOOKUP(K56,数据更新表!R:R,数据更新表!S:S) -> #N/A | T56: =_xlfn.XLOOKUP(K56,数据更新表!V:V,数据更新表!W:W) -> #N/A | V56: =IFERROR(7*O56/CZ56,"0") -> 0 | W56: =CZ56/7 -> 0 | X56: =O56+P56+SUM(BN56:BR56) -> 0 | AF56: =SUM(AG56:BR56) -> 0 | BS56: =_xlfn.XLOOKUP(K56,[1]库销表!$F:$F,[1]库销表!$L:$L) -> 0 | BT56: =SUM(BU56:CV56) -> 0 | CW56: =_xlfn.XLOOKUP(K56,[1]库销表!$F:$F,[1]库销表!$IE:$IE) -> 0 | CX56: =_xlfn.XLOOKUP(K56,[1]库销表!$F:$F,[1]库销表!$IF:$IF) -> 0 | CY56: =_xlfn.XLOOKUP(K56,[1]库销表!$F:$F,[1]库销表!$FL:$FL) -> 0 | CZ56: =_xlfn.XLOOKUP(K56,数据更新表!E:E,数据更新表!F:F,0) -> 0 | DA56: 0 | DB56: =_xlfn.XLOOKUP(K56,数据更新表!E:E,数据更新表!G:G) -> #N/A | DC56: =_xlfn.XLOOKUP(L56,数据更新表!Z:Z,数据更新表!AH:AH) -> 0 | DD56: =_xlfn.XLOOKUP(L56,数据更新表!Z:Z,数据更新表!AE:AE) -> 0 | DE56: =_xlfn.XLOOKUP(L56,数据更新表!Z:Z,数据更新表!AF:AF) -> 0 | DF56: =_xlfn.XLOOKUP(K56,数据更新表!Z:Z,数据更新表!AG:AG) -> #N/A | DG56: =_xlfn.XLOOKUP(L56,数据更新表!Z:Z,数据更新表!AD:AD) -> 0 | DH56: =_xlfn.XLOOKUP(L56,数据更新表!Z:Z,数据更新表!AA:AA) -> 0 | DI56: =_xlfn.XLOOKUP(L56,数据更新表!Z:Z,数据更新表!AB:AB) -> 0 | DJ56: =_xlfn.XLOOKUP(L56,数据更新表!Z:Z,数据更新表!AC:AC) -> 0 | DK56: =_xlfn.XLOOKUP(L56,数据更新表!Z:Z,数据更新表!AI:AI) -> 0 | DL56: =_xlfn.XLOOKUP(L56,数据更新表!AL:AL,数据更新表!AM:AM) -> 0 | DM56: =_xlfn.XLOOKUP(L56,数据更新表!Z:Z,数据更新表!AJ:AJ) -> 0 | EE56: =_xlfn.XLOOKUP(L56,数据更新表!J:J,数据更新表!L:L) -> 0 | EF56: =_xlfn.XLOOKUP(L56,数据更新表!J:J,数据更新表!M:M) -> 0 | EG56: 150 | EH56: =EJ56/(EI56+EL56) -> -1.0382217 | EI56: =EG56*$EI$1 -> 391.5 | EJ56: =EE56-EI56-EL56-EO56-EN56-EP56-EQ56 -> -679.07844 | EK56: =EJ56/EE56 -> #DIV/0! | EL56: =EX56*2500*$EI$1 -> 262.57844 | EM56: =IF(EE56>299,"是","否") -> 否 | EN56: =EE56*0.05 -> 0 | EO56: =EE56*0.175 -> 0 | EP56: =IF(EE56<299,IF(EE56<99,25,IF(EE56<=149,30,IF(EE56<=299,37,85))),IF(EE56<=498,_xlfn.XLOOKUP(EW56,运费表!A:A,运费表!C:C,"重量超限",-1),_xlfn.XLOOKUP(EW56,运费表!A:A,运费表!D:D,"重量超限",-1))) -> 25 | EQ56: =EE56*0.105 -> 0 | ER56: =_xlfn.XLOOKUP(K56,[4]目录表!$H:$H,[4]目录表!$X:$X) -> 10 | ES56: =_xlfn.XLOOKUP(K56,[4]目录表!$H:$H,[4]目录表!$Y:$Y) -> 0 | ET56: =_xlfn.XLOOKUP(K56,[4]目录表!$H:$H,[4]目录表!$Z:$Z) -> 0 | EU56: =_xlfn.XLOOKUP(K56,[4]目录表!$H:$H,[4]目录表!$AA:$AA) -> 0 | EV56: =ES56*ET56*EU56/5000 -> 0 | EW56: =IF(EV56>=ER56,EV56,ER56) -> 10 | EX56: =_xlfn.XLOOKUP(K56,[2]目录表!$H:$H,[2]目录表!$AB:$AB) -> 0.040241906 | EY56: 箱规为4个 | EZ56: =CZ56/7 -> 0 | FK56: =_xlfn.XLOOKUP(K56,[2]目录表!$H:$H,[2]目录表!$AJ:$AJ) -> 装柜
B57: https://articulo.mercadolibre.com.mx/MLM-3412424772-mesa-pasteur-grado-hospitalario-salon-de-belleza-spa-_JM#polycard_client=search-nordic&search_layout=grid&position=1&type=item&tracking_id=d92c673d-14e6-44cd-92d9-ac0be745bd4a&wid=MLM3412424772&sid=search | C57: 13 | D57: 31 | E57: =_xlfn.XLOOKUP(K57,[3]工业配件!$AA:$AA,[3]工业配件!$L:$L) -> #N/A | G57: 塑料推车 | H57: 全塑料推车 | J57: Mesa Pasteur Grado Hospitalario Salón De Belleza Spa | K57: XQ5-YL003 | M57: 未上架 | N57: =_xlfn.XLOOKUP(L57,数据更新表!J:J,数据更新表!K:K) -> 0 | O57: =IFERROR(_xlfn.XLOOKUP(K57,数据更新表!A:A,数据更新表!B:B),"0") -> 0 | P57: =_xlfn.XLOOKUP(K57,[1]库销表!$F:$F,[1]库销表!$L:$L) -> 0 | Q57: =X57/W57 -> #DIV/0! | S57: =_xlfn.XLOOKUP(K57,数据更新表!R:R,数据更新表!S:S) -> #N/A | T57: =_xlfn.XLOOKUP(K57,数据更新表!V:V,数据更新表!W:W) -> #N/A | V57: =IFERROR(7*O57/CZ57,"0") -> 0 | W57: =CZ57/7 -> 0 | X57: =O57+P57+SUM(BN57:BR57) -> 0 | AF57: =SUM(AG57:BR57) -> 0 | BS57: =_xlfn.XLOOKUP(K57,[1]库销表!$F:$F,[1]库销表!$L:$L) -> 0 | BT57: =SUM(BU57:CV57) -> 0 | CW57: =_xlfn.XLOOKUP(K57,[1]库销表!$F:$F,[1]库销表!$IE:$IE) -> 0 | CX57: =_xlfn.XLOOKUP(K57,[1]库销表!$F:$F,[1]库销表!$IF:$IF) -> 0 | CY57: =_xlfn.XLOOKUP(K57,[1]库销表!$F:$F,[1]库销表!$FL:$FL) -> 0 | CZ57: =_xlfn.XLOOKUP(K57,数据更新表!E:E,数据更新表!F:F,0) -> 0 | DA57: 0 | DB57: =_xlfn.XLOOKUP(K57,数据更新表!E:E,数据更新表!G:G) -> #N/A | DC57: =_xlfn.XLOOKUP(L57,数据更新表!Z:Z,数据更新表!AH:AH) -> 0 | DD57: =_xlfn.XLOOKUP(L57,数据更新表!Z:Z,数据更新表!AE:AE) -> 0 | DE57: =_xlfn.XLOOKUP(L57,数据更新表!Z:Z,数据更新表!AF:AF) -> 0 | DF57: =_xlfn.XLOOKUP(K57,数据更新表!Z:Z,数据更新表!AG:AG) -> #N/A | DG57: =_xlfn.XLOOKUP(L57,数据更新表!Z:Z,数据更新表!AD:AD) -> 0 | DH57: =_xlfn.XLOOKUP(L57,数据更新表!Z:Z,数据更新表!AA:AA) -> 0 | DI57: =_xlfn.XLOOKUP(L57,数据更新表!Z:Z,数据更新表!AB:AB) -> 0 | DJ57: =_xlfn.XLOOKUP(L57,数据更新表!Z:Z,数据更新表!AC:AC) -> 0 | DK57: =_xlfn.XLOOKUP(L57,数据更新表!Z:Z,数据更新表!AI:AI) -> 0 | DL57: =_xlfn.XLOOKUP(L57,数据更新表!AL:AL,数据更新表!AM:AM) -> 0 | DM57: =_xlfn.XLOOKUP(L57,数据更新表!Z:Z,数据更新表!AJ:AJ) -> 0 | EE57: =_xlfn.XLOOKUP(L57,数据更新表!J:J,数据更新表!L:L) -> 0 | EF57: =_xlfn.XLOOKUP(L57,数据更新表!J:J,数据更新表!M:M) -> 0 | EG57: 122 | EH57: =EJ57/(EI57+EL57) -> -1.0425789 | EI57: =EG57*$EI$1 -> 318.42 | EJ57: =EE57-EI57-EL57-EO57-EN57-EP57-EQ57 -> -612.1456 | EK57: =EJ57/EE57 -> #DIV/0! | EL57: =EX57*2500*$EI$1 -> 268.7256 | EM57: =IF(EE57>299,"是","否") -> 否 | EN57: =EE57*0.05 -> 0 | EO57: =EE57*0.175 -> 0 | EP57: =IF(EE57<299,IF(EE57<99,25,IF(EE57<=149,30,IF(EE57<=299,37,85))),IF(EE57<=498,_xlfn.XLOOKUP(EW57,运费表!A:A,运费表!C:C,"重量超限",-1),_xlfn.XLOOKUP(EW57,运费表!A:A,运费表!D:D,"重量超限",-1))) -> 25 | EQ57: =EE57*0.105 -> 0 | ER57: =_xlfn.XLOOKUP(K57,[4]目录表!$H:$H,[4]目录表!$X:$X) -> 5.2 | ES57: =_xlfn.XLOOKUP(K57,[4]目录表!$H:$H,[4]目录表!$Y:$Y) -> 52 | ET57: =_xlfn.XLOOKUP(K57,[4]目录表!$H:$H,[4]目录表!$Z:$Z) -> 36 | EU57: =_xlfn.XLOOKUP(K57,[4]目录表!$H:$H,[4]目录表!$AA:$AA) -> 22 | EV57: =ES57*ET57*EU57/5000 -> 8.2368 | EW57: =IF(EV57>=ER57,EV57,ER57) -> 8.2368 | EX57: =_xlfn.XLOOKUP(K57,[2]目录表!$H:$H,[2]目录表!$AB:$AB) -> 0.041184 | EZ57: =CZ57/7 -> 0 | FK57: =_xlfn.XLOOKUP(K57,[2]目录表!$H:$H,[2]目录表!$AJ:$AJ) -> 装柜
B58: Tm-mesa Mayo Con Charola Acero Inoxidable Ajustable Uso Rudo | Envío gratis | C58: 15 | D58: 36 | E58: =_xlfn.XLOOKUP(K58,[3]工业配件!$AA:$AA,[3]工业配件!$L:$L) -> #N/A | G58: 托盘推车 | H58: 单杆托盘-45*35-304 | J58: Tm-mesa Mayo Con Charola Acero Inoxidable Ajustable Uso Rudo | K58: XQ5-YL004 | M58: 未上架 | N58: =_xlfn.XLOOKUP(L58,数据更新表!J:J,数据更新表!K:K) -> 0 | O58: =IFERROR(_xlfn.XLOOKUP(K58,数据更新表!A:A,数据更新表!B:B),"0") -> 0 | P58: =_xlfn.XLOOKUP(K58,[1]库销表!$F:$F,[1]库销表!$L:$L) -> 0 | Q58: =X58/W58 -> #DIV/0! | S58: =_xlfn.XLOOKUP(K58,数据更新表!R:R,数据更新表!S:S) -> #N/A | T58: =_xlfn.XLOOKUP(K58,数据更新表!V:V,数据更新表!W:W) -> #N/A | V58: =IFERROR(7*O58/CZ58,"0") -> 0 | W58: =CZ58/7 -> 0 | X58: =O58+P58+SUM(BN58:BR58) -> 0 | AF58: =SUM(AG58:BR58) -> 0 | BS58: =_xlfn.XLOOKUP(K58,[1]库销表!$F:$F,[1]库销表!$L:$L) -> 0 | BT58: =SUM(BU58:CV58) -> 0 | CW58: =_xlfn.XLOOKUP(K58,[1]库销表!$F:$F,[1]库销表!$IE:$IE) -> 0 | CX58: =_xlfn.XLOOKUP(K58,[1]库销表!$F:$F,[1]库销表!$IF:$IF) -> 0 | CY58: =_xlfn.XLOOKUP(K58,[1]库销表!$F:$F,[1]库销表!$FL:$FL) -> 0 | CZ58: =_xlfn.XLOOKUP(K58,数据更新表!E:E,数据更新表!F:F,0) -> 0 | DA58: 0 | DB58: =_xlfn.XLOOKUP(K58,数据更新表!E:E,数据更新表!G:G) -> #N/A | DC58: =_xlfn.XLOOKUP(L58,数据更新表!Z:Z,数据更新表!AH:AH) -> 0 | DD58: =_xlfn.XLOOKUP(L58,数据更新表!Z:Z,数据更新表!AE:AE) -> 0 | DE58: =_xlfn.XLOOKUP(L58,数据更新表!Z:Z,数据更新表!AF:AF) -> 0 | DF58: =_xlfn.XLOOKUP(K58,数据更新表!Z:Z,数据更新表!AG:AG) -> #N/A | DG58: =_xlfn.XLOOKUP(L58,数据更新表!Z:Z,数据更新表!AD:AD) -> 0 | DH58: =_xlfn.XLOOKUP(L58,数据更新表!Z:Z,数据更新表!AA:AA) -> 0 | DI58: =_xlfn.XLOOKUP(L58,数据更新表!Z:Z,数据更新表!AB:AB) -> 0 | DJ58: =_xlfn.XLOOKUP(L58,数据更新表!Z:Z,数据更新表!AC:AC) -> 0 | DK58: =_xlfn.XLOOKUP(L58,数据更新表!Z:Z,数据更新表!AI:AI) -> 0 | DL58: =_xlfn.XLOOKUP(L58,数据更新表!AL:AL,数据更新表!AM:AM) -> 0 | DM58: =_xlfn.XLOOKUP(L58,数据更新表!Z:Z,数据更新表!AJ:AJ) -> 0 | EE58: =_xlfn.XLOOKUP(L58,数据更新表!J:J,数据更新表!L:L) -> 0 | EF58: =_xlfn.XLOOKUP(L58,数据更新表!J:J,数据更新表!M:M) -> 0 | EG58: 95 | EH58: =EJ58/(EI58+EL58) -> -1.0542409 | EI58: =EG58*$EI$1 -> 247.95 | EJ58: =EE58-EI58-EL58-EO58-EN58-EP58-EQ58 -> -485.90643 | EK58: =EJ58/EE58 -> #DIV/0! | EL58: =EX58*2500*$EI$1 -> 212.95642 | EM58: =IF(EE58>299,"是","否") -> 否 | EN58: =EE58*0.05 -> 0 | EO58: =EE58*0.175 -> 0 | EP58: =IF(EE58<299,IF(EE58<99,25,IF(EE58<=149,30,IF(EE58<=299,37,85))),IF(EE58<=498,_xlfn.XLOOKUP(EW58,运费表!A:A,运费表!C:C,"重量超限",-1),_xlfn.XLOOKUP(EW58,运费表!A:A,运费表!D:D,"重量超限",-1))) -> 25 | EQ58: =EE58*0.105 -> 0 | ER58: =_xlfn.XLOOKUP(K58,[4]目录表!$H:$H,[4]目录表!$X:$X) -> 4.4 | ES58: =_xlfn.XLOOKUP(K58,[4]目录表!$H:$H,[4]目录表!$Y:$Y) -> 43 | ET58: =_xlfn.XLOOKUP(K58,[4]目录表!$H:$H,[4]目录表!$Z:$Z) -> 11 | EU58: =_xlfn.XLOOKUP(K58,[4]目录表!$H:$H,[4]目录表!$AA:$AA) -> 69 | EV58: =ES58*ET58*EU58/5000 -> 6.5274 | EW58: =IF(EV58>=ER58,EV58,ER58) -> 6.5274 | EX58: =_xlfn.XLOOKUP(K58,[2]目录表!$H:$H,[2]目录表!$AB:$AB) -> 0.032637 | EZ58: =CZ58/7 -> 0 | FK58: =_xlfn.XLOOKUP(K58,[2]目录表!$H:$H,[2]目录表!$AJ:$AJ) -> 装柜
B59: Charola Mesa Isla Doble Acero Inoxidable 110x50x85 Cm Color Gris Mindejal | Meses sin interés | C59: 11 | D59: 31 | E59: =_xlfn.XLOOKUP(K59,[3]工业配件!$AA:$AA,[3]工业配件!$L:$L) -> #N/A | G59: 不锈钢操作台 | H59: 三层置物台-110*50*85 | J59: Charola Mesa Isla Doble Acero Inoxidable 110x50x85 Cm Color Gris Mindejal | K59: XQ5-YL007 | M59: 未上架 | N59: =_xlfn.XLOOKUP(L59,数据更新表!J:J,数据更新表!K:K) -> 0 | O59: =IFERROR(_xlfn.XLOOKUP(K59,数据更新表!A:A,数据更新表!B:B),"0") -> 0 | P59: =_xlfn.XLOOKUP(K59,[1]库销表!$F:$F,[1]库销表!$L:$L) -> 0 | Q59: =X59/W59 -> #DIV/0! | S59: =_xlfn.XLOOKUP(K59,数据更新表!R:R,数据更新表!S:S) -> #N/A | T59: =_xlfn.XLOOKUP(K59,数据更新表!V:V,数据更新表!W:W) -> #N/A | V59: =IFERROR(7*O59/CZ59,"0") -> 0 | W59: =CZ59/7 -> 0 | X59: =O59+P59+SUM(BN59:BR59) -> 0 | AF59: =SUM(AG59:BR59) -> 0 | BS59: =_xlfn.XLOOKUP(K59,[1]库销表!$F:$F,[1]库销表!$L:$L) -> 0 | BT59: =SUM(BU59:CV59) -> 0 | CW59: =_xlfn.XLOOKUP(K59,[1]库销表!$F:$F,[1]库销表!$IE:$IE) -> 0 | CX59: =_xlfn.XLOOKUP(K59,[1]库销表!$F:$F,[1]库销表!$IF:$IF) -> 0 | CY59: =_xlfn.XLOOKUP(K59,[1]库销表!$F:$F,[1]库销表!$FL:$FL) -> 0 | CZ59: =_xlfn.XLOOKUP(K59,数据更新表!E:E,数据更新表!F:F,0) -> 0 | DA59: 0 | DB59: =_xlfn.XLOOKUP(K59,数据更新表!E:E,数据更新表!G:G) -> #N/A | DC59: =_xlfn.XLOOKUP(L59,数据更新表!Z:Z,数据更新表!AH:AH) -> 0 | DD59: =_xlfn.XLOOKUP(L59,数据更新表!Z:Z,数据更新表!AE:AE) -> 0 | DE59: =_xlfn.XLOOKUP(L59,数据更新表!Z:Z,数据更新表!AF:AF) -> 0 | DF59: =_xlfn.XLOOKUP(K59,数据更新表!Z:Z,数据更新表!AG:AG) -> #N/A | DG59: =_xlfn.XLOOKUP(L59,数据更新表!Z:Z,数据更新表!AD:AD) -> 0 | DH59: =_xlfn.XLOOKUP(L59,数据更新表!Z:Z,数据更新表!AA:AA) -> 0 | DI59: =_xlfn.XLOOKUP(L59,数据更新表!Z:Z,数据更新表!AB:AB) -> 0 | DJ59: =_xlfn.XLOOKUP(L59,数据更新表!Z:Z,数据更新表!AC:AC) -> 0 | DK59: =_xlfn.XLOOKUP(L59,数据更新表!Z:Z,数据更新表!AI:AI) -> 0 | DL59: =_xlfn.XLOOKUP(L59,数据更新表!AL:AL,数据更新表!AM:AM) -> 0 | DM59: =_xlfn.XLOOKUP(L59,数据更新表!Z:Z,数据更新表!AJ:AJ) -> 0 | EE59: =_xlfn.XLOOKUP(L59,数据更新表!J:J,数据更新表!L:L) -> 0 | EF59: =_xlfn.XLOOKUP(L59,数据更新表!J:J,数据更新表!M:M) -> 0 | EJ59: =EE59-EI59-EL59-EO59-EN59-EP59-EQ59 -> -689.32983 | EL59: =EX59*2500*$EI$1 -> 664.32983 | EO59: =EE59*0.175 -> 0 | EP59: =IF(EE59<299,IF(EE59<99,25,IF(EE59<=149,30,IF(EE59<=299,37,85))),IF(EE59<=498,_xlfn.XLOOKUP(EW59,运费表!A:A,运费表!C:C,"重量超限",-1),_xlfn.XLOOKUP(EW59,运费表!A:A,运费表!D:D,"重量超限",-1))) -> 25 | EQ59: =EE59*0.105 -> 0 | ER59: =_xlfn.XLOOKUP(K59,[4]目录表!$H:$H,[4]目录表!$X:$X) -> 22 | ES59: =_xlfn.XLOOKUP(K59,[4]目录表!$H:$H,[4]目录表!$Y:$Y) -> 113 | ET59: =_xlfn.XLOOKUP(K59,[4]目录表!$H:$H,[4]目录表!$Z:$Z) -> 53 | EU59: =_xlfn.XLOOKUP(K59,[4]目录表!$H:$H,[4]目录表!$AA:$AA) -> 17 | EV59: =ES59*ET59*EU59/5000 -> 20.3626 | EW59: =IF(EV59>=ER59,EV59,ER59) -> 22 | EX59: =_xlfn.XLOOKUP(K59,[2]目录表!$H:$H,[2]目录表!$AB:$AB) -> 0.101813 | EZ59: =CZ59/7 -> 0 | FK59: =_xlfn.XLOOKUP(K59,[2]目录表!$H:$H,[2]目录表!$AJ:$AJ) -> 装柜
B60: Repisa C/soporte Acero Inoxidable Marca Mindejal 1.00 Mts | Meses sin interés | C60: 7 | D60: 13 | E60: =_xlfn.XLOOKUP(K60,[3]工业配件!$AA:$AA,[3]工业配件!$L:$L) -> #N/A | G60: 不锈钢操作台 | H60: 置物墙架-100*30*30 | J60: Repisa C/soporte Acero Inoxidable Marca Mindejal 1.00 Mts | K60: XQ5-YL008 | M60: 未上架 | N60: =_xlfn.XLOOKUP(L60,数据更新表!J:J,数据更新表!K:K) -> 0 | O60: =IFERROR(_xlfn.XLOOKUP(K60,数据更新表!A:A,数据更新表!B:B),"0") -> 0 | P60: =_xlfn.XLOOKUP(K60,[1]库销表!$F:$F,[1]库销表!$L:$L) -> 0 | Q60: =X60/W60 -> #DIV/0! | S60: =_xlfn.XLOOKUP(K60,数据更新表!R:R,数据更新表!S:S) -> #N/A | T60: =_xlfn.XLOOKUP(K60,数据更新表!V:V,数据更新表!W:W) -> #N/A | V60: =IFERROR(7*O60/CZ60,"0") -> 0 | W60: =CZ60/7 -> 0 | X60: =O60+P60+SUM(BN60:BR60) -> 0 | AF60: =SUM(AG60:BR60) -> 0 | BS60: =_xlfn.XLOOKUP(K60,[1]库销表!$F:$F,[1]库销表!$L:$L) -> 0 | BT60: =SUM(BU60:CV60) -> 0 | CW60: =_xlfn.XLOOKUP(K60,[1]库销表!$F:$F,[1]库销表!$IE:$IE) -> 0 | CX60: =_xlfn.XLOOKUP(K60,[1]库销表!$F:$F,[1]库销表!$IF:$IF) -> 0 | CY60: =_xlfn.XLOOKUP(K60,[1]库销表!$F:$F,[1]库销表!$FL:$FL) -> 0 | CZ60: =_xlfn.XLOOKUP(K60,数据更新表!E:E,数据更新表!F:F,0) -> 0 | DA60: 0 | DB60: =_xlfn.XLOOKUP(K60,数据更新表!E:E,数据更新表!G:G) -> #N/A | DC60: =_xlfn.XLOOKUP(L60,数据更新表!Z:Z,数据更新表!AH:AH) -> 0 | DD60: =_xlfn.XLOOKUP(L60,数据更新表!Z:Z,数据更新表!AE:AE) -> 0 | DE60: =_xlfn.XLOOKUP(L60,数据更新表!Z:Z,数据更新表!AF:AF) -> 0 | DF60: =_xlfn.XLOOKUP(K60,数据更新表!Z:Z,数据更新表!AG:AG) -> #N/A | DG60: =_xlfn.XLOOKUP(L60,数据更新表!Z:Z,数据更新表!AD:AD) -> 0 | DH60: =_xlfn.XLOOKUP(L60,数据更新表!Z:Z,数据更新表!AA:AA) -> 0 | DI60: =_xlfn.XLOOKUP(L60,数据更新表!Z:Z,数据更新表!AB:AB) -> 0 | DJ60: =_xlfn.XLOOKUP(L60,数据更新表!Z:Z,数据更新表!AC:AC) -> 0 | DK60: =_xlfn.XLOOKUP(L60,数据更新表!Z:Z,数据更新表!AI:AI) -> 0 | DL60: =_xlfn.XLOOKUP(L60,数据更新表!AL:AL,数据更新表!AM:AM) -> 0 | DM60: =_xlfn.XLOOKUP(L60,数据更新表!Z:Z,数据更新表!AJ:AJ) -> 0 | EE60: =_xlfn.XLOOKUP(L60,数据更新表!J:J,数据更新表!L:L) -> 0 | EF60: =_xlfn.XLOOKUP(L60,数据更新表!J:J,数据更新表!M:M) -> 0 | EJ60: =EE60-EI60-EL60-EO60-EN60-EP60-EQ60 -> -291.1417 | EL60: =EX60*2500*$EI$1 -> 266.1417 | EO60: =EE60*0.175 -> 0 | EP60: =IF(EE60<299,IF(EE60<99,25,IF(EE60<=149,30,IF(EE60<=299,37,85))),IF(EE60<=498,_xlfn.XLOOKUP(EW60,运费表!A:A,运费表!C:C,"重量超限",-1),_xlfn.XLOOKUP(EW60,运费表!A:A,运费表!D:D,"重量超限",-1))) -> 25 | EQ60: =EE60*0.105 -> 0 | ER60: =_xlfn.XLOOKUP(K60,[4]目录表!$H:$H,[4]目录表!$X:$X) -> 6 | ES60: =_xlfn.XLOOKUP(K60,[4]目录表!$H:$H,[4]目录表!$Y:$Y) -> 103 | ET60: =_xlfn.XLOOKUP(K60,[4]目录表!$H:$H,[4]目录表!$Z:$Z) -> 33 | EU60: =_xlfn.XLOOKUP(K60,[4]目录表!$H:$H,[4]目录表!$AA:$AA) -> 12 | EV60: =ES60*ET60*EU60/5000 -> 8.1576 | EW60: =IF(EV60>=ER60,EV60,ER60) -> 8.1576 | EX60: =_xlfn.XLOOKUP(K60,[2]目录表!$H:$H,[2]目录表!$AB:$AB) -> 0.040788 | EZ60: =CZ60/7 -> 0 | FK60: =_xlfn.XLOOKUP(K60,[2]目录表!$H:$H,[2]目录表!$AJ:$AJ) -> 装柜
B61: Mesa A Pared 100% Acero Inoxidable 120x60x90 Marca Ferrinox | Meses sin interés | C61: 11 | D61: 66 | E61: =_xlfn.XLOOKUP(K61,[3]工业配件!$AA:$AA,[3]工业配件!$L:$L) -> #N/A | G61: 不锈钢操作台 | H61: 双层置物台-120*60*90 | J61: Mesa A Pared 100% Acero Inoxidable 120x60x90 Marca Ferrinox | K61: XQ5-YL012 | M61: 未上架 | N61: =_xlfn.XLOOKUP(L61,数据更新表!J:J,数据更新表!K:K) -> 0 | O61: =IFERROR(_xlfn.XLOOKUP(K61,数据更新表!A:A,数据更新表!B:B),"0") -> 0 | P61: =_xlfn.XLOOKUP(K61,[1]库销表!$F:$F,[1]库销表!$L:$L) -> 0 | Q61: =X61/W61 -> #DIV/0! | S61: =_xlfn.XLOOKUP(K61,数据更新表!R:R,数据更新表!S:S) -> #N/A | T61: =_xlfn.XLOOKUP(K61,数据更新表!V:V,数据更新表!W:W) -> #N/A | V61: =IFERROR(7*O61/CZ61,"0") -> 0 | W61: =CZ61/7 -> 0 | X61: =O61+P61+SUM(BN61:BR61) -> 0 | AF61: =SUM(AG61:BR61) -> 0 | BS61: =_xlfn.XLOOKUP(K61,[1]库销表!$F:$F,[1]库销表!$L:$L) -> 0 | BT61: =SUM(BU61:CV61) -> 0 | CW61: =_xlfn.XLOOKUP(K61,[1]库销表!$F:$F,[1]库销表!$IE:$IE) -> 0 | CX61: =_xlfn.XLOOKUP(K61,[1]库销表!$F:$F,[1]库销表!$IF:$IF) -> 0 | CY61: =_xlfn.XLOOKUP(K61,[1]库销表!$F:$F,[1]库销表!$FL:$FL) -> 0 | CZ61: =_xlfn.XLOOKUP(K61,数据更新表!E:E,数据更新表!F:F,0) -> 0 | DA61: 0 | DB61: =_xlfn.XLOOKUP(K61,数据更新表!E:E,数据更新表!G:G) -> #N/A | DC61: =_xlfn.XLOOKUP(L61,数据更新表!Z:Z,数据更新表!AH:AH) -> 0 | DD61: =_xlfn.XLOOKUP(L61,数据更新表!Z:Z,数据更新表!AE:AE) -> 0 | DE61: =_xlfn.XLOOKUP(L61,数据更新表!Z:Z,数据更新表!AF:AF) -> 0 | DF61: =_xlfn.XLOOKUP(K61,数据更新表!Z:Z,数据更新表!AG:AG) -> #N/A | DG61: =_xlfn.XLOOKUP(L61,数据更新表!Z:Z,数据更新表!AD:AD) -> 0 | DH61: =_xlfn.XLOOKUP(L61,数据更新表!Z:Z,数据更新表!AA:AA) -> 0 | DI61: =_xlfn.XLOOKUP(L61,数据更新表!Z:Z,数据更新表!AB:AB) -> 0 | DJ61: =_xlfn.XLOOKUP(L61,数据更新表!Z:Z,数据更新表!AC:AC) -> 0 | DK61: =_xlfn.XLOOKUP(L61,数据更新表!Z:Z,数据更新表!AI:AI) -> 0 | DL61: =_xlfn.XLOOKUP(L61,数据更新表!AL:AL,数据更新表!AM:AM) -> 0 | DM61: =_xlfn.XLOOKUP(L61,数据更新表!Z:Z,数据更新表!AJ:AJ) -> 0 | EE61: =_xlfn.XLOOKUP(L61,数据更新表!J:J,数据更新表!L:L) -> 0 | EF61: =_xlfn.XLOOKUP(L61,数据更新表!J:J,数据更新表!M:M) -> 0 | EJ61: =EE61-EI61-EL61-EO61-EN61-EP61-EQ61 -> -516.1759 | EL61: =EX61*2500*$EI$1 -> 491.1759 | EO61: =EE61*0.175 -> 0 | EP61: =IF(EE61<299,IF(EE61<99,25,IF(EE61<=149,30,IF(EE61<=299,37,85))),IF(EE61<=498,_xlfn.XLOOKUP(EW61,运费表!A:A,运费表!C:C,"重量超限",-1),_xlfn.XLOOKUP(EW61,运费表!A:A,运费表!D:D,"重量超限",-1))) -> 25 | EQ61: =EE61*0.105 -> 0 | ER61: =_xlfn.XLOOKUP(K61,[4]目录表!$H:$H,[4]目录表!$X:$X) -> 23 | ES61: =_xlfn.XLOOKUP(K61,[4]目录表!$H:$H,[4]目录表!$Y:$Y) -> 123 | ET61: =_xlfn.XLOOKUP(K61,[4]目录表!$H:$H,[4]目录表!$Z:$Z) -> 36 | EU61: =_xlfn.XLOOKUP(K61,[4]目录表!$H:$H,[4]目录表!$AA:$AA) -> 17 | EV61: =ES61*ET61*EU61/5000 -> 15.0552 | EW61: =IF(EV61>=ER61,EV61,ER61) -> 23 | EX61: =_xlfn.XLOOKUP(K61,[2]目录表!$H:$H,[2]目录表!$AB:$AB) -> 0.075276 | EZ61: =CZ61/7 -> 0 | FK61: =_xlfn.XLOOKUP(K61,[2]目录表!$H:$H,[2]目录表!$AJ:$AJ) -> 装柜
B62: Mesa Con Repisa 100% Acero Inoxidable Marca Ferrinox | Meses sin interés | C62: 7 | D62: 50 | E62: =_xlfn.XLOOKUP(K62,[3]工业配件!$AA:$AA,[3]工业配件!$L:$L) -> #N/A | G62: 不锈钢操作台 | H62: 三层作业台-110*60*90 | J62: Mesa Con Repisa 100% Acero Inoxidable Marca Ferrinox | K62: XQ5-YL013 | M62: 未上架 | N62: =_xlfn.XLOOKUP(L62,数据更新表!J:J,数据更新表!K:K) -> 0 | O62: =IFERROR(_xlfn.XLOOKUP(K62,数据更新表!A:A,数据更新表!B:B),"0") -> 0 | P62: =_xlfn.XLOOKUP(K62,[1]库销表!$F:$F,[1]库销表!$L:$L) -> 0 | Q62: =X62/W62 -> #DIV/0! | S62: =_xlfn.XLOOKUP(K62,数据更新表!R:R,数据更新表!S:S) -> #N/A | T62: =_xlfn.XLOOKUP(K62,数据更新表!V:V,数据更新表!W:W) -> #N/A | V62: =IFERROR(7*O62/CZ62,"0") -> 0 | W62: =CZ62/7 -> 0 | X62: =O62+P62+SUM(BN62:BR62) -> 0 | AF62: =SUM(AG62:BR62) -> 0 | BS62: =_xlfn.XLOOKUP(K62,[1]库销表!$F:$F,[1]库销表!$L:$L) -> 0 | BT62: =SUM(BU62:CV62) -> 0 | CW62: =_xlfn.XLOOKUP(K62,[1]库销表!$F:$F,[1]库销表!$IE:$IE) -> 0 | CX62: =_xlfn.XLOOKUP(K62,[1]库销表!$F:$F,[1]库销表!$IF:$IF) -> 0 | CY62: =_xlfn.XLOOKUP(K62,[1]库销表!$F:$F,[1]库销表!$FL:$FL) -> 0 | CZ62: =_xlfn.XLOOKUP(K62,数据更新表!E:E,数据更新表!F:F,0) -> 0 | DA62: 0 | DB62: =_xlfn.XLOOKUP(K62,数据更新表!E:E,数据更新表!G:G) -> #N/A | DC62: =_xlfn.XLOOKUP(L62,数据更新表!Z:Z,数据更新表!AH:AH) -> 0 | DD62: =_xlfn.XLOOKUP(L62,数据更新表!Z:Z,数据更新表!AE:AE) -> 0 | DE62: =_xlfn.XLOOKUP(L62,数据更新表!Z:Z,数据更新表!AF:AF) -> 0 | DF62: =_xlfn.XLOOKUP(K62,数据更新表!Z:Z,数据更新表!AG:AG) -> #N/A | DG62: =_xlfn.XLOOKUP(L62,数据更新表!Z:Z,数据更新表!AD:AD) -> 0 | DH62: =_xlfn.XLOOKUP(L62,数据更新表!Z:Z,数据更新表!AA:AA) -> 0 | DI62: =_xlfn.XLOOKUP(L62,数据更新表!Z:Z,数据更新表!AB:AB) -> 0 | DJ62: =_xlfn.XLOOKUP(L62,数据更新表!Z:Z,数据更新表!AC:AC) -> 0 | DK62: =_xlfn.XLOOKUP(L62,数据更新表!Z:Z,数据更新表!AI:AI) -> 0 | DL62: =_xlfn.XLOOKUP(L62,数据更新表!AL:AL,数据更新表!AM:AM) -> 0 | DM62: =_xlfn.XLOOKUP(L62,数据更新表!Z:Z,数据更新表!AJ:AJ) -> 0 | EE62: =_xlfn.XLOOKUP(L62,数据更新表!J:J,数据更新表!L:L) -> 0 | EF62: =_xlfn.XLOOKUP(L62,数据更新表!J:J,数据更新表!M:M) -> 0 | EJ62: =EE62-EI62-EL62-EO62-EN62-EP62-EQ62 -> -814.67507 | EL62: =EX62*2500*$EI$1 -> 789.67507 | EO62: =EE62*0.175 -> 0 | EP62: =IF(EE62<299,IF(EE62<99,25,IF(EE62<=149,30,IF(EE62<=299,37,85))),IF(EE62<=498,_xlfn.XLOOKUP(EW62,运费表!A:A,运费表!C:C,"重量超限",-1),_xlfn.XLOOKUP(EW62,运费表!A:A,运费表!D:D,"重量超限",-1))) -> 25 | EQ62: =EE62*0.105 -> 0 | ER62: =_xlfn.XLOOKUP(K62,[4]目录表!$H:$H,[4]目录表!$X:$X) -> 26 | ES62: =_xlfn.XLOOKUP(K62,[4]目录表!$H:$H,[4]目录表!$Y:$Y) -> 113 | ET62: =_xlfn.XLOOKUP(K62,[4]目录表!$H:$H,[4]目录表!$Z:$Z) -> 63 | EU62: =_xlfn.XLOOKUP(K62,[4]目录表!$H:$H,[4]目录表!$AA:$AA) -> 17 | EV62: =ES62*ET62*EU62/5000 -> 24.2046 | EW62: =IF(EV62>=ER62,EV62,ER62) -> 26 | EX62: =_xlfn.XLOOKUP(K62,[2]目录表!$H:$H,[2]目录表!$AB:$AB) -> 0.121023 | EZ62: =CZ62/7 -> 0 | FK62: =_xlfn.XLOOKUP(K62,[2]目录表!$H:$H,[2]目录表!$AJ:$AJ) -> 装柜
B63: Mesa En Isla Cubierta Acero Inox 90x70x90 Marca Ferrinox | Meses sin interés | C63: 32 | D63: 118 | E63: =_xlfn.XLOOKUP(K63,[3]工业配件!$AA:$AA,[3]工业配件!$L:$L) -> #N/A | G63: 不锈钢操作台 | H63: 双层置物台-90*70*90 | J63: Mesa En Isla Cubierta Acero Inox 90x70x90 Marca Ferrinox | K63: XQ5-YL009 | M63: 未上架 | N63: =_xlfn.XLOOKUP(L63,数据更新表!J:J,数据更新表!K:K) -> 0 | O63: =IFERROR(_xlfn.XLOOKUP(K63,数据更新表!A:A,数据更新表!B:B),"0") -> 0 | P63: =_xlfn.XLOOKUP(K63,[1]库销表!$F:$F,[1]库销表!$L:$L) -> 0 | Q63: =X63/W63 -> #DIV/0! | S63: =_xlfn.XLOOKUP(K63,数据更新表!R:R,数据更新表!S:S) -> #N/A | T63: =_xlfn.XLOOKUP(K63,数据更新表!V:V,数据更新表!W:W) -> #N/A | V63: =IFERROR(7*O63/CZ63,"0") -> 0 | W63: =CZ63/7 -> 0 | X63: =O63+P63+SUM(BN63:BR63) -> 0 | AF63: =SUM(AG63:BR63) -> 0 | BS63: =_xlfn.XLOOKUP(K63,[1]库销表!$F:$F,[1]库销表!$L:$L) -> 0 | BT63: =SUM(BU63:CV63) -> 0 | CW63: =_xlfn.XLOOKUP(K63,[1]库销表!$F:$F,[1]库销表!$IE:$IE) -> 0 | CX63: =_xlfn.XLOOKUP(K63,[1]库销表!$F:$F,[1]库销表!$IF:$IF) -> 0 | CY63: =_xlfn.XLOOKUP(K63,[1]库销表!$F:$F,[1]库销表!$FL:$FL) -> 0 | CZ63: =_xlfn.XLOOKUP(K63,数据更新表!E:E,数据更新表!F:F,0) -> 0 | DA63: 0 | DB63: =_xlfn.XLOOKUP(K63,数据更新表!E:E,数据更新表!G:G) -> #N/A | DC63: =_xlfn.XLOOKUP(L63,数据更新表!Z:Z,数据更新表!AH:AH) -> 0 | DD63: =_xlfn.XLOOKUP(L63,数据更新表!Z:Z,数据更新表!AE:AE) -> 0 | DE63: =_xlfn.XLOOKUP(L63,数据更新表!Z:Z,数据更新表!AF:AF) -> 0 | DF63: =_xlfn.XLOOKUP(K63,数据更新表!Z:Z,数据更新表!AG:AG) -> #N/A | DG63: =_xlfn.XLOOKUP(L63,数据更新表!Z:Z,数据更新表!AD:AD) -> 0 | DH63: =_xlfn.XLOOKUP(L63,数据更新表!Z:Z,数据更新表!AA:AA) -> 0 | DI63: =_xlfn.XLOOKUP(L63,数据更新表!Z:Z,数据更新表!AB:AB) -> 0 | DJ63: =_xlfn.XLOOKUP(L63,数据更新表!Z:Z,数据更新表!AC:AC) -> 0 | DK63: =_xlfn.XLOOKUP(L63,数据更新表!Z:Z,数据更新表!AI:AI) -> 0 | DL63: =_xlfn.XLOOKUP(L63,数据更新表!AL:AL,数据更新表!AM:AM) -> 0 | DM63: =_xlfn.XLOOKUP(L63,数据更新表!Z:Z,数据更新表!AJ:AJ) -> 0 | EE63: =_xlfn.XLOOKUP(L63,数据更新表!J:J,数据更新表!L:L) -> 0 | EF63: =_xlfn.XLOOKUP(L63,数据更新表!J:J,数据更新表!M:M) -> 0 | EJ63: =EE63-EI63-EL63-EO63-EN63-EP63-EQ63 -> -645.17515 | EL63: =EX63*2500*$EI$1 -> 620.17515 | EO63: =EE63*0.175 -> 0 | EP63: =IF(EE63<299,IF(EE63<99,25,IF(EE63<=149,30,IF(EE63<=299,37,85))),IF(EE63<=498,_xlfn.XLOOKUP(EW63,运费表!A:A,运费表!C:C,"重量超限",-1),_xlfn.XLOOKUP(EW63,运费表!A:A,运费表!D:D,"重量超限",-1))) -> 25 | EQ63: =EE63*0.105 -> 0 | ER63: =_xlfn.XLOOKUP(K63,[4]目录表!$H:$H,[4]目录表!$X:$X) -> 19 | ES63: =_xlfn.XLOOKUP(K63,[4]目录表!$H:$H,[4]目录表!$Y:$Y) -> 93 | ET63: =_xlfn.XLOOKUP(K63,[4]目录表!$H:$H,[4]目录表!$Z:$Z) -> 73 | EU63: =_xlfn.XLOOKUP(K63,[4]目录表!$H:$H,[4]目录表!$AA:$AA) -> 14 | EV63: =ES63*ET63*EU63/5000 -> 19.0092 | EW63: =IF(EV63>=ER63,EV63,ER63) -> 19.0092 | EX63: =_xlfn.XLOOKUP(K63,[2]目录表!$H:$H,[2]目录表!$AB:$AB) -> 0.095046 | EZ63: =CZ63/7 -> 0 | FK63: =_xlfn.XLOOKUP(K63,[2]目录表!$H:$H,[2]目录表!$AJ:$AJ) -> 装柜
B64: Mesa Apoyo 100 % Acero Inoxidable 50×50×50 Marca Ferrinox | Meses sin interés | C64: 4 | D64: 14 | E64: =_xlfn.XLOOKUP(K64,[3]工业配件!$AA:$AA,[3]工业配件!$L:$L) -> #N/A | G64: 不锈钢操作台 | H64: 双层置物台-50*50*50 | J64: Mesa Apoyo 100 % Acero Inoxidable 50×50×50 Marca Ferrinox | K64: XQ5-YL010 | M64: 未上架 | N64: =_xlfn.XLOOKUP(L64,数据更新表!J:J,数据更新表!K:K) -> 0 | O64: =IFERROR(_xlfn.XLOOKUP(K64,数据更新表!A:A,数据更新表!B:B),"0") -> 0 | P64: =_xlfn.XLOOKUP(K64,[1]库销表!$F:$F,[1]库销表!$L:$L) -> 0 | Q64: =X64/W64 -> #DIV/0! | S64: =_xlfn.XLOOKUP(K64,数据更新表!R:R,数据更新表!S:S) -> #N/A | T64: =_xlfn.XLOOKUP(K64,数据更新表!V:V,数据更新表!W:W) -> #N/A | V64: =IFERROR(7*O64/CZ64,"0") -> 0 | W64: =CZ64/7 -> 0 | X64: =O64+P64+SUM(BN64:BR64) -> 0 | AF64: =SUM(AG64:BR64) -> 0 | BS64: =_xlfn.XLOOKUP(K64,[1]库销表!$F:$F,[1]库销表!$L:$L) -> 0 | BT64: =SUM(BU64:CV64) -> 0 | CW64: =_xlfn.XLOOKUP(K64,[1]库销表!$F:$F,[1]库销表!$IE:$IE) -> 0 | CX64: =_xlfn.XLOOKUP(K64,[1]库销表!$F:$F,[1]库销表!$IF:$IF) -> 0 | CY64: =_xlfn.XLOOKUP(K64,[1]库销表!$F:$F,[1]库销表!$FL:$FL) -> 0 | CZ64: =_xlfn.XLOOKUP(K64,数据更新表!E:E,数据更新表!F:F,0) -> 0 | DA64: 0 | DB64: =_xlfn.XLOOKUP(K64,数据更新表!E:E,数据更新表!G:G) -> #N/A | DC64: =_xlfn.XLOOKUP(L64,数据更新表!Z:Z,数据更新表!AH:AH) -> 0 | DD64: =_xlfn.XLOOKUP(L64,数据更新表!Z:Z,数据更新表!AE:AE) -> 0 | DE64: =_xlfn.XLOOKUP(L64,数据更新表!Z:Z,数据更新表!AF:AF) -> 0 | DF64: =_xlfn.XLOOKUP(K64,数据更新表!Z:Z,数据更新表!AG:AG) -> #N/A | DG64: =_xlfn.XLOOKUP(L64,数据更新表!Z:Z,数据更新表!AD:AD) -> 0 | DH64: =_xlfn.XLOOKUP(L64,数据更新表!Z:Z,数据更新表!AA:AA) -> 0 | DI64: =_xlfn.XLOOKUP(L64,数据更新表!Z:Z,数据更新表!AB:AB) -> 0 | DJ64: =_xlfn.XLOOKUP(L64,数据更新表!Z:Z,数据更新表!AC:AC) -> 0 | DK64: =_xlfn.XLOOKUP(L64,数据更新表!Z:Z,数据更新表!AI:AI) -> 0 | DL64: =_xlfn.XLOOKUP(L64,数据更新表!AL:AL,数据更新表!AM:AM) -> 0 | DM64: =_xlfn.XLOOKUP(L64,数据更新表!Z:Z,数据更新表!AJ:AJ) -> 0 | EE64: =_xlfn.XLOOKUP(L64,数据更新表!J:J,数据更新表!L:L) -> 0 | EF64: =_xlfn.XLOOKUP(L64,数据更新表!J:J,数据更新表!M:M) -> 0 | EJ64: =EE64-EI64-EL64-EO64-EN64-EP64-EQ64 -> -281.60215 | EL64: =EX64*2500*$EI$1 -> 256.60215 | EO64: =EE64*0.175 -> 0 | EP64: =IF(EE64<299,IF(EE64<99,25,IF(EE64<=149,30,IF(EE64<=299,37,85))),IF(EE64<=498,_xlfn.XLOOKUP(EW64,运费表!A:A,运费表!C:C,"重量超限",-1),_xlfn.XLOOKUP(EW64,运费表!A:A,运费表!D:D,"重量超限",-1))) -> 25 | EQ64: =EE64*0.105 -> 0 | ER64: =_xlfn.XLOOKUP(K64,[4]目录表!$H:$H,[4]目录表!$X:$X) -> 12.5 | ES64: =_xlfn.XLOOKUP(K64,[4]目录表!$H:$H,[4]目录表!$Y:$Y) -> 53 | ET64: =_xlfn.XLOOKUP(K64,[4]目录表!$H:$H,[4]目录表!$Z:$Z) -> 53 | EU64: =_xlfn.XLOOKUP(K64,[4]目录表!$H:$H,[4]目录表!$AA:$AA) -> 14 | EV64: =ES64*ET64*EU64/5000 -> 7.8652 | EW64: =IF(EV64>=ER64,EV64,ER64) -> 12.5 | EX64: =_xlfn.XLOOKUP(K64,[2]目录表!$H:$H,[2]目录表!$AB:$AB) -> 0.039326 | EZ64: =CZ64/7 -> 0 | FK64: =_xlfn.XLOOKUP(K64,[2]目录表!$H:$H,[2]目录表!$AJ:$AJ) -> 装柜
B65: Mesa Isla Doble 100% Acero Inox 60x60x90 Marca Ferrinox | Meses sin interés | C65: 13 | D65: 39 | E65: =_xlfn.XLOOKUP(K65,[3]工业配件!$AA:$AA,[3]工业配件!$L:$L) -> #N/A | G65: 不锈钢操作台 | H65: 三层置物台-60*60*90 | J65: Mesa Isla Doble 100% Acero Inox 60x60x90 Marca Ferrinox | K65: XQ5-YL011 | M65: 未上架 | N65: =_xlfn.XLOOKUP(L65,数据更新表!J:J,数据更新表!K:K) -> 0 | O65: =IFERROR(_xlfn.XLOOKUP(K65,数据更新表!A:A,数据更新表!B:B),"0") -> 0 | P65: =_xlfn.XLOOKUP(K65,[1]库销表!$F:$F,[1]库销表!$L:$L) -> 0 | Q65: =X65/W65 -> #DIV/0! | S65: =_xlfn.XLOOKUP(K65,数据更新表!R:R,数据更新表!S:S) -> #N/A | T65: =_xlfn.XLOOKUP(K65,数据更新表!V:V,数据更新表!W:W) -> #N/A | V65: =IFERROR(7*O65/CZ65,"0") -> 0 | W65: =CZ65/7 -> 0 | X65: =O65+P65+SUM(BN65:BR65) -> 0 | AF65: =SUM(AG65:BR65) -> 0 | BS65: =_xlfn.XLOOKUP(K65,[1]库销表!$F:$F,[1]库销表!$L:$L) -> 0 | BT65: =SUM(BU65:CV65) -> 0 | CW65: =_xlfn.XLOOKUP(K65,[1]库销表!$F:$F,[1]库销表!$IE:$IE) -> 0 | CX65: =_xlfn.XLOOKUP(K65,[1]库销表!$F:$F,[1]库销表!$IF:$IF) -> 0 | CY65: =_xlfn.XLOOKUP(K65,[1]库销表!$F:$F,[1]库销表!$FL:$FL) -> 0 | CZ65: =_xlfn.XLOOKUP(K65,数据更新表!E:E,数据更新表!F:F,0) -> 0 | DA65: 0 | DB65: =_xlfn.XLOOKUP(K65,数据更新表!E:E,数据更新表!G:G) -> #N/A | DC65: =_xlfn.XLOOKUP(L65,数据更新表!Z:Z,数据更新表!AH:AH) -> 0 | DD65: =_xlfn.XLOOKUP(L65,数据更新表!Z:Z,数据更新表!AE:AE) -> 0 | DE65: =_xlfn.XLOOKUP(L65,数据更新表!Z:Z,数据更新表!AF:AF) -> 0 | DF65: =_xlfn.XLOOKUP(K65,数据更新表!Z:Z,数据更新表!AG:AG) -> #N/A | DG65: =_xlfn.XLOOKUP(L65,数据更新表!Z:Z,数据更新表!AD:AD) -> 0 | DH65: =_xlfn.XLOOKUP(L65,数据更新表!Z:Z,数据更新表!AA:AA) -> 0 | DI65: =_xlfn.XLOOKUP(L65,数据更新表!Z:Z,数据更新表!AB:AB) -> 0 | DJ65: =_xlfn.XLOOKUP(L65,数据更新表!Z:Z,数据更新表!AC:AC) -> 0 | DK65: =_xlfn.XLOOKUP(L65,数据更新表!Z:Z,数据更新表!AI:AI) -> 0 | DL65: =_xlfn.XLOOKUP(L65,数据更新表!AL:AL,数据更新表!AM:AM) -> 0 | DM65: =_xlfn.XLOOKUP(L65,数据更新表!Z:Z,数据更新表!AJ:AJ) -> 0 | EE65: =_xlfn.XLOOKUP(L65,数据更新表!J:J,数据更新表!L:L) -> 0 | EF65: =_xlfn.XLOOKUP(L65,数据更新表!J:J,数据更新表!M:M) -> 0 | EJ65: =EE65-EI65-EL65-EO65-EN65-EP65-EQ65 -> -517.05678 | EL65: =EX65*2500*$EI$1 -> 492.05678 | EO65: =EE65*0.175 -> 0 | EP65: =IF(EE65<299,IF(EE65<99,25,IF(EE65<=149,30,IF(EE65<=299,37,85))),IF(EE65<=498,_xlfn.XLOOKUP(EW65,运费表!A:A,运费表!C:C,"重量超限",-1),_xlfn.XLOOKUP(EW65,运费表!A:A,运费表!D:D,"重量超限",-1))) -> 25 | EQ65: =EE65*0.105 -> 0 | ER65: =_xlfn.XLOOKUP(K65,[4]目录表!$H:$H,[4]目录表!$X:$X) -> 18 | ES65: =_xlfn.XLOOKUP(K65,[4]目录表!$H:$H,[4]目录表!$Y:$Y) -> 63 | ET65: =_xlfn.XLOOKUP(K65,[4]目录表!$H:$H,[4]目录表!$Z:$Z) -> 63 | EU65: =_xlfn.XLOOKUP(K65,[4]目录表!$H:$H,[4]目录表!$AA:$AA) -> 19 | EV65: =ES65*ET65*EU65/5000 -> 15.0822 | EW65: =IF(EV65>=ER65,EV65,ER65) -> 18 | EX65: =_xlfn.XLOOKUP(K65,[2]目录表!$H:$H,[2]目录表!$AB:$AB) -> 0.075411 | EZ65: =CZ65/7 -> 0 | FK65: =_xlfn.XLOOKUP(K65,[2]目录表!$H:$H,[2]目录表!$AJ:$AJ) -> 装柜
B66: Mesa Móvil Laboratorio Escuelas Ruedas Giratorias 3 Enchufes | Meses sin interés | C66: 5 | D66: 26 | E66: =_xlfn.XLOOKUP(K66,[3]工业配件!$AA:$AA,[3]工业配件!$L:$L) -> #N/A | G66: 设备推车 | H66: 口扫推车 | J66: Mesa Móvil Laboratorio Escuelas Ruedas Giratorias 3 Enchufes | K66: XQ5-YL001 | M66: 未上架 | N66: =_xlfn.XLOOKUP(L66,数据更新表!J:J,数据更新表!K:K) -> 0 | O66: =IFERROR(_xlfn.XLOOKUP(K66,数据更新表!A:A,数据更新表!B:B),"0") -> 0 | P66: =_xlfn.XLOOKUP(K66,[1]库销表!$F:$F,[1]库销表!$L:$L) -> 0 | Q66: =X66/W66 -> #DIV/0! | S66: =_xlfn.XLOOKUP(K66,数据更新表!R:R,数据更新表!S:S) -> #N/A | T66: =_xlfn.XLOOKUP(K66,数据更新表!V:V,数据更新表!W:W) -> #N/A | V66: =IFERROR(7*O66/CZ66,"0") -> 0 | W66: =CZ66/7 -> 0 | X66: =O66+P66+SUM(BN66:BR66) -> 0 | AF66: =SUM(AG66:BR66) -> 0 | BS66: =_xlfn.XLOOKUP(K66,[1]库销表!$F:$F,[1]库销表!$L:$L) -> 0 | BT66: =SUM(BU66:CV66) -> 0 | CW66: =_xlfn.XLOOKUP(K66,[1]库销表!$F:$F,[1]库销表!$IE:$IE) -> 0 | CX66: =_xlfn.XLOOKUP(K66,[1]库销表!$F:$F,[1]库销表!$IF:$IF) -> 0 | CY66: =_xlfn.XLOOKUP(K66,[1]库销表!$F:$F,[1]库销表!$FL:$FL) -> 0 | CZ66: =_xlfn.XLOOKUP(K66,数据更新表!E:E,数据更新表!F:F,0) -> 0 | DA66: 0 | DB66: =_xlfn.XLOOKUP(K66,数据更新表!E:E,数据更新表!G:G) -> #N/A | DC66: =_xlfn.XLOOKUP(L66,数据更新表!Z:Z,数据更新表!AH:AH) -> 0 | DD66: =_xlfn.XLOOKUP(L66,数据更新表!Z:Z,数据更新表!AE:AE) -> 0 | DE66: =_xlfn.XLOOKUP(L66,数据更新表!Z:Z,数据更新表!AF:AF) -> 0 | DF66: =_xlfn.XLOOKUP(K66,数据更新表!Z:Z,数据更新表!AG:AG) -> #N/A | DG66: =_xlfn.XLOOKUP(L66,数据更新表!Z:Z,数据更新表!AD:AD) -> 0 | DH66: =_xlfn.XLOOKUP(L66,数据更新表!Z:Z,数据更新表!AA:AA) -> 0 | DI66: =_xlfn.XLOOKUP(L66,数据更新表!Z:Z,数据更新表!AB:AB) -> 0 | DJ66: =_xlfn.XLOOKUP(L66,数据更新表!Z:Z,数据更新表!AC:AC) -> 0 | DK66: =_xlfn.XLOOKUP(L66,数据更新表!Z:Z,数据更新表!AI:AI) -> 0 | DL66: =_xlfn.XLOOKUP(L66,数据更新表!AL:AL,数据更新表!AM:AM) -> 0 | DM66: =_xlfn.XLOOKUP(L66,数据更新表!Z:Z,数据更新表!AJ:AJ) -> 0 | EE66: =_xlfn.XLOOKUP(L66,数据更新表!J:J,数据更新表!L:L) -> 0 | EF66: =_xlfn.XLOOKUP(L66,数据更新表!J:J,数据更新表!M:M) -> 0 | EJ66: =EE66-EI66-EL66-EO66-EN66-EP66-EQ66 -> -541.8583 | EL66: =EX66*2500*$EI$1 -> 516.8583 | EO66: =EE66*0.175 -> 0 | EP66: =IF(EE66<299,IF(EE66<99,25,IF(EE66<=149,30,IF(EE66<=299,37,85))),IF(EE66<=498,_xlfn.XLOOKUP(EW66,运费表!A:A,运费表!C:C,"重量超限",-1),_xlfn.XLOOKUP(EW66,运费表!A:A,运费表!D:D,"重量超限",-1))) -> 25 | EQ66: =EE66*0.105 -> 0 | ER66: =_xlfn.XLOOKUP(K66,[4]目录表!$H:$H,[4]目录表!$X:$X) -> 22 | ES66: =_xlfn.XLOOKUP(K66,[4]目录表!$H:$H,[4]目录表!$Y:$Y) -> 80.5 | ET66: =_xlfn.XLOOKUP(K66,[4]目录表!$H:$H,[4]目录表!$Z:$Z) -> 61.5 | EU66: =_xlfn.XLOOKUP(K66,[4]目录表!$H:$H,[4]目录表!$AA:$AA) -> 16 | EV66: =ES66*ET66*EU66/5000 -> 15.8424 | EW66: =IF(EV66>=ER66,EV66,ER66) -> 22 | EX66: =_xlfn.XLOOKUP(K66,[2]目录表!$H:$H,[2]目录表!$AB:$AB) -> 0.079212 | EZ66: =CZ66/7 -> 0 | FK66: =_xlfn.XLOOKUP(K66,[2]目录表!$H:$H,[2]目录表!$AJ:$AJ) -> 装柜
B67: Maniquí Para Capacitación De Rcp | Meses sin interés | C67: 4 | D67: 34 | E67: =_xlfn.XLOOKUP(K67,[3]工业配件!$AA:$AA,[3]工业配件!$L:$L) -> #N/A | G67: 假人模型 | H67: 半身模拟人 | J67: Maniquí Para Capacitación De Rcp | K67: XQ5-YL002 | M67: 未上架 | N67: =_xlfn.XLOOKUP(L67,数据更新表!J:J,数据更新表!K:K) -> 0 | O67: =IFERROR(_xlfn.XLOOKUP(K67,数据更新表!A:A,数据更新表!B:B),"0") -> 0 | P67: =_xlfn.XLOOKUP(K67,[1]库销表!$F:$F,[1]库销表!$L:$L) -> 0 | Q67: =X67/W67 -> #DIV/0! | S67: =_xlfn.XLOOKUP(K67,数据更新表!R:R,数据更新表!S:S) -> #N/A | T67: =_xlfn.XLOOKUP(K67,数据更新表!V:V,数据更新表!W:W) -> #N/A | V67: =IFERROR(7*O67/CZ67,"0") -> 0 | W67: =CZ67/7 -> 0 | X67: =O67+P67+SUM(BN67:BR67) -> 0 | AF67: =SUM(AG67:BR67) -> 0 | BS67: =_xlfn.XLOOKUP(K67,[1]库销表!$F:$F,[1]库销表!$L:$L) -> 0 | BT67: =SUM(BU67:CV67) -> 0 | CW67: =_xlfn.XLOOKUP(K67,[1]库销表!$F:$F,[1]库销表!$IE:$IE) -> 0 | CX67: =_xlfn.XLOOKUP(K67,[1]库销表!$F:$F,[1]库销表!$IF:$IF) -> 0 | CY67: =_xlfn.XLOOKUP(K67,[1]库销表!$F:$F,[1]库销表!$FL:$FL) -> 0 | CZ67: =_xlfn.XLOOKUP(K67,数据更新表!E:E,数据更新表!F:F,0) -> 0 | DA67: 0 | DB67: =_xlfn.XLOOKUP(K67,数据更新表!E:E,数据更新表!G:G) -> #N/A | DC67: =_xlfn.XLOOKUP(L67,数据更新表!Z:Z,数据更新表!AH:AH) -> 0 | DD67: =_xlfn.XLOOKUP(L67,数据更新表!Z:Z,数据更新表!AE:AE) -> 0 | DE67: =_xlfn.XLOOKUP(L67,数据更新表!Z:Z,数据更新表!AF:AF) -> 0 | DF67: =_xlfn.XLOOKUP(K67,数据更新表!Z:Z,数据更新表!AG:AG) -> #N/A | DG67: =_xlfn.XLOOKUP(L67,数据更新表!Z:Z,数据更新表!AD:AD) -> 0 | DH67: =_xlfn.XLOOKUP(L67,数据更新表!Z:Z,数据更新表!AA:AA) -> 0 | DI67: =_xlfn.XLOOKUP(L67,数据更新表!Z:Z,数据更新表!AB:AB) -> 0 | DJ67: =_xlfn.XLOOKUP(L67,数据更新表!Z:Z,数据更新表!AC:AC) -> 0 | DK67: =_xlfn.XLOOKUP(L67,数据更新表!Z:Z,数据更新表!AI:AI) -> 0 | DL67: =_xlfn.XLOOKUP(L67,数据更新表!AL:AL,数据更新表!AM:AM) -> 0 | DM67: =_xlfn.XLOOKUP(L67,数据更新表!Z:Z,数据更新表!AJ:AJ) -> 0 | EE67: =_xlfn.XLOOKUP(L67,数据更新表!J:J,数据更新表!L:L) -> 0 | EF67: =_xlfn.XLOOKUP(L67,数据更新表!J:J,数据更新表!M:M) -> 0 | EJ67: =EE67-EI67-EL67-EO67-EN67-EP67-EQ67 -> -476.9476 | EL67: =EX67*2500*$EI$1 -> 451.9476 | EO67: =EE67*0.175 -> 0 | EP67: =IF(EE67<299,IF(EE67<99,25,IF(EE67<=149,30,IF(EE67<=299,37,85))),IF(EE67<=498,_xlfn.XLOOKUP(EW67,运费表!A:A,运费表!C:C,"重量超限",-1),_xlfn.XLOOKUP(EW67,运费表!A:A,运费表!D:D,"重量超限",-1))) -> 25 | EQ67: =EE67*0.105 -> 0 | ER67: =_xlfn.XLOOKUP(K67,[4]目录表!$H:$H,[4]目录表!$X:$X) -> 6.7 | ES67: =_xlfn.XLOOKUP(K67,[4]目录表!$H:$H,[4]目录表!$Y:$Y) -> 74 | ET67: =_xlfn.XLOOKUP(K67,[4]目录表!$H:$H,[4]目录表!$Z:$Z) -> 26 | EU67: =_xlfn.XLOOKUP(K67,[4]目录表!$H:$H,[4]目录表!$AA:$AA) -> 36 | EV67: =ES67*ET67*EU67/5000 -> 13.8528 | EW67: =IF(EV67>=ER67,EV67,ER67) -> 13.8528 | EX67: =_xlfn.XLOOKUP(K67,[2]目录表!$H:$H,[2]目录表!$AB:$AB) -> 0.069264 | EZ67: =CZ67/7 -> 0 | FK67: =_xlfn.XLOOKUP(K67,[2]目录表!$H:$H,[2]目录表!$AJ:$AJ) -> 装柜
B68: Repisa Con Garabato 100 Cm Color Gris | Meses sin interés | C68: 3 | D68: 31 | E68: =_xlfn.XLOOKUP(K68,[3]工业配件!$AA:$AA,[3]工业配件!$L:$L) -> #N/A | G68: 不锈钢操作台 | H68: 挂钩墙架-100*30*30 | J68: Repisa Con Garabato 100 Cm Color Gris | K68: XQ5-YL022 | M68: 未上架 | N68: =_xlfn.XLOOKUP(L68,数据更新表!J:J,数据更新表!K:K) -> 0 | O68: =IFERROR(_xlfn.XLOOKUP(K68,数据更新表!A:A,数据更新表!B:B),"0") -> 0 | P68: =_xlfn.XLOOKUP(K68,[1]库销表!$F:$F,[1]库销表!$L:$L) -> 0 | Q68: =X68/W68 -> #DIV/0! | S68: =_xlfn.XLOOKUP(K68,数据更新表!R:R,数据更新表!S:S) -> #N/A | T68: =_xlfn.XLOOKUP(K68,数据更新表!V:V,数据更新表!W:W) -> #N/A | V68: =IFERROR(7*O68/CZ68,"0") -> 0 | W68: =CZ68/7 -> 0 | X68: =O68+P68+SUM(BN68:BR68) -> 0 | AF68: =SUM(AG68:BR68) -> 0 | BS68: =_xlfn.XLOOKUP(K68,[1]库销表!$F:$F,[1]库销表!$L:$L) -> 0 | BT68: =SUM(BU68:CV68) -> 0 | CW68: =_xlfn.XLOOKUP(K68,[1]库销表!$F:$F,[1]库销表!$IE:$IE) -> 0 | CX68: =_xlfn.XLOOKUP(K68,[1]库销表!$F:$F,[1]库销表!$IF:$IF) -> 0 | CY68: =_xlfn.XLOOKUP(K68,[1]库销表!$F:$F,[1]库销表!$FL:$FL) -> 0 | CZ68: =_xlfn.XLOOKUP(K68,数据更新表!E:E,数据更新表!F:F,0) -> 0 | DA68: 0 | DB68: =_xlfn.XLOOKUP(K68,数据更新表!E:E,数据更新表!G:G) -> #N/A | DC68: =_xlfn.XLOOKUP(L68,数据更新表!Z:Z,数据更新表!AH:AH) -> 0 | DD68: =_xlfn.XLOOKUP(L68,数据更新表!Z:Z,数据更新表!AE:AE) -> 0 | DE68: =_xlfn.XLOOKUP(L68,数据更新表!Z:Z,数据更新表!AF:AF) -> 0 | DF68: =_xlfn.XLOOKUP(K68,数据更新表!Z:Z,数据更新表!AG:AG) -> #N/A | DG68: =_xlfn.XLOOKUP(L68,数据更新表!Z:Z,数据更新表!AD:AD) -> 0 | DH68: =_xlfn.XLOOKUP(L68,数据更新表!Z:Z,数据更新表!AA:AA) -> 0 | DI68: =_xlfn.XLOOKUP(L68,数据更新表!Z:Z,数据更新表!AB:AB) -> 0 | DJ68: =_xlfn.XLOOKUP(L68,数据更新表!Z:Z,数据更新表!AC:AC) -> 0 | DK68: =_xlfn.XLOOKUP(L68,数据更新表!Z:Z,数据更新表!AI:AI) -> 0 | DL68: =_xlfn.XLOOKUP(L68,数据更新表!AL:AL,数据更新表!AM:AM) -> 0 | DM68: =_xlfn.XLOOKUP(L68,数据更新表!Z:Z,数据更新表!AJ:AJ) -> 0 | EE68: =_xlfn.XLOOKUP(L68,数据更新表!J:J,数据更新表!L:L) -> 0 | EF68: =_xlfn.XLOOKUP(L68,数据更新表!J:J,数据更新表!M:M) -> 0 | EJ68: =EE68-EI68-EL68-EO68-EN68-EP68-EQ68 -> -291.1417 | EL68: =EX68*2500*$EI$1 -> 266.1417 | EO68: =EE68*0.175 -> 0 | EP68: =IF(EE68<299,IF(EE68<99,25,IF(EE68<=149,30,IF(EE68<=299,37,85))),IF(EE68<=498,_xlfn.XLOOKUP(EW68,运费表!A:A,运费表!C:C,"重量超限",-1),_xlfn.XLOOKUP(EW68,运费表!A:A,运费表!D:D,"重量超限",-1))) -> 25 | EQ68: =EE68*0.105 -> 0 | ER68: =_xlfn.XLOOKUP(K68,[4]目录表!$H:$H,[4]目录表!$X:$X) -> 7 | ES68: =_xlfn.XLOOKUP(K68,[4]目录表!$H:$H,[4]目录表!$Y:$Y) -> 103 | ET68: =_xlfn.XLOOKUP(K68,[4]目录表!$H:$H,[4]目录表!$Z:$Z) -> 33 | EU68: =_xlfn.XLOOKUP(K68,[4]目录表!$H:$H,[4]目录表!$AA:$AA) -> 12 | EV68: =ES68*ET68*EU68/5000 -> 8.1576 | EW68: =IF(EV68>=ER68,EV68,ER68) -> 8.1576 | EX68: =_xlfn.XLOOKUP(K68,[2]目录表!$H:$H,[2]目录表!$AB:$AB) -> 0.040788 | EZ68: =CZ68/7 -> 0 | FK68: =_xlfn.XLOOKUP(K68,[2]目录表!$H:$H,[2]目录表!$AJ:$AJ) -> 装柜
B69: 50plato Base,plato Base Dorado,para Vento,decoración De Mesa Dorado Oscuro Lisa | Envío gratis | C69: 7 | D69: 62 | E69: =_xlfn.XLOOKUP(K69,[3]工业配件!$AA:$AA,[3]工业配件!$L:$L) -> #N/A | G69: 餐具托盘 | H69: 餐具托盘-50件套 | J69: 50plato Base,plato Base Dorado,para Vento,decoración De Mesa Dorado Oscuro Lisa | K69: XQ5-YL023 | M69: 未上架 | N69: =_xlfn.XLOOKUP(L69,数据更新表!J:J,数据更新表!K:K) -> 0 | O69: =IFERROR(_xlfn.XLOOKUP(K69,数据更新表!A:A,数据更新表!B:B),"0") -> 0 | P69: =_xlfn.XLOOKUP(K69,[1]库销表!$F:$F,[1]库销表!$L:$L) -> 0 | Q69: =X69/W69 -> #DIV/0! | S69: =_xlfn.XLOOKUP(K69,数据更新表!R:R,数据更新表!S:S) -> #N/A | T69: =_xlfn.XLOOKUP(K69,数据更新表!V:V,数据更新表!W:W) -> #N/A | V69: =IFERROR(7*O69/CZ69,"0") -> 0 | W69: =CZ69/7 -> 0 | X69: =O69+P69+SUM(BN69:BR69) -> 0 | AF69: =SUM(AG69:BR69) -> 0 | BS69: =_xlfn.XLOOKUP(K69,[1]库销表!$F:$F,[1]库销表!$L:$L) -> 0 | BT69: =SUM(BU69:CV69) -> 0 | CW69: =_xlfn.XLOOKUP(K69,[1]库销表!$F:$F,[1]库销表!$IE:$IE) -> 0 | CX69: =_xlfn.XLOOKUP(K69,[1]库销表!$F:$F,[1]库销表!$IF:$IF) -> 0 | CY69: =_xlfn.XLOOKUP(K69,[1]库销表!$F:$F,[1]库销表!$FL:$FL) -> 0 | CZ69: =_xlfn.XLOOKUP(K69,数据更新表!E:E,数据更新表!F:F,0) -> 0 | DA69: 0 | DB69: =_xlfn.XLOOKUP(K69,数据更新表!E:E,数据更新表!G:G) -> #N/A | DC69: =_xlfn.XLOOKUP(L69,数据更新表!Z:Z,数据更新表!AH:AH) -> 0 | DD69: =_xlfn.XLOOKUP(L69,数据更新表!Z:Z,数据更新表!AE:AE) -> 0 | DE69: =_xlfn.XLOOKUP(L69,数据更新表!Z:Z,数据更新表!AF:AF) -> 0 | DF69: =_xlfn.XLOOKUP(K69,数据更新表!Z:Z,数据更新表!AG:AG) -> #N/A | DG69: =_xlfn.XLOOKUP(L69,数据更新表!Z:Z,数据更新表!AD:AD) -> 0 | DH69: =_xlfn.XLOOKUP(L69,数据更新表!Z:Z,数据更新表!AA:AA) -> 0 | DI69: =_xlfn.XLOOKUP(L69,数据更新表!Z:Z,数据更新表!AB:AB) -> 0 | DJ69: =_xlfn.XLOOKUP(L69,数据更新表!Z:Z,数据更新表!AC:AC) -> 0 | DK69: =_xlfn.XLOOKUP(L69,数据更新表!Z:Z,数据更新表!AI:AI) -> 0 | DL69: =_xlfn.XLOOKUP(L69,数据更新表!AL:AL,数据更新表!AM:AM) -> 0 | DM69: =_xlfn.XLOOKUP(L69,数据更新表!Z:Z,数据更新表!AJ:AJ) -> 0 | EE69: 2600 | EG69: 223.2 | EH69: =EJ69/(EI69+EL69) -> 0.63516433 | EI69: =EG69*$EI$1 -> 582.552 | EJ69: =EE69-EI69-EL69-EO69-EN69-EP69-EQ69 -> 590.2356 | EK69: =EJ69/EE69 -> 0.22701369 | EL69: =EX69*2500*$EI$1 -> 346.7124 | EM69: =IF(EE69>299,"是","否") -> 是 | EN69: =EE69*0.05 -> 130 | EO69: =EE69*0.175 -> 455 | EP69: =IF(EE69<299,IF(EE69<99,25,IF(EE69<=149,30,IF(EE69<=299,37,85))),IF(EE69<=498,_xlfn.XLOOKUP(EW69,运费表!A:A,运费表!C:C,"重量超限",-1),_xlfn.XLOOKUP(EW69,运费表!A:A,运费表!D:D,"重量超限",-1))) -> 222.5 | EQ69: =EE69*0.105 -> 273 | ER69: =_xlfn.XLOOKUP(K69,[4]目录表!$H:$H,[4]目录表!$X:$X) -> 16.5 | ES69: =_xlfn.XLOOKUP(K69,[4]目录表!$H:$H,[4]目录表!$Y:$Y) -> 41 | ET69: =_xlfn.XLOOKUP(K69,[4]目录表!$H:$H,[4]目录表!$Z:$Z) -> 36 | EU69: =_xlfn.XLOOKUP(K69,[4]目录表!$H:$H,[4]目录表!$AA:$AA) -> 36 | EV69: =ES69*ET69*EU69/5000 -> 10.6272 | EW69: =IF(EV69>=ER69,EV69,ER69) -> 16.5 | EX69: =_xlfn.XLOOKUP(K69,[2]目录表!$H:$H,[2]目录表!$AB:$AB) -> 0.053136 | EZ69: =CZ69/7 -> 0 | FK69: =_xlfn.XLOOKUP(K69,[2]目录表!$H:$H,[2]目录表!$AJ:$AJ) -> 装柜
B70: https://articulo.mercadolibre.com.mx/MLM-4244427330-porta-suero-con-base-de-acero-inoxidable-4-ganchos-ajustable-_JM#polycard_client=search_best-seller&tracking_id=9d1b34c6-9202-4e3e-bc85-8f191599ab49 | C70: 15 | D70: 89 | E70: =_xlfn.XLOOKUP(K70,[3]工业配件!$AA:$AA,[3]工业配件!$L:$L) -> #N/A | G70: 医疗架 | H70: 三脚输液架-带轮 | J70: Porta Suero Con Base De Acero Inoxidable 4 Ganchos Ajustable | K70: XQ5-YL024 | M70: 未上架 | N70: =_xlfn.XLOOKUP(L70,数据更新表!J:J,数据更新表!K:K) -> 0 | O70: =IFERROR(_xlfn.XLOOKUP(K70,数据更新表!A:A,数据更新表!B:B),"0") -> 0 | P70: =_xlfn.XLOOKUP(K70,[1]库销表!$F:$F,[1]库销表!$L:$L) -> 0 | Q70: =X70/W70 -> #DIV/0! | S70: =_xlfn.XLOOKUP(K70,数据更新表!R:R,数据更新表!S:S) -> #N/A | T70: =_xlfn.XLOOKUP(K70,数据更新表!V:V,数据更新表!W:W) -> #N/A | V70: =IFERROR(7*O70/CZ70,"0") -> 0 | W70: =CZ70/7 -> 0 | X70: =O70+P70+SUM(BN70:BR70) -> 0 | AF70: =SUM(AG70:BR70) -> 0 | BS70: =_xlfn.XLOOKUP(K70,[1]库销表!$F:$F,[1]库销表!$L:$L) -> 0 | BT70: =SUM(BU70:CV70) -> 0 | CW70: =_xlfn.XLOOKUP(K70,[1]库销表!$F:$F,[1]库销表!$IE:$IE) -> 0 | CX70: =_xlfn.XLOOKUP(K70,[1]库销表!$F:$F,[1]库销表!$IF:$IF) -> 0 | CY70: =_xlfn.XLOOKUP(K70,[1]库销表!$F:$F,[1]库销表!$FL:$FL) -> 0 | CZ70: =_xlfn.XLOOKUP(K70,数据更新表!E:E,数据更新表!F:F,0) -> 0 | DA70: 0 | DB70: =_xlfn.XLOOKUP(K70,数据更新表!E:E,数据更新表!G:G) -> #N/A | DC70: =_xlfn.XLOOKUP(L70,数据更新表!Z:Z,数据更新表!AH:AH) -> 0 | DD70: =_xlfn.XLOOKUP(L70,数据更新表!Z:Z,数据更新表!AE:AE) -> 0 | DE70: =_xlfn.XLOOKUP(L70,数据更新表!Z:Z,数据更新表!AF:AF) -> 0 | DF70: =_xlfn.XLOOKUP(K70,数据更新表!Z:Z,数据更新表!AG:AG) -> #N/A | DG70: =_xlfn.XLOOKUP(L70,数据更新表!Z:Z,数据更新表!AD:AD) -> 0 | DH70: =_xlfn.XLOOKUP(L70,数据更新表!Z:Z,数据更新表!AA:AA) -> 0 | DI70: =_xlfn.XLOOKUP(L70,数据更新表!Z:Z,数据更新表!AB:AB) -> 0 | DJ70: =_xlfn.XLOOKUP(L70,数据更新表!Z:Z,数据更新表!AC:AC) -> 0 | DK70: =_xlfn.XLOOKUP(L70,数据更新表!Z:Z,数据更新表!AI:AI) -> 0 | DL70: =_xlfn.XLOOKUP(L70,数据更新表!AL:AL,数据更新表!AM:AM) -> 0 | DM70: =_xlfn.XLOOKUP(L70,数据更新表!Z:Z,数据更新表!AJ:AJ) -> 0 | EE70: 550 | EG70: 33 | EH70: =EJ70/(EI70+EL70) -> 0.68607035 | EI70: =EG70*$EI$1 -> 86.13 | EJ70: =EE70-EI70-EL70-EO70-EN70-EP70-EQ70 -> 111.2885 | EK70: =EJ70/EE70 -> 0.20234273 | EL70: =EX70*2500*$EI$1 -> 76.0815 | EM70: =IF(EE70>299,"是","否") -> 是 | EN70: =EE70*0.05 -> 27.5 | EO70: =EE70*0.175 -> 96.25 | EP70: =IF(EE70<299,IF(EE70<99,25,IF(EE70<=149,30,IF(EE70<=299,37,85))),IF(EE70<=498,_xlfn.XLOOKUP(EW70,运费表!A:A,运费表!C:C,"重量超限",-1),_xlfn.XLOOKUP(EW70,运费表!A:A,运费表!D:D,"重量超限",-1))) -> 95 | EQ70: =EE70*0.105 -> 57.75 | ER70: =_xlfn.XLOOKUP(K70,[4]目录表!$H:$H,[4]目录表!$X:$X) -> 2.2 | ES70: =_xlfn.XLOOKUP(K70,[4]目录表!$H:$H,[4]目录表!$Y:$Y) -> 106 | ET70: =_xlfn.XLOOKUP(K70,[4]目录表!$H:$H,[4]目录表!$Z:$Z) -> 10 | EU70: =_xlfn.XLOOKUP(K70,[4]目录表!$H:$H,[4]目录表!$AA:$AA) -> 11 | EV70: =ES70*ET70*EU70/5000 -> 2.332 | EW70: =IF(EV70>=ER70,EV70,ER70) -> 2.332 | EX70: =_xlfn.XLOOKUP(K70,[2]目录表!$H:$H,[2]目录表!$AB:$AB) -> 0.01166 | EZ70: =CZ70/7 -> 0 | FK70: =_xlfn.XLOOKUP(K70,[2]目录表!$H:$H,[2]目录表!$AJ:$AJ) -> 装柜
B71: https://www.mercadolibre.com.mx/porta-suero-tripie-base-de-metalica-4-ganchos-ajustable/up/MLMU3439512412#polycard_client=search_best-seller&tracking_id=9d1b34c6-9202-4e3e-bc85-8f191599ab49&wid=MLM4111535692&sid=search | C71: 37 | D71: 214 | E71: =_xlfn.XLOOKUP(K71,[3]工业配件!$AA:$AA,[3]工业配件!$L:$L) -> #N/A | G71: 医疗架 | H71: 三脚输液架-固定折叠 | J71: Porta Suero Tripie Base De Metálica 4 Ganchos Ajustable | K71: XQ5-YL025 | M71: 未上架 | N71: =_xlfn.XLOOKUP(L71,数据更新表!J:J,数据更新表!K:K) -> 0 | O71: =IFERROR(_xlfn.XLOOKUP(K71,数据更新表!A:A,数据更新表!B:B),"0") -> 0 | P71: =_xlfn.XLOOKUP(K71,[1]库销表!$F:$F,[1]库销表!$L:$L) -> 0 | Q71: =X71/W71 -> #DIV/0! | S71: =_xlfn.XLOOKUP(K71,数据更新表!R:R,数据更新表!S:S) -> #N/A | T71: =_xlfn.XLOOKUP(K71,数据更新表!V:V,数据更新表!W:W) -> #N/A | V71: =IFERROR(7*O71/CZ71,"0") -> 0 | W71: =CZ71/7 -> 0 | X71: =O71+P71+SUM(BN71:BR71) -> 0 | AF71: =SUM(AG71:BR71) -> 0 | BS71: =_xlfn.XLOOKUP(K71,[1]库销表!$F:$F,[1]库销表!$L:$L) -> 0 | BT71: =SUM(BU71:CV71) -> 0 | CW71: =_xlfn.XLOOKUP(K71,[1]库销表!$F:$F,[1]库销表!$IE:$IE) -> 0 | CX71: =_xlfn.XLOOKUP(K71,[1]库销表!$F:$F,[1]库销表!$IF:$IF) -> 0 | CY71: =_xlfn.XLOOKUP(K71,[1]库销表!$F:$F,[1]库销表!$FL:$FL) -> 0 | CZ71: =_xlfn.XLOOKUP(K71,数据更新表!E:E,数据更新表!F:F,0) -> 0 | DA71: 0 | DB71: =_xlfn.XLOOKUP(K71,数据更新表!E:E,数据更新表!G:G) -> #N/A | DC71: =_xlfn.XLOOKUP(L71,数据更新表!Z:Z,数据更新表!AH:AH) -> 0 | DD71: =_xlfn.XLOOKUP(L71,数据更新表!Z:Z,数据更新表!AE:AE) -> 0 | DE71: =_xlfn.XLOOKUP(L71,数据更新表!Z:Z,数据更新表!AF:AF) -> 0 | DF71: =_xlfn.XLOOKUP(K71,数据更新表!Z:Z,数据更新表!AG:AG) -> #N/A | DG71: =_xlfn.XLOOKUP(L71,数据更新表!Z:Z,数据更新表!AD:AD) -> 0 | DH71: =_xlfn.XLOOKUP(L71,数据更新表!Z:Z,数据更新表!AA:AA) -> 0 | DI71: =_xlfn.XLOOKUP(L71,数据更新表!Z:Z,数据更新表!AB:AB) -> 0 | DJ71: =_xlfn.XLOOKUP(L71,数据更新表!Z:Z,数据更新表!AC:AC) -> 0 | DK71: =_xlfn.XLOOKUP(L71,数据更新表!Z:Z,数据更新表!AI:AI) -> 0 | DL71: =_xlfn.XLOOKUP(L71,数据更新表!AL:AL,数据更新表!AM:AM) -> 0 | DM71: =_xlfn.XLOOKUP(L71,数据更新表!Z:Z,数据更新表!AJ:AJ) -> 0 | EE71: 250 | EG71: 20.5 | EH71: =EJ71/(EI71+EL71) -> 0.67042512 | EI71: =EG71*$EI$1 -> 53.505 | EJ71: =EE71-EI71-EL71-EO71-EN71-EP71-EQ71 -> 52.376175 | EK71: =EJ71/EE71 -> 0.2095047 | EL71: =EX71*2500*$EI$1 -> 24.618825 | EM71: =IF(EE71>299,"是","否") -> 否 | EN71: =EE71*0.05 -> 12.5 | EO71: =EE71*0.175 -> 43.75 | EP71: =IF(EE71<299,IF(EE71<99,25,IF(EE71<=149,30,IF(EE71<=299,37,85))),IF(EE71<=498,_xlfn.XLOOKUP(EW71,运费表!A:A,运费表!C:C,"重量超限",-1),_xlfn.XLOOKUP(EW71,运费表!A:A,运费表!D:D,"重量超限",-1))) -> 37 | EQ71: =EE71*0.105 -> 26.25 | ER71: =_xlfn.XLOOKUP(K71,[4]目录表!$H:$H,[4]目录表!$X:$X) -> 3 | ES71: =_xlfn.XLOOKUP(K71,[4]目录表!$H:$H,[4]目录表!$Y:$Y) -> 77 | ET71: =_xlfn.XLOOKUP(K71,[4]目录表!$H:$H,[4]目录表!$Z:$Z) -> 7 | EU71: =_xlfn.XLOOKUP(K71,[4]目录表!$H:$H,[4]目录表!$AA:$AA) -> 7 | EV71: =ES71*ET71*EU71/5000 -> 0.7546 | EW71: =IF(EV71>=ER71,EV71,ER71) -> 3 | EX71: =_xlfn.XLOOKUP(K71,[2]目录表!$H:$H,[2]目录表!$AB:$AB) -> 0.003773 | EZ71: =CZ71/7 -> 0 | FK71: =_xlfn.XLOOKUP(K71,[2]目录表!$H:$H,[2]目录表!$AJ:$AJ) -> 装柜
B72: Toldo Techo Para Puerta Ventana De Policarbonato 120 X 80cm | Envío gratis (mercadolibre.com.mx) | C72: 19 | D72: 51 | E72: =_xlfn.XLOOKUP(K72,[3]工业配件!$AA:$AA,[3]工业配件!$L:$L) -> #N/A | G72: 雨棚 | H72: 塑钢雨棚-白色120*80 | J72: Toldo Techo Para Puerta Ventana De Policarbonato 120 X 80cm | K72: XQ5-YL026 | M72: 未上架 | N72: =_xlfn.XLOOKUP(L72,数据更新表!J:J,数据更新表!K:K) -> 0 | O72: =IFERROR(_xlfn.XLOOKUP(K72,数据更新表!A:A,数据更新表!B:B),"0") -> 0 | P72: =_xlfn.XLOOKUP(K72,[1]库销表!$F:$F,[1]库销表!$L:$L) -> 0 | Q72: =X72/W72 -> #DIV/0! | S72: =_xlfn.XLOOKUP(K72,数据更新表!R:R,数据更新表!S:S) -> #N/A | T72: =_xlfn.XLOOKUP(K72,数据更新表!V:V,数据更新表!W:W) -> #N/A | V72: =IFERROR(7*O72/CZ72,"0") -> 0 | W72: =CZ72/7 -> 0 | X72: =O72+P72+SUM(BN72:BR72) -> 0 | AF72: =SUM(AG72:BR72) -> 0 | BS72: =_xlfn.XLOOKUP(K72,[1]库销表!$F:$F,[1]库销表!$L:$L) -> 0 | BT72: =SUM(BU72:CV72) -> 0 | CW72: =_xlfn.XLOOKUP(K72,[1]库销表!$F:$F,[1]库销表!$IE:$IE) -> 0 | CX72: =_xlfn.XLOOKUP(K72,[1]库销表!$F:$F,[1]库销表!$IF:$IF) -> 0 | CY72: =_xlfn.XLOOKUP(K72,[1]库销表!$F:$F,[1]库销表!$FL:$FL) -> 0 | CZ72: =_xlfn.XLOOKUP(K72,数据更新表!E:E,数据更新表!F:F,0) -> 0 | DA72: 0 | DB72: =_xlfn.XLOOKUP(K72,数据更新表!E:E,数据更新表!G:G) -> #N/A | DC72: =_xlfn.XLOOKUP(L72,数据更新表!Z:Z,数据更新表!AH:AH) -> 0 | DD72: =_xlfn.XLOOKUP(L72,数据更新表!Z:Z,数据更新表!AE:AE) -> 0 | DE72: =_xlfn.XLOOKUP(L72,数据更新表!Z:Z,数据更新表!AF:AF) -> 0 | DF72: =_xlfn.XLOOKUP(K72,数据更新表!Z:Z,数据更新表!AG:AG) -> #N/A | DG72: =_xlfn.XLOOKUP(L72,数据更新表!Z:Z,数据更新表!AD:AD) -> 0 | DH72: =_xlfn.XLOOKUP(L72,数据更新表!Z:Z,数据更新表!AA:AA) -> 0 | DI72: =_xlfn.XLOOKUP(L72,数据更新表!Z:Z,数据更新表!AB:AB) -> 0 | DJ72: =_xlfn.XLOOKUP(L72,数据更新表!Z:Z,数据更新表!AC:AC) -> 0 | DK72: =_xlfn.XLOOKUP(L72,数据更新表!Z:Z,数据更新表!AI:AI) -> 0 | DL72: =_xlfn.XLOOKUP(L72,数据更新表!AL:AL,数据更新表!AM:AM) -> 0 | DM72: =_xlfn.XLOOKUP(L72,数据更新表!Z:Z,数据更新表!AJ:AJ) -> 0 | EE72: 1200 | EG72: 71 | EH72: =EJ72/(EI72+EL72) -> 0.5100694 | EI72: =EG72*$EI$1 -> 185.31 | EJ72: =EE72-EI72-EL72-EO72-EN72-EP72-EQ72 -> 224.454 | EK72: =EJ72/EE72 -> 0.187045 | EL72: =EX72*2500*$EI$1 -> 254.736 | EM72: =IF(EE72>299,"是","否") -> 是 | EN72: =EE72*0.05 -> 60 | EO72: =EE72*0.175 -> 210 | EP72: =IF(EE72<299,IF(EE72<99,25,IF(EE72<=149,30,IF(EE72<=299,37,85))),IF(EE72<=498,_xlfn.XLOOKUP(EW72,运费表!A:A,运费表!C:C,"重量超限",-1),_xlfn.XLOOKUP(EW72,运费表!A:A,运费表!D:D,"重量超限",-1))) -> 139.5 | EQ72: =EE72*0.105 -> 126 | ER72: =_xlfn.XLOOKUP(K72,[4]目录表!$H:$H,[4]目录表!$X:$X) -> 4 | ES72: =_xlfn.XLOOKUP(K72,[4]目录表!$H:$H,[4]目录表!$Y:$Y) -> 40 | ET72: =_xlfn.XLOOKUP(K72,[4]目录表!$H:$H,[4]目录表!$Z:$Z) -> 122 | EU72: =_xlfn.XLOOKUP(K72,[4]目录表!$H:$H,[4]目录表!$AA:$AA) -> 8 | EV72: =ES72*ET72*EU72/5000 -> 7.808 | EW72: =IF(EV72>=ER72,EV72,ER72) -> 7.808 | EX72: =_xlfn.XLOOKUP(K72,[2]目录表!$H:$H,[2]目录表!$AB:$AB) -> 0.03904 | EZ72: =CZ72/7 -> 0 | FK72: =_xlfn.XLOOKUP(K72,[2]目录表!$H:$H,[2]目录表!$AJ:$AJ) -> 装柜
